Workbook

Sheet Geral
B1: Local (país) | D1: Local (estado) | E1: Designação do repositório | G1: Designação do conjunto documental | I1: Designação do subconjunto documental | K1: Gênero documental | M1: Espécie/Tipo documental | O1: Técnica de registro | Q1: Forma documental | S1: Unidade de descrição
A2: 1 | B2: BR | C2: - | D2: SP | E2: APESP | F2: _ | G2: DASP | H2: - | I2: PENITPRE-CSDTCARANDIRU | J2: _ | K2: ICO | L2: - | M2: FOT | N2: - | O2: DGZ | P2: - | Q2: MT0 | R2: _ | S2: 3055-005- | T2: 001 | U2: F | V2: .jpg
A3: 2 | B3: BR | C3: - | D3: SP | E3: APESP | F3: _ | G3: DASP | H3: - | I3: PENITPRE-CSDTCARANDIRU | J3: _ | K3: ICO | L3: - | M3: FOT | N3: - | O3: DGZ | P3: - | Q3: MT0 | R3: _ | S3: 3055-005- | T3: 001 | U3: V | V3: .jpg
A4: 3 | B4: BR | C4: - | D4: SP | E4: APESP | F4: _ | G4: DASP | H4: - | I4: PENITPRE-CSDTCARANDIRU | J4: _ | K4: ICO | L4: - | M4: FOT | N4: - | O4: DGZ | P4: - | Q4: MT0 | R4: _ | S4: 3055-005- | T4: 002 | U4: F | V4: .jpg
A5: 4 | B5: BR | C5: - | D5: SP | E5: APESP | F5: _ | G5: DASP | H5: - | I5: PENITPRE-CSDTCARANDIRU | J5: _ | K5: ICO | L5: - | M5: FOT | N5: - | O5: DGZ | P5: - | Q5: MT0 | R5: _ | S5: 3055-005- | T5: 002 | U5: V | V5: .jpg
A6: 5 | B6: BR | C6: - | D6: SP | E6: APESP | F6: _ | G6: DASP | H6: - | I6: PENITPRE-CSDTCARANDIRU | J6: _ | K6: ICO | L6: - | M6: FOT | N6: - | O6: DGZ | P6: - | Q6: MT0 | R6: _ | S6: 3055-005- | T6: 003 | U6: F | V6: .jpg
A7: 6 | B7: BR | C7: - | D7: SP | E7: APESP | F7: _ | G7: DASP | H7: - | I7: PENITPRE-CSDTCARANDIRU | J7: _ | K7: ICO | L7: - | M7: FOT | N7: - | O7: DGZ | P7: - | Q7: MT0 | R7: _ | S7: 3055-005- | T7: 003 | U7: V | V7: .jpg
A8: 7 | B8: BR | C8: - | D8: SP | E8: APESP | F8: _ | G8: DASP | H8: - | I8: PENITPRE-CSDTCARANDIRU | J8: _ | K8: ICO | L8: - | M8: FOT | N8: - | O8: DGZ | P8: - | Q8: MT0 | R8: _ | S8: 3055-005- | T8: 004 | U8: F | V8: .jpg
A9: 8 | B9: BR | C9: - | D9: SP | E9: APESP | F9: _ | G9: DASP | H9: - | I9: PENITPRE-CSDTCARANDIRU | J9: _ | K9: ICO | L9: - | M9: FOT | N9: - | O9: DGZ | P9: - | Q9: MT0 | R9: _ | S9: 3055-005- | T9: 004 | U9: V | V9: .jpg
A10: 9 | B10: BR | C10: - | D10: SP | E10: APESP | F10: _ | G10: DASP | H10: - | I10: PENITPRE-CSDTCARANDIRU | J10: _ | K10: ICO | L10: - | M10: FOT | N10: - | O10: DGZ | P10: - | Q10: MT0 | R10: _ | S10: 3055-005- | T10: 006 | U10: F | V10: .jpg
A11: 10 | B11: BR | C11: - | D11: SP | E11: APESP | F11: _ | G11: DASP | H11: - | I11: PENITPRE-CSDTCARANDIRU | J11: _ | K11: ICO | L11: - | M11: FOT | N11: - | O11: DGZ | P11: - | Q11: MT0 | R11: _ | S11: 3055-005- | T11: 006 | U11: V | V11: .jpg
A12: 11 | B12: BR | C12: - | D12: SP | E12: APESP | F12: _ | G12: DASP | H12: - | I12: PENITPRE-CSDTCARANDIRU | J12: _ | K12: ICO | L12: - | M12: FOT | N12: - | O12: DGZ | P12: - | Q12: MT0 | R12: _ | S12: 3055-005- | T12: 007 | U12: F | V12: .jpg
A13: 12 | B13: BR | C13: - | D13: SP | E13: APESP | F13: _ | G13: DASP | H13: - | I13: PENITPRE-CSDTCARANDIRU | J13: _ | K13: ICO | L13: - | M13: FOT | N13: - | O13: DGZ | P13: - | Q13: MT0 | R13: _ | S13: 3055-005- | T13: 007 | U13: V | V13: .jpg
... A174: 173 | B174: BR | C174: - | D174: SP | E174: APESP | F174: _ | G174: DASP | H174: - | I174: PENITPRE-CSDTCARANDIRU | J174: _ | K174: ICO | L174: - | M174: FOT | N174: - | O174: DGZ | P174: - | Q174: MT0 | R174: _ | S174: 3055-005- | T174: 088 | U174: V | V174: .jpg
A175: 174 | B175: BR | C175: - | D175: SP | E175: APESP | F175: _ | G175: DASP | H175: - | I175: PENITPRE-CSDTCARANDIRU | J175: _ | K175: ICO | L175: - | M175: FOT | N175: - | O175: DGZ | P175: - | Q175: MT0 | S175: 2767-011- | T175: 001 | U175: F | V175: .jpg
A176: 175 | B176: BR | C176: - | D176: SP | E176: APESP | F176: _ | G176: DASP | H176: - | I176: PENITPRE-CSDTCARANDIRU | J176: _ | K176: ICO | L176: - | M176: FOT | N176: - | O176: DGZ | P176: - | Q176: MT0 | R176: _ | S176: 2767-011- | T176: 001 | U176: V | V176: .jpg
A177: 176 | B177: BR | C177: - | D177: SP | E177: APESP | F177: _ | G177: DASP | H177: - | I177: PENITPRE-CSDTCARANDIRU | J177: _ | K177: ICO | L177: - | M177: FOT | N177: - | O177: DGZ | P177: - | Q177: MT0 | R177: _ | S177: 2767-011- | T177: 002 | U177: F | V177: .jpg
A178: 177 | B178: BR | C178: - | D178: SP | E178: APESP | F178: _ | G178: DASP | H178: - | I178: PENITPRE-CSDTCARANDIRU | J178: _ | K178: ICO | L178: - | M178: FOT | N178: - | O178: DGZ | P178: - | Q178: MT0 | R178: _ | S178: 2767-011- | T178: 002 | U178: V | V178: .jpg
A179: 178 | B179: BR | C179: - | D179: SP | E179: APESP | F179: _ | G179: DASP | H179: - | I179: PENITPRE-CSDTCARANDIRU | J179: _ | K179: ICO | L179: - | M179: FOT | N179: - | O179: DGZ | P179: - | Q179: MT0 | R179: _ | S179: 2767-011- | T179: 003 | U179: F | V179: .jpg
A180: 179 | B180: BR | C180: - | D180: SP | E180: APESP | F180: _ | G180: DASP | H180: - | I180: PENITPRE-CSDTCARANDIRU | J180: _ | K180: ICO | L180: - | M180: FOT | N180: - | O180: DGZ | P180: - | Q180: MT0 | R180: _ | S180: 2767-011- | T180: 003 | U180: V | V180: .jpg
A181: 180 | B181: BR | C181: - | D181: SP | E181: APESP | F181: _ | G181: DASP | H181: - | I181: PENITPRE-CSDTCARANDIRU | J181: _ | K181: ICO | L181: - | M181: FOT | N181: - | O181: DGZ | P181: - | Q181: MT0 | R181: _ | S181: 2767-011- | T181: 004 | U181: F | V181: .jpg
A182: 181 | B182: BR | C182: - | D182: SP | E182: APESP | F182: _ | G182: DASP | H182: - | I182: PENITPRE-CSDTCARANDIRU | J182: _ | K182: ICO | L182: - | M182: FOT | N182: - | O182: DGZ | P182: - | Q182: MT0 | R182: _ | S182: 2767-011- | T182: 004 | U182: V | V182: .jpg
A183: 182 | B183: BR | C183: - | D183: SP | E183: APESP | F183: _ | G183: DASP | H183: - | I183: PENITPRE-CSDTCARANDIRU | J183: _ | K183: ICO | L183: - | M183: FOT | N183: - | O183: DGZ | P183: - | Q183: MT0 | R183: _ | S183: 2767-011- | T183: 005 | U183: F | V183: .jpg
A184: 183 | B184: BR | C184: - | D184: SP | E184: APESP | F184: _ | G184: DASP | H184: - | I184: PENITPRE-CSDTCARANDIRU | J184: _ | K184: ICO | L184: - | M184: FOT | N184: - | O184: DGZ | P184: - | Q184: MT0 | R184: _ | S184: 2767-011- | T184: 005 | U184: V | V184: .jpg
A185: 184 | B185: BR | C185: - | D185: SP | E185: APESP | F185: _ | G185: DASP | H185: - | I185: PENITPRE-CSDTCARANDIRU | J185: _ | K185: ICO | L185: - | M185: FOT | N185: - | O185: DGZ | P185: - | Q185: MT0 | R185: _ | S185: 2767-011- | T185: 006 | U185: F | V185: .jpg
A186: 185 | B186: BR | C186: - | D186: SP | E186: APESP | F186: _ | G186: DASP | H186: - | I186: PENITPRE-CSDTCARANDIRU | J186: _ | K186: ICO | L186: - | M186: FOT | N186: - | O186: DGZ | P186: - | Q186: MT0 | R186: _ | S186: 2767-011- | T186: 006 | U186: V | V186: .jpg
A187: 186 | B187: BR | C187: - | D187: SP | E187: APESP | F187: _ | G187: DASP | H187: - | I187: PENITPRE-CSDTCARANDIRU | J187: _ | K187: ICO | L187: - | M187: FOT | N187: - | O187: DGZ | P187: - | Q187: MT0 | R187: _ | S187: 2767-011- | T187: 007 | U187: F | V187: .jpg
... A366: 365 | B366: BR | C366: - | D366: SP | E366: APESP | F366: _ | G366: DASP | H366: - | I366: PENITPRE-CSDTCARANDIRU | J366: _ | K366: ICO | L366: - | M366: FOT | N366: - | O366: DGZ | P366: - | Q366: MT0 | R366: _ | S366: 3055-003- | T366: 030 | U366: V | V366: .jpg

Sheet 3055-005
A1: Cód. | B1: Título descritivo (atribuído) | C1: Nível de descrição | D1: Data de difusão da fotografia (mais antiga contida no verso) | E1: Tamanho | F1: Suporte | G1: Local | H1: Autor/Responsável | I1: Denominação do catálogo temático (APESP DASP) | J1: Localização | K1: Código de referência | L1: História arquivística | M1: Conteúdo/Assunto | N1: Condições de acesso e reprodução | O1: Palavras-chave | P1: Gênero | Q1: Técnica de registro | R1: Legenda para publicações | S1: Citação ABNT | T1: Notas (transcrição das informações do verso)
A2: =RIGHT(K2,3) -> 001 | B2: Av. Cruzeiro do Sul (1979) | C2: Item | D2: 19150 | E2: Gerado pelo Dataverse | F2: Fotografia digitalizada; preto e branco; suporte em papel fotográfico | G2: São Paulo, Brasil | H2: Arquivo Público do Estado de São Paulo, Jornal Diários Associados | I2: Estado De São Paulo - Penitenciárias e Presídios - Casa de Detenção do Carandiru (Fotografias) | J2: Caixa: 3055 Folder: 5 | K2: =TEXTJOIN("", TRUE, Geral!B2:T2) -> BR-SPAPESP_DASP-PENITPRE-CSDTCARANDIRU_ICO-FOT-DGZ-MT0_3055-005-001 | L2: A Casa de Detenção de São Paulo, conhecida como Carandiru, foi formalmente criada em 1938 por decreto do interventor Adhemar de Barros, embora ainda instalada no edifício da Avenida Tiradentes. Sua implantação no bairro do Carandiru só se iniciou décadas depois, quando o governo estadual contratou, em 1951, o Escritório Técnico Ramos de Azevedo, Severo & Villares para projetar e conduzir a construção do novo complexo penitenciário em terreno contíguo à Penitenciária do Estado. As obras avançaram de forma modular, e o primeiro edifício concluído — o Pavilhão 2 — foi inaugurado em 1956, marcando a abertura parcial da chamada “Nova Casa de Detenção”. Ao longo dos anos seguintes, novos pavilhões foram sendo erguidos e inaugurados, compondo um conjunto arquitetônico que se consolidaria como um dos principais símbolos do sistema prisional paulista no século XX. Esta fotografia integra o fundo documental do grupo Diários Associados do Estado de São Paulo (DASP), custodiado pelo Arquivo Público do Estado de São Paulo (APESP), e registra aspectos desse prolongado processo de criação (1938), construção (a partir de 1951) e inauguração (a partir de 1956) da Casa de Detenção, conforme aponta a pesquisa de Maíra Rocha Machado, Bianca Tavolari e Maira Rosín (2025)[1]. | M2: Fotografia em preto e branco mostrando a fachada principal da Casa de Detenção, com a inscrição “CASA DE DETENÇÃO” visível na parte superior da imagem. No primeiro plano, observam-se pessoas reunidas junto ao portão de entrada e dois veículos estacionados. Iluminação artificial, tomada noturna ou ao entardecer. | N2: O acesso aos documentos deste acervo está condicionado ao compromisso de não repassá-los a terceiros, à obrigatoriedade de mencionar que os originais pertencem ao Arquivo Público do Estado de São Paulo, e à necessidade de novo Termo de Responsabilidade em caso de reutilização ou uso diverso do inicialmente acordado. O uso está sujeito às restrições previstas na Lei de Arquivos (Lei nº 8.159/1991), na Lei de Direitos Autorais (Lei nº 9.610/1998), nos artigos 138 e 145 do Código Penal, e no artigo 5º, inciso X, da Constituição Federal, especialmente quanto à proteção da honra e imagem de terceiros. A pessoa física ou jurídica responsável assume integral responsabilidade civil e penal por eventuais danos decorrentes do uso das reproduções e informações, eximindo o Arquivo Público do Estado de São Paulo de qualquer responsabilidade. | O2: Sistema prisional; Arquitetura prisional; Casa de Detenção de São Paulo; Carandiru; Fotografia documental. | P2: Fotografia (Iconográfico) | Q2: Digitalização de fotografia em preto e branco (analógica original) | R2: ="Figura n – ["&B2&"]"&CHAR(10)&"Fonte: Arquivo do Estado de São Paulo, "&TEXT(D2,"yyyy")&"." -> Figura n – [Av. Cruzeiro do Sul (1979)] Fonte: Arquivo do Estado de São Paulo, 1952. | S2: ="ARQUIVO PÚBLICO DO ESTADO DE SÃO PAULO (Brasil). ["&B2&"]. "&G2&". "&TEXT(D2,"dd")&" "&LOWER(TEXT(D2,"mmm"))&" "&TEXT(D2,"yyyy")&". "&F2&". Disponível em: <link do dataverse>. Acesso em: 28 out. 2025." -> ARQUIVO PÚBLICO DO ESTADO DE SÃO PAULO (Brasil). [Av. Cruzeiro do Sul (1979)]. São Paulo, Brasil. 05 jun. 1952. Fotografia digitalizada; preto e branco; suporte em papel fotográfico. Disponível em: <link do dataverse>. Acesso em: 28 out. 2025. | T2: Estado de São Paulo – XXXXX penitenciárias e presídios – Casa de Detenção DN – 23/06/1979
A3: =RIGHT(K3,3) -> 002 | B3: Sentinela em passarela de vigilância — Casa de Detenção (Carandiru) em 1979 | C3: Item | D3: 19150 | E3: Gerado pelo Dataverse | F3: Fotografia digitalizada; preto e branco; suporte em papel fotográfico | G3: São Paulo, Brasil | H3: Arquivo Público do Estado de São Paulo, Jornal Diários Associados | I3: Estado De São Paulo - Penitenciárias e Presídios - Casa de Detenção do Carandiru (Fotografias) | J3: Caixa: 3055 Folder: 5 | K3: =TEXTJOIN("", TRUE, Geral!B4:T4) -> BR-SPAPESP_DASP-PENITPRE-CSDTCARANDIRU_ICO-FOT-DGZ-MT0_3055-005-002 | L3: =$L$2 -> A Casa de Detenção de São Paulo, conhecida como Carandiru, foi formalmente criada em 1938 por decreto do interventor Adhemar de Barros, embora ainda instalada no edifício da Avenida Tiradentes. Sua implantação no bairro do Carandiru só se iniciou décadas depois, quando o governo estadual contratou, em 1951, o Escritório Técnico Ramos de Azevedo, Severo & Villares para projetar e conduzir a construção do novo complexo penitenciário em terreno contíguo à Penitenciária do Estado. As obras avançaram de forma modular, e o primeiro edifício concluído — o Pavilhão 2 — foi inaugurado em 1956, marcando a abertura parcial da chamada “Nova Casa de Detenção”. Ao longo dos anos seguintes, novos pavilhões foram sendo erguidos e inaugurados, compondo um conjunto arquitetônico que se consolidaria como um dos principais símbolos do sistema prisional paulista no século XX. Esta fotografia integra o fundo documental do grupo Diários Associados do Estado de São Paulo (DASP), custodiado pelo Arquivo Público do Estado de São Paulo (APESP), e registra aspectos desse prolongado processo de criação (1938), construção (a partir de 1951) e inauguração (a partir de 1956) da Casa de Detenção, conforme aponta a pesquisa de Maíra Rocha Machado, Bianca Tavolari e Maira Rosín (2025)[1]. | M3: Fotografia em preto e branco retratando um agente de segurança armado caminhando sobre uma passarela elevada junto à fachada de um dos pavilhões da Casa de Detenção. A construção exibe janelas gradeadas e estrutura de concreto que caracteriza a arquitetura prisional. | N3: O acesso aos documentos deste acervo está condicionado ao compromisso de não repassá-los a terceiros, à obrigatoriedade de mencionar que os originais pertencem ao Arquivo Público do Estado de São Paulo, e à necessidade de novo Termo de Responsabilidade em caso de reutilização ou uso diverso do inicialmente acordado. O uso está sujeito às restrições previstas na Lei de Arquivos (Lei nº 8.159/1991), na Lei de Direitos Autorais (Lei nº 9.610/1998), nos artigos 138 e 145 do Código Penal, e no artigo 5º, inciso X, da Constituição Federal, especialmente quanto à proteção da honra e imagem de terceiros. A pessoa física ou jurídica responsável assume integral responsabilidade civil e penal por eventuais danos decorrentes do uso das reproduções e informações, eximindo o Arquivo Público do Estado de São Paulo de qualquer responsabilidade. | O3: Sistema prisional; Vigilância penitenciária; Segurança prisional; Arquitetura carcerária; Casa de Detenção de São Paulo; Carandiru. | P3: Fotografia (Iconográfico) | Q3: Digitalização de fotografia em preto e branco (analógica original) | R3: ="Figura n – ["&B3&"]"&CHAR(10)&"Fonte: Arquivo do Estado de São Paulo, "&TEXT(D3,"yyyy")&"." -> Figura n – [Sentinela em passarela de vigilância — Casa de Detenção (Carandiru) em 1979] Fonte: Arquivo do Estado de São Paulo, 1952. | S3: ="ARQUIVO PÚBLICO DO ESTADO DE SÃO PAULO (Brasil). ["&B3&"]. "&G3&". "&TEXT(D3,"dd")&" "&LOWER(TEXT(D3,"mmm"))&" "&TEXT(D3,"yyyy")&". "&F3&". Disponível em: <link do dataverse>. Acesso em: 28 out. 2025." -> ARQUIVO PÚBLICO DO ESTADO DE SÃO PAULO (Brasil). [Sentinela em passarela de vigilância — Casa de Detenção (Carandiru) em 1979]. São Paulo, Brasil. 05 jun. 1952. Fotografia digitalizada; preto e branco; suporte em papel fotográfico. Disponível em: <link do dataverse>. Acesso em: 28 out. 2025. | T3: Estado de São Paulo – Penitenciárias e presídios – Casa de Detenção Vista parcial da Detenção. DN – 16/02/1979
A4: =RIGHT(K4,3) -> 003 | B4: Celebração da Páscoa na Casa de Detenção (Carandiru) em 1963 | C4: Item | D4: 19150 | E4: Gerado pelo Dataverse | F4: Fotografia digitalizada; preto e branco; suporte em papel fotográfico | G4: São Paulo, Brasil | H4: Arquivo Público do Estado de São Paulo, Jornal Diários Associados | I4: Estado De São Paulo - Penitenciárias e Presídios - Casa de Detenção do Carandiru (Fotografias) | J4: Caixa: 3055 Folder: 5 | K4: =TEXTJOIN("", TRUE, Geral!B6:T6) -> BR-SPAPESP_DASP-PENITPRE-CSDTCARANDIRU_ICO-FOT-DGZ-MT0_3055-005-003 | L4: =$L$2 -> A Casa de Detenção de São Paulo, conhecida como Carandiru, foi formalmente criada em 1938 por decreto do interventor Adhemar de Barros, embora ainda instalada no edifício da Avenida Tiradentes. Sua implantação no bairro do Carandiru só se iniciou décadas depois, quando o governo estadual contratou, em 1951, o Escritório Técnico Ramos de Azevedo, Severo & Villares para projetar e conduzir a construção do novo complexo penitenciário em terreno contíguo à Penitenciária do Estado. As obras avançaram de forma modular, e o primeiro edifício concluído — o Pavilhão 2 — foi inaugurado em 1956, marcando a abertura parcial da chamada “Nova Casa de Detenção”. Ao longo dos anos seguintes, novos pavilhões foram sendo erguidos e inaugurados, compondo um conjunto arquitetônico que se consolidaria como um dos principais símbolos do sistema prisional paulista no século XX. Esta fotografia integra o fundo documental do grupo Diários Associados do Estado de São Paulo (DASP), custodiado pelo Arquivo Público do Estado de São Paulo (APESP), e registra aspectos desse prolongado processo de criação (1938), construção (a partir de 1951) e inauguração (a partir de 1956) da Casa de Detenção, conforme aponta a pesquisa de Maíra Rocha Machado, Bianca Tavolari e Maira Rosín (2025)[1]. | M4: Fotografia em preto e branco registra a celebração da comunhão pascal dos detentos da Casa de Detenção do Carandiru, realizada em 7 de julho de 1963. A cerimônia litúrgica ocorre em área interna do complexo, diante do pátio da Capela de Nossa Senhora Aparecida. Em primeiro plano, um altar improvisado com toalha branca e arranjo floral serve de ponto focal para o ofício conduzido pelo padre Paulo Ruffier, capelão da Penitenciária do Estado. Participam da celebração freiras, mulheres e homens em trajes formais, dispostos em atitude reverente. Ao fundo, vê-se o pátio cercado por galerias com janelas gradeadas, decorado com bandeirolas, compondo um cenário de fé e solenidade em meio ao ambiente prisional. | N4: O acesso aos documentos deste acervo está condicionado ao compromisso de não repassá-los a terceiros, à obrigatoriedade de mencionar que os originais pertencem ao Arquivo Público do Estado de São Paulo, e à necessidade de novo Termo de Responsabilidade em caso de reutilização ou uso diverso do inicialmente acordado. O uso está sujeito às restrições previstas na Lei de Arquivos (Lei nº 8.159/1991), na Lei de Direitos Autorais (Lei nº 9.610/1998), nos artigos 138 e 145 do Código Penal, e no artigo 5º, inciso X, da Constituição Federal, especialmente quanto à proteção da honra e imagem de terceiros. A pessoa física ou jurídica responsável assume integral responsabilidade civil e penal por eventuais danos decorrentes do uso das reproduções e informações, eximindo o Arquivo Público do Estado de São Paulo de qualquer responsabilidade. | O4: Sistema prisional; Assistência religiosa; Cerimônias católicas; Vida institucional; Casa de Detenção de São Paulo; Carandiru. | P4: Fotografia (Iconográfico) | Q4: Digitalização de fotografia em preto e branco (analógica original) | R4: ="Figura n – ["&B4&"]"&CHAR(10)&"Fonte: Arquivo do Estado de São Paulo, "&TEXT(D4,"yyyy")&"." -> Figura n – [Celebração da Páscoa na Casa de Detenção (Carandiru) em 1963] Fonte: Arquivo do Estado de São Paulo, 1952. | S4: ="ARQUIVO PÚBLICO DO ESTADO DE SÃO PAULO (Brasil). ["&B4&"]. "&G4&". "&TEXT(D4,"dd")&" "&LOWER(TEXT(D4,"mmm"))&" "&TEXT(D4,"yyyy")&". "&F4&". Disponível em: <link do dataverse>. Acesso em: 28 out. 2025." -> ARQUIVO PÚBLICO DO ESTADO DE SÃO PAULO (Brasil). [Celebração da Páscoa na Casa de Detenção (Carandiru) em 1963]. São Paulo, Brasil. 05 jun. 1952. Fotografia digitalizada; preto e branco; suporte em papel fotográfico. Disponível em: <link do dataverse>. Acesso em: 28 out. 2025. | T4: Penitenciárias e presídios – Casa de Detenção do Carandiru Detentos tiveram a sua comunhão pascal Aspecto da Páscoa dos detentos da Casa de Detenção do Carandiru, ontem realizada. DN. 1ª Ed., 8/7/1963 - wpj Reverentes, concentrados e em absoluto silêncio, os detentos recolhidos no Pavilhão n. 8 da Casa de Detenção fizeram na manhã de ontem a sua comunhão pascal. A cerimonia litúrgica, que se constituiu num admirável espetáculo de fé cristã, foi celebrada defronte ao pátio da Capela de Nossa Senhora Aparecida, pelo pe. Paulo Ruffier, capelão da Penitenciária do Estado.
A5: =RIGHT(K5,3) -> 004 | B5: Mulheres em atividade de artesanato em cômodo com decoração religiosa na Casa de Detenção (Carandiru) em 1963 | C5: Item | D5: 19312 | E5: Gerado pelo Dataverse | F5: Fotografia digitalizada; preto e branco; suporte em papel fotográfico | G5: São Paulo, Brasil | H5: Arquivo Público do Estado de São Paulo, Jornal Diários Associados | I5: Estado De São Paulo - Penitenciárias e Presídios - Casa de Detenção do Carandiru (Fotografias) | J5: Caixa: 3055 Folder: 5 | K5: =TEXTJOIN("", TRUE, Geral!B8:T8) -> BR-SPAPESP_DASP-PENITPRE-CSDTCARANDIRU_ICO-FOT-DGZ-MT0_3055-005-004 | L5: =$L$2 -> A Casa de Detenção de São Paulo, conhecida como Carandiru, foi formalmente criada em 1938 por decreto do interventor Adhemar de Barros, embora ainda instalada no edifício da Avenida Tiradentes. Sua implantação no bairro do Carandiru só se iniciou décadas depois, quando o governo estadual contratou, em 1951, o Escritório Técnico Ramos de Azevedo, Severo & Villares para projetar e conduzir a construção do novo complexo penitenciário em terreno contíguo à Penitenciária do Estado. As obras avançaram de forma modular, e o primeiro edifício concluído — o Pavilhão 2 — foi inaugurado em 1956, marcando a abertura parcial da chamada “Nova Casa de Detenção”. Ao longo dos anos seguintes, novos pavilhões foram sendo erguidos e inaugurados, compondo um conjunto arquitetônico que se consolidaria como um dos principais símbolos do sistema prisional paulista no século XX. Esta fotografia integra o fundo documental do grupo Diários Associados do Estado de São Paulo (DASP), custodiado pelo Arquivo Público do Estado de São Paulo (APESP), e registra aspectos desse prolongado processo de criação (1938), construção (a partir de 1951) e inauguração (a partir de 1956) da Casa de Detenção, conforme aponta a pesquisa de Maíra Rocha Machado, Bianca Tavolari e Maira Rosín (2025)[1]. | M5: A imagem em preto e branco mostra um grupo de seis mulheres (quatro brancas e duas negras) reunidas em uma mesa de trabalho. Elas parecem concentradas em atividades manuais, talvez de corte, desenho ou modelagem de moldes — há réguas, papéis e ferramentas sobre a mesa. No centro da composição, ao fundo, há um crucifixo fixado na parede, logo acima da mesa. As mulheres usam roupas simples e claras, o que reforça uma atmosfera de disciplina e uniformidade. | N5: O acesso aos documentos deste acervo está condicionado ao compromisso de não repassá-los a terceiros, à obrigatoriedade de mencionar que os originais pertencem ao Arquivo Público do Estado de São Paulo, e à necessidade de novo Termo de Responsabilidade em caso de reutilização ou uso diverso do inicialmente acordado. O uso está sujeito às restrições previstas na Lei de Arquivos (Lei nº 8.159/1991), na Lei de Direitos Autorais (Lei nº 9.610/1998), nos artigos 138 e 145 do Código Penal, e no artigo 5º, inciso X, da Constituição Federal, especialmente quanto à proteção da honra e imagem de terceiros. A pessoa física ou jurídica responsável assume integral responsabilidade civil e penal por eventuais danos decorrentes do uso das reproduções e informações, eximindo o Arquivo Público do Estado de São Paulo de qualquer responsabilidade. | O5: Trabalho feminino; religião e cárcere; oficinas de artesanato; ressocialização. | P5: Fotografia (Iconográfico) | Q5: Digitalização de fotografia em preto e branco (analógica original) | R5: ="Figura n – ["&B5&"]"&CHAR(10)&"Fonte: Arquivo do Estado de São Paulo, "&TEXT(D5,"yyyy")&"." -> Figura n – [Mulheres em atividade de artesanato em cômodo com decoração religiosa na Casa de Detenção (Carandiru) em 1963] Fonte: Arquivo do Estado de São Paulo, 1952. | S5: ="ARQUIVO PÚBLICO DO ESTADO DE SÃO PAULO (Brasil). ["&B5&"]. "&G5&". "&TEXT(D5,"dd")&" "&LOWER(TEXT(D5,"mmm"))&" "&TEXT(D5,"yyyy")&". "&F5&". Disponível em: <link do dataverse>. Acesso em: 28 out. 2025." -> ARQUIVO PÚBLICO DO ESTADO DE SÃO PAULO (Brasil). [Mulheres em atividade de artesanato em cômodo com decoração religiosa na Casa de Detenção (Carandiru) em 1963]. São Paulo, Brasil. 14 nov. 1952. Fotografia digitalizada; preto e branco; suporte em papel fotográfico. Disponível em: <link do dataverse>. Acesso em: 28 out. 2025. | T5: Estado de São Paulo – Casa de Detenção do Carandiru Detentas do presidio do Carandirú, são preparadas pela Madre do Divino Salvador, para retornar ao convívio da sociedade. Recebem um pecúlio e os ensinamentos necessários para enfrentar a vida nas grandes cidades. Arq. 24/1/1963
A6: =RIGHT(K6,3) -> 006 | B6: Autoridades de gravata e de farda cruzam portões da Casa de Detenção “por ocasião de sua inauguração”, conforme legenda (12.11.1956) | C6: Item | D6: 20086 | E6: Gerado pelo Dataverse | F6: Fotografia digitalizada; preto e branco; suporte em papel fotográfico | G6: São Paulo, Brasil | H6: Arquivo Público do Estado de São Paulo, Jornal Diários Associados | I6: Estado De São Paulo - Penitenciárias e Presídios - Casa de Detenção do Carandiru (Fotografias) | J6: Caixa: 3055 Folder: 5 | K6: =TEXTJOIN("", TRUE, Geral!B10:T10) -> BR-SPAPESP_DASP-PENITPRE-CSDTCARANDIRU_ICO-FOT-DGZ-MT0_3055-005-006 | L6: =$L$2 -> A Casa de Detenção de São Paulo, conhecida como Carandiru, foi formalmente criada em 1938 por decreto do interventor Adhemar de Barros, embora ainda instalada no edifício da Avenida Tiradentes. Sua implantação no bairro do Carandiru só se iniciou décadas depois, quando o governo estadual contratou, em 1951, o Escritório Técnico Ramos de Azevedo, Severo & Villares para projetar e conduzir a construção do novo complexo penitenciário em terreno contíguo à Penitenciária do Estado. As obras avançaram de forma modular, e o primeiro edifício concluído — o Pavilhão 2 — foi inaugurado em 1956, marcando a abertura parcial da chamada “Nova Casa de Detenção”. Ao longo dos anos seguintes, novos pavilhões foram sendo erguidos e inaugurados, compondo um conjunto arquitetônico que se consolidaria como um dos principais símbolos do sistema prisional paulista no século XX. Esta fotografia integra o fundo documental do grupo Diários Associados do Estado de São Paulo (DASP), custodiado pelo Arquivo Público do Estado de São Paulo (APESP), e registra aspectos desse prolongado processo de criação (1938), construção (a partir de 1951) e inauguração (a partir de 1956) da Casa de Detenção, conforme aponta a pesquisa de Maíra Rocha Machado, Bianca Tavolari e Maira Rosín (2025)[1]. | M6: Imagem em preto e branco registra autoridades civis e militares em deslocamento por área externa do complexo penitenciário do Carandiru, em São Paulo. À frente do grupo, homens trajando ternos e uniformes dialogam enquanto atravessam um portão de ferro. A cena documenta um momento da inauguração oficial do novo pavilhão da Casa de Detenção, realizada em 12 de setembro de 1956, nos terrenos da Penitenciária do Estado, na avenida General Ataliba Leonel. Presentes estavam representantes do Judiciário, da Segurança Pública, da Justiça, da Guarda Civil, da Força Pública, da Polícia Feminina e de comandos militares da região. | N6: O acesso aos documentos deste acervo está condicionado ao compromisso de não repassá-los a terceiros, à obrigatoriedade de mencionar que os originais pertencem ao Arquivo Público do Estado de São Paulo, e à necessidade de novo Termo de Responsabilidade em caso de reutilização ou uso diverso do inicialmente acordado. O uso está sujeito às restrições previstas na Lei de Arquivos (Lei nº 8.159/1991), na Lei de Direitos Autorais (Lei nº 9.610/1998), nos artigos 138 e 145 do Código Penal, e no artigo 5º, inciso X, da Constituição Federal, especialmente quanto à proteção da honra e imagem de terceiros. A pessoa física ou jurídica responsável assume integral responsabilidade civil e penal por eventuais danos decorrentes do uso das reproduções e informações, eximindo o Arquivo Público do Estado de São Paulo de qualquer responsabilidade. | O6: Administração penitenciária; visita institucional; segurança pública; Carandiru; autoridades civis e militares. | P6: Fotografia (Iconográfico) | Q6: Digitalização de fotografia em preto e branco (analógica original) | R6: ="Figura n – ["&B6&"]"&CHAR(10)&"Fonte: Arquivo do Estado de São Paulo, "&TEXT(D6,"yyyy")&"." -> Figura n – [Autoridades de gravata e de farda cruzam portões da Casa de Detenção “por ocasião de sua inauguração”, conforme legenda (12.11.1956)] Fonte: Arquivo do Estado de São Paulo, 1954. | S6: ="ARQUIVO PÚBLICO DO ESTADO DE SÃO PAULO (Brasil). ["&B6&"]. "&G6&". "&TEXT(D6,"dd")&" "&LOWER(TEXT(D6,"mmm"))&" "&TEXT(D6,"yyyy")&". "&F6&". Disponível em: <link do dataverse>. Acesso em: 28 out. 2025." -> ARQUIVO PÚBLICO DO ESTADO DE SÃO PAULO (Brasil). [Autoridades de gravata e de farda cruzam portões da Casa de Detenção “por ocasião de sua inauguração”, conforme legenda (12.11.1956)]. São Paulo, Brasil. 28 dez. 1954. Fotografia digitalizada; preto e branco; suporte em papel fotográfico. Disponível em: <link do dataverse>. Acesso em: 28 out. 2025. | T6: Estado de São Paulo - Penitenciárias e Presídios – Casa de Detenção - Carandiru Realizou-se a inauguração oficial do novo pavilhão da Casa de Detenção, construído nos terrenos da Penitenciária do Estado. Da inauguração é o flagrante. DN, ed. 12/9/1956 Inaugurado um pavilhão na nova Casa de Detenção – Realizou-se ontem a inauguração oficial do novo pavilhão da Casa de Detenção, construído nos terrenos da Penitenciária do Estado, na Avenida General Ataliba Leonel. O edifício, que estava praticamente terminado há algum tempo, necessitava de obras complementares externas, bem como do aparelhamento indispensável para o seu funcionamento. Ainda assim, porém, parte do prédio vinha sendo utilizada há alguns meses, sendo ali alojados parte dos detentos — os mais perigosos — que se achavam no Presídio do Hipódromo ou na Casa de Detenção. O novo pavilhão, que faz parte de um conjunto a ser construído o mais rapidamente possível, tem capacidade para 500 presos, alojados em quatro pavimentos distintos. Ao ato inaugural compareceram o juiz das Execuções Criminais, sr. Valentim Alves da Silva; o sr. Nereu César de Morais, diretor-geral dos Presídios; o sr. Carlos Eugênio Bittencourt da Fonseca, secretário da Segurança Pública; o sr. Lincoln Feliciano, secretário da Justiça; a diretoria da Guarda Civil; o comandante da Força Pública; representantes do comando da 2ª Região Militar e da Zona Militar Centro; delegados auxiliares, especializados e de distritos; bem como a diretora da Polícia Feminina. O clichê fixa aspecto tomado durante a solenidade.
A7: =RIGHT(K7,3) -> 007 | B7: Repórter examinando o colchão cujos panos foram utilizados para a produção de uma corda para a fuga de detentos da Casa de Detenção (Carandiru) em 1956 | C7: Item | D7: 20086 | E7: Gerado pelo Dataverse | F7: Fotografia digitalizada; preto e branco; suporte em papel fotográfico | G7: São Paulo, Brasil | H7: Arquivo Público do Estado de São Paulo, Jornal Diários Associados | I7: Estado De São Paulo - Penitenciárias e Presídios - Casa de Detenção do Carandiru (Fotografias) | J7: Caixa: 3055 Folder: 5 | K7: =TEXTJOIN("", TRUE, Geral!B12:T12) -> BR-SPAPESP_DASP-PENITPRE-CSDTCARANDIRU_ICO-FOT-DGZ-MT0_3055-005-007 | L7: =$L$2 -> A Casa de Detenção de São Paulo, conhecida como Carandiru, foi formalmente criada em 1938 por decreto do interventor Adhemar de Barros, embora ainda instalada no edifício da Avenida Tiradentes. Sua implantação no bairro do Carandiru só se iniciou décadas depois, quando o governo estadual contratou, em 1951, o Escritório Técnico Ramos de Azevedo, Severo & Villares para projetar e conduzir a construção do novo complexo penitenciário em terreno contíguo à Penitenciária do Estado. As obras avançaram de forma modular, e o primeiro edifício concluído — o Pavilhão 2 — foi inaugurado em 1956, marcando a abertura parcial da chamada “Nova Casa de Detenção”. Ao longo dos anos seguintes, novos pavilhões foram sendo erguidos e inaugurados, compondo um conjunto arquitetônico que se consolidaria como um dos principais símbolos do sistema prisional paulista no século XX. Esta fotografia integra o fundo documental do grupo Diários Associados do Estado de São Paulo (DASP), custodiado pelo Arquivo Público do Estado de São Paulo (APESP), e registra aspectos desse prolongado processo de criação (1938), construção (a partir de 1951) e inauguração (a partir de 1956) da Casa de Detenção, conforme aponta a pesquisa de Maíra Rocha Machado, Bianca Tavolari e Maira Rosín (2025)[1]. | M7: Fotografia em preto e branco mostra uma pessoa curvada dentro de uma cela da Casa de Detenção do Carandiru, ao lado de um monte de palha. Sobre a palha, repousam um colchão listrado e tecidos, evidenciando improviso nas condições de repouso. O ambiente revela aspectos da precariedade estrutural do sistema prisional à época. O registro está relacionado à fuga de quatro detentos, ocorrida na madrugada de 6 de julho de 1956, quando lençóis e partes de colchões foram utilizados na confecção de uma corda improvisada. | N7: O acesso aos documentos deste acervo está condicionado ao compromisso de não repassá-los a terceiros, à obrigatoriedade de mencionar que os originais pertencem ao Arquivo Público do Estado de São Paulo, e à necessidade de novo Termo de Responsabilidade em caso de reutilização ou uso diverso do inicialmente acordado. O uso está sujeito às restrições previstas na Lei de Arquivos (Lei nº 8.159/1991), na Lei de Direitos Autorais (Lei nº 9.610/1998), nos artigos 138 e 145 do Código Penal, e no artigo 5º, inciso X, da Constituição Federal, especialmente quanto à proteção da honra e imagem de terceiros. A pessoa física ou jurídica responsável assume integral responsabilidade civil e penal por eventuais danos decorrentes do uso das reproduções e informações, eximindo o Arquivo Público do Estado de São Paulo de qualquer responsabilidade. | O7: Fuga de detentos; Cela (Prisional); Precariedade estrutural; Colchão improvisado; Palha (Leito); Reporter examinando; Carandiru; Incidentes de segurança; Meios de fuga; Cotidiano carcerário. | P7: Fotografia (Iconográfico) | Q7: Digitalização de fotografia em preto e branco (analógica original) | R7: ="Figura n – ["&B7&"]"&CHAR(10)&"Fonte: Arquivo do Estado de São Paulo, "&TEXT(D7,"yyyy")&"." -> Figura n – [Repórter examinando o colchão cujos panos foram utilizados para a produção de uma corda para a fuga de detentos da Casa de Detenção (Carandiru) em 1956] Fonte: Arquivo do Estado de São Paulo, 1954. | S7: ="ARQUIVO PÚBLICO DO ESTADO DE SÃO PAULO (Brasil). ["&B7&"]. "&G7&". "&TEXT(D7,"dd")&" "&LOWER(TEXT(D7,"mmm"))&" "&TEXT(D7,"yyyy")&". "&F7&". Disponível em: <link do dataverse>. Acesso em: 28 out. 2025." -> ARQUIVO PÚBLICO DO ESTADO DE SÃO PAULO (Brasil). [Repórter examinando o colchão cujos panos foram utilizados para a produção de uma corda para a fuga de detentos da Casa de Detenção (Carandiru) em 1956]. São Paulo, Brasil. 28 dez. 1954. Fotografia digitalizada; preto e branco; suporte em papel fotográfico. Disponível em: <link do dataverse>. Acesso em: 28 out. 2025. | T7: Estado de São Paulo - Penitenciárias e Presídios – Casa de Detenção Carandiru Quatro delinquentes fugiram de madrugada da Casa de Detenção O repórter examina o colchão que foi destruído pelos fugitivos, cujo pano aproveitaram para reforçar a improvisada corda feita com lençóis. DN, 1ª ed., 6/7/1956 – W
A8: =RIGHT(K8,3) -> 008 | B8: Mulheres em atividade de artesanato em ambiente com elementos religiosos na Casa de Detenção (Carandiru), 1963 | C8: Item | D8: 20116 | E8: Gerado pelo Dataverse | F8: Fotografia digitalizada; preto e branco; suporte em papel fotográfico | G8: São Paulo, Brasil | H8: Arquivo Público do Estado de São Paulo, Jornal Diários Associados | I8: Estado De São Paulo - Penitenciárias e Presídios - Casa de Detenção do Carandiru (Fotografias) | J8: Caixa: 3055 Folder: 5 | K8: =TEXTJOIN("", TRUE, Geral!B14:T14) -> BR-SPAPESP_DASP-PENITPRE-CSDTCARANDIRU_ICO-FOT-DGZ-MT0_3055-005-008 | L8: =$L$2 -> A Casa de Detenção de São Paulo, conhecida como Carandiru, foi formalmente criada em 1938 por decreto do interventor Adhemar de Barros, embora ainda instalada no edifício da Avenida Tiradentes. Sua implantação no bairro do Carandiru só se iniciou décadas depois, quando o governo estadual contratou, em 1951, o Escritório Técnico Ramos de Azevedo, Severo & Villares para projetar e conduzir a construção do novo complexo penitenciário em terreno contíguo à Penitenciária do Estado. As obras avançaram de forma modular, e o primeiro edifício concluído — o Pavilhão 2 — foi inaugurado em 1956, marcando a abertura parcial da chamada “Nova Casa de Detenção”. Ao longo dos anos seguintes, novos pavilhões foram sendo erguidos e inaugurados, compondo um conjunto arquitetônico que se consolidaria como um dos principais símbolos do sistema prisional paulista no século XX. Esta fotografia integra o fundo documental do grupo Diários Associados do Estado de São Paulo (DASP), custodiado pelo Arquivo Público do Estado de São Paulo (APESP), e registra aspectos desse prolongado processo de criação (1938), construção (a partir de 1951) e inauguração (a partir de 1956) da Casa de Detenção, conforme aponta a pesquisa de Maíra Rocha Machado, Bianca Tavolari e Maira Rosín (2025)[1]. | M8: A imagem em preto e branco mostra um grupo de seis mulheres (quatro brancas e duas negras) reunidas em uma mesa de trabalho. Elas parecem concentradas em atividades manuais, talvez de corte, desenho ou modelagem de moldes — há réguas, papéis e ferramentas sobre a mesa. No centro da composição, ao fundo, há um crucifixo fixado na parede, logo acima da mesa. As mulheres usam roupas simples e claras, o que reforça uma atmosfera de disciplina e uniformidade. | N8: O acesso aos documentos deste acervo está condicionado ao compromisso de não repassá-los a terceiros, à obrigatoriedade de mencionar que os originais pertencem ao Arquivo Público do Estado de São Paulo, e à necessidade de novo Termo de Responsabilidade em caso de reutilização ou uso diverso do inicialmente acordado. O uso está sujeito às restrições previstas na Lei de Arquivos (Lei nº 8.159/1991), na Lei de Direitos Autorais (Lei nº 9.610/1998), nos artigos 138 e 145 do Código Penal, e no artigo 5º, inciso X, da Constituição Federal, especialmente quanto à proteção da honra e imagem de terceiros. A pessoa física ou jurídica responsável assume integral responsabilidade civil e penal por eventuais danos decorrentes do uso das reproduções e informações, eximindo o Arquivo Público do Estado de São Paulo de qualquer responsabilidade. | O8: Trabalho feminino; religião e cárcere; oficinas de artesanato; ressocialização. | P8: Fotografia (Iconográfico) | Q8: Digitalização de fotografia em preto e branco (analógica original) | R8: ="Figura n – ["&B8&"]"&CHAR(10)&"Fonte: Arquivo do Estado de São Paulo, "&TEXT(D8,"yyyy")&"." -> Figura n – [Mulheres em atividade de artesanato em ambiente com elementos religiosos na Casa de Detenção (Carandiru), 1963] Fonte: Arquivo do Estado de São Paulo, 1955. | S8: ="ARQUIVO PÚBLICO DO ESTADO DE SÃO PAULO (Brasil). ["&B8&"]. "&G8&". "&TEXT(D8,"dd")&" "&LOWER(TEXT(D8,"mmm"))&" "&TEXT(D8,"yyyy")&". "&F8&". Disponível em: <link do dataverse>. Acesso em: 28 out. 2025." -> ARQUIVO PÚBLICO DO ESTADO DE SÃO PAULO (Brasil). [Mulheres em atividade de artesanato em ambiente com elementos religiosos na Casa de Detenção (Carandiru), 1963]. São Paulo, Brasil. 27 jan. 1955. Fotografia digitalizada; preto e branco; suporte em papel fotográfico. Disponível em: <link do dataverse>. Acesso em: 28 out. 2025. | T8: Estado de São Paulo - Penitenciárias e Presídios – Casa de Detenção do Carandiru Detentas do presídio do Carandiru são preparadas pela Madre do Divino Salvador para retornar ao convívio da sociedade. Recebem um pecúlio e os ensinamentos necessários para enfrentar a vida nas grandes cidades. Arq., 24/1/1963 – ACF
A9: =RIGHT(K9,3) -> 009 | B9: Pessoa com a mão estendida através de abertura em porta metálica prisional da Casa de Detenção (Carandiru) em 1979 | C9: Item | D9: 20641 | E9: Gerado pelo Dataverse | F9: Fotografia digitalizada; preto e branco; suporte em papel fotográfico | G9: São Paulo, Brasil | H9: Arquivo Público do Estado de São Paulo, Jornal Diários Associados | I9: Estado De São Paulo - Penitenciárias e Presídios - Casa de Detenção do Carandiru (Fotografias) | J9: Caixa: 3055 Folder: 5 | K9: =TEXTJOIN("", TRUE, Geral!B16:T16) -> BR-SPAPESP_DASP-PENITPRE-CSDTCARANDIRU_ICO-FOT-DGZ-MT0_3055-005-009 | L9: =$L$2 -> A Casa de Detenção de São Paulo, conhecida como Carandiru, foi formalmente criada em 1938 por decreto do interventor Adhemar de Barros, embora ainda instalada no edifício da Avenida Tiradentes. Sua implantação no bairro do Carandiru só se iniciou décadas depois, quando o governo estadual contratou, em 1951, o Escritório Técnico Ramos de Azevedo, Severo & Villares para projetar e conduzir a construção do novo complexo penitenciário em terreno contíguo à Penitenciária do Estado. As obras avançaram de forma modular, e o primeiro edifício concluído — o Pavilhão 2 — foi inaugurado em 1956, marcando a abertura parcial da chamada “Nova Casa de Detenção”. Ao longo dos anos seguintes, novos pavilhões foram sendo erguidos e inaugurados, compondo um conjunto arquitetônico que se consolidaria como um dos principais símbolos do sistema prisional paulista no século XX. Esta fotografia integra o fundo documental do grupo Diários Associados do Estado de São Paulo (DASP), custodiado pelo Arquivo Público do Estado de São Paulo (APESP), e registra aspectos desse prolongado processo de criação (1938), construção (a partir de 1951) e inauguração (a partir de 1956) da Casa de Detenção, conforme aponta a pesquisa de Maíra Rocha Machado, Bianca Tavolari e Maira Rosín (2025)[1]. | M9: A imagem em preto e branco retrata uma pessoa estendendo a mão através de uma pequena abertura retangular em uma porta metálica, da cela prisional. O gesto sugere tentativa de contato, comunicação ou expressão com o ambiente exterior. Registro associado à superlotação na Casa de Detenção (Carandiru) | N9: O acesso aos documentos deste acervo está condicionado ao compromisso de não repassá-los a terceiros, à obrigatoriedade de mencionar que os originais pertencem ao Arquivo Público do Estado de São Paulo, e à necessidade de novo Termo de Responsabilidade em caso de reutilização ou uso diverso do inicialmente acordado. O uso está sujeito às restrições previstas na Lei de Arquivos (Lei nº 8.159/1991), na Lei de Direitos Autorais (Lei nº 9.610/1998), nos artigos 138 e 145 do Código Penal, e no artigo 5º, inciso X, da Constituição Federal, especialmente quanto à proteção da honra e imagem de terceiros. A pessoa física ou jurídica responsável assume integral responsabilidade civil e penal por eventuais danos decorrentes do uso das reproduções e informações, eximindo o Arquivo Público do Estado de São Paulo de qualquer responsabilidade. | O9: Cela (Prisional); Precariedade estrutural; Carandiru; Superlotação. | P9: Fotografia (Iconográfico) | Q9: Digitalização de fotografia em preto e branco (analógica original) | R9: ="Figura n – ["&B9&"]"&CHAR(10)&"Fonte: Arquivo do Estado de São Paulo, "&TEXT(D9,"yyyy")&"." -> Figura n – [Pessoa com a mão estendida através de abertura em porta metálica prisional da Casa de Detenção (Carandiru) em 1979] Fonte: Arquivo do Estado de São Paulo, 1956. | S9: ="ARQUIVO PÚBLICO DO ESTADO DE SÃO PAULO (Brasil). ["&B9&"]. "&G9&". "&TEXT(D9,"dd")&" "&LOWER(TEXT(D9,"mmm"))&" "&TEXT(D9,"yyyy")&". "&F9&". Disponível em: <link do dataverse>. Acesso em: 28 out. 2025." -> ARQUIVO PÚBLICO DO ESTADO DE SÃO PAULO (Brasil). [Pessoa com a mão estendida através de abertura em porta metálica prisional da Casa de Detenção (Carandiru) em 1979]. São Paulo, Brasil. 05 jul. 1956. Fotografia digitalizada; preto e branco; suporte em papel fotográfico. Disponível em: <link do dataverse>. Acesso em: 28 out. 2025. | T9: Estado de São Paulo – Penitenciárias e Presídios – Casa de Detenção A Detenção está com superlotação e ameaça explodir. DN, 31/5/1979
A10: =RIGHT(K10,3) -> 010 | B10: Detentos com transtornos psiquiátricos em celas isoladas da Casa de Detenção da Avenida Tiradentes (1955) | C10: Item | D10: 20642 | E10: Gerado pelo Dataverse | F10: Fotografia digitalizada; preto e branco; suporte em papel fotográfico | G10: São Paulo, Brasil | H10: Arquivo Público do Estado de São Paulo, Jornal Diários Associados | I10: Estado De São Paulo - Penitenciárias e Presídios - Casa de Detenção do Carandiru (Fotografias) | J10: Caixa: 3055 Folder: 5 | K10: =TEXTJOIN("", TRUE, Geral!B18:T18) -> BR-SPAPESP_DASP-PENITPRE-CSDTCARANDIRU_ICO-FOT-DGZ-MT0_3055-005-010 | L10: =$L$2 -> A Casa de Detenção de São Paulo, conhecida como Carandiru, foi formalmente criada em 1938 por decreto do interventor Adhemar de Barros, embora ainda instalada no edifício da Avenida Tiradentes. Sua implantação no bairro do Carandiru só se iniciou décadas depois, quando o governo estadual contratou, em 1951, o Escritório Técnico Ramos de Azevedo, Severo & Villares para projetar e conduzir a construção do novo complexo penitenciário em terreno contíguo à Penitenciária do Estado. As obras avançaram de forma modular, e o primeiro edifício concluído — o Pavilhão 2 — foi inaugurado em 1956, marcando a abertura parcial da chamada “Nova Casa de Detenção”. Ao longo dos anos seguintes, novos pavilhões foram sendo erguidos e inaugurados, compondo um conjunto arquitetônico que se consolidaria como um dos principais símbolos do sistema prisional paulista no século XX. Esta fotografia integra o fundo documental do grupo Diários Associados do Estado de São Paulo (DASP), custodiado pelo Arquivo Público do Estado de São Paulo (APESP), e registra aspectos desse prolongado processo de criação (1938), construção (a partir de 1951) e inauguração (a partir de 1956) da Casa de Detenção, conforme aponta a pesquisa de Maíra Rocha Machado, Bianca Tavolari e Maira Rosín (2025)[1]. | M10: A fotografia em preto e branco registra um homem, detento da Casa de Detenção da Avenida Tiradentes (presídio anterior ao Carandiru), posicionado em uma área que o verso identifica como a "Isolada". O homem negro veste camisa de manga longa e encontra-se com os braços apoiados em uma superfície grade e as mãos entrelaçadas, olhando para cima. | N10: O acesso aos documentos deste acervo está condicionado ao compromisso de não repassá-los a terceiros, à obrigatoriedade de mencionar que os originais pertencem ao Arquivo Público do Estado de São Paulo, e à necessidade de novo Termo de Responsabilidade em caso de reutilização ou uso diverso do inicialmente acordado. O uso está sujeito às restrições previstas na Lei de Arquivos (Lei nº 8.159/1991), na Lei de Direitos Autorais (Lei nº 9.610/1998), nos artigos 138 e 145 do Código Penal, e no artigo 5º, inciso X, da Constituição Federal, especialmente quanto à proteção da honra e imagem de terceiros. A pessoa física ou jurídica responsável assume integral responsabilidade civil e penal por eventuais danos decorrentes do uso das reproduções e informações, eximindo o Arquivo Público do Estado de São Paulo de qualquer responsabilidade. | O10: Detento psiquiátrico; Cela isolada; Condições carcerárias; Assistência psiquiátrica; Presídio Tiradentes; Casa de Detenção (Avenida Tiradentes); Manicômio Judiciário; Superlotação; 1955; Fotojornalismo. | P10: Fotografia (Iconográfico) | Q10: Digitalização de fotografia em preto e branco (analógica original) | R10: ="Figura n – ["&B10&"]"&CHAR(10)&"Fonte: Arquivo do Estado de São Paulo, "&TEXT(D10,"yyyy")&"." -> Figura n – [Detentos com transtornos psiquiátricos em celas isoladas da Casa de Detenção da Avenida Tiradentes (1955)] Fonte: Arquivo do Estado de São Paulo, 1956. | S10: ="ARQUIVO PÚBLICO DO ESTADO DE SÃO PAULO (Brasil). ["&B10&"]. "&G10&". "&TEXT(D10,"dd")&" "&LOWER(TEXT(D10,"mmm"))&" "&TEXT(D10,"yyyy")&". "&F10&". Disponível em: <link do dataverse>. Acesso em: 28 out. 2025." -> ARQUIVO PÚBLICO DO ESTADO DE SÃO PAULO (Brasil). [Detentos com transtornos psiquiátricos em celas isoladas da Casa de Detenção da Avenida Tiradentes (1955)]. São Paulo, Brasil. 06 jul. 1956. Fotografia digitalizada; preto e branco; suporte em papel fotográfico. Disponível em: <link do dataverse>. Acesso em: 28 out. 2025. | T10: Estado de São Paulo – Penitenciárias e Presídios – Casa de Detenção da Avenida Tiradentes Na “Isolada” Detentos com transtornos mentais estão, irregularmente, jogados nas celas isoladas no presídio da Avenida Tiradentes. O Estado não toma nenhuma providência para removê-los para o Manicômio Judiciário. D.N., 2ª ed., 27/1/1955 – JL
A11: =RIGHT(K11,3) -> 011 | B11: Corredor de celas e circulação de pessoas no interior da Casa de Detenção (1978) | C11: Item | D11: 20710 | E11: Gerado pelo Dataverse | F11: Fotografia digitalizada; preto e branco; suporte em papel fotográfico | G11: São Paulo, Brasil | H11: Arquivo Público do Estado de São Paulo, Jornal Diários Associados | I11: Estado De São Paulo - Penitenciárias e Presídios - Casa de Detenção do Carandiru (Fotografias) | J11: Caixa: 3055 Folder: 5 | K11: =TEXTJOIN("", TRUE, Geral!B20:T20) -> BR-SPAPESP_DASP-PENITPRE-CSDTCARANDIRU_ICO-FOT-DGZ-MT0_3055-005-011 | L11: =$L$2 -> A Casa de Detenção de São Paulo, conhecida como Carandiru, foi formalmente criada em 1938 por decreto do interventor Adhemar de Barros, embora ainda instalada no edifício da Avenida Tiradentes. Sua implantação no bairro do Carandiru só se iniciou décadas depois, quando o governo estadual contratou, em 1951, o Escritório Técnico Ramos de Azevedo, Severo & Villares para projetar e conduzir a construção do novo complexo penitenciário em terreno contíguo à Penitenciária do Estado. As obras avançaram de forma modular, e o primeiro edifício concluído — o Pavilhão 2 — foi inaugurado em 1956, marcando a abertura parcial da chamada “Nova Casa de Detenção”. Ao longo dos anos seguintes, novos pavilhões foram sendo erguidos e inaugurados, compondo um conjunto arquitetônico que se consolidaria como um dos principais símbolos do sistema prisional paulista no século XX. Esta fotografia integra o fundo documental do grupo Diários Associados do Estado de São Paulo (DASP), custodiado pelo Arquivo Público do Estado de São Paulo (APESP), e registra aspectos desse prolongado processo de criação (1938), construção (a partir de 1951) e inauguração (a partir de 1956) da Casa de Detenção, conforme aponta a pesquisa de Maíra Rocha Machado, Bianca Tavolari e Maira Rosín (2025)[1]. | M11: Fotografia em preto e branco de corredor com portas metálicas dispostas em ambos os lados. Duas pessoas caminham pelo corredor com as costas voltadas para a câmera. Outras figuras são visíveis ao fundo. As portas possuem pequenas janelas e mecanismos de travamento. Registro de circulação em espaço prisional. | N11: O acesso aos documentos deste acervo está condicionado ao compromisso de não repassá-los a terceiros, à obrigatoriedade de mencionar que os originais pertencem ao Arquivo Público do Estado de São Paulo, e à necessidade de novo Termo de Responsabilidade em caso de reutilização ou uso diverso do inicialmente acordado. O uso está sujeito às restrições previstas na Lei de Arquivos (Lei nº 8.159/1991), na Lei de Direitos Autorais (Lei nº 9.610/1998), nos artigos 138 e 145 do Código Penal, e no artigo 5º, inciso X, da Constituição Federal, especialmente quanto à proteção da honra e imagem de terceiros. A pessoa física ou jurídica responsável assume integral responsabilidade civil e penal por eventuais danos decorrentes do uso das reproduções e informações, eximindo o Arquivo Público do Estado de São Paulo de qualquer responsabilidade. | O11: Sistema prisional; Arquitetura prisional; Casa de Detenção (Carandiru); Carandiru; Fotografia documental. | P11: Fotografia (Iconográfico) | Q11: Digitalização de fotografia em preto e branco (analógica original) | R11: ="Figura n – ["&B11&"]"&CHAR(10)&"Fonte: Arquivo do Estado de São Paulo, "&TEXT(D11,"yyyy")&"." -> Figura n – [Corredor de celas e circulação de pessoas no interior da Casa de Detenção (1978)] Fonte: Arquivo do Estado de São Paulo, 1956. | S11: ="ARQUIVO PÚBLICO DO ESTADO DE SÃO PAULO (Brasil). ["&B11&"]. "&G11&". "&TEXT(D11,"dd")&" "&LOWER(TEXT(D11,"mmm"))&" "&TEXT(D11,"yyyy")&". "&F11&". Disponível em: <link do dataverse>. Acesso em: 28 out. 2025." -> ARQUIVO PÚBLICO DO ESTADO DE SÃO PAULO (Brasil). [Corredor de celas e circulação de pessoas no interior da Casa de Detenção (1978)]. São Paulo, Brasil. 12 set. 1956. Fotografia digitalizada; preto e branco; suporte em papel fotográfico. Disponível em: <link do dataverse>. Acesso em: 28 out. 2025. | T11: Estado de São Paulo – Penitenciárias e Presídios – Casa de Detenção DN, 17/2/1978
A12: =RIGHT(K12,3) -> 012 | B12: Visita de familiares após motim na Casa de Detenção do Carandiru (1964) | C12: Item | D12: 20710 | E12: Gerado pelo Dataverse | F12: Fotografia digitalizada; preto e branco; suporte em papel fotográfico | G12: São Paulo, Brasil | H12: Arquivo Público do Estado de São Paulo, Jornal Diários Associados | I12: Estado De São Paulo - Penitenciárias e Presídios - Casa de Detenção do Carandiru (Fotografias) | J12: Caixa: 3055 Folder: 5 | K12: =TEXTJOIN("", TRUE, Geral!B22:T22) -> BR-SPAPESP_DASP-PENITPRE-CSDTCARANDIRU_ICO-FOT-DGZ-MT0_3055-005-012 | L12: =$L$2 -> A Casa de Detenção de São Paulo, conhecida como Carandiru, foi formalmente criada em 1938 por decreto do interventor Adhemar de Barros, embora ainda instalada no edifício da Avenida Tiradentes. Sua implantação no bairro do Carandiru só se iniciou décadas depois, quando o governo estadual contratou, em 1951, o Escritório Técnico Ramos de Azevedo, Severo & Villares para projetar e conduzir a construção do novo complexo penitenciário em terreno contíguo à Penitenciária do Estado. As obras avançaram de forma modular, e o primeiro edifício concluído — o Pavilhão 2 — foi inaugurado em 1956, marcando a abertura parcial da chamada “Nova Casa de Detenção”. Ao longo dos anos seguintes, novos pavilhões foram sendo erguidos e inaugurados, compondo um conjunto arquitetônico que se consolidaria como um dos principais símbolos do sistema prisional paulista no século XX. Esta fotografia integra o fundo documental do grupo Diários Associados do Estado de São Paulo (DASP), custodiado pelo Arquivo Público do Estado de São Paulo (APESP), e registra aspectos desse prolongado processo de criação (1938), construção (a partir de 1951) e inauguração (a partir de 1956) da Casa de Detenção, conforme aponta a pesquisa de Maíra Rocha Machado, Bianca Tavolari e Maira Rosín (2025)[1]. | M12: A fotografia em preto e branco registra o momento de visita familiar em frente ao portão de acesso da Casa de Detenção do Carandiru. O primeiro plano exibe dois grupos de familiares: à esquerda, uma mulher e duas crianças, e, à direita, outra mulher e um homem. O verso da fotografia contextualiza este momento como um período de alta tensão em 17 de agosto de 1964, seguindo um motim causado pelo "Regime do Terror", no qual os familiares foram mantidos em "afflictiva espera" de notícias ou permissão para visitar. O registro, portanto, documenta a dimensão afetiva da rotina prisional em um cenário de crise e repressão institucional. | N12: O acesso aos documentos deste acervo está condicionado ao compromisso de não repassá-los a terceiros, à obrigatoriedade de mencionar que os originais pertencem ao Arquivo Público do Estado de São Paulo, e à necessidade de novo Termo de Responsabilidade em caso de reutilização ou uso diverso do inicialmente acordado. O uso está sujeito às restrições previstas na Lei de Arquivos (Lei nº 8.159/1991), na Lei de Direitos Autorais (Lei nº 9.610/1998), nos artigos 138 e 145 do Código Penal, e no artigo 5º, inciso X, da Constituição Federal, especialmente quanto à proteção da honra e imagem de terceiros. A pessoa física ou jurídica responsável assume integral responsabilidade civil e penal por eventuais danos decorrentes do uso das reproduções e informações, eximindo o Arquivo Público do Estado de São Paulo de qualquer responsabilidade. | O12: Visita familiar; Motim; Regime do terror; Crise prisional; Tensão; Agente penitenciário; Grades (prisão); Família de detento; Carandiru; Casa de Detenção; 1964; Fotojornalismo. | P12: Fotografia (Iconográfico) | Q12: Digitalização de fotografia em preto e branco (analógica original) | R12: ="Figura n – ["&B12&"]"&CHAR(10)&"Fonte: Arquivo do Estado de São Paulo, "&TEXT(D12,"yyyy")&"." -> Figura n – [Visita de familiares após motim na Casa de Detenção do Carandiru (1964)] Fonte: Arquivo do Estado de São Paulo, 1956. | S12: ="ARQUIVO PÚBLICO DO ESTADO DE SÃO PAULO (Brasil). ["&B12&"]. "&G12&". "&TEXT(D12,"dd")&" "&LOWER(TEXT(D12,"mmm"))&" "&TEXT(D12,"yyyy")&". "&F12&". Disponível em: <link do dataverse>. Acesso em: 28 out. 2025." -> ARQUIVO PÚBLICO DO ESTADO DE SÃO PAULO (Brasil). [Visita de familiares após motim na Casa de Detenção do Carandiru (1964)]. São Paulo, Brasil. 12 set. 1956. Fotografia digitalizada; preto e branco; suporte em papel fotográfico. Disponível em: <link do dataverse>. Acesso em: 28 out. 2025. | T12: Estado de São Paulo – Penitenciárias e Presídios – Casa de Detenção do Carandiru Detenção: regime do terror provocou motim [Texto em pequeno retângulo, possivelmente um recorte de legenda ou matéria] Cenas dramáticas foram registradas na Casa de Detenção, defronte ao portão principal. Familiares de presos ficaram horas e horas em aflitiva espera, até que a direção do presídio permitisse a visitação. DN, 2ª ed., 17/8/1964 – CJS Miliciano comandava a tortura de presos na Casa de Detenção DN, 2ª ed., 18/8/1964 – CJS Cadeia vai abrir suas portas DN, 1ª ed., 1/9/1971 – DEC
A13: =RIGHT(K13,3) -> 014 | B13: Cela individual da Casa de Detenção do Carandiru | C13: Item | D13: 20710 | E13: Gerado pelo Dataverse | F13: Fotografia digitalizada; preto e branco; suporte em papel fotográfico | G13: São Paulo, Brasil | H13: Arquivo Público do Estado de São Paulo, Jornal Diários Associados | I13: Estado De São Paulo - Penitenciárias e Presídios - Casa de Detenção do Carandiru (Fotografias) | J13: Caixa: 3055 Folder: 5 | K13: =TEXTJOIN("", TRUE, Geral!B24:T24) -> BR-SPAPESP_DASP-PENITPRE-CSDTCARANDIRU_ICO-FOT-DGZ-MT0_3055-005-014 | L13: =$L$2 -> A Casa de Detenção de São Paulo, conhecida como Carandiru, foi formalmente criada em 1938 por decreto do interventor Adhemar de Barros, embora ainda instalada no edifício da Avenida Tiradentes. Sua implantação no bairro do Carandiru só se iniciou décadas depois, quando o governo estadual contratou, em 1951, o Escritório Técnico Ramos de Azevedo, Severo & Villares para projetar e conduzir a construção do novo complexo penitenciário em terreno contíguo à Penitenciária do Estado. As obras avançaram de forma modular, e o primeiro edifício concluído — o Pavilhão 2 — foi inaugurado em 1956, marcando a abertura parcial da chamada “Nova Casa de Detenção”. Ao longo dos anos seguintes, novos pavilhões foram sendo erguidos e inaugurados, compondo um conjunto arquitetônico que se consolidaria como um dos principais símbolos do sistema prisional paulista no século XX. Esta fotografia integra o fundo documental do grupo Diários Associados do Estado de São Paulo (DASP), custodiado pelo Arquivo Público do Estado de São Paulo (APESP), e registra aspectos desse prolongado processo de criação (1938), construção (a partir de 1951) e inauguração (a partir de 1956) da Casa de Detenção, conforme aponta a pesquisa de Maíra Rocha Machado, Bianca Tavolari e Maira Rosín (2025)[1]. | M13: A fotografia em preto e branco registra o interior de uma cela individual da Casa de Detenção do Carandiru. O ambiente, que o verso descreve como "sombrio", revela a mobília básica, incluindo uma cama simples e poucos objetos pessoais, além de uma janela de inspeção ou uma abertura gradeada. O verso da fotografia (data: 07/08/1965) estabelece um contexto de reforma prisional, indicando que as celas individuais estavam sendo substituídas por outra estrutura para cinco ou seis detentos. O registro é, portanto, um documento visual da estrutura original da prisão em um momento em que a superlotação já forçava a adaptação para celas coletivas. | N13: O acesso aos documentos deste acervo está condicionado ao compromisso de não repassá-los a terceiros, à obrigatoriedade de mencionar que os originais pertencem ao Arquivo Público do Estado de São Paulo, e à necessidade de novo Termo de Responsabilidade em caso de reutilização ou uso diverso do inicialmente acordado. O uso está sujeito às restrições previstas na Lei de Arquivos (Lei nº 8.159/1991), na Lei de Direitos Autorais (Lei nº 9.610/1998), nos artigos 138 e 145 do Código Penal, e no artigo 5º, inciso X, da Constituição Federal, especialmente quanto à proteção da honra e imagem de terceiros. A pessoa física ou jurídica responsável assume integral responsabilidade civil e penal por eventuais danos decorrentes do uso das reproduções e informações, eximindo o Arquivo Público do Estado de São Paulo de qualquer responsabilidade. | O13: Cela individual; Superlotação (crítica); Reforma prisional; Estrutura original; Carandiru; Presídio do Hipódromo (fechamento); Xadrezes-apartamentos; 1965; Condições carcerárias. | P13: Fotografia (Iconográfico) | Q13: Digitalização de fotografia em preto e branco (analógica original) | R13: ="Figura n – ["&B13&"]"&CHAR(10)&"Fonte: Arquivo do Estado de São Paulo, "&TEXT(D13,"yyyy")&"." -> Figura n – [Cela individual da Casa de Detenção do Carandiru] Fonte: Arquivo do Estado de São Paulo, 1956. | S13: ="ARQUIVO PÚBLICO DO ESTADO DE SÃO PAULO (Brasil). ["&B13&"]. "&G13&". "&TEXT(D13,"dd")&" "&LOWER(TEXT(D13,"mmm"))&" "&TEXT(D13,"yyyy")&". "&F13&". Disponível em: <link do dataverse>. Acesso em: 28 out. 2025." -> ARQUIVO PÚBLICO DO ESTADO DE SÃO PAULO (Brasil). [Cela individual da Casa de Detenção do Carandiru]. São Paulo, Brasil. 12 set. 1956. Fotografia digitalizada; preto e branco; suporte em papel fotográfico. Disponível em: <link do dataverse>. Acesso em: 28 out. 2025. | T13: Estado de São Paulo – Penitenciárias e Presídios – Casa de Detenção do Carandiru Será fechado em 15 dias o Presídio do Hipódromo [Texto em pequeno retângulo, recorte de matéria] As sombrias celas individuais da Casa de Detenção, onde os homens ficam enjaulados como feras, estão desaparecendo para dar lugar a xadrezes-apartamentos para cinco ou seis detentos. DN, 1ª ed., 7/8/1965
A14: =RIGHT(K14,3) -> 013 | B14: Trabalho de pessoas em situação de privação de liberdade na construção da nova Casa de Detenção do Carandiru (1952) | C14: Item | D14: 20710 | E14: Gerado pelo Dataverse | F14: Fotografia digitalizada; preto e branco; suporte em papel fotográfico | G14: São Paulo, Brasil | H14: Arquivo Público do Estado de São Paulo, Jornal Diários Associados | I14: Estado De São Paulo - Penitenciárias e Presídios - Casa de Detenção do Carandiru (Fotografias) | J14: Caixa: 3055 Folder: 5 | K14: =TEXTJOIN("", TRUE, Geral!B26:T26) -> BR-SPAPESP_DASP-PENITPRE-CSDTCARANDIRU_ICO-FOT-DGZ-MT0_3055-005-013 | L14: =$L$2 -> A Casa de Detenção de São Paulo, conhecida como Carandiru, foi formalmente criada em 1938 por decreto do interventor Adhemar de Barros, embora ainda instalada no edifício da Avenida Tiradentes. Sua implantação no bairro do Carandiru só se iniciou décadas depois, quando o governo estadual contratou, em 1951, o Escritório Técnico Ramos de Azevedo, Severo & Villares para projetar e conduzir a construção do novo complexo penitenciário em terreno contíguo à Penitenciária do Estado. As obras avançaram de forma modular, e o primeiro edifício concluído — o Pavilhão 2 — foi inaugurado em 1956, marcando a abertura parcial da chamada “Nova Casa de Detenção”. Ao longo dos anos seguintes, novos pavilhões foram sendo erguidos e inaugurados, compondo um conjunto arquitetônico que se consolidaria como um dos principais símbolos do sistema prisional paulista no século XX. Esta fotografia integra o fundo documental do grupo Diários Associados do Estado de São Paulo (DASP), custodiado pelo Arquivo Público do Estado de São Paulo (APESP), e registra aspectos desse prolongado processo de criação (1938), construção (a partir de 1951) e inauguração (a partir de 1956) da Casa de Detenção, conforme aponta a pesquisa de Maíra Rocha Machado, Bianca Tavolari e Maira Rosín (2025)[1]. | M14: A fotografia em preto e branco documenta a realização de trabalho externo em um terreno irregular e com terra revolvida, o que o verso identifica como a construção da nova Casa de Detenção do Carandiru. Em primeiro plano, dois detentos em uniformes escuros de trabalho e com numeração grande nas costas estão curvados, trabalhando diretamente no solo, sem o uso visível de ferramentas pesadas. Seus uniformes e a numeração (é parcialmente visível) denotam a identificação e o controle institucional dos internos. Ao fundo, um pequeno grupo de pessoas supervisiona a atividade; um dos homens usa um chapéu, e o cenário inclui vegetação, postes e um muro/edificação. O registro, datado de 14 de novembro de 1952, documenta o uso de mão de obra carcerária no projeto de expansão do sistema prisional. | N14: O acesso aos documentos deste acervo está condicionado ao compromisso de não repassá-los a terceiros, à obrigatoriedade de mencionar que os originais pertencem ao Arquivo Público do Estado de São Paulo, e à necessidade de novo Termo de Responsabilidade em caso de reutilização ou uso diverso do inicialmente acordado. O uso está sujeito às restrições previstas na Lei de Arquivos (Lei nº 8.159/1991), na Lei de Direitos Autorais (Lei nº 9.610/1998), nos artigos 138 e 145 do Código Penal, e no artigo 5º, inciso X, da Constituição Federal, especialmente quanto à proteção da honra e imagem de terceiros. A pessoa física ou jurídica responsável assume integral responsabilidade civil e penal por eventuais danos decorrentes do uso das reproduções e informações, eximindo o Arquivo Público do Estado de São Paulo de qualquer responsabilidade. | O14: Trabalho prisional; Construção (nova Casa de Detenção); Mão de obra carcerária; Uniforme (preso); Carandiru; Obra (penitenciária); 1952; Identificação numérica; Ressocialização. | P14: Fotografia (Iconográfico) | Q14: Digitalização de fotografia em preto e branco (analógica original) | R14: ="Figura n – ["&B14&"]"&CHAR(10)&"Fonte: Arquivo do Estado de São Paulo, "&TEXT(D14,"yyyy")&"." -> Figura n – [Trabalho de pessoas em situação de privação de liberdade na construção da nova Casa de Detenção do Carandiru (1952)] Fonte: Arquivo do Estado de São Paulo, 1956. | S14: ="ARQUIVO PÚBLICO DO ESTADO DE SÃO PAULO (Brasil). ["&B14&"]. "&G14&". "&TEXT(D14,"dd")&" "&LOWER(TEXT(D14,"mmm"))&" "&TEXT(D14,"yyyy")&". "&F14&". Disponível em: <link do dataverse>. Acesso em: 28 out. 2025." -> ARQUIVO PÚBLICO DO ESTADO DE SÃO PAULO (Brasil). [Trabalho de pessoas em situação de privação de liberdade na construção da nova Casa de Detenção do Carandiru (1952)]. São Paulo, Brasil. 12 set. 1956. Fotografia digitalizada; preto e branco; suporte em papel fotográfico. Disponível em: <link do dataverse>. Acesso em: 28 out. 2025. | T14: Estado de São Paulo – Penitenciária e Presídios – Casa de Detenção do Carandiru Na foto, grupo dos 25 sentenciados que foram autorizados a trabalhar na construção da nova Casa de Detenção, com o amparo das leis vigentes no país. DN, 2ª ed., 14/11/1952 – MMG
A15: =RIGHT(K15,3) -> 015 | B15: Mulheres em espera após motim no Carandiru (1964) | C15: Item | D15: 20710 | E15: Gerado pelo Dataverse | F15: Fotografia digitalizada; preto e branco; suporte em papel fotográfico | G15: São Paulo, Brasil | H15: Arquivo Público do Estado de São Paulo, Jornal Diários Associados | I15: Estado De São Paulo - Penitenciárias e Presídios - Casa de Detenção do Carandiru (Fotografias) | J15: Caixa: 3055 Folder: 5 | K15: =TEXTJOIN("", TRUE, Geral!B28:T28) -> BR-SPAPESP_DASP-PENITPRE-CSDTCARANDIRU_ICO-FOT-DGZ-MT0_3055-005-015 | L15: =$L$2 -> A Casa de Detenção de São Paulo, conhecida como Carandiru, foi formalmente criada em 1938 por decreto do interventor Adhemar de Barros, embora ainda instalada no edifício da Avenida Tiradentes. Sua implantação no bairro do Carandiru só se iniciou décadas depois, quando o governo estadual contratou, em 1951, o Escritório Técnico Ramos de Azevedo, Severo & Villares para projetar e conduzir a construção do novo complexo penitenciário em terreno contíguo à Penitenciária do Estado. As obras avançaram de forma modular, e o primeiro edifício concluído — o Pavilhão 2 — foi inaugurado em 1956, marcando a abertura parcial da chamada “Nova Casa de Detenção”. Ao longo dos anos seguintes, novos pavilhões foram sendo erguidos e inaugurados, compondo um conjunto arquitetônico que se consolidaria como um dos principais símbolos do sistema prisional paulista no século XX. Esta fotografia integra o fundo documental do grupo Diários Associados do Estado de São Paulo (DASP), custodiado pelo Arquivo Público do Estado de São Paulo (APESP), e registra aspectos desse prolongado processo de criação (1938), construção (a partir de 1951) e inauguração (a partir de 1956) da Casa de Detenção, conforme aponta a pesquisa de Maíra Rocha Machado, Bianca Tavolari e Maira Rosín (2025)[1]. | M15: A fotografia em preto e branco registra um momento tenso de acesso e controle de visita em frente a um portão metálico da Casa de Detenção. Em primeiro plano, um militar/policial em uniforme de serviço e capacete, com as mãos na cintura, vigia a entrada. Três mulheres estão na porta: duas delas de costas, interagindo com dois homens que estão no interior do prédio (um de camiseta e outro de óculos). O verso da fotografia contextualiza esta cena como um evento ligado ao "Regime de Terror" e a um motim ocorrido em 17 de agosto de 1964. A descrição original menciona a "dúvida, intranquilidade e temor" que levaram familiares (mulheres) às portas da Casa de Detenção. O registro, portanto, ilustra a entrada ou interação inicial de familiares em um cenário de crise institucional e repressão, sublinhando o rigoroso controle policial/militar sobre o acesso e a informação. | N15: O acesso aos documentos deste acervo está condicionado ao compromisso de não repassá-los a terceiros, à obrigatoriedade de mencionar que os originais pertencem ao Arquivo Público do Estado de São Paulo, e à necessidade de novo Termo de Responsabilidade em caso de reutilização ou uso diverso do inicialmente acordado. O uso está sujeito às restrições previstas na Lei de Arquivos (Lei nº 8.159/1991), na Lei de Direitos Autorais (Lei nº 9.610/1998), nos artigos 138 e 145 do Código Penal, e no artigo 5º, inciso X, da Constituição Federal, especialmente quanto à proteção da honra e imagem de terceiros. A pessoa física ou jurídica responsável assume integral responsabilidade civil e penal por eventuais danos decorrentes do uso das reproduções e informações, eximindo o Arquivo Público do Estado de São Paulo de qualquer responsabilidade. | O15: Visita familiar (tensa); Motim (consequências); Polícia Militar (vigilância); Crise prisional; Controle de acesso; Mulheres e familiares; Carandiru; Regime de Terror; 1964; Fotojornalismo. | P15: Fotografia (Iconográfico) | Q15: Digitalização de fotografia em preto e branco (analógica original) | R15: ="Figura n – ["&B15&"]"&CHAR(10)&"Fonte: Arquivo do Estado de São Paulo, "&TEXT(D15,"yyyy")&"." -> Figura n – [Mulheres em espera após motim no Carandiru (1964)] Fonte: Arquivo do Estado de São Paulo, 1956. | S15: ="ARQUIVO PÚBLICO DO ESTADO DE SÃO PAULO (Brasil). ["&B15&"]. "&G15&". "&TEXT(D15,"dd")&" "&LOWER(TEXT(D15,"mmm"))&" "&TEXT(D15,"yyyy")&". "&F15&". Disponível em: <link do dataverse>. Acesso em: 28 out. 2025." -> ARQUIVO PÚBLICO DO ESTADO DE SÃO PAULO (Brasil). [Mulheres em espera após motim no Carandiru (1964)]. São Paulo, Brasil. 12 set. 1956. Fotografia digitalizada; preto e branco; suporte em papel fotográfico. Disponível em: <link do dataverse>. Acesso em: 28 out. 2025. | T15: Estado de São Paulo – Penitenciárias e Presídios – Casa de Detenção do Carandiru Detenção: regime de terror provocou motim Dúvida, intranquilidade e temor levaram essa gente às portas da Casa de Detenção, cuja barreira foi vencida pela resignação. A proibição caiu e todos puderam entrar no cenário da rebelião. Ver. DN, 2ª ed., 17/8/1964 – DMC
A16: =RIGHT(K16,3) -> 016 | B16: Familiares (mulheres e criança) em espera tensa no dia do motim do Carandiru (1964) | C16: Item | D16: 20710 | E16: Gerado pelo Dataverse | F16: Fotografia digitalizada; sépia; suporte em papel fotográfico | G16: São Paulo, Brasil | H16: Arquivo Público do Estado de São Paulo, Jornal Diários Associados | I16: Estado De São Paulo - Penitenciárias e Presídios - Casa de Detenção do Carandiru (Fotografias) | J16: Caixa: 3055 Folder: 5 | K16: =TEXTJOIN("", TRUE, Geral!B30:T30) -> BR-SPAPESP_DASP-PENITPRE-CSDTCARANDIRU_ICO-FOT-DGZ-MT0_3055-005-016 | L16: =$L$2 -> A Casa de Detenção de São Paulo, conhecida como Carandiru, foi formalmente criada em 1938 por decreto do interventor Adhemar de Barros, embora ainda instalada no edifício da Avenida Tiradentes. Sua implantação no bairro do Carandiru só se iniciou décadas depois, quando o governo estadual contratou, em 1951, o Escritório Técnico Ramos de Azevedo, Severo & Villares para projetar e conduzir a construção do novo complexo penitenciário em terreno contíguo à Penitenciária do Estado. As obras avançaram de forma modular, e o primeiro edifício concluído — o Pavilhão 2 — foi inaugurado em 1956, marcando a abertura parcial da chamada “Nova Casa de Detenção”. Ao longo dos anos seguintes, novos pavilhões foram sendo erguidos e inaugurados, compondo um conjunto arquitetônico que se consolidaria como um dos principais símbolos do sistema prisional paulista no século XX. Esta fotografia integra o fundo documental do grupo Diários Associados do Estado de São Paulo (DASP), custodiado pelo Arquivo Público do Estado de São Paulo (APESP), e registra aspectos desse prolongado processo de criação (1938), construção (a partir de 1951) e inauguração (a partir de 1956) da Casa de Detenção, conforme aponta a pesquisa de Maíra Rocha Machado, Bianca Tavolari e Maira Rosín (2025)[1]. | M16: A fotografia em preto e branco registra um grupo de familiares de detentos aguardando em uma área externa, sob a cobertura da portaria da Casa de Detenção. Em primeiro plano, o grupo é composto por uma mulher idosa, duas mulheres jovens (uma sentada, outra em pé com os braços cruzados) e uma criança pequena, olhando diretamente para a frente. O verso da fotografia contextualiza esta cena como um evento de crise, ligado ao motim e ao "Regime de Terror" ocorrido em 17 de agosto de 1964. A legenda original descreve a "dúvida, intranquilidade e temor" que levaram "essa gente" às portas da prisão. O registro ilustra a dimensão humana e o sofrimento da espera dos familiares durante uma das crises da Casa de Detenção. | N16: O acesso aos documentos deste acervo está condicionado ao compromisso de não repassá-los a terceiros, à obrigatoriedade de mencionar que os originais pertencem ao Arquivo Público do Estado de São Paulo, e à necessidade de novo Termo de Responsabilidade em caso de reutilização ou uso diverso do inicialmente acordado. O uso está sujeito às restrições previstas na Lei de Arquivos (Lei nº 8.159/1991), na Lei de Direitos Autorais (Lei nº 9.610/1998), nos artigos 138 e 145 do Código Penal, e no artigo 5º, inciso X, da Constituição Federal, especialmente quanto à proteção da honra e imagem de terceiros. A pessoa física ou jurídica responsável assume integral responsabilidade civil e penal por eventuais danos decorrentes do uso das reproduções e informações, eximindo o Arquivo Público do Estado de São Paulo de qualquer responsabilidade. | O16: Visita familiar (tensa); Espera; Mulheres (família de preso); Criança; Motim (consequências); Crise prisional; Carandiru; Regime de Terror; 1964; Fotojornalismo. | P16: Fotografia (Iconográfico) | Q16: Digitalização de fotografia em sépia (analógica original) | R16: ="Figura n – ["&B16&"]"&CHAR(10)&"Fonte: Arquivo do Estado de São Paulo, "&TEXT(D16,"yyyy")&"." -> Figura n – [Familiares (mulheres e criança) em espera tensa no dia do motim do Carandiru (1964)] Fonte: Arquivo do Estado de São Paulo, 1956. | S16: ="ARQUIVO PÚBLICO DO ESTADO DE SÃO PAULO (Brasil). ["&B16&"]. "&G16&". "&TEXT(D16,"dd")&" "&LOWER(TEXT(D16,"mmm"))&" "&TEXT(D16,"yyyy")&". "&F16&". Disponível em: <link do dataverse>. Acesso em: 28 out. 2025." -> ARQUIVO PÚBLICO DO ESTADO DE SÃO PAULO (Brasil). [Familiares (mulheres e criança) em espera tensa no dia do motim do Carandiru (1964)]. São Paulo, Brasil. 12 set. 1956. Fotografia digitalizada; sépia; suporte em papel fotográfico. Disponível em: <link do dataverse>. Acesso em: 28 out. 2025. | T16: Estado de São Paulo – Penitenciárias e Presídios – Casa de Detenção do Carandiru Detenção: regime de terror provocou motim Dúvida, intranquilidade e temor levaram essa gente às portas da Casa de Detenção, cuja barreira foi vencida pela resignação. A proibição caiu e todos puderam entrar no cenário da rebelião. Ver. DN, 2ª ed., 17/8/1964 – DMC
A17: =RIGHT(K17,3) -> 017 | B17: Soldados da Força Pública em formação durante a ocupação militar do Carandiru (1964) | C17: Item | D17: 20710 | E17: Gerado pelo Dataverse | F17: Fotografia digitalizada; preto e branco; suporte em papel fotográfico | G17: São Paulo, Brasil | H17: Arquivo Público do Estado de São Paulo, Jornal Diários Associados | I17: Estado De São Paulo - Penitenciárias e Presídios - Casa de Detenção do Carandiru (Fotografias) | J17: Caixa: 3055 Folder: 5 | K17: =TEXTJOIN("", TRUE, Geral!B32:T32) -> BR-SPAPESP_DASP-PENITPRE-CSDTCARANDIRU_ICO-FOT-DGZ-MT0_3055-005-017 | L17: =$L$2 -> A Casa de Detenção de São Paulo, conhecida como Carandiru, foi formalmente criada em 1938 por decreto do interventor Adhemar de Barros, embora ainda instalada no edifício da Avenida Tiradentes. Sua implantação no bairro do Carandiru só se iniciou décadas depois, quando o governo estadual contratou, em 1951, o Escritório Técnico Ramos de Azevedo, Severo & Villares para projetar e conduzir a construção do novo complexo penitenciário em terreno contíguo à Penitenciária do Estado. As obras avançaram de forma modular, e o primeiro edifício concluído — o Pavilhão 2 — foi inaugurado em 1956, marcando a abertura parcial da chamada “Nova Casa de Detenção”. Ao longo dos anos seguintes, novos pavilhões foram sendo erguidos e inaugurados, compondo um conjunto arquitetônico que se consolidaria como um dos principais símbolos do sistema prisional paulista no século XX. Esta fotografia integra o fundo documental do grupo Diários Associados do Estado de São Paulo (DASP), custodiado pelo Arquivo Público do Estado de São Paulo (APESP), e registra aspectos desse prolongado processo de criação (1938), construção (a partir de 1951) e inauguração (a partir de 1956) da Casa de Detenção, conforme aponta a pesquisa de Maíra Rocha Machado, Bianca Tavolari e Maira Rosín (2025)[1]. | M17: A fotografia em preto e branco registra um momento interno de formação e presença ostensiva de militares na Casa de Detenção. O ambiente, com bandeiras e flâmulas decorativas nas paredes (incluindo uma com "Ypiranga" e "Julho"), sugere um salão de reuniões ou uma sala de instrução da própria instituição. Um grande grupo de soldados da Força Pública está em formação, usando uniformes de combate, capacetes (com as letras "F P" ou "FP" visíveis, indicando Força Pública ou Força Policial) e portando cassetetes ou coldres. A cena é observada por homens em trajes civis (ternos), provavelmente autoridades. O verso da fotografia contextualiza este evento como a "OCUPAÇÃO MILITAR" da prisão por mais de 200 soldados em 4 de julho de 1964, após um motim inédito iniciado pelos próprios guardas do presídio contra o diretor. A imagem, portanto, documenta a intervenção militar na Casa de Detenção para restabelecer a ordem após uma grave crise interna de gestão e segurança. | N17: O acesso aos documentos deste acervo está condicionado ao compromisso de não repassá-los a terceiros, à obrigatoriedade de mencionar que os originais pertencem ao Arquivo Público do Estado de São Paulo, e à necessidade de novo Termo de Responsabilidade em caso de reutilização ou uso diverso do inicialmente acordado. O uso está sujeito às restrições previstas na Lei de Arquivos (Lei nº 8.159/1991), na Lei de Direitos Autorais (Lei nº 9.610/1998), nos artigos 138 e 145 do Código Penal, e no artigo 5º, inciso X, da Constituição Federal, especialmente quanto à proteção da honra e imagem de terceiros. A pessoa física ou jurídica responsável assume integral responsabilidade civil e penal por eventuais danos decorrentes do uso das reproduções e informações, eximindo o Arquivo Público do Estado de São Paulo de qualquer responsabilidade. | O17: Ocupação militar; Força Pública; Crise prisional; Motim de guardas; Intervenção estadual; Soldados em formação; Carandiru; Regime de terror; Autoridades (visita); 1964. | P17: Fotografia (Iconográfico) | Q17: Digitalização de fotografia em preto e branco (analógica original) | R17: ="Figura n – ["&B17&"]"&CHAR(10)&"Fonte: Arquivo do Estado de São Paulo, "&TEXT(D17,"yyyy")&"." -> Figura n – [Soldados da Força Pública em formação durante a ocupação militar do Carandiru (1964)] Fonte: Arquivo do Estado de São Paulo, 1956. | S17: ="ARQUIVO PÚBLICO DO ESTADO DE SÃO PAULO (Brasil). ["&B17&"]. "&G17&". "&TEXT(D17,"dd")&" "&LOWER(TEXT(D17,"mmm"))&" "&TEXT(D17,"yyyy")&". "&F17&". Disponível em: <link do dataverse>. Acesso em: 28 out. 2025." -> ARQUIVO PÚBLICO DO ESTADO DE SÃO PAULO (Brasil). [Soldados da Força Pública em formação durante a ocupação militar do Carandiru (1964)]. São Paulo, Brasil. 12 set. 1956. Fotografia digitalizada; preto e branco; suporte em papel fotográfico. Disponível em: <link do dataverse>. Acesso em: 28 out. 2025. | T17: Estado de São Paulo – Penitenciárias e Presídios – Casa de Detenção do Carandiru Motim sangrento demite o diretor Ocupação militar – Mais de 200 soldados da Força Pública do Estado de São Paulo ocuparam ontem a Casa de Detenção do Carandiru, em consequência de um motim iniciado por um grupo de guardas-presídios, que se rebelaram contra o diretor daquele presídio. DN, Ed. ún., 4/7/1964 – WJP
A18: =RIGHT(K18,3) -> 018 | B18: Procedimento de ingresso ou movimentação na Casa de Detenção no dia da chegada de novos presos (1979) | C18: Item | D18: 20710 | E18: Gerado pelo Dataverse | F18: Fotografia digitalizada; preto e branco; suporte em papel fotográfico | G18: São Paulo, Brasil | H18: Arquivo Público do Estado de São Paulo, Jornal Diários Associados | I18: Estado De São Paulo - Penitenciárias e Presídios - Casa de Detenção do Carandiru (Fotografias) | J18: Caixa: 3055 Folder: 5 | K18: =TEXTJOIN("", TRUE, Geral!B34:T34) -> BR-SPAPESP_DASP-PENITPRE-CSDTCARANDIRU_ICO-FOT-DGZ-MT0_3055-005-018 | L18: =$L$2 -> A Casa de Detenção de São Paulo, conhecida como Carandiru, foi formalmente criada em 1938 por decreto do interventor Adhemar de Barros, embora ainda instalada no edifício da Avenida Tiradentes. Sua implantação no bairro do Carandiru só se iniciou décadas depois, quando o governo estadual contratou, em 1951, o Escritório Técnico Ramos de Azevedo, Severo & Villares para projetar e conduzir a construção do novo complexo penitenciário em terreno contíguo à Penitenciária do Estado. As obras avançaram de forma modular, e o primeiro edifício concluído — o Pavilhão 2 — foi inaugurado em 1956, marcando a abertura parcial da chamada “Nova Casa de Detenção”. Ao longo dos anos seguintes, novos pavilhões foram sendo erguidos e inaugurados, compondo um conjunto arquitetônico que se consolidaria como um dos principais símbolos do sistema prisional paulista no século XX. Esta fotografia integra o fundo documental do grupo Diários Associados do Estado de São Paulo (DASP), custodiado pelo Arquivo Público do Estado de São Paulo (APESP), e registra aspectos desse prolongado processo de criação (1938), construção (a partir de 1951) e inauguração (a partir de 1956) da Casa de Detenção, conforme aponta a pesquisa de Maíra Rocha Machado, Bianca Tavolari e Maira Rosín (2025)[1]. | M18: A fotografia em preto e branco registra um momento de circulação e controle em uma área interna da Casa de Detenção. O ambiente é definido por grades de metal, que formam a entrada de uma galeria ou portão de segurança, iluminada por uma forte luz vinda do interior. Em primeiro plano, um homem, está de costas, caminhando em direção à área gradeada, empurrando o que parece ser um carrinho ou carregando algum objeto volumoso. À direita, um homem usando um boné ou chapéu xadrez está sentado em um balcão (possivelmente um posto de controle), observando a movimentação e, talvez, fumando. A cena sugere um procedimento de ingresso, transferência de pertences ou distribuição de materiais. O verso da fotografia contextualiza este evento como "Um dia dos novos 'hospedes' da Casa de Detenção", datado de 29 de maio de 1979. | N18: O acesso aos documentos deste acervo está condicionado ao compromisso de não repassá-los a terceiros, à obrigatoriedade de mencionar que os originais pertencem ao Arquivo Público do Estado de São Paulo, e à necessidade de novo Termo de Responsabilidade em caso de reutilização ou uso diverso do inicialmente acordado. O uso está sujeito às restrições previstas na Lei de Arquivos (Lei nº 8.159/1991), na Lei de Direitos Autorais (Lei nº 9.610/1998), nos artigos 138 e 145 do Código Penal, e no artigo 5º, inciso X, da Constituição Federal, especialmente quanto à proteção da honra e imagem de terceiros. A pessoa física ou jurídica responsável assume integral responsabilidade civil e penal por eventuais danos decorrentes do uso das reproduções e informações, eximindo o Arquivo Público do Estado de São Paulo de qualquer responsabilidade. | O18: Ingresso (presídio); Novos detentos; Chegada de presos; Rotina prisional; Grades; Carrinho (logística); Funcionário penitenciário; Casa de Detenção; Carandiru; 1979; Controle de acesso. | P18: Fotografia (Iconográfico) | Q18: Digitalização de fotografia em preto e branco (analógica original) | R18: ="Figura n – ["&B18&"]"&CHAR(10)&"Fonte: Arquivo do Estado de São Paulo, "&TEXT(D18,"yyyy")&"." -> Figura n – [Procedimento de ingresso ou movimentação na Casa de Detenção no dia da chegada de novos presos (1979)] Fonte: Arquivo do Estado de São Paulo, 1956. | S18: ="ARQUIVO PÚBLICO DO ESTADO DE SÃO PAULO (Brasil). ["&B18&"]. "&G18&". "&TEXT(D18,"dd")&" "&LOWER(TEXT(D18,"mmm"))&" "&TEXT(D18,"yyyy")&". "&F18&". Disponível em: <link do dataverse>. Acesso em: 28 out. 2025." -> ARQUIVO PÚBLICO DO ESTADO DE SÃO PAULO (Brasil). [Procedimento de ingresso ou movimentação na Casa de Detenção no dia da chegada de novos presos (1979)]. São Paulo, Brasil. 12 set. 1956. Fotografia digitalizada; preto e branco; suporte em papel fotográfico. Disponível em: <link do dataverse>. Acesso em: 28 out. 2025. | T18: Estado de São Paulo – Penitenciárias e Presídios – Casa de Detenção Um dia dos novos “hóspedes” da Casa de Detenção. DN, 29/5/1979
A19: =RIGHT(K19,3) -> 019 | B19: Preleição do Diretor Coronel Fernão Guedes aos novos detentos da Casa de Detenção (1979) | C19: Item | D19: 20710 | E19: Gerado pelo Dataverse | F19: Fotografia digitalizada; preto e branco; suporte em papel fotográfico | G19: São Paulo, Brasil | H19: Arquivo Público do Estado de São Paulo, Jornal Diários Associados | I19: Estado De São Paulo - Penitenciárias e Presídios - Casa de Detenção do Carandiru (Fotografias) | J19: Caixa: 3055 Folder: 5 | K19: =TEXTJOIN("", TRUE, Geral!B36:T36) -> BR-SPAPESP_DASP-PENITPRE-CSDTCARANDIRU_ICO-FOT-DGZ-MT0_3055-005-019 | L19: =$L$2 -> A Casa de Detenção de São Paulo, conhecida como Carandiru, foi formalmente criada em 1938 por decreto do interventor Adhemar de Barros, embora ainda instalada no edifício da Avenida Tiradentes. Sua implantação no bairro do Carandiru só se iniciou décadas depois, quando o governo estadual contratou, em 1951, o Escritório Técnico Ramos de Azevedo, Severo & Villares para projetar e conduzir a construção do novo complexo penitenciário em terreno contíguo à Penitenciária do Estado. As obras avançaram de forma modular, e o primeiro edifício concluído — o Pavilhão 2 — foi inaugurado em 1956, marcando a abertura parcial da chamada “Nova Casa de Detenção”. Ao longo dos anos seguintes, novos pavilhões foram sendo erguidos e inaugurados, compondo um conjunto arquitetônico que se consolidaria como um dos principais símbolos do sistema prisional paulista no século XX. Esta fotografia integra o fundo documental do grupo Diários Associados do Estado de São Paulo (DASP), custodiado pelo Arquivo Público do Estado de São Paulo (APESP), e registra aspectos desse prolongado processo de criação (1938), construção (a partir de 1951) e inauguração (a partir de 1956) da Casa de Detenção, conforme aponta a pesquisa de Maíra Rocha Machado, Bianca Tavolari e Maira Rosín (2025)[1]. | M19: A fotografia em preto e branco registra uma cerimônia de instrução (preleção) para detentos recém-chegados em um ambiente interno formal (sala de administração). O grupo de novos detentos está alinhado à direita, de perfil, com a cabeça raspada (corte "zero") e vestindo camisetas e calças claras (uniformes prisionais). À esquerda, o Diretor, Coronel Fernão Guedes (identificado pelo verso), aparece curvado sobre uma mesa de madeira, apontando para documentos, conduzindo o procedimento de registro ou instrução. Outros homens, de terno e roupas civis, observam o ato ao fundo, indicando a presença de funcionários ou autoridades. O verso, datado de 29 de maio de 1979, confirma que a imagem documenta o "1º dia de novos detentos", marcando a recepção e o estabelecimento das regras da Casa de Detenção pelas autoridades máximas da instituição. | N19: O acesso aos documentos deste acervo está condicionado ao compromisso de não repassá-los a terceiros, à obrigatoriedade de mencionar que os originais pertencem ao Arquivo Público do Estado de São Paulo, e à necessidade de novo Termo de Responsabilidade em caso de reutilização ou uso diverso do inicialmente acordado. O uso está sujeito às restrições previstas na Lei de Arquivos (Lei nº 8.159/1991), na Lei de Direitos Autorais (Lei nº 9.610/1998), nos artigos 138 e 145 do Código Penal, e no artigo 5º, inciso X, da Constituição Federal, especialmente quanto à proteção da honra e imagem de terceiros. A pessoa física ou jurídica responsável assume integral responsabilidade civil e penal por eventuais danos decorrentes do uso das reproduções e informações, eximindo o Arquivo Público do Estado de São Paulo de qualquer responsabilidade. | O19: Preleição (diretor); Novos detentos; Chegada de presos; Coronel Fernão Guedes; Uniforme prisional; Corte militar; Cerimônia de registro; Casa de Detenção; Carandiru; 1979; Autoridade prisional. | P19: Fotografia (Iconográfico) | Q19: Digitalização de fotografia em preto e branco (analógica original) | R19: ="Figura n – ["&B19&"]"&CHAR(10)&"Fonte: Arquivo do Estado de São Paulo, "&TEXT(D19,"yyyy")&"." -> Figura n – [Preleição do Diretor Coronel Fernão Guedes aos novos detentos da Casa de Detenção (1979)] Fonte: Arquivo do Estado de São Paulo, 1956. | S19: ="ARQUIVO PÚBLICO DO ESTADO DE SÃO PAULO (Brasil). ["&B19&"]. "&G19&". "&TEXT(D19,"dd")&" "&LOWER(TEXT(D19,"mmm"))&" "&TEXT(D19,"yyyy")&". "&F19&". Disponível em: <link do dataverse>. Acesso em: 28 out. 2025." -> ARQUIVO PÚBLICO DO ESTADO DE SÃO PAULO (Brasil). [Preleição do Diretor Coronel Fernão Guedes aos novos detentos da Casa de Detenção (1979)]. São Paulo, Brasil. 12 set. 1956. Fotografia digitalizada; preto e branco; suporte em papel fotográfico. Disponível em: <link do dataverse>. Acesso em: 28 out. 2025. | T19: Estado de São Paulo – Penitenciárias e Presídios – Casa de Detenção O 1º dia de novos detentos na Casa de Detenção, com a preleção do diretor Cel. Fernão Guedes. DN, 29/5/1979
A20: =RIGHT(K20,3) -> 020 | B20: Aglomeração de detentos durante a revista do Henfil no Carandiru (1979) | C20: Item | D20: 20710 | E20: Gerado pelo Dataverse | F20: Fotografia digitalizada; preto e branco; suporte em papel fotográfico | G20: São Paulo, Brasil | H20: Arquivo Público do Estado de São Paulo, Jornal Diários Associados | I20: Estado De São Paulo - Penitenciárias e Presídios - Casa de Detenção do Carandiru (Fotografias) | J20: Caixa: 3055 Folder: 5 | K20: =TEXTJOIN("", TRUE, Geral!B38:T38) -> BR-SPAPESP_DASP-PENITPRE-CSDTCARANDIRU_ICO-FOT-DGZ-MT0_3055-005-020 | L20: =$L$2 -> A Casa de Detenção de São Paulo, conhecida como Carandiru, foi formalmente criada em 1938 por decreto do interventor Adhemar de Barros, embora ainda instalada no edifício da Avenida Tiradentes. Sua implantação no bairro do Carandiru só se iniciou décadas depois, quando o governo estadual contratou, em 1951, o Escritório Técnico Ramos de Azevedo, Severo & Villares para projetar e conduzir a construção do novo complexo penitenciário em terreno contíguo à Penitenciária do Estado. As obras avançaram de forma modular, e o primeiro edifício concluído — o Pavilhão 2 — foi inaugurado em 1956, marcando a abertura parcial da chamada “Nova Casa de Detenção”. Ao longo dos anos seguintes, novos pavilhões foram sendo erguidos e inaugurados, compondo um conjunto arquitetônico que se consolidaria como um dos principais símbolos do sistema prisional paulista no século XX. Esta fotografia integra o fundo documental do grupo Diários Associados do Estado de São Paulo (DASP), custodiado pelo Arquivo Público do Estado de São Paulo (APESP), e registra aspectos desse prolongado processo de criação (1938), construção (a partir de 1951) e inauguração (a partir de 1956) da Casa de Detenção, conforme aponta a pesquisa de Maíra Rocha Machado, Bianca Tavolari e Maira Rosín (2025)[1]. | M20: A fotografia em preto e branco, em plano alto, captura uma aglomeração massiva de homens (detentos) sentados ou agachados no chão de um amplo espaço interno (possivelmente um salão ou pátio coberto), ilustrando graficamente a superlotação da Casa de Detenção. As pessoas vestem roupas civis variadas, sem padronização, e todos estão olhando em uma direção comum, indicando a atenção a um palco ou ponto focal não visível. Um equipamento de iluminação ou sonorização está visível no canto superior direito. O verso da fotografia, datado de 1º de junho de 1979, contextualiza o evento como a "revista do Henfil". | N20: O acesso aos documentos deste acervo está condicionado ao compromisso de não repassá-los a terceiros, à obrigatoriedade de mencionar que os originais pertencem ao Arquivo Público do Estado de São Paulo, e à necessidade de novo Termo de Responsabilidade em caso de reutilização ou uso diverso do inicialmente acordado. O uso está sujeito às restrições previstas na Lei de Arquivos (Lei nº 8.159/1991), na Lei de Direitos Autorais (Lei nº 9.610/1998), nos artigos 138 e 145 do Código Penal, e no artigo 5º, inciso X, da Constituição Federal, especialmente quanto à proteção da honra e imagem de terceiros. A pessoa física ou jurídica responsável assume integral responsabilidade civil e penal por eventuais danos decorrentes do uso das reproduções e informações, eximindo o Arquivo Público do Estado de São Paulo de qualquer responsabilidade. | O20: Superlotação; Aglomeração de detentos; Evento (cultural/mídia); Revista do Henfil; Roupas civis; Pátio (interno); Casa de Detenção; Carandiru; 1979; Fotojornalismo. | P20: Fotografia (Iconográfico) | Q20: Digitalização de fotografia em preto e branco (analógica original) | R20: ="Figura n – ["&B20&"]"&CHAR(10)&"Fonte: Arquivo do Estado de São Paulo, "&TEXT(D20,"yyyy")&"." -> Figura n – [Aglomeração de detentos durante a revista do Henfil no Carandiru (1979)] Fonte: Arquivo do Estado de São Paulo, 1956. | S20: ="ARQUIVO PÚBLICO DO ESTADO DE SÃO PAULO (Brasil). ["&B20&"]. "&G20&". "&TEXT(D20,"dd")&" "&LOWER(TEXT(D20,"mmm"))&" "&TEXT(D20,"yyyy")&". "&F20&". Disponível em: <link do dataverse>. Acesso em: 28 out. 2025." -> ARQUIVO PÚBLICO DO ESTADO DE SÃO PAULO (Brasil). [Aglomeração de detentos durante a revista do Henfil no Carandiru (1979)]. São Paulo, Brasil. 12 set. 1956. Fotografia digitalizada; preto e branco; suporte em papel fotográfico. Disponível em: <link do dataverse>. Acesso em: 28 out. 2025. | T20: Estado de São Paulo – Penitenciárias e Presídios – Casa de Detenção A revista do Henfil na Casa de Detenção. DN, 1/6/1979
A21: =RIGHT(K21,3) -> 021 | B21: Movimentação de detentos por portão gradeado em contexto de superpopulação no Carandiru (1979) | C21: Item | D21: 20710 | E21: Gerado pelo Dataverse | F21: Fotografia digitalizada; preto e branco; suporte em papel fotográfico | G21: São Paulo, Brasil | H21: Arquivo Público do Estado de São Paulo, Jornal Diários Associados | I21: Estado De São Paulo - Penitenciárias e Presídios - Casa de Detenção do Carandiru (Fotografias) | J21: Caixa: 3055 Folder: 5 | K21: =TEXTJOIN("", TRUE, Geral!B40:T40) -> BR-SPAPESP_DASP-PENITPRE-CSDTCARANDIRU_ICO-FOT-DGZ-MT0_3055-005-021 | L21: =$L$2 -> A Casa de Detenção de São Paulo, conhecida como Carandiru, foi formalmente criada em 1938 por decreto do interventor Adhemar de Barros, embora ainda instalada no edifício da Avenida Tiradentes. Sua implantação no bairro do Carandiru só se iniciou décadas depois, quando o governo estadual contratou, em 1951, o Escritório Técnico Ramos de Azevedo, Severo & Villares para projetar e conduzir a construção do novo complexo penitenciário em terreno contíguo à Penitenciária do Estado. As obras avançaram de forma modular, e o primeiro edifício concluído — o Pavilhão 2 — foi inaugurado em 1956, marcando a abertura parcial da chamada “Nova Casa de Detenção”. Ao longo dos anos seguintes, novos pavilhões foram sendo erguidos e inaugurados, compondo um conjunto arquitetônico que se consolidaria como um dos principais símbolos do sistema prisional paulista no século XX. Esta fotografia integra o fundo documental do grupo Diários Associados do Estado de São Paulo (DASP), custodiado pelo Arquivo Público do Estado de São Paulo (APESP), e registra aspectos desse prolongado processo de criação (1938), construção (a partir de 1951) e inauguração (a partir de 1956) da Casa de Detenção, conforme aponta a pesquisa de Maíra Rocha Machado, Bianca Tavolari e Maira Rosín (2025)[1]. | M21: A fotografia em preto e branco registra um momento de circulação controlada de detentos em uma área interna da Casa de Detenção. A cena é emoldurada por grades de metal que formam um portão de segurança parcialmente aberto, separando seções do corredor. Dois homens estão em movimento através da abertura. O homem em primeiro plano está de costas, vestindo roupas casuais, caminhando para o interior do corredor. O homem logo atrás dele olha diretamente para a câmera com uma expressão atenta. O ambiente é um corredor com paredes claras e portas fechadas visíveis ao fundo, reforçando a natureza confinada do local. O verso da fotografia, datado de 31 de maio de 1979, contextualiza esta rotina de movimentação em um cenário de crise: "Detenção com super população, ameaça explodir." O registro, portanto, documenta a vida e a circulação interna dos presos em um momento em que a superlotação estava no limite da capacidade institucional. | N21: O acesso aos documentos deste acervo está condicionado ao compromisso de não repassá-los a terceiros, à obrigatoriedade de mencionar que os originais pertencem ao Arquivo Público do Estado de São Paulo, e à necessidade de novo Termo de Responsabilidade em caso de reutilização ou uso diverso do inicialmente acordado. O uso está sujeito às restrições previstas na Lei de Arquivos (Lei nº 8.159/1991), na Lei de Direitos Autorais (Lei nº 9.610/1998), nos artigos 138 e 145 do Código Penal, e no artigo 5º, inciso X, da Constituição Federal, especialmente quanto à proteção da honra e imagem de terceiros. A pessoa física ou jurídica responsável assume integral responsabilidade civil e penal por eventuais danos decorrentes do uso das reproduções e informações, eximindo o Arquivo Público do Estado de São Paulo de qualquer responsabilidade. | O21: Circulação de detentos; Portão de cela; Grades; Superlotação (crítica); Casa de Detenção; Carandiru; Rotina prisional; 1979; Confinamento; Controle de movimentação. | P21: Fotografia (Iconográfico) | Q21: Digitalização de fotografia em preto e branco (analógica original) | R21: ="Figura n – ["&B21&"]"&CHAR(10)&"Fonte: Arquivo do Estado de São Paulo, "&TEXT(D21,"yyyy")&"." -> Figura n – [Movimentação de detentos por portão gradeado em contexto de superpopulação no Carandiru (1979)] Fonte: Arquivo do Estado de São Paulo, 1956. | S21: ="ARQUIVO PÚBLICO DO ESTADO DE SÃO PAULO (Brasil). ["&B21&"]. "&G21&". "&TEXT(D21,"dd")&" "&LOWER(TEXT(D21,"mmm"))&" "&TEXT(D21,"yyyy")&". "&F21&". Disponível em: <link do dataverse>. Acesso em: 28 out. 2025." -> ARQUIVO PÚBLICO DO ESTADO DE SÃO PAULO (Brasil). [Movimentação de detentos por portão gradeado em contexto de superpopulação no Carandiru (1979)]. São Paulo, Brasil. 12 set. 1956. Fotografia digitalizada; preto e branco; suporte em papel fotográfico. Disponível em: <link do dataverse>. Acesso em: 28 out. 2025. | T21: Estado de São Paulo – Penitenciárias e Presídios – Casa de Detenção A Detenção com superpopulação, ameaça explodir. DN, 31/5/1979
A22: =RIGHT(K22,3) -> 022 | B22: Passagem de funcionário por portão de segurança no período da revolta causada pela extinção do Projeto JUS (1979) | C22: Item | D22: 21165 | E22: Gerado pelo Dataverse | F22: Fotografia digitalizada; preto e branco; suporte em papel fotográfico | G22: São Paulo, Brasil | H22: Arquivo Público do Estado de São Paulo, Jornal Diários Associados | I22: Estado De São Paulo - Penitenciárias e Presídios - Casa de Detenção do Carandiru (Fotografias) | J22: Caixa: 3055 Folder: 5 | K22: =TEXTJOIN("", TRUE, Geral!B42:T42) -> BR-SPAPESP_DASP-PENITPRE-CSDTCARANDIRU_ICO-FOT-DGZ-MT0_3055-005-022 | L22: =$L$2 -> A Casa de Detenção de São Paulo, conhecida como Carandiru, foi formalmente criada em 1938 por decreto do interventor Adhemar de Barros, embora ainda instalada no edifício da Avenida Tiradentes. Sua implantação no bairro do Carandiru só se iniciou décadas depois, quando o governo estadual contratou, em 1951, o Escritório Técnico Ramos de Azevedo, Severo & Villares para projetar e conduzir a construção do novo complexo penitenciário em terreno contíguo à Penitenciária do Estado. As obras avançaram de forma modular, e o primeiro edifício concluído — o Pavilhão 2 — foi inaugurado em 1956, marcando a abertura parcial da chamada “Nova Casa de Detenção”. Ao longo dos anos seguintes, novos pavilhões foram sendo erguidos e inaugurados, compondo um conjunto arquitetônico que se consolidaria como um dos principais símbolos do sistema prisional paulista no século XX. Esta fotografia integra o fundo documental do grupo Diários Associados do Estado de São Paulo (DASP), custodiado pelo Arquivo Público do Estado de São Paulo (APESP), e registra aspectos desse prolongado processo de criação (1938), construção (a partir de 1951) e inauguração (a partir de 1956) da Casa de Detenção, conforme aponta a pesquisa de Maíra Rocha Machado, Bianca Tavolari e Maira Rosín (2025)[1]. | M22: A fotografia em preto e branco, com foco suave ou desfocado, registra a passagem de uma pessoa por um portão de grades em uma área interna de controle da Casa de Detenção. A pessoa, vista de costas, veste uma camisa ou jaleco claro. Ela atravessa um portão de segurança de barras de ferro, que está parcialmente aberto. Em primeiro plano, uma estrutura de metal desfocada, talvez um carrinho ou objeto de rotina, ocupa o rodapé. O verso da fotografia, datado de 21 de junho de 1979, contextualiza esta cena em um cenário de crise e revolta, pois a "extinção do Projeto JUS aumentou a revolta dos presos" na Detenção. A imagem, portanto, documenta a rotina de controle e circulação de pessoal em um ambiente de alta tensão institucional, provavelmente logo após ou durante a manifestação de descontentamento dos detentos. | N22: O acesso aos documentos deste acervo está condicionado ao compromisso de não repassá-los a terceiros, à obrigatoriedade de mencionar que os originais pertencem ao Arquivo Público do Estado de São Paulo, e à necessidade de novo Termo de Responsabilidade em caso de reutilização ou uso diverso do inicialmente acordado. O uso está sujeito às restrições previstas na Lei de Arquivos (Lei nº 8.159/1991), na Lei de Direitos Autorais (Lei nº 9.610/1998), nos artigos 138 e 145 do Código Penal, e no artigo 5º, inciso X, da Constituição Federal, especialmente quanto à proteção da honra e imagem de terceiros. A pessoa física ou jurídica responsável assume integral responsabilidade civil e penal por eventuais danos decorrentes do uso das reproduções e informações, eximindo o Arquivo Público do Estado de São Paulo de qualquer responsabilidade. | O22: Passagem (funcionário); Portão de grades; Controle de segurança; Revolta de presos; Extinção Projeto JUS; Funcionário prisional; Casa de Detenção; Carandiru; Crise prisional; 1979. | P22: Fotografia (Iconográfico) | Q22: Digitalização de fotografia em preto e branco (analógica original) | R22: ="Figura n – ["&B22&"]"&CHAR(10)&"Fonte: Arquivo do Estado de São Paulo, "&TEXT(D22,"yyyy")&"." -> Figura n – [Passagem de funcionário por portão de segurança no período da revolta causada pela extinção do Projeto JUS (1979)] Fonte: Arquivo do Estado de São Paulo, 1957. | S22: ="ARQUIVO PÚBLICO DO ESTADO DE SÃO PAULO (Brasil). ["&B22&"]. "&G22&". "&TEXT(D22,"dd")&" "&LOWER(TEXT(D22,"mmm"))&" "&TEXT(D22,"yyyy")&". "&F22&". Disponível em: <link do dataverse>. Acesso em: 28 out. 2025." -> ARQUIVO PÚBLICO DO ESTADO DE SÃO PAULO (Brasil). [Passagem de funcionário por portão de segurança no período da revolta causada pela extinção do Projeto JUS (1979)]. São Paulo, Brasil. 11 dez. 1957. Fotografia digitalizada; preto e branco; suporte em papel fotográfico. Disponível em: <link do dataverse>. Acesso em: 28 out. 2025. | T22: Estado de São Paulo – Penitenciárias e Presídios – Casa de Detenção A extinção do Projeto JUS aumentou a revolta dos presos na Detenção. DN, 21/6/1979
A23: =RIGHT(K23,3) -> 023 | B23: Corredor de celas da Casa de Detenção (Carandiru) no contexto de crise e revolta (1979) | C23: Item | D23: 21716 | E23: Gerado pelo Dataverse | F23: Fotografia digitalizada; preto e branco; suporte em papel fotográfico | G23: São Paulo, Brasil | H23: Arquivo Público do Estado de São Paulo, Jornal Diários Associados | I23: Estado De São Paulo - Penitenciárias e Presídios - Casa de Detenção do Carandiru (Fotografias) | J23: Caixa: 3055 Folder: 5 | K23: =TEXTJOIN("", TRUE, Geral!B44:T44) -> BR-SPAPESP_DASP-PENITPRE-CSDTCARANDIRU_ICO-FOT-DGZ-MT0_3055-005-023 | L23: =$L$2 -> A Casa de Detenção de São Paulo, conhecida como Carandiru, foi formalmente criada em 1938 por decreto do interventor Adhemar de Barros, embora ainda instalada no edifício da Avenida Tiradentes. Sua implantação no bairro do Carandiru só se iniciou décadas depois, quando o governo estadual contratou, em 1951, o Escritório Técnico Ramos de Azevedo, Severo & Villares para projetar e conduzir a construção do novo complexo penitenciário em terreno contíguo à Penitenciária do Estado. As obras avançaram de forma modular, e o primeiro edifício concluído — o Pavilhão 2 — foi inaugurado em 1956, marcando a abertura parcial da chamada “Nova Casa de Detenção”. Ao longo dos anos seguintes, novos pavilhões foram sendo erguidos e inaugurados, compondo um conjunto arquitetônico que se consolidaria como um dos principais símbolos do sistema prisional paulista no século XX. Esta fotografia integra o fundo documental do grupo Diários Associados do Estado de São Paulo (DASP), custodiado pelo Arquivo Público do Estado de São Paulo (APESP), e registra aspectos desse prolongado processo de criação (1938), construção (a partir de 1951) e inauguração (a partir de 1956) da Casa de Detenção, conforme aponta a pesquisa de Maíra Rocha Machado, Bianca Tavolari e Maira Rosín (2025)[1]. | M23: A fotografia em preto e branco utiliza uma perspectiva acentuada para registrar um corredor estreito e austero em uma galeria da Casa de Detenção. O corredor é ladeado por uma fileira de portas sólidas de metal, idênticas e repetitivas, que são as entradas das celas. O foco da imagem está nos detalhes das portas mais próximas, evidenciando grandes puxadores/alças e pequenas aberturas de inspeção (escotilhas) na parte superior. O piso de cimento ou ladrilho está sujo e desgastado. A profundidade do corredor, que se perde na escuridão, reforça a sensação de confinamento e claustrofobia. O verso da fotografia, datado de 21 de junho de 1979, contextualiza esta arquitetura repressiva em um cenário de crise, mencionando que a "extinção do Projeto JUS aumentou a revolta dos presos". A imagem, portanto, documenta o ambiente físico de confinamento onde se manifestavam a tensão e o descontentamento das pessoas em situação de privação de liberdade em 1979. | N23: O acesso aos documentos deste acervo está condicionado ao compromisso de não repassá-los a terceiros, à obrigatoriedade de mencionar que os originais pertencem ao Arquivo Público do Estado de São Paulo, e à necessidade de novo Termo de Responsabilidade em caso de reutilização ou uso diverso do inicialmente acordado. O uso está sujeito às restrições previstas na Lei de Arquivos (Lei nº 8.159/1991), na Lei de Direitos Autorais (Lei nº 9.610/1998), nos artigos 138 e 145 do Código Penal, e no artigo 5º, inciso X, da Constituição Federal, especialmente quanto à proteção da honra e imagem de terceiros. A pessoa física ou jurídica responsável assume integral responsabilidade civil e penal por eventuais danos decorrentes do uso das reproduções e informações, eximindo o Arquivo Público do Estado de São Paulo de qualquer responsabilidade. | O23: Corredor de celas; Arquitetura prisional; Porta metálica; Confinamento; Claustrofobia; Revolta de presos; Extinção Projeto JUS; Casa de Detenção; Carandiru; 1979. | P23: Fotografia (Iconográfico) | Q23: Digitalização de fotografia em preto e branco (analógica original) | R23: ="Figura n – ["&B23&"]"&CHAR(10)&"Fonte: Arquivo do Estado de São Paulo, "&TEXT(D23,"yyyy")&"." -> Figura n – [Corredor de celas da Casa de Detenção (Carandiru) no contexto de crise e revolta (1979)] Fonte: Arquivo do Estado de São Paulo, 1959. | S23: ="ARQUIVO PÚBLICO DO ESTADO DE SÃO PAULO (Brasil). ["&B23&"]. "&G23&". "&TEXT(D23,"dd")&" "&LOWER(TEXT(D23,"mmm"))&" "&TEXT(D23,"yyyy")&". "&F23&". Disponível em: <link do dataverse>. Acesso em: 28 out. 2025." -> ARQUIVO PÚBLICO DO ESTADO DE SÃO PAULO (Brasil). [Corredor de celas da Casa de Detenção (Carandiru) no contexto de crise e revolta (1979)]. São Paulo, Brasil. 15 jun. 1959. Fotografia digitalizada; preto e branco; suporte em papel fotográfico. Disponível em: <link do dataverse>. Acesso em: 28 out. 2025. | T23: Estado de São Paulo – Penitenciárias e Presídios – Casa de Detenção A extinção do Projeto JUS aumentou a revolta dos presos da Detenção. DN, 21/6/1979
A24: =RIGHT(K24,3) -> 024 | B24: Intenso movimento de familiares no portão da Casa de Detenção (Carandiru) após o Natal de 1979 | C24: Item | D24: 22057 | E24: Gerado pelo Dataverse | F24: Fotografia digitalizada; preto e branco; suporte em papel fotográfico | G24: São Paulo, Brasil | H24: Arquivo Público do Estado de São Paulo, Jornal Diários Associados | I24: Estado De São Paulo - Penitenciárias e Presídios - Casa de Detenção do Carandiru (Fotografias) | J24: Caixa: 3055 Folder: 5 | K24: =TEXTJOIN("", TRUE, Geral!B46:T46) -> BR-SPAPESP_DASP-PENITPRE-CSDTCARANDIRU_ICO-FOT-DGZ-MT0_3055-005-024 | L24: =$L$2 -> A Casa de Detenção de São Paulo, conhecida como Carandiru, foi formalmente criada em 1938 por decreto do interventor Adhemar de Barros, embora ainda instalada no edifício da Avenida Tiradentes. Sua implantação no bairro do Carandiru só se iniciou décadas depois, quando o governo estadual contratou, em 1951, o Escritório Técnico Ramos de Azevedo, Severo & Villares para projetar e conduzir a construção do novo complexo penitenciário em terreno contíguo à Penitenciária do Estado. As obras avançaram de forma modular, e o primeiro edifício concluído — o Pavilhão 2 — foi inaugurado em 1956, marcando a abertura parcial da chamada “Nova Casa de Detenção”. Ao longo dos anos seguintes, novos pavilhões foram sendo erguidos e inaugurados, compondo um conjunto arquitetônico que se consolidaria como um dos principais símbolos do sistema prisional paulista no século XX. Esta fotografia integra o fundo documental do grupo Diários Associados do Estado de São Paulo (DASP), custodiado pelo Arquivo Público do Estado de São Paulo (APESP), e registra aspectos desse prolongado processo de criação (1938), construção (a partir de 1951) e inauguração (a partir de 1956) da Casa de Detenção, conforme aponta a pesquisa de Maíra Rocha Machado, Bianca Tavolari e Maira Rosín (2025)[1]. | M24: A fotografia em preto e branco registra o intenso movimento e a aglomeração de pessoas na área externa ou portaria da Casa de Detenção em um dia de visita. Em primeiro plano, diversos casais e familiares caminham em direção ou afastando-se do portão de grades visível ao fundo. Um homem à esquerda carrega uma volumosa sacola de itens (jumbo), elemento típico da rotina de visitas. À direita, um casal caminha junto, com a mulher sorridente, evidenciando o aspecto social e emocional do encontro. O cenário é urbano, com lojas, tráfego e uma placa de "EXAME MÉDICOS MOTORISTAS" ao fundo, contrastando o rigor prisional com a vida na cidade. O verso da fotografia, datado de 27 de dezembro de 1979, contextualiza esta movimentação logo após o Natal, registrando que "Dos 51 presos que passaram o Natal em casa, 8 não voltaram". | N24: O acesso aos documentos deste acervo está condicionado ao compromisso de não repassá-los a terceiros, à obrigatoriedade de mencionar que os originais pertencem ao Arquivo Público do Estado de São Paulo, e à necessidade de novo Termo de Responsabilidade em caso de reutilização ou uso diverso do inicialmente acordado. O uso está sujeito às restrições previstas na Lei de Arquivos (Lei nº 8.159/1991), na Lei de Direitos Autorais (Lei nº 9.610/1998), nos artigos 138 e 145 do Código Penal, e no artigo 5º, inciso X, da Constituição Federal, especialmente quanto à proteção da honra e imagem de terceiros. A pessoa física ou jurídica responsável assume integral responsabilidade civil e penal por eventuais danos decorrentes do uso das reproduções e informações, eximindo o Arquivo Público do Estado de São Paulo de qualquer responsabilidade. | O24: Visita familiar; Saída temporária (quebra); Falta disciplinar; Sacola (jumbo); Aglomeração; Portaria; Carandiru; Cotidiano prisional; Natal (evento); 1979. | P24: Fotografia (Iconográfico) | Q24: Digitalização de fotografia em preto e branco (analógica original) | R24: ="Figura n – ["&B24&"]"&CHAR(10)&"Fonte: Arquivo do Estado de São Paulo, "&TEXT(D24,"yyyy")&"." -> Figura n – [Intenso movimento de familiares no portão da Casa de Detenção (Carandiru) após o Natal de 1979] Fonte: Arquivo do Estado de São Paulo, 1960. | S24: ="ARQUIVO PÚBLICO DO ESTADO DE SÃO PAULO (Brasil). ["&B24&"]. "&G24&". "&TEXT(D24,"dd")&" "&LOWER(TEXT(D24,"mmm"))&" "&TEXT(D24,"yyyy")&". "&F24&". Disponível em: <link do dataverse>. Acesso em: 28 out. 2025." -> ARQUIVO PÚBLICO DO ESTADO DE SÃO PAULO (Brasil). [Intenso movimento de familiares no portão da Casa de Detenção (Carandiru) após o Natal de 1979]. São Paulo, Brasil. 21 mai. 1960. Fotografia digitalizada; preto e branco; suporte em papel fotográfico. Disponível em: <link do dataverse>. Acesso em: 28 out. 2025. | T24: Estado de São Paulo – Penitenciárias e Presídios – Casa de Detenção Dos 51 presos que passaram o Natal em casa, 8 não voltaram. DN, 27/12/1979
A25: =RIGHT(K25,3) -> 025 | B25: Grupo de detentos assistindo a partida de futebol "Santos versus Palmeiras" no pátio do Carandiru (1969) | C25: Item | D25: 22151 | E25: Gerado pelo Dataverse | F25: Fotografia digitalizada; preto e branco; suporte em papel fotográfico | G25: São Paulo, Brasil | H25: Arquivo Público do Estado de São Paulo, Jornal Diários Associados | I25: Estado De São Paulo - Penitenciárias e Presídios - Casa de Detenção do Carandiru (Fotografias) | J25: Caixa: 3055 Folder: 5 | K25: =TEXTJOIN("", TRUE, Geral!B48:T48) -> BR-SPAPESP_DASP-PENITPRE-CSDTCARANDIRU_ICO-FOT-DGZ-MT0_3055-005-025 | L25: =$L$2 -> A Casa de Detenção de São Paulo, conhecida como Carandiru, foi formalmente criada em 1938 por decreto do interventor Adhemar de Barros, embora ainda instalada no edifício da Avenida Tiradentes. Sua implantação no bairro do Carandiru só se iniciou décadas depois, quando o governo estadual contratou, em 1951, o Escritório Técnico Ramos de Azevedo, Severo & Villares para projetar e conduzir a construção do novo complexo penitenciário em terreno contíguo à Penitenciária do Estado. As obras avançaram de forma modular, e o primeiro edifício concluído — o Pavilhão 2 — foi inaugurado em 1956, marcando a abertura parcial da chamada “Nova Casa de Detenção”. Ao longo dos anos seguintes, novos pavilhões foram sendo erguidos e inaugurados, compondo um conjunto arquitetônico que se consolidaria como um dos principais símbolos do sistema prisional paulista no século XX. Esta fotografia integra o fundo documental do grupo Diários Associados do Estado de São Paulo (DASP), custodiado pelo Arquivo Público do Estado de São Paulo (APESP), e registra aspectos desse prolongado processo de criação (1938), construção (a partir de 1951) e inauguração (a partir de 1956) da Casa de Detenção, conforme aponta a pesquisa de Maíra Rocha Machado, Bianca Tavolari e Maira Rosín (2025)[1]. | M25: A fotografia em preto e branco registra um grupo de detentos reunidos em um pátio externo da Casa de Detenção, claramente atuando como público ou torcida em um evento. Os homens estão dispostos em dois níveis: a maioria sentada em um banco improvisado em primeiro plano, e outros de pé, atrás. Eles vestem roupas civis variadas. As expressões e, principalmente, os gestos de entusiasmo de alguns homens (como o que está com o braço levantado ou boquiabertos), sugerem que estão reagindo a uma partida. O fundo é dominado por um muro de concreto e uma edificação prisional. O verso da fotografia, datado de 27 de agosto de 1969, contextualiza a cena como o público do jogo de futebol "Santos" versus "Palmeiras" (parte do Torneio "Fernando José Fernandes"), assistido por "quase três mil detentos" no campo da prisão. | N25: O acesso aos documentos deste acervo está condicionado ao compromisso de não repassá-los a terceiros, à obrigatoriedade de mencionar que os originais pertencem ao Arquivo Público do Estado de São Paulo, e à necessidade de novo Termo de Responsabilidade em caso de reutilização ou uso diverso do inicialmente acordado. O uso está sujeito às restrições previstas na Lei de Arquivos (Lei nº 8.159/1991), na Lei de Direitos Autorais (Lei nº 9.610/1998), nos artigos 138 e 145 do Código Penal, e no artigo 5º, inciso X, da Constituição Federal, especialmente quanto à proteção da honra e imagem de terceiros. A pessoa física ou jurídica responsável assume integral responsabilidade civil e penal por eventuais danos decorrentes do uso das reproduções e informações, eximindo o Arquivo Público do Estado de São Paulo de qualquer responsabilidade. | O25: Evento esportivo; Futebol (Santos vs Palmeiras); Pátio (externo); Torcida; Detentos (público); Lazer; Carandiru; Roupas civis; 1969; Torneio Fernando José Fernandes. | P25: Fotografia (Iconográfico) | Q25: Digitalização de fotografia em preto e branco (analógica original) | R25: ="Figura n – ["&B25&"]"&CHAR(10)&"Fonte: Arquivo do Estado de São Paulo, "&TEXT(D25,"yyyy")&"." -> Figura n – [Grupo de detentos assistindo a partida de futebol "Santos versus Palmeiras" no pátio do Carandiru (1969)] Fonte: Arquivo do Estado de São Paulo, 1960. | S25: ="ARQUIVO PÚBLICO DO ESTADO DE SÃO PAULO (Brasil). ["&B25&"]. "&G25&". "&TEXT(D25,"dd")&" "&LOWER(TEXT(D25,"mmm"))&" "&TEXT(D25,"yyyy")&". "&F25&". Disponível em: <link do dataverse>. Acesso em: 28 out. 2025." -> ARQUIVO PÚBLICO DO ESTADO DE SÃO PAULO (Brasil). [Grupo de detentos assistindo a partida de futebol "Santos versus Palmeiras" no pátio do Carandiru (1969)]. São Paulo, Brasil. 23 ago. 1960. Fotografia digitalizada; preto e branco; suporte em papel fotográfico. Disponível em: <link do dataverse>. Acesso em: 28 out. 2025. | T25: Estado de São Paulo – Penitenciária e Presídios – Casa de Detenção Dado é o palco da Detenção Quase três mil detentos assistiram, ontem, ao jogo “Santos” versus “Palmeiras”, no campo de futebol da Casa de Detenção, pelo torneio “Fernando José Fernandes”. DN, 2ª ed., 27/8/1969 – GRL
A26: =RIGHT(K26,3) -> 026 | B26: Show da "Caravana Sentimental" para 3200 detentos no pátio da Casa de Detenção (1969) | C26: Item | D26: 22151 | E26: Gerado pelo Dataverse | F26: Fotografia digitalizada; preto e branco; suporte em papel fotográfico | G26: São Paulo, Brasil | H26: Arquivo Público do Estado de São Paulo, Jornal Diários Associados | I26: Estado De São Paulo - Penitenciárias e Presídios - Casa de Detenção do Carandiru (Fotografias) | J26: Caixa: 3055 Folder: 5 | K26: =TEXTJOIN("", TRUE, Geral!B50:T50) -> BR-SPAPESP_DASP-PENITPRE-CSDTCARANDIRU_ICO-FOT-DGZ-MT0_3055-005-026 | L26: =$L$2 -> A Casa de Detenção de São Paulo, conhecida como Carandiru, foi formalmente criada em 1938 por decreto do interventor Adhemar de Barros, embora ainda instalada no edifício da Avenida Tiradentes. Sua implantação no bairro do Carandiru só se iniciou décadas depois, quando o governo estadual contratou, em 1951, o Escritório Técnico Ramos de Azevedo, Severo & Villares para projetar e conduzir a construção do novo complexo penitenciário em terreno contíguo à Penitenciária do Estado. As obras avançaram de forma modular, e o primeiro edifício concluído — o Pavilhão 2 — foi inaugurado em 1956, marcando a abertura parcial da chamada “Nova Casa de Detenção”. Ao longo dos anos seguintes, novos pavilhões foram sendo erguidos e inaugurados, compondo um conjunto arquitetônico que se consolidaria como um dos principais símbolos do sistema prisional paulista no século XX. Esta fotografia integra o fundo documental do grupo Diários Associados do Estado de São Paulo (DASP), custodiado pelo Arquivo Público do Estado de São Paulo (APESP), e registra aspectos desse prolongado processo de criação (1938), construção (a partir de 1951) e inauguração (a partir de 1956) da Casa de Detenção, conforme aponta a pesquisa de Maíra Rocha Machado, Bianca Tavolari e Maira Rosín (2025)[1]. | M26: A fotografia em preto e branco, capturada em plano alto, registra uma grande concentração de homens (detentos) em um pátio externo, dispostos de forma organizada para assistir a um evento. A plateia massiva (o verso menciona 3.200 prisioneiros) está sentada no chão e em arquibancadas improvisadas. O foco do evento é uma estrutura coberta (palco) à esquerda, onde há músicos e equipamentos de som visíveis. Um grupo de pessoas (aparentemente autoridades e organizadores) está sentado em um semicírculo na área central superior. O verso da fotografia, datado de 11 de fevereiro de 1969, contextualiza o evento como a primeira apresentação da "Caravana Sentimental", com a participação de artistas como Ary Sanchez, Ed Wilson e Marta Mendonça, em uma série de shows beneficentes. | N26: O acesso aos documentos deste acervo está condicionado ao compromisso de não repassá-los a terceiros, à obrigatoriedade de mencionar que os originais pertencem ao Arquivo Público do Estado de São Paulo, e à necessidade de novo Termo de Responsabilidade em caso de reutilização ou uso diverso do inicialmente acordado. O uso está sujeito às restrições previstas na Lei de Arquivos (Lei nº 8.159/1991), na Lei de Direitos Autorais (Lei nº 9.610/1998), nos artigos 138 e 145 do Código Penal, e no artigo 5º, inciso X, da Constituição Federal, especialmente quanto à proteção da honra e imagem de terceiros. A pessoa física ou jurídica responsável assume integral responsabilidade civil e penal por eventuais danos decorrentes do uso das reproduções e informações, eximindo o Arquivo Público do Estado de São Paulo de qualquer responsabilidade. | O26: Show musical; Caravana Sentimental; Evento cultural; Detentos (plateia); Pátio (externo); Superlotação; Artistas (Ary Sanchez, Ed Wilson); Carandiru; 1969; Correção (respeito). | P26: Fotografia (Iconográfico) | Q26: Digitalização de fotografia em preto e branco (analógica original) | R26: ="Figura n – ["&B26&"]"&CHAR(10)&"Fonte: Arquivo do Estado de São Paulo, "&TEXT(D26,"yyyy")&"." -> Figura n – [Show da "Caravana Sentimental" para 3200 detentos no pátio da Casa de Detenção (1969)] Fonte: Arquivo do Estado de São Paulo, 1960. | S26: ="ARQUIVO PÚBLICO DO ESTADO DE SÃO PAULO (Brasil). ["&B26&"]. "&G26&". "&TEXT(D26,"dd")&" "&LOWER(TEXT(D26,"mmm"))&" "&TEXT(D26,"yyyy")&". "&F26&". Disponível em: <link do dataverse>. Acesso em: 28 out. 2025." -> ARQUIVO PÚBLICO DO ESTADO DE SÃO PAULO (Brasil). [Show da "Caravana Sentimental" para 3200 detentos no pátio da Casa de Detenção (1969)]. São Paulo, Brasil. 23 ago. 1960. Fotografia digitalizada; preto e branco; suporte em papel fotográfico. Disponível em: <link do dataverse>. Acesso em: 28 out. 2025. | T26: Estado de São Paulo – Capital – Penitenciárias e Presídios – Casa de Detenção do Carandiru Artistas fazem “show” na Casa de Detenção [Texto em pequeno retângulo, recorte de matéria] Os 3.200 prisioneiros da Casa de Detenção ouviram Ary Sanchez, Ed Wilson, Marta Mendonça, Fred Jorge e Nalva Aguiar cantarem nas primeiras apresentações que a “Caravana Sentimental”, de uma série de “shows”, programou para entidades beneficentes, de correção e hospitais. A ideia surgiu com uma carta de um prisioneiro que queria ouvir o cantor. Agora é receber dele um par de sapatos. Além disso, o conjunto, a partir de agora, vai realizar shows na primeira segunda-feira de cada mês. Depois dos detentos, os internos do Hospital do Câncer poderão assistir ao mesmo espetáculo. DSP, 11/2/1969 – AA
A27: =RIGHT(K27,3) -> 027 | B27: Show musical em pátio com imensa plateia de detentos na Casa de Detenção da Av. Tiradentes (1977) | C27: Item | D27: 22151 | E27: Gerado pelo Dataverse | F27: Fotografia digitalizada; preto e branco; suporte em papel fotográfico | G27: São Paulo, Brasil | H27: Arquivo Público do Estado de São Paulo, Jornal Diários Associados | I27: Estado De São Paulo - Penitenciárias e Presídios - Casa de Detenção do Carandiru (Fotografias) | J27: Caixa: 3055 Folder: 5 | K27: =TEXTJOIN("", TRUE, Geral!B52:T52) -> BR-SPAPESP_DASP-PENITPRE-CSDTCARANDIRU_ICO-FOT-DGZ-MT0_3055-005-027 | L27: =$L$2 -> A Casa de Detenção de São Paulo, conhecida como Carandiru, foi formalmente criada em 1938 por decreto do interventor Adhemar de Barros, embora ainda instalada no edifício da Avenida Tiradentes. Sua implantação no bairro do Carandiru só se iniciou décadas depois, quando o governo estadual contratou, em 1951, o Escritório Técnico Ramos de Azevedo, Severo & Villares para projetar e conduzir a construção do novo complexo penitenciário em terreno contíguo à Penitenciária do Estado. As obras avançaram de forma modular, e o primeiro edifício concluído — o Pavilhão 2 — foi inaugurado em 1956, marcando a abertura parcial da chamada “Nova Casa de Detenção”. Ao longo dos anos seguintes, novos pavilhões foram sendo erguidos e inaugurados, compondo um conjunto arquitetônico que se consolidaria como um dos principais símbolos do sistema prisional paulista no século XX. Esta fotografia integra o fundo documental do grupo Diários Associados do Estado de São Paulo (DASP), custodiado pelo Arquivo Público do Estado de São Paulo (APESP), e registra aspectos desse prolongado processo de criação (1938), construção (a partir de 1951) e inauguração (a partir de 1956) da Casa de Detenção, conforme aponta a pesquisa de Maíra Rocha Machado, Bianca Tavolari e Maira Rosín (2025)[1]. | M27: A fotografia em preto e branco registra um show musical de grande escala realizado no pátio da instituição. Em primeiro plano, no palco, membros da banda ou grupo artístico (homens e mulheres) estão vestidos com roupas claras e casuais, tocando instrumentos (bateria, guitarra, etc.). O plano de fundo é dominado por uma muralha alta e sólida, onde há inscrições esparsas. Em frente a esta muralha, uma imensa multidão de homens (detentos) preenche completamente o espaço, olhando fixamente para o palco, evidenciando a superlotação e o grande público do evento. O verso da fotografia, datado de Junho de 1977, contextualiza a cena como a apresentação de um "show musical com vários nomes da música brasileira" na Casa de Detenção da Av. Tiradentes. | N27: O acesso aos documentos deste acervo está condicionado ao compromisso de não repassá-los a terceiros, à obrigatoriedade de mencionar que os originais pertencem ao Arquivo Público do Estado de São Paulo, e à necessidade de novo Termo de Responsabilidade em caso de reutilização ou uso diverso do inicialmente acordado. O uso está sujeito às restrições previstas na Lei de Arquivos (Lei nº 8.159/1991), na Lei de Direitos Autorais (Lei nº 9.610/1998), nos artigos 138 e 145 do Código Penal, e no artigo 5º, inciso X, da Constituição Federal, especialmente quanto à proteção da honra e imagem de terceiros. A pessoa física ou jurídica responsável assume integral responsabilidade civil e penal por eventuais danos decorrentes do uso das reproduções e informações, eximindo o Arquivo Público do Estado de São Paulo de qualquer responsabilidade. | O27: Show musical; Evento cultural; Aglomeração de detentos; Superlotação; Artistas (música brasileira); Pátio (externo); Muralha (prisão); Casa de Detenção (Avenida Tiradentes); 1977. | P27: Fotografia (Iconográfico) | Q27: Digitalização de fotografia em preto e branco (analógica original) | R27: ="Figura n – ["&B27&"]"&CHAR(10)&"Fonte: Arquivo do Estado de São Paulo, "&TEXT(D27,"yyyy")&"." -> Figura n – [Show musical em pátio com imensa plateia de detentos na Casa de Detenção da Av. Tiradentes (1977)] Fonte: Arquivo do Estado de São Paulo, 1960. | S27: ="ARQUIVO PÚBLICO DO ESTADO DE SÃO PAULO (Brasil). ["&B27&"]. "&G27&". "&TEXT(D27,"dd")&" "&LOWER(TEXT(D27,"mmm"))&" "&TEXT(D27,"yyyy")&". "&F27&". Disponível em: <link do dataverse>. Acesso em: 28 out. 2025." -> ARQUIVO PÚBLICO DO ESTADO DE SÃO PAULO (Brasil). [Show musical em pátio com imensa plateia de detentos na Casa de Detenção da Av. Tiradentes (1977)]. São Paulo, Brasil. 23 ago. 1960. Fotografia digitalizada; preto e branco; suporte em papel fotográfico. Disponível em: <link do dataverse>. Acesso em: 28 out. 2025. | T27: Estado de São Paulo – Penitenciárias e Presídios – Casa de Detenção da Av. Tiradentes Ontem, na Casa de Detenção, houve um show musical com vários nomes da música brasileira. DSP, 4/6/1977 – DCQ
A28: =RIGHT(K28,3) -> 028 | B28: Show musical para detentos no pátio, com o pavilhão da Casa de Detenção (Carandiru) ao fundo (1977) | C28: Item | D28: 22240 | E28: Gerado pelo Dataverse | F28: Fotografia digitalizada; preto e branco; suporte em papel fotográfico | G28: São Paulo, Brasil | H28: Arquivo Público do Estado de São Paulo, Jornal Diários Associados | I28: Estado De São Paulo - Penitenciárias e Presídios - Casa de Detenção do Carandiru (Fotografias) | J28: Caixa: 3055 Folder: 5 | K28: =TEXTJOIN("", TRUE, Geral!B54:T54) -> BR-SPAPESP_DASP-PENITPRE-CSDTCARANDIRU_ICO-FOT-DGZ-MT0_3055-005-028 | L28: =$L$2 -> A Casa de Detenção de São Paulo, conhecida como Carandiru, foi formalmente criada em 1938 por decreto do interventor Adhemar de Barros, embora ainda instalada no edifício da Avenida Tiradentes. Sua implantação no bairro do Carandiru só se iniciou décadas depois, quando o governo estadual contratou, em 1951, o Escritório Técnico Ramos de Azevedo, Severo & Villares para projetar e conduzir a construção do novo complexo penitenciário em terreno contíguo à Penitenciária do Estado. As obras avançaram de forma modular, e o primeiro edifício concluído — o Pavilhão 2 — foi inaugurado em 1956, marcando a abertura parcial da chamada “Nova Casa de Detenção”. Ao longo dos anos seguintes, novos pavilhões foram sendo erguidos e inaugurados, compondo um conjunto arquitetônico que se consolidaria como um dos principais símbolos do sistema prisional paulista no século XX. Esta fotografia integra o fundo documental do grupo Diários Associados do Estado de São Paulo (DASP), custodiado pelo Arquivo Público do Estado de São Paulo (APESP), e registra aspectos desse prolongado processo de criação (1938), construção (a partir de 1951) e inauguração (a partir de 1956) da Casa de Detenção, conforme aponta a pesquisa de Maíra Rocha Machado, Bianca Tavolari e Maira Rosín (2025)[1]. | M28: A fotografia em preto e branco registra a realização de um show musical em um pátio da Casa de Detenção. Em primeiro plano, um palco elevado abriga a banda, com músicos e equipamentos (amplificadores, bateria, mesa de som). Uma pequena plateia de pessoas em trajes civis, possivelmente autoridades, organizadores ou visitantes, assiste o show em cadeiras no canto inferior esquerdo. O público principal, composto por uma multidão de detentos, aglomera-se no pátio em frente ao palco. O elemento dominante da composição é o imponente Pavilhão prisional de vários andares, visível em toda a extensão do fundo. Suas fileiras simétricas de pequenas janelas e a arquitetura austera contrastam dramaticamente com a atividade cultural. O verso da fotografia, datado de 17 de dezembro de 1977, confirma que a imagem é um "Flagrante colhido... durante a apresentação de um show para os detentos". O registro documenta a justaposição de lazer e entretenimento com a rígida estrutura de contenção da prisão. | N28: O acesso aos documentos deste acervo está condicionado ao compromisso de não repassá-los a terceiros, à obrigatoriedade de mencionar que os originais pertencem ao Arquivo Público do Estado de São Paulo, e à necessidade de novo Termo de Responsabilidade em caso de reutilização ou uso diverso do inicialmente acordado. O uso está sujeito às restrições previstas na Lei de Arquivos (Lei nº 8.159/1991), na Lei de Direitos Autorais (Lei nº 9.610/1998), nos artigos 138 e 145 do Código Penal, e no artigo 5º, inciso X, da Constituição Federal, especialmente quanto à proteção da honra e imagem de terceiros. A pessoa física ou jurídica responsável assume integral responsabilidade civil e penal por eventuais danos decorrentes do uso das reproduções e informações, eximindo o Arquivo Público do Estado de São Paulo de qualquer responsabilidade. | O28: Show musical; Palco; Pavilhão (prisional); Estrutura arquitetônica; Público de detentos; Lazer; Evento cultural; Casa de Detenção; Carandiru; 1977. | P28: Fotografia (Iconográfico) | Q28: Digitalização de fotografia em preto e branco (analógica original) | R28: ="Figura n – ["&B28&"]"&CHAR(10)&"Fonte: Arquivo do Estado de São Paulo, "&TEXT(D28,"yyyy")&"." -> Figura n – [Show musical para detentos no pátio, com o pavilhão da Casa de Detenção (Carandiru) ao fundo (1977)] Fonte: Arquivo do Estado de São Paulo, 1960. | S28: ="ARQUIVO PÚBLICO DO ESTADO DE SÃO PAULO (Brasil). ["&B28&"]. "&G28&". "&TEXT(D28,"dd")&" "&LOWER(TEXT(D28,"mmm"))&" "&TEXT(D28,"yyyy")&". "&F28&". Disponível em: <link do dataverse>. Acesso em: 28 out. 2025." -> ARQUIVO PÚBLICO DO ESTADO DE SÃO PAULO (Brasil). [Show musical para detentos no pátio, com o pavilhão da Casa de Detenção (Carandiru) ao fundo (1977)]. São Paulo, Brasil. 20 nov. 1960. Fotografia digitalizada; preto e branco; suporte em papel fotográfico. Disponível em: <link do dataverse>. Acesso em: 28 out. 2025. | T28: Estado de São Paulo – Penitenciárias e Presídios – Casa de Detenção Flagrante colhido na Casa de Detenção, durante a apresentação de um show para os detentos. DN, 17/12/1977
A29: =RIGHT(K29,3) -> 029 | B29: Entrega de diplomas à primeira turma de detentos formandos (Curso Supletivo e Datilografia) no Carandiru (1973) | C29: Item | D29: 22250 | E29: Gerado pelo Dataverse | F29: Fotografia digitalizada; preto e branco; suporte em papel fotográfico | G29: São Paulo, Brasil | H29: Arquivo Público do Estado de São Paulo, Jornal Diários Associados | I29: Estado De São Paulo - Penitenciárias e Presídios - Casa de Detenção do Carandiru (Fotografias) | J29: Caixa: 3055 Folder: 5 | K29: =TEXTJOIN("", TRUE, Geral!B56:T56) -> BR-SPAPESP_DASP-PENITPRE-CSDTCARANDIRU_ICO-FOT-DGZ-MT0_3055-005-029 | L29: =$L$2 -> A Casa de Detenção de São Paulo, conhecida como Carandiru, foi formalmente criada em 1938 por decreto do interventor Adhemar de Barros, embora ainda instalada no edifício da Avenida Tiradentes. Sua implantação no bairro do Carandiru só se iniciou décadas depois, quando o governo estadual contratou, em 1951, o Escritório Técnico Ramos de Azevedo, Severo & Villares para projetar e conduzir a construção do novo complexo penitenciário em terreno contíguo à Penitenciária do Estado. As obras avançaram de forma modular, e o primeiro edifício concluído — o Pavilhão 2 — foi inaugurado em 1956, marcando a abertura parcial da chamada “Nova Casa de Detenção”. Ao longo dos anos seguintes, novos pavilhões foram sendo erguidos e inaugurados, compondo um conjunto arquitetônico que se consolidaria como um dos principais símbolos do sistema prisional paulista no século XX. Esta fotografia integra o fundo documental do grupo Diários Associados do Estado de São Paulo (DASP), custodiado pelo Arquivo Público do Estado de São Paulo (APESP), e registra aspectos desse prolongado processo de criação (1938), construção (a partir de 1951) e inauguração (a partir de 1956) da Casa de Detenção, conforme aponta a pesquisa de Maíra Rocha Machado, Bianca Tavolari e Maira Rosín (2025)[1]. | M29: A fotografia em primeiro plano captura o ponto alto de uma cerimônia de formatura na Casa de Detenção. À esquerda, uma autoridade em terno e gravata (identificado pelo verso como sendo uma das diversas autoridades presentes, como o diretor ou representantes do governo) estende a mão para cumprimentar um detento formando (o diplomando), enquanto lhe entrega o diploma enrolado (o objeto fino). O detento veste roupas casuais (camisa polo) e é o foco da celebração. O verso da fotografia, datado de 5 de maio de 1973, confirma que se trata da "entrega de diplomas à 1.a turma de detentos formandos" (totalizando 64 pessoas), nos cursos Supletivo e de Datilografia. | N29: O acesso aos documentos deste acervo está condicionado ao compromisso de não repassá-los a terceiros, à obrigatoriedade de mencionar que os originais pertencem ao Arquivo Público do Estado de São Paulo, e à necessidade de novo Termo de Responsabilidade em caso de reutilização ou uso diverso do inicialmente acordado. O uso está sujeito às restrições previstas na Lei de Arquivos (Lei nº 8.159/1991), na Lei de Direitos Autorais (Lei nº 9.610/1998), nos artigos 138 e 145 do Código Penal, e no artigo 5º, inciso X, da Constituição Federal, especialmente quanto à proteção da honra e imagem de terceiros. A pessoa física ou jurídica responsável assume integral responsabilidade civil e penal por eventuais danos decorrentes do uso das reproduções e informações, eximindo o Arquivo Público do Estado de São Paulo de qualquer responsabilidade. | O29: Formatura de detentos; Entrega de diplomas; Educação prisional; Reintegração social; Curso Supletivo; Curso de Datilografia; Autoridade (cumprimento); Detento (formando); Carandiru; 1973. | P29: Fotografia (Iconográfico) | Q29: Digitalização de fotografia em preto e branco (analógica original) | R29: ="Figura n – ["&B29&"]"&CHAR(10)&"Fonte: Arquivo do Estado de São Paulo, "&TEXT(D29,"yyyy")&"." -> Figura n – [Entrega de diplomas à primeira turma de detentos formandos (Curso Supletivo e Datilografia) no Carandiru (1973)] Fonte: Arquivo do Estado de São Paulo, 1960. | S29: ="ARQUIVO PÚBLICO DO ESTADO DE SÃO PAULO (Brasil). ["&B29&"]. "&G29&". "&TEXT(D29,"dd")&" "&LOWER(TEXT(D29,"mmm"))&" "&TEXT(D29,"yyyy")&". "&F29&". Disponível em: <link do dataverse>. Acesso em: 28 out. 2025." -> ARQUIVO PÚBLICO DO ESTADO DE SÃO PAULO (Brasil). [Entrega de diplomas à primeira turma de detentos formandos (Curso Supletivo e Datilografia) no Carandiru (1973)]. São Paulo, Brasil. 30 nov. 1960. Fotografia digitalizada; preto e branco; suporte em papel fotográfico. Disponível em: <link do dataverse>. Acesso em: 28 out. 2025. | T29: Estado de São Paulo – Penitenciárias e Presídios – Casa de Detenção Ontem, às 10 horas, na Casa de Detenção de São Paulo, realizou-se a entrega de diplomas (foto) aos integrantes da 1ª turma de detentos formandos. Foram diplomados 64 presidiários, sendo 46 no Curso Supletivo e 18 no Curso de Datilografia. Presentes ao ato: coronel Fernão Guedes de Souza, diretor da Casa de Detenção; Valério Giuli, representando o secretário do Trabalho; Dr. Werner Rodrigues Nogueira, diretor-geral do Departamento de Presídios Penais; Dra. Sofia Necolan, diretora do Ensino Supletivo do Estado; Edwaldo de Azevedo Sampaio, do CONTEL; e Dr. Silvio Barbosa, do SENAC. DSP, 5/5/1973 – MBO
A30: =RIGHT(K30,3) -> 030 | B30: Remoção de mortos ou feridos em lençóis após o motim sangrento na Casa de Detenção (1964) | C30: Item | D30: 22250 | E30: Gerado pelo Dataverse | F30: Fotografia digitalizada; sépia; suporte em papel fotográfico | G30: São Paulo, Brasil | H30: Arquivo Público do Estado de São Paulo, Jornal Diários Associados | I30: Estado De São Paulo - Penitenciárias e Presídios - Casa de Detenção do Carandiru (Fotografias) | J30: Caixa: 3055 Folder: 5 | K30: =TEXTJOIN("", TRUE, Geral!B58:T58) -> BR-SPAPESP_DASP-PENITPRE-CSDTCARANDIRU_ICO-FOT-DGZ-MT0_3055-005-030 | L30: =$L$2 -> A Casa de Detenção de São Paulo, conhecida como Carandiru, foi formalmente criada em 1938 por decreto do interventor Adhemar de Barros, embora ainda instalada no edifício da Avenida Tiradentes. Sua implantação no bairro do Carandiru só se iniciou décadas depois, quando o governo estadual contratou, em 1951, o Escritório Técnico Ramos de Azevedo, Severo & Villares para projetar e conduzir a construção do novo complexo penitenciário em terreno contíguo à Penitenciária do Estado. As obras avançaram de forma modular, e o primeiro edifício concluído — o Pavilhão 2 — foi inaugurado em 1956, marcando a abertura parcial da chamada “Nova Casa de Detenção”. Ao longo dos anos seguintes, novos pavilhões foram sendo erguidos e inaugurados, compondo um conjunto arquitetônico que se consolidaria como um dos principais símbolos do sistema prisional paulista no século XX. Esta fotografia integra o fundo documental do grupo Diários Associados do Estado de São Paulo (DASP), custodiado pelo Arquivo Público do Estado de São Paulo (APESP), e registra aspectos desse prolongado processo de criação (1938), construção (a partir de 1951) e inauguração (a partir de 1956) da Casa de Detenção, conforme aponta a pesquisa de Maíra Rocha Machado, Bianca Tavolari e Maira Rosín (2025)[1]. | M30: A fotografia em tom sépia, em ambiente de pouca luz (sugerindo noite ou área interna), registra a remoção de uma vítima (morto ou gravemente ferido) da Casa de Detenção. O foco da cena está em dois homens que carregam um volume pesado e disforme envolto em um tecido claro (lençol ou coberta). O verso confirma que "Mortos e feridos eram retirados em colchões, lençóis e cobertas" após o motim. O transporte ocorre junto a um portão de grades aberto, sob a supervisão de um policial ou agente penitenciário uniformizado à esquerda. Ao fundo, um veículo (provavelmente para transporte) e figuras em trajes civis (autoridades, imprensa ou investigadores) observam a ação, reforçando a natureza oficial e séria do evento. O verso da fotografia, datado de 16 de agosto de 1964, estabelece o contexto de "MOTIM SANGRENTO" na prisão, com "muitos mortos e centenas de feridos". | N30: O acesso aos documentos deste acervo está condicionado ao compromisso de não repassá-los a terceiros, à obrigatoriedade de mencionar que os originais pertencem ao Arquivo Público do Estado de São Paulo, e à necessidade de novo Termo de Responsabilidade em caso de reutilização ou uso diverso do inicialmente acordado. O uso está sujeito às restrições previstas na Lei de Arquivos (Lei nº 8.159/1991), na Lei de Direitos Autorais (Lei nº 9.610/1998), nos artigos 138 e 145 do Código Penal, e no artigo 5º, inciso X, da Constituição Federal, especialmente quanto à proteção da honra e imagem de terceiros. A pessoa física ou jurídica responsável assume integral responsabilidade civil e penal por eventuais danos decorrentes do uso das reproduções e informações, eximindo o Arquivo Público do Estado de São Paulo de qualquer responsabilidade. | O30: Motim (consequências); Remoção de corpos; Violência carcerária; Lençóis (transporte); Policial (supervisão); Crise prisional; Casa de Detenção; Carandiru; 1964; Mortos e feridos; Flagrante. | P30: Fotografia (Iconográfico) | Q30: Digitalização de fotografia em sépia (analógica original) | R30: ="Figura n – ["&B30&"]"&CHAR(10)&"Fonte: Arquivo do Estado de São Paulo, "&TEXT(D30,"yyyy")&"." -> Figura n – [Remoção de mortos ou feridos em lençóis após o motim sangrento na Casa de Detenção (1964)] Fonte: Arquivo do Estado de São Paulo, 1960. | S30: ="ARQUIVO PÚBLICO DO ESTADO DE SÃO PAULO (Brasil). ["&B30&"]. "&G30&". "&TEXT(D30,"dd")&" "&LOWER(TEXT(D30,"mmm"))&" "&TEXT(D30,"yyyy")&". "&F30&". Disponível em: <link do dataverse>. Acesso em: 28 out. 2025." -> ARQUIVO PÚBLICO DO ESTADO DE SÃO PAULO (Brasil). [Remoção de mortos ou feridos em lençóis após o motim sangrento na Casa de Detenção (1964)]. São Paulo, Brasil. 30 nov. 1960. Fotografia digitalizada; sépia; suporte em papel fotográfico. Disponível em: <link do dataverse>. Acesso em: 28 out. 2025. | T30: Estado de São Paulo – Penitenciárias e Presídios – Casa de Detenção do Carandiru Sangrento motim na Casa de Detenção: muitos mortos e centenas de feridos [Texto em pequeno retângulo, recorte de legenda ou matéria] Cenas como a da foto repetiram-se continuamente, após dominado o motim. Mortos e feridos eram retirados em colchões, lençóis e cobertas. A reportagem não tinha dados sobre a quantidade ou a relação dos que perderam a vida ou dos que ficaram feridos. DSP, 16/8/1964 – W
A31: =RIGHT(K31,3) -> 031 | B31: Remoção de vítima fatal ou ferido em lençol listrado após o motim de 14 de agosto de 1964 no Carandiru | C31: Item | D31: 22451 | E31: Gerado pelo Dataverse | F31: Fotografia digitalizada; sépia; suporte em papel fotográfico | G31: São Paulo, Brasil | H31: Arquivo Público do Estado de São Paulo, Jornal Diários Associados | I31: Estado De São Paulo - Penitenciárias e Presídios - Casa de Detenção do Carandiru (Fotografias) | J31: Caixa: 3055 Folder: 5 | K31: =TEXTJOIN("", TRUE, Geral!B60:T60) -> BR-SPAPESP_DASP-PENITPRE-CSDTCARANDIRU_ICO-FOT-DGZ-MT0_3055-005-031 | L31: =$L$2 -> A Casa de Detenção de São Paulo, conhecida como Carandiru, foi formalmente criada em 1938 por decreto do interventor Adhemar de Barros, embora ainda instalada no edifício da Avenida Tiradentes. Sua implantação no bairro do Carandiru só se iniciou décadas depois, quando o governo estadual contratou, em 1951, o Escritório Técnico Ramos de Azevedo, Severo & Villares para projetar e conduzir a construção do novo complexo penitenciário em terreno contíguo à Penitenciária do Estado. As obras avançaram de forma modular, e o primeiro edifício concluído — o Pavilhão 2 — foi inaugurado em 1956, marcando a abertura parcial da chamada “Nova Casa de Detenção”. Ao longo dos anos seguintes, novos pavilhões foram sendo erguidos e inaugurados, compondo um conjunto arquitetônico que se consolidaria como um dos principais símbolos do sistema prisional paulista no século XX. Esta fotografia integra o fundo documental do grupo Diários Associados do Estado de São Paulo (DASP), custodiado pelo Arquivo Público do Estado de São Paulo (APESP), e registra aspectos desse prolongado processo de criação (1938), construção (a partir de 1951) e inauguração (a partir de 1956) da Casa de Detenção, conforme aponta a pesquisa de Maíra Rocha Machado, Bianca Tavolari e Maira Rosín (2025)[1]. | M31: A fotografia em tom sépia, em close-up, registra a remoção urgente de uma vítima (morto ou ferido) da Casa de Detenção, envolta em um tecido listrado. A ação é realizada por dois homens com vestimentas civis, que se curvam para carregar o volume pesado. A cena ocorre na área de saída, próximo a grades e portões. Em segundo plano, diversas figuras de autoridades, funcionários e possivelmente imprensa (vestindo ternos e chapéus) observam a remoção com expressões de seriedade, indicando a natureza oficial e crítica da situação. O verso da fotografia contextualiza o evento, afirmando que a imagem é um "Flagrante tomado durante o tragico motim" ocorrido na noite do dia 14 de agosto de 1964. A legenda secundária questiona a condição da vítima ("MORTO OU FERIDO?"), descrevendo que a cena se tornou comum após a revolta e destacando a incerteza e a falta de comunicação oficial sobre as vítimas. A imagem é um forte registro da violência e do caos pós-motim. | N31: O acesso aos documentos deste acervo está condicionado ao compromisso de não repassá-los a terceiros, à obrigatoriedade de mencionar que os originais pertencem ao Arquivo Público do Estado de São Paulo, e à necessidade de novo Termo de Responsabilidade em caso de reutilização ou uso diverso do inicialmente acordado. O uso está sujeito às restrições previstas na Lei de Arquivos (Lei nº 8.159/1991), na Lei de Direitos Autorais (Lei nº 9.610/1998), nos artigos 138 e 145 do Código Penal, e no artigo 5º, inciso X, da Constituição Federal, especialmente quanto à proteção da honra e imagem de terceiros. A pessoa física ou jurídica responsável assume integral responsabilidade civil e penal por eventuais danos decorrentes do uso das reproduções e informações, eximindo o Arquivo Público do Estado de São Paulo de qualquer responsabilidade. | O31: Remoção de corpo; Motim trágico; Violência carcerária; Vítima (morta/ferida); Lençol (transporte); Autoridades (investigação); Crise prisional; Casa de Detenção; Carandiru; 1964. | P31: Fotografia (Iconográfico) | Q31: Digitalização de fotografia em sépia (analógica original) | R31: ="Figura n – ["&B31&"]"&CHAR(10)&"Fonte: Arquivo do Estado de São Paulo, "&TEXT(D31,"yyyy")&"." -> Figura n – [Remoção de vítima fatal ou ferido em lençol listrado após o motim de 14 de agosto de 1964 no Carandiru] Fonte: Arquivo do Estado de São Paulo, 1961. | S31: ="ARQUIVO PÚBLICO DO ESTADO DE SÃO PAULO (Brasil). ["&B31&"]. "&G31&". "&TEXT(D31,"dd")&" "&LOWER(TEXT(D31,"mmm"))&" "&TEXT(D31,"yyyy")&". "&F31&". Disponível em: <link do dataverse>. Acesso em: 28 out. 2025." -> ARQUIVO PÚBLICO DO ESTADO DE SÃO PAULO (Brasil). [Remoção de vítima fatal ou ferido em lençol listrado após o motim de 14 de agosto de 1964 no Carandiru]. São Paulo, Brasil. 19 jun. 1961. Fotografia digitalizada; sépia; suporte em papel fotográfico. Disponível em: <link do dataverse>. Acesso em: 28 out. 2025. | T31: Estado de São Paulo – Penitenciárias e Presídios – Casa de Detenção do Carandiru Motim de ódio e desespero sacudiu a Casa de Detenção Flagrante tomado durante o trágico motim ocorrido na Casa de Detenção do Carandiru na noite do dia 14. DN, 1ª ed., 17/8/1964 – W [Texto em pequeno retângulo, recorte de legenda ou matéria] Morto ou ferido? – Cenas como esta, da foto de Orlando Alves, chegaram a ser comuns após debelada a revolta do ódio na Casa de Detenção. Ninguém sabia informar se se tratava de mortos ou feridos. A Secretaria da Segurança Pública ainda não expediu nenhum comunicado a respeito. Tudo gira no terreno das hipóteses.
A32: =RIGHT(K32,3) -> 032 | B32: Mulher idosa (familiar) pressiona entrada na Casa de Detenção durante motim (1964) | C32: Item | D32: 22502 | E32: Gerado pelo Dataverse | F32: Fotografia digitalizada; sépia; suporte em papel fotográfico | G32: São Paulo, Brasil | H32: Arquivo Público do Estado de São Paulo, Jornal Diários Associados | I32: Estado De São Paulo - Penitenciárias e Presídios - Casa de Detenção do Carandiru (Fotografias) | J32: Caixa: 3055 Folder: 5 | K32: =TEXTJOIN("", TRUE, Geral!B62:T62) -> BR-SPAPESP_DASP-PENITPRE-CSDTCARANDIRU_ICO-FOT-DGZ-MT0_3055-005-032 | L32: =$L$2 -> A Casa de Detenção de São Paulo, conhecida como Carandiru, foi formalmente criada em 1938 por decreto do interventor Adhemar de Barros, embora ainda instalada no edifício da Avenida Tiradentes. Sua implantação no bairro do Carandiru só se iniciou décadas depois, quando o governo estadual contratou, em 1951, o Escritório Técnico Ramos de Azevedo, Severo & Villares para projetar e conduzir a construção do novo complexo penitenciário em terreno contíguo à Penitenciária do Estado. As obras avançaram de forma modular, e o primeiro edifício concluído — o Pavilhão 2 — foi inaugurado em 1956, marcando a abertura parcial da chamada “Nova Casa de Detenção”. Ao longo dos anos seguintes, novos pavilhões foram sendo erguidos e inaugurados, compondo um conjunto arquitetônico que se consolidaria como um dos principais símbolos do sistema prisional paulista no século XX. Esta fotografia integra o fundo documental do grupo Diários Associados do Estado de São Paulo (DASP), custodiado pelo Arquivo Público do Estado de São Paulo (APESP), e registra aspectos desse prolongado processo de criação (1938), construção (a partir de 1951) e inauguração (a partir de 1956) da Casa de Detenção, conforme aponta a pesquisa de Maíra Rocha Machado, Bianca Tavolari e Maira Rosín (2025)[1]. | M32: A fotografia em tom sépia, capturada em plano próximo, registra uma mulher idosa junto a uma porta ou portão da Casa de Detenção, em uma posição de insistência ou espera. A mulher com lenço de bolinhas na cabeça, está de perfil, com as mãos visíveis sobre a porta, sugerindo que está tentando abri-la ou interagir com alguém do lado de dentro. A luz forte destaca a figura. O verso da fotografia, datado de 17 de agosto de 1964, contextualiza a cena em um cenário de crise após um motim provocado pelo "Regime de Terror". A legenda original descreve a "Dúvida, intranquilidade e temor" que levaram "essa gente às portas da Casa de Detenção", mencionando que a "barreira foi vencida pela resignação" para que pudessem entrar no "cenário da rebelião". | N32: O acesso aos documentos deste acervo está condicionado ao compromisso de não repassá-los a terceiros, à obrigatoriedade de mencionar que os originais pertencem ao Arquivo Público do Estado de São Paulo, e à necessidade de novo Termo de Responsabilidade em caso de reutilização ou uso diverso do inicialmente acordado. O uso está sujeito às restrições previstas na Lei de Arquivos (Lei nº 8.159/1991), na Lei de Direitos Autorais (Lei nº 9.610/1998), nos artigos 138 e 145 do Código Penal, e no artigo 5º, inciso X, da Constituição Federal, especialmente quanto à proteção da honra e imagem de terceiros. A pessoa física ou jurídica responsável assume integral responsabilidade civil e penal por eventuais danos decorrentes do uso das reproduções e informações, eximindo o Arquivo Público do Estado de São Paulo de qualquer responsabilidade. | O32: Familiar (visita); Mulher idosa; Motim (consequências); Tensão; Controle de acesso; Persistência (familiar); Crise prisional; Casa de Detenção; Carandiru; 1964; Lenço na cabeça. | P32: Fotografia (Iconográfico) | Q32: Digitalização de fotografia em sépia (analógica original) | R32: ="Figura n – ["&B32&"]"&CHAR(10)&"Fonte: Arquivo do Estado de São Paulo, "&TEXT(D32,"yyyy")&"." -> Figura n – [Mulher idosa (familiar) pressiona entrada na Casa de Detenção durante motim (1964)] Fonte: Arquivo do Estado de São Paulo, 1961. | S32: ="ARQUIVO PÚBLICO DO ESTADO DE SÃO PAULO (Brasil). ["&B32&"]. "&G32&". "&TEXT(D32,"dd")&" "&LOWER(TEXT(D32,"mmm"))&" "&TEXT(D32,"yyyy")&". "&F32&". Disponível em: <link do dataverse>. Acesso em: 28 out. 2025." -> ARQUIVO PÚBLICO DO ESTADO DE SÃO PAULO (Brasil). [Mulher idosa (familiar) pressiona entrada na Casa de Detenção durante motim (1964)]. São Paulo, Brasil. 09 ago. 1961. Fotografia digitalizada; sépia; suporte em papel fotográfico. Disponível em: <link do dataverse>. Acesso em: 28 out. 2025. | T32: Estado de São Paulo – Penitenciárias e Presídios – Casa de Detenção do Carandiru Detenção: regime de terror provocou motim Dúvida, intranquilidade e temor levaram essa gente às portas da Casa de Detenção, cuja barreira foi vencida pela resignação. A proibição caiu e todos puderam entrar no cenário da rebelião. Ver. DN, 2ª ed., 17/8/1964 – DMC
A33: =RIGHT(K33,3) -> 033 | B33: Agente prisional em contato com familiares e crianças na entrada da Casa de Detenção durante crise (1964) | C33: Item | D33: 22502 | E33: Gerado pelo Dataverse | F33: Fotografia digitalizada; sépia; suporte em papel fotográfico | G33: São Paulo, Brasil | H33: Arquivo Público do Estado de São Paulo, Jornal Diários Associados | I33: Estado De São Paulo - Penitenciárias e Presídios - Casa de Detenção do Carandiru (Fotografias) | J33: Caixa: 3055 Folder: 5 | K33: =TEXTJOIN("", TRUE, Geral!B64:T64) -> BR-SPAPESP_DASP-PENITPRE-CSDTCARANDIRU_ICO-FOT-DGZ-MT0_3055-005-033 | L33: =$L$2 -> A Casa de Detenção de São Paulo, conhecida como Carandiru, foi formalmente criada em 1938 por decreto do interventor Adhemar de Barros, embora ainda instalada no edifício da Avenida Tiradentes. Sua implantação no bairro do Carandiru só se iniciou décadas depois, quando o governo estadual contratou, em 1951, o Escritório Técnico Ramos de Azevedo, Severo & Villares para projetar e conduzir a construção do novo complexo penitenciário em terreno contíguo à Penitenciária do Estado. As obras avançaram de forma modular, e o primeiro edifício concluído — o Pavilhão 2 — foi inaugurado em 1956, marcando a abertura parcial da chamada “Nova Casa de Detenção”. Ao longo dos anos seguintes, novos pavilhões foram sendo erguidos e inaugurados, compondo um conjunto arquitetônico que se consolidaria como um dos principais símbolos do sistema prisional paulista no século XX. Esta fotografia integra o fundo documental do grupo Diários Associados do Estado de São Paulo (DASP), custodiado pelo Arquivo Público do Estado de São Paulo (APESP), e registra aspectos desse prolongado processo de criação (1938), construção (a partir de 1951) e inauguração (a partir de 1956) da Casa de Detenção, conforme aponta a pesquisa de Maíra Rocha Machado, Bianca Tavolari e Maira Rosín (2025)[1]. | M33: A fotografia em tom sépia, em plano médio, registra a interação de uma família com um agente de segurança na entrada da Casa de Detenção. O agente está posicionado na abertura do portão de metal escuro, vestindo uniforme claro, que inclui quepe e gravata, e tem a mão levantada em um gesto que sugere interrupção ou instrução. Em frente ao agente, um grupo de familiares o confronta: há um homem de terno claro, duas mulheres (vistas de costas) e duas crianças pequenas. A presença das crianças no local e a postura do agente indicam a natureza da visita familiar sob estrito controle. O verso da fotografia, datado de 17 de agosto de 1964, contextualiza a cena em um cenário de crise após um motim provocado pelo "Regime de Terror". A legenda original descreve a "Dúvida, intranquilidade e temor" que levaram "essa gente às portas da Casa de Detenção" e a posterior permissão para entrar no "cenário da rebelião". | N33: O acesso aos documentos deste acervo está condicionado ao compromisso de não repassá-los a terceiros, à obrigatoriedade de mencionar que os originais pertencem ao Arquivo Público do Estado de São Paulo, e à necessidade de novo Termo de Responsabilidade em caso de reutilização ou uso diverso do inicialmente acordado. O uso está sujeito às restrições previstas na Lei de Arquivos (Lei nº 8.159/1991), na Lei de Direitos Autorais (Lei nº 9.610/1998), nos artigos 138 e 145 do Código Penal, e no artigo 5º, inciso X, da Constituição Federal, especialmente quanto à proteção da honra e imagem de terceiros. A pessoa física ou jurídica responsável assume integral responsabilidade civil e penal por eventuais danos decorrentes do uso das reproduções e informações, eximindo o Arquivo Público do Estado de São Paulo de qualquer responsabilidade. | O33: Visita familiar; Agente penitenciário; Crianças (visita); Entrada (presídio); Motim (consequências); Crise prisional; Controle de acesso; Casa de Detenção; Carandiru; 1964. | P33: Fotografia (Iconográfico) | Q33: Digitalização de fotografia em sépia (analógica original) | R33: ="Figura n – ["&B33&"]"&CHAR(10)&"Fonte: Arquivo do Estado de São Paulo, "&TEXT(D33,"yyyy")&"." -> Figura n – [Agente prisional em contato com familiares e crianças na entrada da Casa de Detenção durante crise (1964)] Fonte: Arquivo do Estado de São Paulo, 1961. | S33: ="ARQUIVO PÚBLICO DO ESTADO DE SÃO PAULO (Brasil). ["&B33&"]. "&G33&". "&TEXT(D33,"dd")&" "&LOWER(TEXT(D33,"mmm"))&" "&TEXT(D33,"yyyy")&". "&F33&". Disponível em: <link do dataverse>. Acesso em: 28 out. 2025." -> ARQUIVO PÚBLICO DO ESTADO DE SÃO PAULO (Brasil). [Agente prisional em contato com familiares e crianças na entrada da Casa de Detenção durante crise (1964)]. São Paulo, Brasil. 09 ago. 1961. Fotografia digitalizada; sépia; suporte em papel fotográfico. Disponível em: <link do dataverse>. Acesso em: 28 out. 2025. | T33: Estado de São Paulo – Penitenciárias e Presídios – Casa de Detenção do Carandiru Detenção: regime de terror provocou motim Dúvida, intranquilidade e temor levaram essa gente às portas da Casa de Detenção, cuja barreira foi vencida pela resignação. A proibição caiu e todos puderam entrar no cenário da rebelião. Ver. DN, 2ª ed., 17/8/1964 – DMC
A34: =RIGHT(K34,3) -> 034 | B34: Artista do Circo Orlando Orfei se apresentando para a plateia de detentos no pátio do Carandiru (1979) | C34: Item | D34: 22517 | E34: Gerado pelo Dataverse | F34: Fotografia digitalizada; sépia; suporte em papel fotográfico | G34: São Paulo, Brasil | H34: Arquivo Público do Estado de São Paulo, Jornal Diários Associados | I34: Estado De São Paulo - Penitenciárias e Presídios - Casa de Detenção do Carandiru (Fotografias) | J34: Caixa: 3055 Folder: 5 | K34: =TEXTJOIN("", TRUE, Geral!B66:T66) -> BR-SPAPESP_DASP-PENITPRE-CSDTCARANDIRU_ICO-FOT-DGZ-MT0_3055-005-034 | L34: =$L$2 -> A Casa de Detenção de São Paulo, conhecida como Carandiru, foi formalmente criada em 1938 por decreto do interventor Adhemar de Barros, embora ainda instalada no edifício da Avenida Tiradentes. Sua implantação no bairro do Carandiru só se iniciou décadas depois, quando o governo estadual contratou, em 1951, o Escritório Técnico Ramos de Azevedo, Severo & Villares para projetar e conduzir a construção do novo complexo penitenciário em terreno contíguo à Penitenciária do Estado. As obras avançaram de forma modular, e o primeiro edifício concluído — o Pavilhão 2 — foi inaugurado em 1956, marcando a abertura parcial da chamada “Nova Casa de Detenção”. Ao longo dos anos seguintes, novos pavilhões foram sendo erguidos e inaugurados, compondo um conjunto arquitetônico que se consolidaria como um dos principais símbolos do sistema prisional paulista no século XX. Esta fotografia integra o fundo documental do grupo Diários Associados do Estado de São Paulo (DASP), custodiado pelo Arquivo Público do Estado de São Paulo (APESP), e registra aspectos desse prolongado processo de criação (1938), construção (a partir de 1951) e inauguração (a partir de 1956) da Casa de Detenção, conforme aponta a pesquisa de Maíra Rocha Machado, Bianca Tavolari e Maira Rosín (2025)[1]. | M34: A fotografia em tom sépia, capturada em plano aberto, registra um espetáculo circense no pátio externo da Casa de Detenção. O foco está em uma artista em performance, equilibrando-se sobre um adereço de cabeça ou objeto esférico, e manipulando aros no ar. A artista veste um traje acrobático claro, justo e com detalhes de amarração. O cenário é dominado por uma grande plateia de detentos aglomerados, observando a apresentação com atenção. Ao fundo, o muro alto e sólido da prisão demarca o limite do pátio, com figuras de guarda ou agentes de vigilância visíveis no topo. Uma placa com a inscrição "ESPORTES" está parcialmente visível na lateral. O verso da fotografia, datado de 24 de julho de 1979, contextualiza a cena como um "espetáculo" apresentado pelos "artistas do Circo Orlando Orfei". | N34: O acesso aos documentos deste acervo está condicionado ao compromisso de não repassá-los a terceiros, à obrigatoriedade de mencionar que os originais pertencem ao Arquivo Público do Estado de São Paulo, e à necessidade de novo Termo de Responsabilidade em caso de reutilização ou uso diverso do inicialmente acordado. O uso está sujeito às restrições previstas na Lei de Arquivos (Lei nº 8.159/1991), na Lei de Direitos Autorais (Lei nº 9.610/1998), nos artigos 138 e 145 do Código Penal, e no artigo 5º, inciso X, da Constituição Federal, especialmente quanto à proteção da honra e imagem de terceiros. A pessoa física ou jurídica responsável assume integral responsabilidade civil e penal por eventuais danos decorrentes do uso das reproduções e informações, eximindo o Arquivo Público do Estado de São Paulo de qualquer responsabilidade. | O34: Circo Orlando Orfei; Espetáculo circense; Artista (performance); Pátio (externo); Entretenimento; Detentos (plateia); Muro prisional; Carandiru; Lazer; 1979. | P34: Fotografia (Iconográfico) | Q34: Digitalização de fotografia em sépia (analógica original) | R34: ="Figura n – ["&B34&"]"&CHAR(10)&"Fonte: Arquivo do Estado de São Paulo, "&TEXT(D34,"yyyy")&"." -> Figura n – [Artista do Circo Orlando Orfei se apresentando para a plateia de detentos no pátio do Carandiru (1979)] Fonte: Arquivo do Estado de São Paulo, 1961. | S34: ="ARQUIVO PÚBLICO DO ESTADO DE SÃO PAULO (Brasil). ["&B34&"]. "&G34&". "&TEXT(D34,"dd")&" "&LOWER(TEXT(D34,"mmm"))&" "&TEXT(D34,"yyyy")&". "&F34&". Disponível em: <link do dataverse>. Acesso em: 28 out. 2025." -> ARQUIVO PÚBLICO DO ESTADO DE SÃO PAULO (Brasil). [Artista do Circo Orlando Orfei se apresentando para a plateia de detentos no pátio do Carandiru (1979)]. São Paulo, Brasil. 24 ago. 1961. Fotografia digitalizada; sépia; suporte em papel fotográfico. Disponível em: <link do dataverse>. Acesso em: 28 out. 2025. | T34: Estado de São Paulo – Penitenciária e Presídios – Carandiru Os artistas do Circo Orlando Orfei, durante espetáculo na Casa de Detenção de São Paulo. DN, 24/7/1979
A35: =RIGHT(K35,3) -> 035 | B35: Vista frontal de um dos pavilhões da Casa de Detenção (Carandiru) em 1979 | C35: Item | D35: 22533 | E35: Gerado pelo Dataverse | F35: Fotografia digitalizada; preto e branco; suporte em papel fotográfico | G35: São Paulo, Brasil | H35: Arquivo Público do Estado de São Paulo, Jornal Diários Associados | I35: Estado De São Paulo - Penitenciárias e Presídios - Casa de Detenção do Carandiru (Fotografias) | J35: Caixa: 3055 Folder: 5 | K35: =TEXTJOIN("", TRUE, Geral!B68:T68) -> BR-SPAPESP_DASP-PENITPRE-CSDTCARANDIRU_ICO-FOT-DGZ-MT0_3055-005-035 | L35: =$L$2 -> A Casa de Detenção de São Paulo, conhecida como Carandiru, foi formalmente criada em 1938 por decreto do interventor Adhemar de Barros, embora ainda instalada no edifício da Avenida Tiradentes. Sua implantação no bairro do Carandiru só se iniciou décadas depois, quando o governo estadual contratou, em 1951, o Escritório Técnico Ramos de Azevedo, Severo & Villares para projetar e conduzir a construção do novo complexo penitenciário em terreno contíguo à Penitenciária do Estado. As obras avançaram de forma modular, e o primeiro edifício concluído — o Pavilhão 2 — foi inaugurado em 1956, marcando a abertura parcial da chamada “Nova Casa de Detenção”. Ao longo dos anos seguintes, novos pavilhões foram sendo erguidos e inaugurados, compondo um conjunto arquitetônico que se consolidaria como um dos principais símbolos do sistema prisional paulista no século XX. Esta fotografia integra o fundo documental do grupo Diários Associados do Estado de São Paulo (DASP), custodiado pelo Arquivo Público do Estado de São Paulo (APESP), e registra aspectos desse prolongado processo de criação (1938), construção (a partir de 1951) e inauguração (a partir de 1956) da Casa de Detenção, conforme aponta a pesquisa de Maíra Rocha Machado, Bianca Tavolari e Maira Rosín (2025)[1]. | M35: A fotografia em preto e branco registra a arquitetura de contenção do Complexo Carandiru. O plano de fundo é dominado por um Pavilhão de múltiplos andares, com fileiras simétricas e repetitivas de pequenas janelas gradeadas. A base deste pavilhão é separada do pátio por um muro de concreto alto e sólido, sobre o qual há cercas e pequenas guaritas. No canto esquerdo, uma torre de vigilância elevada, com um foco de luz, reforça o controle de segurança. A composição enfatiza o caráter imponente, austero e fechado do presídio. O verso da fotografia, datado de 31 de maio de 1979, contextualiza a imagem como uma denúncia, com a legenda: "Quem passa pela avenida Cruzeiro do Sul não imagina o que acontece lá dentro". | N35: O acesso aos documentos deste acervo está condicionado ao compromisso de não repassá-los a terceiros, à obrigatoriedade de mencionar que os originais pertencem ao Arquivo Público do Estado de São Paulo, e à necessidade de novo Termo de Responsabilidade em caso de reutilização ou uso diverso do inicialmente acordado. O uso está sujeito às restrições previstas na Lei de Arquivos (Lei nº 8.159/1991), na Lei de Direitos Autorais (Lei nº 9.610/1998), nos artigos 138 e 145 do Código Penal, e no artigo 5º, inciso X, da Constituição Federal, especialmente quanto à proteção da honra e imagem de terceiros. A pessoa física ou jurídica responsável assume integral responsabilidade civil e penal por eventuais danos decorrentes do uso das reproduções e informações, eximindo o Arquivo Público do Estado de São Paulo de qualquer responsabilidade. | O35: Arquitetura prisional; Pavilhão (prisional); Muro de contenção; Torre de vigilância; Confinamento; Isolamento social; Denúncia (condições); Casa de Detenção; Carandiru; 1979. | P35: Fotografia (Iconográfico) | Q35: Digitalização de fotografia em preto e branco (analógica original) | R35: ="Figura n – ["&B35&"]"&CHAR(10)&"Fonte: Arquivo do Estado de São Paulo, "&TEXT(D35,"yyyy")&"." -> Figura n – [Vista frontal de um dos pavilhões da Casa de Detenção (Carandiru) em 1979] Fonte: Arquivo do Estado de São Paulo, 1961. | S35: ="ARQUIVO PÚBLICO DO ESTADO DE SÃO PAULO (Brasil). ["&B35&"]. "&G35&". "&TEXT(D35,"dd")&" "&LOWER(TEXT(D35,"mmm"))&" "&TEXT(D35,"yyyy")&". "&F35&". Disponível em: <link do dataverse>. Acesso em: 28 out. 2025." -> ARQUIVO PÚBLICO DO ESTADO DE SÃO PAULO (Brasil). [Vista frontal de um dos pavilhões da Casa de Detenção (Carandiru) em 1979]. São Paulo, Brasil. 09 set. 1961. Fotografia digitalizada; preto e branco; suporte em papel fotográfico. Disponível em: <link do dataverse>. Acesso em: 28 out. 2025. | T35: Estado de São Paulo – Penitenciária e Presídios – Casa de Detenção de São Paulo Quem passa pela Avenida Cruzeiro do Sul não imagina o que acontece lá dentro. DSP, 31/5/1979 – AAT
A36: =RIGHT(K36,3) -> 036 | B36: Apresentação e registro dos novos detentos na administração da Casa de Detenção (1979) | C36: Item | D36: 22533 | E36: Gerado pelo Dataverse | F36: Fotografia digitalizada; preto e branco; suporte em papel fotográfico | G36: São Paulo, Brasil | H36: Arquivo Público do Estado de São Paulo, Jornal Diários Associados | I36: Estado De São Paulo - Penitenciárias e Presídios - Casa de Detenção do Carandiru (Fotografias) | J36: Caixa: 3055 Folder: 5 | K36: =TEXTJOIN("", TRUE, Geral!B70:T70) -> BR-SPAPESP_DASP-PENITPRE-CSDTCARANDIRU_ICO-FOT-DGZ-MT0_3055-005-036 | L36: =$L$2 -> A Casa de Detenção de São Paulo, conhecida como Carandiru, foi formalmente criada em 1938 por decreto do interventor Adhemar de Barros, embora ainda instalada no edifício da Avenida Tiradentes. Sua implantação no bairro do Carandiru só se iniciou décadas depois, quando o governo estadual contratou, em 1951, o Escritório Técnico Ramos de Azevedo, Severo & Villares para projetar e conduzir a construção do novo complexo penitenciário em terreno contíguo à Penitenciária do Estado. As obras avançaram de forma modular, e o primeiro edifício concluído — o Pavilhão 2 — foi inaugurado em 1956, marcando a abertura parcial da chamada “Nova Casa de Detenção”. Ao longo dos anos seguintes, novos pavilhões foram sendo erguidos e inaugurados, compondo um conjunto arquitetônico que se consolidaria como um dos principais símbolos do sistema prisional paulista no século XX. Esta fotografia integra o fundo documental do grupo Diários Associados do Estado de São Paulo (DASP), custodiado pelo Arquivo Público do Estado de São Paulo (APESP), e registra aspectos desse prolongado processo de criação (1938), construção (a partir de 1951) e inauguração (a partir de 1956) da Casa de Detenção, conforme aponta a pesquisa de Maíra Rocha Machado, Bianca Tavolari e Maira Rosín (2025)[1]. | M36: A fotografia em preto e branco registra um momento de apresentação formal ou entrevista na Casa de Detenção. O enquadramento é feito por cima do ombro de uma autoridade/funcionário (visto de costas, em primeiro plano, sentado a uma mesa). Em frente à mesa, um grupo de jovens detentos recém-chegados está alinhado e de pé. Eles estão com a cabeça raspada e vestem camisetas padronizadas claras (possivelmente uniformes), alguns com inscrições escuras visíveis, como "CD" (Casa de Detenção). As expressões faciais são sérias e atentas. O ambiente interno possui papel de parede decorado. O verso da fotografia, datado de 29 de maio de 1979, contextualiza a cena como "Os novos 'hospedes' da Casa de Detenção". A imagem documenta o procedimento inicial de recepção e instrução, no qual os novos presos são recebidos por figuras administrativas para o registro e a transmissão das primeiras regras do ambiente carcerário. | N36: O acesso aos documentos deste acervo está condicionado ao compromisso de não repassá-los a terceiros, à obrigatoriedade de mencionar que os originais pertencem ao Arquivo Público do Estado de São Paulo, e à necessidade de novo Termo de Responsabilidade em caso de reutilização ou uso diverso do inicialmente acordado. O uso está sujeito às restrições previstas na Lei de Arquivos (Lei nº 8.159/1991), na Lei de Direitos Autorais (Lei nº 9.610/1998), nos artigos 138 e 145 do Código Penal, e no artigo 5º, inciso X, da Constituição Federal, especialmente quanto à proteção da honra e imagem de terceiros. A pessoa física ou jurídica responsável assume integral responsabilidade civil e penal por eventuais danos decorrentes do uso das reproduções e informações, eximindo o Arquivo Público do Estado de São Paulo de qualquer responsabilidade. | O36: Novos detentos; Chegada de presos; Uniforme prisional; Corte de cabelo (cabeça raspada); Procedimento de registro; Administração prisional; Autoridade (entrevista); Casa de Detenção; Carandiru; 1979. | P36: Fotografia (Iconográfico) | Q36: Digitalização de fotografia em preto e branco (analógica original) | R36: ="Figura n – ["&B36&"]"&CHAR(10)&"Fonte: Arquivo do Estado de São Paulo, "&TEXT(D36,"yyyy")&"." -> Figura n – [Apresentação e registro dos novos detentos na administração da Casa de Detenção (1979)] Fonte: Arquivo do Estado de São Paulo, 1961. | S36: ="ARQUIVO PÚBLICO DO ESTADO DE SÃO PAULO (Brasil). ["&B36&"]. "&G36&". "&TEXT(D36,"dd")&" "&LOWER(TEXT(D36,"mmm"))&" "&TEXT(D36,"yyyy")&". "&F36&". Disponível em: <link do dataverse>. Acesso em: 28 out. 2025." -> ARQUIVO PÚBLICO DO ESTADO DE SÃO PAULO (Brasil). [Apresentação e registro dos novos detentos na administração da Casa de Detenção (1979)]. São Paulo, Brasil. 09 set. 1961. Fotografia digitalizada; preto e branco; suporte em papel fotográfico. Disponível em: <link do dataverse>. Acesso em: 28 out. 2025. | T36: Estado de São Paulo – Penitenciárias e Presídios – Casa de Detenção Os novos “hóspedes” da Casa de Detenção. DN, 29/5/1979
A37: =RIGHT(K37,3) -> 037 | B37: Mulheres e crianças em filas na entrada da Casa de Detenção durante motim (1964) | C37: Item | D37: 22598 | E37: Gerado pelo Dataverse | F37: Fotografia digitalizada; sépia; suporte em papel fotográfico | G37: São Paulo, Brasil | H37: Arquivo Público do Estado de São Paulo, Jornal Diários Associados | I37: Estado De São Paulo - Penitenciárias e Presídios - Casa de Detenção do Carandiru (Fotografias) | J37: Caixa: 3055 Folder: 5 | K37: =TEXTJOIN("", TRUE, Geral!B72:T72) -> BR-SPAPESP_DASP-PENITPRE-CSDTCARANDIRU_ICO-FOT-DGZ-MT0_3055-005-037 | L37: =$L$2 -> A Casa de Detenção de São Paulo, conhecida como Carandiru, foi formalmente criada em 1938 por decreto do interventor Adhemar de Barros, embora ainda instalada no edifício da Avenida Tiradentes. Sua implantação no bairro do Carandiru só se iniciou décadas depois, quando o governo estadual contratou, em 1951, o Escritório Técnico Ramos de Azevedo, Severo & Villares para projetar e conduzir a construção do novo complexo penitenciário em terreno contíguo à Penitenciária do Estado. As obras avançaram de forma modular, e o primeiro edifício concluído — o Pavilhão 2 — foi inaugurado em 1956, marcando a abertura parcial da chamada “Nova Casa de Detenção”. Ao longo dos anos seguintes, novos pavilhões foram sendo erguidos e inaugurados, compondo um conjunto arquitetônico que se consolidaria como um dos principais símbolos do sistema prisional paulista no século XX. Esta fotografia integra o fundo documental do grupo Diários Associados do Estado de São Paulo (DASP), custodiado pelo Arquivo Público do Estado de São Paulo (APESP), e registra aspectos desse prolongado processo de criação (1938), construção (a partir de 1951) e inauguração (a partir de 1956) da Casa de Detenção, conforme aponta a pesquisa de Maíra Rocha Machado, Bianca Tavolari e Maira Rosín (2025)[1]. | M37: A fotografia em tom sépia, capturada em plano aberto, registra um grupo de mulheres e crianças (familiares de detentos) aglomerados e possivelmente formando uma fila junto ao prédio de arquitetura institucional. O chão está coberto por papéis ou detritos. As mulheres carregam sacolas (provavelmente com itens para os presos), típicas do dia de visita. As expressões faciais são de seriedade, espera ou intranquilidade, características de um momento de tensão. A arquitetura de colunas ao fundo sugere a entrada ou a fachada de um dos prédios do complexo. O verso da fotografia, datado de 17 de agosto de 1964, contextualiza a cena em um cenário de crise após um motim provocado pelo "Regime de Terror". A legenda original descreve a "Dúvida, intranquilidade e temor" que levaram "essa gente às portas da Casa de Detenção" e a posterior permissão para entrar no "cenário da rebelião". A imagem é um registro da dimensão social da crise, mostrando a pressão e a vulnerabilidade dos familiares em busca de contato com os presos em meio à repressão. | N37: O acesso aos documentos deste acervo está condicionado ao compromisso de não repassá-los a terceiros, à obrigatoriedade de mencionar que os originais pertencem ao Arquivo Público do Estado de São Paulo, e à necessidade de novo Termo de Responsabilidade em caso de reutilização ou uso diverso do inicialmente acordado. O uso está sujeito às restrições previstas na Lei de Arquivos (Lei nº 8.159/1991), na Lei de Direitos Autorais (Lei nº 9.610/1998), nos artigos 138 e 145 do Código Penal, e no artigo 5º, inciso X, da Constituição Federal, especialmente quanto à proteção da honra e imagem de terceiros. A pessoa física ou jurídica responsável assume integral responsabilidade civil e penal por eventuais danos decorrentes do uso das reproduções e informações, eximindo o Arquivo Público do Estado de São Paulo de qualquer responsabilidade. | O37: Visita familiar; Filas (espera); Mulheres (família de preso); Sacola (jumbo); Motim (consequências); Crise prisional; Regime de Terror; Casa de Detenção; Carandiru; 1964. | P37: Fotografia (Iconográfico) | Q37: Digitalização de fotografia em sépia (analógica original) | R37: ="Figura n – ["&B37&"]"&CHAR(10)&"Fonte: Arquivo do Estado de São Paulo, "&TEXT(D37,"yyyy")&"." -> Figura n – [Mulheres e crianças em filas na entrada da Casa de Detenção durante motim (1964)] Fonte: Arquivo do Estado de São Paulo, 1961. | S37: ="ARQUIVO PÚBLICO DO ESTADO DE SÃO PAULO (Brasil). ["&B37&"]. "&G37&". "&TEXT(D37,"dd")&" "&LOWER(TEXT(D37,"mmm"))&" "&TEXT(D37,"yyyy")&". "&F37&". Disponível em: <link do dataverse>. Acesso em: 28 out. 2025." -> ARQUIVO PÚBLICO DO ESTADO DE SÃO PAULO (Brasil). [Mulheres e crianças em filas na entrada da Casa de Detenção durante motim (1964)]. São Paulo, Brasil. 13 nov. 1961. Fotografia digitalizada; sépia; suporte em papel fotográfico. Disponível em: <link do dataverse>. Acesso em: 28 out. 2025. | T37: Estado de São Paulo – Penitenciárias e Presídios – Casa de Detenção do Carandiru Detenção: regime de terror provocou motim Dúvida, intranquilidade e temor levaram essa gente às portas da Casa de Detenção, cuja barreira foi vencida pela resignação. A proibição caiu e todos puderam entrar no cenário da rebelião. Ver. DN, 2ª ed., 17/8/1964 – DMC
A38: =RIGHT(K38,3) -> 038 | B38: Show do artista Wilson Simonal para detentos, observado por guardas na torre e autoridades no Carandiru (1977) | C38: Item | D38: 22937 | E38: Gerado pelo Dataverse | F38: Fotografia digitalizada; preto e branco; suporte em papel fotográfico | G38: São Paulo, Brasil | H38: Arquivo Público do Estado de São Paulo, Jornal Diários Associados | I38: Estado De São Paulo - Penitenciárias e Presídios - Casa de Detenção do Carandiru (Fotografias) | J38: Caixa: 3055 Folder: 5 | K38: =TEXTJOIN("", TRUE, Geral!B74:T74) -> BR-SPAPESP_DASP-PENITPRE-CSDTCARANDIRU_ICO-FOT-DGZ-MT0_3055-005-038 | L38: =$L$2 -> A Casa de Detenção de São Paulo, conhecida como Carandiru, foi formalmente criada em 1938 por decreto do interventor Adhemar de Barros, embora ainda instalada no edifício da Avenida Tiradentes. Sua implantação no bairro do Carandiru só se iniciou décadas depois, quando o governo estadual contratou, em 1951, o Escritório Técnico Ramos de Azevedo, Severo & Villares para projetar e conduzir a construção do novo complexo penitenciário em terreno contíguo à Penitenciária do Estado. As obras avançaram de forma modular, e o primeiro edifício concluído — o Pavilhão 2 — foi inaugurado em 1956, marcando a abertura parcial da chamada “Nova Casa de Detenção”. Ao longo dos anos seguintes, novos pavilhões foram sendo erguidos e inaugurados, compondo um conjunto arquitetônico que se consolidaria como um dos principais símbolos do sistema prisional paulista no século XX. Esta fotografia integra o fundo documental do grupo Diários Associados do Estado de São Paulo (DASP), custodiado pelo Arquivo Público do Estado de São Paulo (APESP), e registra aspectos desse prolongado processo de criação (1938), construção (a partir de 1951) e inauguração (a partir de 1956) da Casa de Detenção, conforme aponta a pesquisa de Maíra Rocha Machado, Bianca Tavolari e Maira Rosín (2025)[1]. | M38: A fotografia em preto e branco registra um show musical realizado em um pátio externo, com o Pavilhão de múltiplos andares dominando o fundo. Em primeiro plano, no palco elevado, músicos se apresentam, sendo um deles (o vocalista central, Wilson Simonal) o ponto focal da cena. A plateia de detentos está aglomerada logo abaixo do palco, separada por uma grade baixa. A arquitetura prisional é evidente: o Pavilhão com suas janelas gradeadas serve de cenário e, à direita, uma torre de vigilância de concreto abriga agentes de segurança uniformizados observando o evento de cima. O verso da fotografia, datado de 29 de setembro de 1977, confirma o evento como um show de Wilson Simonal para 6.500 detentos, com a presença de diversas autoridades civis, militares e eclesiásticas. O texto indica que o show foi uma recompensa disciplinar para os presos do Pavilhão Oito. | N38: O acesso aos documentos deste acervo está condicionado ao compromisso de não repassá-los a terceiros, à obrigatoriedade de mencionar que os originais pertencem ao Arquivo Público do Estado de São Paulo, e à necessidade de novo Termo de Responsabilidade em caso de reutilização ou uso diverso do inicialmente acordado. O uso está sujeito às restrições previstas na Lei de Arquivos (Lei nº 8.159/1991), na Lei de Direitos Autorais (Lei nº 9.610/1998), nos artigos 138 e 145 do Código Penal, e no artigo 5º, inciso X, da Constituição Federal, especialmente quanto à proteção da honra e imagem de terceiros. A pessoa física ou jurídica responsável assume integral responsabilidade civil e penal por eventuais danos decorrentes do uso das reproduções e informações, eximindo o Arquivo Público do Estado de São Paulo de qualquer responsabilidade. | O38: Show musical; Wilson Simonal; Recompensa disciplinar; Pavilhão (prisional); Torre de vigilância; Autoridades (visita); Detentos (plateia); Carandiru; 1977; Cultura (prisão). | P38: Fotografia (Iconográfico) | Q38: Digitalização de fotografia em preto e branco (analógica original) | R38: ="Figura n – ["&B38&"]"&CHAR(10)&"Fonte: Arquivo do Estado de São Paulo, "&TEXT(D38,"yyyy")&"." -> Figura n – [Show do artista Wilson Simonal para detentos, observado por guardas na torre e autoridades no Carandiru (1977)] Fonte: Arquivo do Estado de São Paulo, 1962. | S38: ="ARQUIVO PÚBLICO DO ESTADO DE SÃO PAULO (Brasil). ["&B38&"]. "&G38&". "&TEXT(D38,"dd")&" "&LOWER(TEXT(D38,"mmm"))&" "&TEXT(D38,"yyyy")&". "&F38&". Disponível em: <link do dataverse>. Acesso em: 28 out. 2025." -> ARQUIVO PÚBLICO DO ESTADO DE SÃO PAULO (Brasil). [Show do artista Wilson Simonal para detentos, observado por guardas na torre e autoridades no Carandiru (1977)]. São Paulo, Brasil. 18 out. 1962. Fotografia digitalizada; preto e branco; suporte em papel fotográfico. Disponível em: <link do dataverse>. Acesso em: 28 out. 2025. | T38: Estado de São Paulo – Penitenciárias e Presídios – Casa de Detenção [Texto em pequeno retângulo, recorte de matéria] Com a presença de várias autoridades civis, militares e eclesiásticas, foi realizado na Casa de Detenção de São Paulo um “show” para entretenimento dos presos. Estiveram presentes naquele estabelecimento penal o MM. Juiz de Direito Corregedor dos Presídios e da Polícia Judiciária da Capital, Dr. Renato Laércio Talli; Dr. Omar Cassin, diretor da Divisão Judiciária do Departamento dos Institutos Penais do Estado; Sr. Aurelino Soares da Silva, diretor da Bolsa de Cereais do Estado de São Paulo; e o pároco Pe. Aluízio Pena, da Paróquia São Luiz, com seus assessores. No final do “show”, usou da palavra o Cel. Fernão Guedes de Souza, diretor da Casa de Detenção, que agradeceu, em nome dos 6.500 detentos, a presença das autoridades e do artista Wilson Simonal, além dos demais visitantes. Falou ainda o Cel. Fernão Guedes que, em virtude do exemplar comportamento demonstrado pelos detentos durante o “show”, o Pavilhão Oito voltaria a frequentar a sala de cinema normalmente, já que há vários meses os detentos daquele pavilhão não assistiam projeção cinematográfica, em virtude de faltas disciplinares cometidas anteriormente. DN, 29/9/1977
A39: =RIGHT(K39,3) -> 039 | B39: Pátio externo gramado, com muro de contenção e torre de vigilância, no Complexo Penitenciário do Carandiru | C39: Item | D39: 22937 | E39: Gerado pelo Dataverse | F39: Fotografia digitalizada; preto e branco; suporte em papel fotográfico | G39: São Paulo, Brasil | H39: Arquivo Público do Estado de São Paulo, Jornal Diários Associados | I39: Estado De São Paulo - Penitenciárias e Presídios - Casa de Detenção do Carandiru (Fotografias) | J39: Caixa: 3055 Folder: 5 | K39: =TEXTJOIN("", TRUE, Geral!B76:T76) -> BR-SPAPESP_DASP-PENITPRE-CSDTCARANDIRU_ICO-FOT-DGZ-MT0_3055-005-039 | L39: =$L$2 -> A Casa de Detenção de São Paulo, conhecida como Carandiru, foi formalmente criada em 1938 por decreto do interventor Adhemar de Barros, embora ainda instalada no edifício da Avenida Tiradentes. Sua implantação no bairro do Carandiru só se iniciou décadas depois, quando o governo estadual contratou, em 1951, o Escritório Técnico Ramos de Azevedo, Severo & Villares para projetar e conduzir a construção do novo complexo penitenciário em terreno contíguo à Penitenciária do Estado. As obras avançaram de forma modular, e o primeiro edifício concluído — o Pavilhão 2 — foi inaugurado em 1956, marcando a abertura parcial da chamada “Nova Casa de Detenção”. Ao longo dos anos seguintes, novos pavilhões foram sendo erguidos e inaugurados, compondo um conjunto arquitetônico que se consolidaria como um dos principais símbolos do sistema prisional paulista no século XX. Esta fotografia integra o fundo documental do grupo Diários Associados do Estado de São Paulo (DASP), custodiado pelo Arquivo Público do Estado de São Paulo (APESP), e registra aspectos desse prolongado processo de criação (1938), construção (a partir de 1951) e inauguração (a partir de 1956) da Casa de Detenção, conforme aponta a pesquisa de Maíra Rocha Machado, Bianca Tavolari e Maira Rosín (2025)[1]. | M39: A fotografia em preto e branco registra um pátio externo amplo e gramado em um dia claro, em região não explicitamente identificada como interior ou exterior à Casa de Detenção. O primeiro plano é dominado por uma área de grama e vegetação, com uma pequena árvore e estruturas baixas no chão (possivelmente tampas de bueiro). O plano de fundo é a estrutura de contenção da prisão: uma muralha alta e sólida circunda o complexo, e acima dela, à direita, ergue-se uma torre de vigilância (guarita) alta e proeminente, um elemento de controle característico. Ao lado da torre, parte de uma edificação prisional é visível. No centro da imagem, próximo à muralha, há um pequeno prédio ou quiosque e algumas crianças reunidas. Estruturas metálicas horizontais e tubulações também são visíveis. A imagem documenta um espaço verde e aberto dentro do complexo, que contrasta com a rigidez da arquitetura de segurança (muros e torre), sugerindo uma área utilizada para lazer. | N39: O acesso aos documentos deste acervo está condicionado ao compromisso de não repassá-los a terceiros, à obrigatoriedade de mencionar que os originais pertencem ao Arquivo Público do Estado de São Paulo, e à necessidade de novo Termo de Responsabilidade em caso de reutilização ou uso diverso do inicialmente acordado. O uso está sujeito às restrições previstas na Lei de Arquivos (Lei nº 8.159/1991), na Lei de Direitos Autorais (Lei nº 9.610/1998), nos artigos 138 e 145 do Código Penal, e no artigo 5º, inciso X, da Constituição Federal, especialmente quanto à proteção da honra e imagem de terceiros. A pessoa física ou jurídica responsável assume integral responsabilidade civil e penal por eventuais danos decorrentes do uso das reproduções e informações, eximindo o Arquivo Público do Estado de São Paulo de qualquer responsabilidade. | O39: Pátio (externo); Gramado; Muralha (contenção); Torre de vigilância; Arquitetura prisional; Carandiru; Lazer (potencial); Vigilância; Estrutura prisional. | P39: Fotografia (Iconográfico) | Q39: Digitalização de fotografia em preto e branco (analógica original) | R39: ="Figura n – ["&B39&"]"&CHAR(10)&"Fonte: Arquivo do Estado de São Paulo, "&TEXT(D39,"yyyy")&"." -> Figura n – [Pátio externo gramado, com muro de contenção e torre de vigilância, no Complexo Penitenciário do Carandiru] Fonte: Arquivo do Estado de São Paulo, 1962. | S39: ="ARQUIVO PÚBLICO DO ESTADO DE SÃO PAULO (Brasil). ["&B39&"]. "&G39&". "&TEXT(D39,"dd")&" "&LOWER(TEXT(D39,"mmm"))&" "&TEXT(D39,"yyyy")&". "&F39&". Disponível em: <link do dataverse>. Acesso em: 28 out. 2025." -> ARQUIVO PÚBLICO DO ESTADO DE SÃO PAULO (Brasil). [Pátio externo gramado, com muro de contenção e torre de vigilância, no Complexo Penitenciário do Carandiru]. São Paulo, Brasil. 18 out. 1962. Fotografia digitalizada; preto e branco; suporte em papel fotográfico. Disponível em: <link do dataverse>. Acesso em: 28 out. 2025. | T39: Não contém
A40: =RIGHT(K40,3) -> 040 | B40: Retrato de Gilberto Calixto, detento assassinado por colegas de cela no Carandiru (1978) | C40: Item | D40: 23035 | E40: Gerado pelo Dataverse | F40: Fotografia digitalizada; preto e branco; suporte em papel fotográfico | G40: São Paulo, Brasil | H40: Arquivo Público do Estado de São Paulo, Jornal Diários Associados | I40: Estado De São Paulo - Penitenciárias e Presídios - Casa de Detenção do Carandiru (Fotografias) | J40: Caixa: 3055 Folder: 5 | K40: =TEXTJOIN("", TRUE, Geral!B77:T77) -> BR-SPAPESP_DASP-PENITPRE-CSDTCARANDIRU_ICO-FOT-DGZ-MT0_3055-005-040 | L40: =$L$2 -> A Casa de Detenção de São Paulo, conhecida como Carandiru, foi formalmente criada em 1938 por decreto do interventor Adhemar de Barros, embora ainda instalada no edifício da Avenida Tiradentes. Sua implantação no bairro do Carandiru só se iniciou décadas depois, quando o governo estadual contratou, em 1951, o Escritório Técnico Ramos de Azevedo, Severo & Villares para projetar e conduzir a construção do novo complexo penitenciário em terreno contíguo à Penitenciária do Estado. As obras avançaram de forma modular, e o primeiro edifício concluído — o Pavilhão 2 — foi inaugurado em 1956, marcando a abertura parcial da chamada “Nova Casa de Detenção”. Ao longo dos anos seguintes, novos pavilhões foram sendo erguidos e inaugurados, compondo um conjunto arquitetônico que se consolidaria como um dos principais símbolos do sistema prisional paulista no século XX. Esta fotografia integra o fundo documental do grupo Diários Associados do Estado de São Paulo (DASP), custodiado pelo Arquivo Público do Estado de São Paulo (APESP), e registra aspectos desse prolongado processo de criação (1938), construção (a partir de 1951) e inauguração (a partir de 1956) da Casa de Detenção, conforme aponta a pesquisa de Maíra Rocha Machado, Bianca Tavolari e Maira Rosín (2025)[1]. | M40: A fotografia em preto e branco é um retrato frontal (tipo mugshot ou foto 3x4) em plano fechado, com fundo claro e neutro. O retratado é um homem (identificado no verso como Gilberto Calixto), com corte de cabelo "militar" ou raspado nas laterais e bigode, vestindo uma camiseta escura. A imagem, por seu formato e foco, é uma foto de identificação institucional (registro de entrada ou prontuário). O verso da fotografia, datado de 8 de abril de 1978, contextualiza a cena com um registro trágico: "Gilberto Calixto, preso da Casa de Detenção morto, pelos colegas de cela." A imagem, portanto, é um documento institucional que se transforma em um registro da violência interna e do assassinato de um detento por outros presos no Carandiru, ocorrido no mesmo dia de Euripedes B. de Azevedo. | N40: O acesso aos documentos deste acervo está condicionado ao compromisso de não repassá-los a terceiros, à obrigatoriedade de mencionar que os originais pertencem ao Arquivo Público do Estado de São Paulo, e à necessidade de novo Termo de Responsabilidade em caso de reutilização ou uso diverso do inicialmente acordado. O uso está sujeito às restrições previstas na Lei de Arquivos (Lei nº 8.159/1991), na Lei de Direitos Autorais (Lei nº 9.610/1998), nos artigos 138 e 145 do Código Penal, e no artigo 5º, inciso X, da Constituição Federal, especialmente quanto à proteção da honra e imagem de terceiros. A pessoa física ou jurídica responsável assume integral responsabilidade civil e penal por eventuais danos decorrentes do uso das reproduções e informações, eximindo o Arquivo Público do Estado de São Paulo de qualquer responsabilidade. | O40: Retrato (identificação); Mugshot; Detento assassinado; Violência carcerária; Homicídio (interno); Gilberto Calixto; Carandiru; Foto de prontuário; 1978. | P40: Fotografia (Iconográfico) | Q40: Digitalização de fotografia em preto e branco (analógica original) | R40: ="Figura n – ["&B40&"]"&CHAR(10)&"Fonte: Arquivo do Estado de São Paulo, "&TEXT(D40,"yyyy")&"." -> Figura n – [Retrato de Gilberto Calixto, detento assassinado por colegas de cela no Carandiru (1978)] Fonte: Arquivo do Estado de São Paulo, 1963. | S40: ="ARQUIVO PÚBLICO DO ESTADO DE SÃO PAULO (Brasil). ["&B40&"]. "&G40&". "&TEXT(D40,"dd")&" "&LOWER(TEXT(D40,"mmm"))&" "&TEXT(D40,"yyyy")&". "&F40&". Disponível em: <link do dataverse>. Acesso em: 28 out. 2025." -> ARQUIVO PÚBLICO DO ESTADO DE SÃO PAULO (Brasil). [Retrato de Gilberto Calixto, detento assassinado por colegas de cela no Carandiru (1978)]. São Paulo, Brasil. 24 jan. 1963. Fotografia digitalizada; preto e branco; suporte em papel fotográfico. Disponível em: <link do dataverse>. Acesso em: 28 out. 2025. | T40: Estado de São Paulo – Penitenciárias e Presídios – Casa de Detenção Carandiru Gilberto Calixto, preso da Casa de Detenção, foi morto pelos colegas de cela. DN, 8/4/1978
