Workbook

Sheet Geral
B1: Local (país) | D1: Local (estado) | E1: Designação do repositório | G1: Designação do conjunto documental | I1: Designação do subconjunto documental | K1: Gênero documental | M1: Espécie/Tipo documental | O1: Técnica de registro | Q1: Forma documental | S1: Unidade de descrição
A2: 1 | B2: BR | C2: - | D2: SP | E2: GPDVE | F2: _ | G2: ARCOENGE | H2: - | I2: DEMOLICAO-CSDTCARANDIRU | J2: _ | K2: ICO | L2: - | M2: FOT | N2: - | O2: DGZ | P2: - | Q2: MB0 | R2: _ | S2: 0001- | T2: 001 | U2: .JPG
A3: 2 | B3: BR | C3: - | D3: SP | E3: GPDVE | F3: _ | G3: ARCOENGE | H3: - | I3: DEMOLICAO-CSDTCARANDIRU | J3: _ | K3: ICO | L3: - | M3: FOT | N3: - | O3: DGZ | P3: - | Q3: MB0 | R3: _ | S3: 0001- | T3: 002 | U3: .JPG
A4: 3 | B4: BR | C4: - | D4: SP | E4: GPDVE | F4: _ | G4: ARCOENGE | H4: - | I4: DEMOLICAO-CSDTCARANDIRU | J4: _ | K4: ICO | L4: - | M4: FOT | N4: - | O4: DGZ | P4: - | Q4: MB0 | R4: _ | S4: 0001- | T4: 003 | U4: .JPG
A5: 4 | B5: BR | C5: - | D5: SP | E5: GPDVE | F5: _ | G5: ARCOENGE | H5: - | I5: DEMOLICAO-CSDTCARANDIRU | J5: _ | K5: ICO | L5: - | M5: FOT | N5: - | O5: DGZ | P5: - | Q5: MB0 | R5: _ | S5: 0001- | T5: 004 | U5: .JPG
A6: 5 | B6: BR | C6: - | D6: SP | E6: GPDVE | F6: _ | G6: ARCOENGE | H6: - | I6: DEMOLICAO-CSDTCARANDIRU | J6: _ | K6: ICO | L6: - | M6: FOT | N6: - | O6: DGZ | P6: - | Q6: MB0 | R6: _ | S6: 0001- | T6: 005 | U6: .JPG
A7: 6 | B7: BR | C7: - | D7: SP | E7: GPDVE | F7: _ | G7: ARCOENGE | H7: - | I7: DEMOLICAO-CSDTCARANDIRU | J7: _ | K7: ICO | L7: - | M7: FOT | N7: - | O7: DGZ | P7: - | Q7: MB0 | R7: _ | S7: 0001- | T7: 006 | U7: .JPG
A8: 7 | B8: BR | C8: - | D8: SP | E8: GPDVE | F8: _ | G8: ARCOENGE | H8: - | I8: DEMOLICAO-CSDTCARANDIRU | J8: _ | K8: ICO | L8: - | M8: FOT | N8: - | O8: DGZ | P8: - | Q8: MB0 | R8: _ | S8: 0001- | T8: 007 | U8: .JPG
A9: 8 | B9: BR | C9: - | D9: SP | E9: GPDVE | F9: _ | G9: ARCOENGE | H9: - | I9: DEMOLICAO-CSDTCARANDIRU | J9: _ | K9: ICO | L9: - | M9: FOT | N9: - | O9: DGZ | P9: - | Q9: MB0 | R9: _ | S9: 0001- | T9: 008 | U9: .JPG
A10: 9 | B10: BR | C10: - | D10: SP | E10: GPDVE | F10: _ | G10: ARCOENGE | H10: - | I10: DEMOLICAO-CSDTCARANDIRU | J10: _ | K10: ICO | L10: - | M10: FOT | N10: - | O10: DGZ | P10: - | Q10: MB0 | R10: _ | S10: 0001- | T10: 009 | U10: .JPG
A11: 10 | B11: BR | C11: - | D11: SP | E11: GPDVE | F11: _ | G11: ARCOENGE | H11: - | I11: DEMOLICAO-CSDTCARANDIRU | J11: _ | K11: ICO | L11: - | M11: FOT | N11: - | O11: DGZ | P11: - | Q11: MB0 | R11: _ | S11: 0001- | T11: 010 | U11: .JPG
A12: 11 | B12: BR | C12: - | D12: SP | E12: GPDVE | F12: _ | G12: ARCOENGE | H12: - | I12: DEMOLICAO-CSDTCARANDIRU | J12: _ | K12: ICO | L12: - | M12: FOT | N12: - | O12: DGZ | P12: - | Q12: MB0 | R12: _ | S12: 0001- | T12: 011 | U12: .JPG
A13: 12 | B13: BR | C13: - | D13: SP | E13: GPDVE | F13: _ | G13: ARCOENGE | H13: - | I13: DEMOLICAO-CSDTCARANDIRU | J13: _ | K13: ICO | L13: - | M13: FOT | N13: - | O13: DGZ | P13: - | Q13: MB0 | R13: _ | S13: 0001- | T13: 012 | U13: .JPG
... A106: 105 | B106: BR | C106: - | D106: SP | E106: GPDVE | F106: _ | G106: ARCOENGE | H106: - | I106: DEMOLICAO-CSDTCARANDIRU | J106: _ | K106: ICO | L106: - | M106: FOT | N106: - | O106: DGZ | P106: - | Q106: MB0 | R106: _ | S106: 0004- | T106: 024 | U106: .JPG
A107: 106 | B107: BR | C107: - | D107: SP | E107: GPDVE | F107: _ | G107: ARCOENGE | H107: - | I107: DEMOLICAO-CSDTCARANDIRU | J107: _ | L107: - | N107: - | P107: - | R107: _ | U107: .JPG
A108: 107 | B108: BR | C108: - | D108: SP | E108: GPDVE | F108: _ | G108: ARCOENGE | H108: - | I108: DEMOLICAO-CSDTCARANDIRU | J108: _ | L108: - | N108: - | P108: - | R108: _ | U108: .JPG
A109: 108 | B109: BR | C109: - | D109: SP | E109: GPDVE | F109: _ | G109: ARCOENGE | H109: - | I109: DEMOLICAO-CSDTCARANDIRU | J109: _ | L109: - | N109: - | P109: - | R109: _ | U109: .JPG
A110: 109 | B110: BR | C110: - | D110: SP | E110: GPDVE | F110: _ | G110: ARCOENGE | H110: - | I110: DEMOLICAO-CSDTCARANDIRU | J110: _ | L110: - | N110: - | P110: - | R110: _ | U110: .JPG
A111: 110 | B111: BR | C111: - | D111: SP | E111: GPDVE | F111: _ | G111: ARCOENGE | H111: - | I111: DEMOLICAO-CSDTCARANDIRU | J111: _ | L111: - | N111: - | P111: - | R111: _ | U111: .JPG
A112: 111 | B112: BR | C112: - | D112: SP | E112: GPDVE | F112: _ | G112: ARCOENGE | H112: - | I112: DEMOLICAO-CSDTCARANDIRU | J112: _ | L112: - | N112: - | P112: - | R112: _ | U112: .JPG
A113: 112 | B113: BR | C113: - | D113: SP | E113: GPDVE | F113: _ | G113: ARCOENGE | H113: - | I113: DEMOLICAO-CSDTCARANDIRU | J113: _ | L113: - | N113: - | P113: - | R113: _ | U113: .JPG
A114: 113 | B114: BR | C114: - | D114: SP | E114: GPDVE | F114: _ | G114: ARCOENGE | H114: - | I114: DEMOLICAO-CSDTCARANDIRU | J114: _ | L114: - | N114: - | P114: - | R114: _ | U114: .JPG
A115: 114 | B115: BR | C115: - | D115: SP | E115: GPDVE | F115: _ | G115: ARCOENGE | H115: - | I115: DEMOLICAO-CSDTCARANDIRU | J115: _ | L115: - | N115: - | P115: - | R115: _ | U115: .JPG
A116: 115 | B116: BR | C116: - | D116: SP | E116: GPDVE | F116: _ | G116: ARCOENGE | H116: - | I116: DEMOLICAO-CSDTCARANDIRU | J116: _ | L116: - | N116: - | P116: - | R116: _ | U116: .JPG
A117: 116 | B117: BR | C117: - | D117: SP | E117: GPDVE | F117: _ | G117: ARCOENGE | H117: - | I117: DEMOLICAO-CSDTCARANDIRU | J117: _ | L117: - | N117: - | P117: - | R117: _ | U117: .JPG
A118: 117 | B118: BR | C118: - | D118: SP | E118: GPDVE | F118: _ | G118: ARCOENGE | H118: - | I118: DEMOLICAO-CSDTCARANDIRU | J118: _ | L118: - | N118: - | P118: - | R118: _ | U118: .JPG
... A365: 364 | B365: BR | C365: - | D365: SP | E365: GPDVE | F365: _ | G365: ARCOENGE | H365: - | I365: DEMOLICAO-CSDTCARANDIRU | J365: _ | L365: - | N365: - | P365: - | R365: _ | U365: .JPG

Sheet 0001
A1: Cód. | B1: Título descritivo (atribuído) | C1: Nível de descrição | D1: Data da fotografia | E1: Tamanho | F1: Suporte | G1: Local | H1: Autor/Responsável | I1: Denominação do catálogo temático (GPDVE ARCOENGE) | J1: Localização | K1: Código de referência | L1: História arquivística | M1: Conteúdo/Assunto | N1: Condições de acesso e reprodução | O1: Palavras-chave | P1: Gênero | Q1: Técnica de registro | R1: Legenda para publicações | S1: Citação ABNT | T1: Notas
A2: =MID(K2, LEN(K2)-6, 3) -> 001 | B2: Corredor de terra ladeado por muro de concreto e pavilhão com roupas estendidas, com silhuetas urbanas ao fundo. | C2: Item | D2: Sem data | E2: Gerado pelo Dataverse | F2: Fotografia digitalizada; colorida; suporte em papel fotográfico | G2: São Paulo, Brasil | H2: Grupo de Pesquisa em Direito e Violência de Estado | I2: Arcoenge - Demolição - Casa de Detenção do Carandiru (Fotografias) | J2: Pasta: 0001 | K2: =TEXTJOIN("", TRUE, Geral!B2:U2) -> BR-SPGPDVE_ARCOENGE-DEMOLICAO-CSDTCARANDIRU_ICO-FOT-DGZ-MB0_0001-001.JPG | L2: A Casa de Detenção de São Paulo, conhecida como Carandiru, foi demolida em etapas. Em 2002, ocorreu a implosão dos pavilhões 6, 8 e 9. Já em 2005, dos pavilhões 2 e 5 pela empresa Arcoenge (contratada pelo governo do estado de São Paulo). A coleção Arcoenge contém subgrupos de fotos, vídeos e texto, totalizando 164 peças documentais. | M2: Corredor longo e estreito de terra. À esquerda, um muro alto e contínuo de concreto. À direita, a fachada de um pavilhão com diversas roupas estendidas para fora das janelas. Na parte central da imagem, ao longe, pessoas caminham pelo espaço térreo. Ao fundo, despontam silhuetas de prédios modernos da cidade. | N2: O acesso aos documentos deste acervo está condicionado ao compromisso de não repassá-los a terceiros, à obrigatoriedade de mencionar que os originais pertencem ao GPDVE (?), e à necessidade de novo Termo de Responsabilidade em caso de reutilização ou uso diverso do inicialmente acordado. O uso está sujeito às restrições previstas na Lei de Arquivos (Lei nº 8.159/1991), na Lei de Direitos Autorais (Lei nº 9.610/1998), nos artigos 138 e 145 do Código Penal, e no artigo 5º, inciso X, da Constituição Federal, especialmente quanto à proteção da honra e imagem de terceiros. A pessoa física ou jurídica responsável assume integral responsabilidade civil e penal por eventuais danos decorrentes do uso das reproduções e informações, eximindo o GPDVE de qualquer responsabilidade. | O2: Sistema prisional; Arquitetura prisional; Casa de Detenção de São Paulo; Carandiru | P2: Fotografia (Iconográfico) | Q2: Digitalização de fotografia colorida (analógica original) | R2: ="Figura n – ["&B2&"]"&CHAR(10)&"Fonte: Arquivo do Estado de São Paulo, "&TEXT(D2,"yyyy")&"." -> Figura n – [Corredor de terra ladeado por muro de concreto e pavilhão com roupas estendidas, com silhuetas urbanas ao fundo.] Fonte: Arquivo do Estado de São Paulo, Sem data. | S2: ="ARQUIVO PÚBLICO DO ESTADO DE SÃO PAULO (Brasil). ["&B2&"]. "&G2&". "&TEXT(D2,"dd")&" "&LOWER(TEXT(D2,"mmm"))&" "&TEXT(D2,"yyyy")&". "&F2&". Disponível em: <link do dataverse>. Acesso em: 28 out. 2025." -> ARQUIVO PÚBLICO DO ESTADO DE SÃO PAULO (Brasil). [Corredor de terra ladeado por muro de concreto e pavilhão com roupas estendidas, com silhuetas urbanas ao fundo.]. São Paulo, Brasil. Sem data sem data Sem data. Fotografia digitalizada; colorida; suporte em papel fotográfico. Disponível em: <link do dataverse>. Acesso em: 28 out. 2025. | T2: Este item pertencia à pasta intitulada "fotos escaneadas".
A3: =MID(K3, LEN(K3)-6, 3) -> 002 | B3: Fachada de edifício retangular de cinco andares com janelas padronizadas e guarda-corpo metálico em primeiro plano. | C3: Item | D3: Sem data | E3: Gerado pelo Dataverse | F3: Fotografia digitalizada; colorida; suporte em papel fotográfico | G3: São Paulo, Brasil | H3: Grupo de Pesquisa em Direito e Violência de Estado | I3: Arcoenge - Demolição - Casa de Detenção do Carandiru (Fotografias) | J3: Pasta: 0001 | K3: =TEXTJOIN("", TRUE, Geral!B3:U3) -> BR-SPGPDVE_ARCOENGE-DEMOLICAO-CSDTCARANDIRU_ICO-FOT-DGZ-MB0_0001-002.JPG | L3: ='0001'!$L$2 -> A Casa de Detenção de São Paulo, conhecida como Carandiru, foi demolida em etapas. Em 2002, ocorreu a implosão dos pavilhões 6, 8 e 9. Já em 2005, dos pavilhões 2 e 5 pela empresa Arcoenge (contratada pelo governo do estado de São Paulo). A coleção Arcoenge contém subgrupos de fotos, vídeos e texto, totalizando 164 peças documentais. | M3: Plano fechado focado na fachada de um grande edifício retangular de concreto, com cinco andares de janelas visíveis, padronizadas e recuadas. Em primeiro plano, um muro com guarda-corpo de metal margeia o que aparenta ser um pátio rebaixado. | N3: ='0001'!$N$2 -> O acesso aos documentos deste acervo está condicionado ao compromisso de não repassá-los a terceiros, à obrigatoriedade de mencionar que os originais pertencem ao GPDVE (?), e à necessidade de novo Termo de Responsabilidade em caso de reutilização ou uso diverso do inicialmente acordado. O uso está sujeito às restrições previstas na Lei de Arquivos (Lei nº 8.159/1991), na Lei de Direitos Autorais (Lei nº 9.610/1998), nos artigos 138 e 145 do Código Penal, e no artigo 5º, inciso X, da Constituição Federal, especialmente quanto à proteção da honra e imagem de terceiros. A pessoa física ou jurídica responsável assume integral responsabilidade civil e penal por eventuais danos decorrentes do uso das reproduções e informações, eximindo o GPDVE de qualquer responsabilidade. | O3: Sistema prisional; Arquitetura prisional; Casa de Detenção de São Paulo; Carandiru | P3: Fotografia (Iconográfico) | Q3: Digitalização de fotografia colorida (analógica original) | R3: ="Figura n – ["&B3&"]"&CHAR(10)&"Fonte: Arquivo do Estado de São Paulo, "&TEXT(D3,"yyyy")&"." -> Figura n – [Fachada de edifício retangular de cinco andares com janelas padronizadas e guarda-corpo metálico em primeiro plano.] Fonte: Arquivo do Estado de São Paulo, Sem data. | S3: ="ARQUIVO PÚBLICO DO ESTADO DE SÃO PAULO (Brasil). ["&B3&"]. "&G3&". "&TEXT(D3,"dd")&" "&LOWER(TEXT(D3,"mmm"))&" "&TEXT(D3,"yyyy")&". "&F3&". Disponível em: <link do dataverse>. Acesso em: 28 out. 2025." -> ARQUIVO PÚBLICO DO ESTADO DE SÃO PAULO (Brasil). [Fachada de edifício retangular de cinco andares com janelas padronizadas e guarda-corpo metálico em primeiro plano.]. São Paulo, Brasil. Sem data sem data Sem data. Fotografia digitalizada; colorida; suporte em papel fotográfico. Disponível em: <link do dataverse>. Acesso em: 28 out. 2025. | T3: Este item pertencia à pasta intitulada "fotos escaneadas".
A4: =MID(K4, LEN(K4)-6, 3) -> 003 | B4: Corredor de concreto com pessoas em trânsito, ladeado por muro alto e pavilhão com roupas penduradas. | C4: Item | D4: Sem data | E4: Gerado pelo Dataverse | F4: Fotografia digitalizada; colorida; suporte em papel fotográfico | G4: São Paulo, Brasil | H4: Grupo de Pesquisa em Direito e Violência de Estado | I4: Arcoenge - Demolição - Casa de Detenção do Carandiru (Fotografias) | J4: Pasta: 0001 | K4: =TEXTJOIN("", TRUE, Geral!B4:U4) -> BR-SPGPDVE_ARCOENGE-DEMOLICAO-CSDTCARANDIRU_ICO-FOT-DGZ-MB0_0001-003.JPG | L4: ='0001'!$L$2 -> A Casa de Detenção de São Paulo, conhecida como Carandiru, foi demolida em etapas. Em 2002, ocorreu a implosão dos pavilhões 6, 8 e 9. Já em 2005, dos pavilhões 2 e 5 pela empresa Arcoenge (contratada pelo governo do estado de São Paulo). A coleção Arcoenge contém subgrupos de fotos, vídeos e texto, totalizando 164 peças documentais. | M4: Ângulo e composição muito semelhantes à foto BR-SPGPDVE_ARCOENGE-DEMOLICAO-CSDTCARANDIRU_ICO-FOT-DGZ-MB0_0001-001.JPG. Vista em perspectiva de um corredor de concreto margeado por um muro alto à esquerda e um pavilhão com roupas penduradas à direita. Pessoas transitam pelo térreo. | N4: ='0001'!$N$2 -> O acesso aos documentos deste acervo está condicionado ao compromisso de não repassá-los a terceiros, à obrigatoriedade de mencionar que os originais pertencem ao GPDVE (?), e à necessidade de novo Termo de Responsabilidade em caso de reutilização ou uso diverso do inicialmente acordado. O uso está sujeito às restrições previstas na Lei de Arquivos (Lei nº 8.159/1991), na Lei de Direitos Autorais (Lei nº 9.610/1998), nos artigos 138 e 145 do Código Penal, e no artigo 5º, inciso X, da Constituição Federal, especialmente quanto à proteção da honra e imagem de terceiros. A pessoa física ou jurídica responsável assume integral responsabilidade civil e penal por eventuais danos decorrentes do uso das reproduções e informações, eximindo o GPDVE de qualquer responsabilidade. | O4: Sistema prisional; Arquitetura prisional; Casa de Detenção de São Paulo; Carandiru | P4: Fotografia (Iconográfico) | Q4: Digitalização de fotografia colorida (analógica original) | R4: ="Figura n – ["&B4&"]"&CHAR(10)&"Fonte: Arquivo do Estado de São Paulo, "&TEXT(D4,"yyyy")&"." -> Figura n – [Corredor de concreto com pessoas em trânsito, ladeado por muro alto e pavilhão com roupas penduradas.] Fonte: Arquivo do Estado de São Paulo, Sem data. | S4: ="ARQUIVO PÚBLICO DO ESTADO DE SÃO PAULO (Brasil). ["&B4&"]. "&G4&". "&TEXT(D4,"dd")&" "&LOWER(TEXT(D4,"mmm"))&" "&TEXT(D4,"yyyy")&". "&F4&". Disponível em: <link do dataverse>. Acesso em: 28 out. 2025." -> ARQUIVO PÚBLICO DO ESTADO DE SÃO PAULO (Brasil). [Corredor de concreto com pessoas em trânsito, ladeado por muro alto e pavilhão com roupas penduradas.]. São Paulo, Brasil. Sem data sem data Sem data. Fotografia digitalizada; colorida; suporte em papel fotográfico. Disponível em: <link do dataverse>. Acesso em: 28 out. 2025. | T4: Este item pertencia à pasta intitulada "fotos escaneadas".
A5: =MID(K5, LEN(K5)-6, 3) -> 004 | B5: Vista superior de telhados de fibrocimento e amplo pavilhão com bloco central elevado. | C5: Item | D5: Sem data | E5: Gerado pelo Dataverse | F5: Fotografia digitalizada; colorida; suporte em papel fotográfico | G5: São Paulo, Brasil | H5: Grupo de Pesquisa em Direito e Violência de Estado | I5: Arcoenge - Demolição - Casa de Detenção do Carandiru (Fotografias) | J5: Pasta: 0001 | K5: =TEXTJOIN("", TRUE, Geral!B5:U5) -> BR-SPGPDVE_ARCOENGE-DEMOLICAO-CSDTCARANDIRU_ICO-FOT-DGZ-MB0_0001-004.JPG | L5: ='0001'!$L$2 -> A Casa de Detenção de São Paulo, conhecida como Carandiru, foi demolida em etapas. Em 2002, ocorreu a implosão dos pavilhões 6, 8 e 9. Já em 2005, dos pavilhões 2 e 5 pela empresa Arcoenge (contratada pelo governo do estado de São Paulo). A coleção Arcoenge contém subgrupos de fotos, vídeos e texto, totalizando 164 peças documentais. | M5: Enquadramento voltado para as partes superiores das estruturas. Telhados de fibrocimento compõem o primeiro plano inferior. Ao fundo, um amplo pavilhão de concreto que possui um bloco central arquitetonicamente mais alto do que suas alas laterais. | N5: ='0001'!$N$2 -> O acesso aos documentos deste acervo está condicionado ao compromisso de não repassá-los a terceiros, à obrigatoriedade de mencionar que os originais pertencem ao GPDVE (?), e à necessidade de novo Termo de Responsabilidade em caso de reutilização ou uso diverso do inicialmente acordado. O uso está sujeito às restrições previstas na Lei de Arquivos (Lei nº 8.159/1991), na Lei de Direitos Autorais (Lei nº 9.610/1998), nos artigos 138 e 145 do Código Penal, e no artigo 5º, inciso X, da Constituição Federal, especialmente quanto à proteção da honra e imagem de terceiros. A pessoa física ou jurídica responsável assume integral responsabilidade civil e penal por eventuais danos decorrentes do uso das reproduções e informações, eximindo o GPDVE de qualquer responsabilidade. | O5: Sistema prisional; Arquitetura prisional; Casa de Detenção de São Paulo; Carandiru | P5: Fotografia (Iconográfico) | Q5: Digitalização de fotografia colorida (analógica original) | R5: ="Figura n – ["&B5&"]"&CHAR(10)&"Fonte: Arquivo do Estado de São Paulo, "&TEXT(D5,"yyyy")&"." -> Figura n – [Vista superior de telhados de fibrocimento e amplo pavilhão com bloco central elevado.] Fonte: Arquivo do Estado de São Paulo, Sem data. | S5: ="ARQUIVO PÚBLICO DO ESTADO DE SÃO PAULO (Brasil). ["&B5&"]. "&G5&". "&TEXT(D5,"dd")&" "&LOWER(TEXT(D5,"mmm"))&" "&TEXT(D5,"yyyy")&". "&F5&". Disponível em: <link do dataverse>. Acesso em: 28 out. 2025." -> ARQUIVO PÚBLICO DO ESTADO DE SÃO PAULO (Brasil). [Vista superior de telhados de fibrocimento e amplo pavilhão com bloco central elevado.]. São Paulo, Brasil. Sem data sem data Sem data. Fotografia digitalizada; colorida; suporte em papel fotográfico. Disponível em: <link do dataverse>. Acesso em: 28 out. 2025. | T5: Este item pertencia à pasta intitulada "fotos escaneadas".
A6: =MID(K6, LEN(K6)-6, 3) -> 005 | B6: Pátio arborizado com reboque azul em primeiro plano, van estacionada e pavilhão ao fundo. | C6: Item | D6: Sem data | E6: Gerado pelo Dataverse | F6: Fotografia digitalizada; colorida; suporte em papel fotográfico | G6: São Paulo, Brasil | H6: Grupo de Pesquisa em Direito e Violência de Estado | I6: Arcoenge - Demolição - Casa de Detenção do Carandiru (Fotografias) | J6: Pasta: 0001 | K6: =TEXTJOIN("", TRUE, Geral!B6:U6) -> BR-SPGPDVE_ARCOENGE-DEMOLICAO-CSDTCARANDIRU_ICO-FOT-DGZ-MB0_0001-005.JPG | L6: ='0001'!$L$2 -> A Casa de Detenção de São Paulo, conhecida como Carandiru, foi demolida em etapas. Em 2002, ocorreu a implosão dos pavilhões 6, 8 e 9. Já em 2005, dos pavilhões 2 e 5 pela empresa Arcoenge (contratada pelo governo do estado de São Paulo). A coleção Arcoenge contém subgrupos de fotos, vídeos e texto, totalizando 164 peças documentais. | M6: Pátio arborizado com composição semelhante à foto BR-SPGPDVE_ARCOENGE-DEMOLICAO-CSDTCARANDIRU_ICO-FOT-DGZ-MB0_0001-010.JPG, contendo a van branca estacionada e as mesmas edificações ao fundo. A imagem se diferencia pela presença de um reboque ou equipamento azul estacionado no pátio em destaque no primeiro plano. | N6: ='0001'!$N$2 -> O acesso aos documentos deste acervo está condicionado ao compromisso de não repassá-los a terceiros, à obrigatoriedade de mencionar que os originais pertencem ao GPDVE (?), e à necessidade de novo Termo de Responsabilidade em caso de reutilização ou uso diverso do inicialmente acordado. O uso está sujeito às restrições previstas na Lei de Arquivos (Lei nº 8.159/1991), na Lei de Direitos Autorais (Lei nº 9.610/1998), nos artigos 138 e 145 do Código Penal, e no artigo 5º, inciso X, da Constituição Federal, especialmente quanto à proteção da honra e imagem de terceiros. A pessoa física ou jurídica responsável assume integral responsabilidade civil e penal por eventuais danos decorrentes do uso das reproduções e informações, eximindo o GPDVE de qualquer responsabilidade. | O6: Sistema prisional; Arquitetura prisional; Casa de Detenção de São Paulo; Carandiru | P6: Fotografia (Iconográfico) | Q6: Digitalização de fotografia colorida (analógica original) | R6: ="Figura n – ["&B6&"]"&CHAR(10)&"Fonte: Arquivo do Estado de São Paulo, "&TEXT(D6,"yyyy")&"." -> Figura n – [Pátio arborizado com reboque azul em primeiro plano, van estacionada e pavilhão ao fundo.] Fonte: Arquivo do Estado de São Paulo, Sem data. | S6: ="ARQUIVO PÚBLICO DO ESTADO DE SÃO PAULO (Brasil). ["&B6&"]. "&G6&". "&TEXT(D6,"dd")&" "&LOWER(TEXT(D6,"mmm"))&" "&TEXT(D6,"yyyy")&". "&F6&". Disponível em: <link do dataverse>. Acesso em: 28 out. 2025." -> ARQUIVO PÚBLICO DO ESTADO DE SÃO PAULO (Brasil). [Pátio arborizado com reboque azul em primeiro plano, van estacionada e pavilhão ao fundo.]. São Paulo, Brasil. Sem data sem data Sem data. Fotografia digitalizada; colorida; suporte em papel fotográfico. Disponível em: <link do dataverse>. Acesso em: 28 out. 2025. | T6: Este item pertencia à pasta intitulada "fotos escaneadas".
A7: =MID(K7, LEN(K7)-6, 3) -> 006 | B7: Área externa com lajes de concreto, varal transversal de cobertores e campo de terra com pessoas distribuídas. | C7: Item | D7: Sem data | E7: Gerado pelo Dataverse | F7: Fotografia digitalizada; colorida; suporte em papel fotográfico | G7: São Paulo, Brasil | H7: Grupo de Pesquisa em Direito e Violência de Estado | I7: Arcoenge - Demolição - Casa de Detenção do Carandiru (Fotografias) | J7: Pasta: 0001 | K7: =TEXTJOIN("", TRUE, Geral!B7:U7) -> BR-SPGPDVE_ARCOENGE-DEMOLICAO-CSDTCARANDIRU_ICO-FOT-DGZ-MB0_0001-006.JPG | L7: ='0001'!$L$2 -> A Casa de Detenção de São Paulo, conhecida como Carandiru, foi demolida em etapas. Em 2002, ocorreu a implosão dos pavilhões 6, 8 e 9. Já em 2005, dos pavilhões 2 e 5 pela empresa Arcoenge (contratada pelo governo do estado de São Paulo). A coleção Arcoenge contém subgrupos de fotos, vídeos e texto, totalizando 164 peças documentais. | M7: Ampla área externa. Em primeiro plano, lajes de concreto no chão com recortes quadrados e circulares. Uma separação visual é formada por cobertores e tecidos escuros pendurados transversalmente. Atrás dessa barreira, há um grande campo de terra onde diversas pessoas estão distribuídas. A lateral de um pavilhão preenche o canto superior direito. | N7: ='0001'!$N$2 -> O acesso aos documentos deste acervo está condicionado ao compromisso de não repassá-los a terceiros, à obrigatoriedade de mencionar que os originais pertencem ao GPDVE (?), e à necessidade de novo Termo de Responsabilidade em caso de reutilização ou uso diverso do inicialmente acordado. O uso está sujeito às restrições previstas na Lei de Arquivos (Lei nº 8.159/1991), na Lei de Direitos Autorais (Lei nº 9.610/1998), nos artigos 138 e 145 do Código Penal, e no artigo 5º, inciso X, da Constituição Federal, especialmente quanto à proteção da honra e imagem de terceiros. A pessoa física ou jurídica responsável assume integral responsabilidade civil e penal por eventuais danos decorrentes do uso das reproduções e informações, eximindo o GPDVE de qualquer responsabilidade. | O7: Sistema prisional; Arquitetura prisional; Casa de Detenção de São Paulo; Carandiru | P7: Fotografia (Iconográfico) | Q7: Digitalização de fotografia colorida (analógica original) | R7: ="Figura n – ["&B7&"]"&CHAR(10)&"Fonte: Arquivo do Estado de São Paulo, "&TEXT(D7,"yyyy")&"." -> Figura n – [Área externa com lajes de concreto, varal transversal de cobertores e campo de terra com pessoas distribuídas.] Fonte: Arquivo do Estado de São Paulo, Sem data. | S7: ="ARQUIVO PÚBLICO DO ESTADO DE SÃO PAULO (Brasil). ["&B7&"]. "&G7&". "&TEXT(D7,"dd")&" "&LOWER(TEXT(D7,"mmm"))&" "&TEXT(D7,"yyyy")&". "&F7&". Disponível em: <link do dataverse>. Acesso em: 28 out. 2025." -> ARQUIVO PÚBLICO DO ESTADO DE SÃO PAULO (Brasil). [Área externa com lajes de concreto, varal transversal de cobertores e campo de terra com pessoas distribuídas.]. São Paulo, Brasil. Sem data sem data Sem data. Fotografia digitalizada; colorida; suporte em papel fotográfico. Disponível em: <link do dataverse>. Acesso em: 28 out. 2025. | T7: Este item pertencia à pasta intitulada "fotos escaneadas".
A8: =MID(K8, LEN(K8)-6, 3) -> 007 | B8: Pessoa encostada em parapeito diante de amplo pátio de terra e pavilhão retangular ao fundo. | C8: Item | D8: Sem data | E8: Gerado pelo Dataverse | F8: Fotografia digitalizada; colorida; suporte em papel fotográfico | G8: São Paulo, Brasil | H8: Grupo de Pesquisa em Direito e Violência de Estado | I8: Arcoenge - Demolição - Casa de Detenção do Carandiru (Fotografias) | J8: Pasta: 0001 | K8: =TEXTJOIN("", TRUE, Geral!B8:U8) -> BR-SPGPDVE_ARCOENGE-DEMOLICAO-CSDTCARANDIRU_ICO-FOT-DGZ-MB0_0001-007.JPG | L8: ='0001'!$L$2 -> A Casa de Detenção de São Paulo, conhecida como Carandiru, foi demolida em etapas. Em 2002, ocorreu a implosão dos pavilhões 6, 8 e 9. Já em 2005, dos pavilhões 2 e 5 pela empresa Arcoenge (contratada pelo governo do estado de São Paulo). A coleção Arcoenge contém subgrupos de fotos, vídeos e texto, totalizando 164 peças documentais. | M8: Fotografia horizontal. Em primeiro plano, à direita, parte do braço e tronco de uma pessoa de camisa clara encostada em um parapeito. Ao centro, um amplo pátio liso de terra. Ao fundo, um pavilhão retangular de concreto com fileiras regulares de janelas pequenas. | N8: ='0001'!$N$2 -> O acesso aos documentos deste acervo está condicionado ao compromisso de não repassá-los a terceiros, à obrigatoriedade de mencionar que os originais pertencem ao GPDVE (?), e à necessidade de novo Termo de Responsabilidade em caso de reutilização ou uso diverso do inicialmente acordado. O uso está sujeito às restrições previstas na Lei de Arquivos (Lei nº 8.159/1991), na Lei de Direitos Autorais (Lei nº 9.610/1998), nos artigos 138 e 145 do Código Penal, e no artigo 5º, inciso X, da Constituição Federal, especialmente quanto à proteção da honra e imagem de terceiros. A pessoa física ou jurídica responsável assume integral responsabilidade civil e penal por eventuais danos decorrentes do uso das reproduções e informações, eximindo o GPDVE de qualquer responsabilidade. | O8: Sistema prisional; Arquitetura prisional; Casa de Detenção de São Paulo; Carandiru | P8: Fotografia (Iconográfico) | Q8: Digitalização de fotografia colorida (analógica original) | R8: ="Figura n – ["&B8&"]"&CHAR(10)&"Fonte: Arquivo do Estado de São Paulo, "&TEXT(D8,"yyyy")&"." -> Figura n – [Pessoa encostada em parapeito diante de amplo pátio de terra e pavilhão retangular ao fundo.] Fonte: Arquivo do Estado de São Paulo, Sem data. | S8: ="ARQUIVO PÚBLICO DO ESTADO DE SÃO PAULO (Brasil). ["&B8&"]. "&G8&". "&TEXT(D8,"dd")&" "&LOWER(TEXT(D8,"mmm"))&" "&TEXT(D8,"yyyy")&". "&F8&". Disponível em: <link do dataverse>. Acesso em: 28 out. 2025." -> ARQUIVO PÚBLICO DO ESTADO DE SÃO PAULO (Brasil). [Pessoa encostada em parapeito diante de amplo pátio de terra e pavilhão retangular ao fundo.]. São Paulo, Brasil. Sem data sem data Sem data. Fotografia digitalizada; colorida; suporte em papel fotográfico. Disponível em: <link do dataverse>. Acesso em: 28 out. 2025. | T8: Este item pertencia à pasta intitulada "fotos escaneadas".
A9: =MID(K9, LEN(K9)-6, 3) -> 008 | B9: Pátio de terra dividido por muro baixo, com trave de futebol ao centro e ladeado por dois pavilhões. | C9: Item | D9: Sem data | E9: Gerado pelo Dataverse | F9: Fotografia digitalizada; colorida; suporte em papel fotográfico | G9: São Paulo, Brasil | H9: Grupo de Pesquisa em Direito e Violência de Estado | I9: Arcoenge - Demolição - Casa de Detenção do Carandiru (Fotografias) | J9: Pasta: 0001 | K9: =TEXTJOIN("", TRUE, Geral!B9:U9) -> BR-SPGPDVE_ARCOENGE-DEMOLICAO-CSDTCARANDIRU_ICO-FOT-DGZ-MB0_0001-008.JPG | L9: ='0001'!$L$2 -> A Casa de Detenção de São Paulo, conhecida como Carandiru, foi demolida em etapas. Em 2002, ocorreu a implosão dos pavilhões 6, 8 e 9. Já em 2005, dos pavilhões 2 e 5 pela empresa Arcoenge (contratada pelo governo do estado de São Paulo). A coleção Arcoenge contém subgrupos de fotos, vídeos e texto, totalizando 164 peças documentais. | M9: Pátio de terra contendo uma trave de futebol metálica no centro. O espaço é ladeado por dois grandes pavilhões de concreto. Há roupas penduradas em várias janelas do prédio à esquerda. Um muro baixo divide horizontalmente o terreno. | N9: ='0001'!$N$2 -> O acesso aos documentos deste acervo está condicionado ao compromisso de não repassá-los a terceiros, à obrigatoriedade de mencionar que os originais pertencem ao GPDVE (?), e à necessidade de novo Termo de Responsabilidade em caso de reutilização ou uso diverso do inicialmente acordado. O uso está sujeito às restrições previstas na Lei de Arquivos (Lei nº 8.159/1991), na Lei de Direitos Autorais (Lei nº 9.610/1998), nos artigos 138 e 145 do Código Penal, e no artigo 5º, inciso X, da Constituição Federal, especialmente quanto à proteção da honra e imagem de terceiros. A pessoa física ou jurídica responsável assume integral responsabilidade civil e penal por eventuais danos decorrentes do uso das reproduções e informações, eximindo o GPDVE de qualquer responsabilidade. | O9: Sistema prisional; Arquitetura prisional; Casa de Detenção de São Paulo; Carandiru | P9: Fotografia (Iconográfico) | Q9: Digitalização de fotografia colorida (analógica original) | R9: ="Figura n – ["&B9&"]"&CHAR(10)&"Fonte: Arquivo do Estado de São Paulo, "&TEXT(D9,"yyyy")&"." -> Figura n – [Pátio de terra dividido por muro baixo, com trave de futebol ao centro e ladeado por dois pavilhões.] Fonte: Arquivo do Estado de São Paulo, Sem data. | S9: ="ARQUIVO PÚBLICO DO ESTADO DE SÃO PAULO (Brasil). ["&B9&"]. "&G9&". "&TEXT(D9,"dd")&" "&LOWER(TEXT(D9,"mmm"))&" "&TEXT(D9,"yyyy")&". "&F9&". Disponível em: <link do dataverse>. Acesso em: 28 out. 2025." -> ARQUIVO PÚBLICO DO ESTADO DE SÃO PAULO (Brasil). [Pátio de terra dividido por muro baixo, com trave de futebol ao centro e ladeado por dois pavilhões.]. São Paulo, Brasil. Sem data sem data Sem data. Fotografia digitalizada; colorida; suporte em papel fotográfico. Disponível em: <link do dataverse>. Acesso em: 28 out. 2025. | T9: Este item pertencia à pasta intitulada "fotos escaneadas".
A10: =MID(K10, LEN(K10)-6, 3) -> 009 | B10: Vista de passarela elevada com pessoa caminhando de costas, pátio com portão verde e torre de vigilância ao fundo. | C10: Item | D10: Sem data | E10: Gerado pelo Dataverse | F10: Fotografia digitalizada; colorida; suporte em papel fotográfico | G10: São Paulo, Brasil | H10: Grupo de Pesquisa em Direito e Violência de Estado | I10: Arcoenge - Demolição - Casa de Detenção do Carandiru (Fotografias) | J10: Pasta: 0001 | K10: =TEXTJOIN("", TRUE, Geral!B10:U10) -> BR-SPGPDVE_ARCOENGE-DEMOLICAO-CSDTCARANDIRU_ICO-FOT-DGZ-MB0_0001-009.JPG | L10: ='0001'!$L$2 -> A Casa de Detenção de São Paulo, conhecida como Carandiru, foi demolida em etapas. Em 2002, ocorreu a implosão dos pavilhões 6, 8 e 9. Já em 2005, dos pavilhões 2 e 5 pela empresa Arcoenge (contratada pelo governo do estado de São Paulo). A coleção Arcoenge contém subgrupos de fotos, vídeos e texto, totalizando 164 peças documentais. | M10: Vista a partir de uma passarela elevada de concreto. Uma pessoa vestindo camisa clara e calça caminha de costas pela passarela. Abaixo, vê-se um pátio com uma pequena estrutura e um portão verde. Ao fundo, um longo pavilhão e uma torre de vigilância. | N10: ='0001'!$N$2 -> O acesso aos documentos deste acervo está condicionado ao compromisso de não repassá-los a terceiros, à obrigatoriedade de mencionar que os originais pertencem ao GPDVE (?), e à necessidade de novo Termo de Responsabilidade em caso de reutilização ou uso diverso do inicialmente acordado. O uso está sujeito às restrições previstas na Lei de Arquivos (Lei nº 8.159/1991), na Lei de Direitos Autorais (Lei nº 9.610/1998), nos artigos 138 e 145 do Código Penal, e no artigo 5º, inciso X, da Constituição Federal, especialmente quanto à proteção da honra e imagem de terceiros. A pessoa física ou jurídica responsável assume integral responsabilidade civil e penal por eventuais danos decorrentes do uso das reproduções e informações, eximindo o GPDVE de qualquer responsabilidade. | O10: Sistema prisional; Arquitetura prisional; Casa de Detenção de São Paulo; Carandiru | P10: Fotografia (Iconográfico) | Q10: Digitalização de fotografia colorida (analógica original) | R10: ="Figura n – ["&B10&"]"&CHAR(10)&"Fonte: Arquivo do Estado de São Paulo, "&TEXT(D10,"yyyy")&"." -> Figura n – [Vista de passarela elevada com pessoa caminhando de costas, pátio com portão verde e torre de vigilância ao fundo.] Fonte: Arquivo do Estado de São Paulo, Sem data. | S10: ="ARQUIVO PÚBLICO DO ESTADO DE SÃO PAULO (Brasil). ["&B10&"]. "&G10&". "&TEXT(D10,"dd")&" "&LOWER(TEXT(D10,"mmm"))&" "&TEXT(D10,"yyyy")&". "&F10&". Disponível em: <link do dataverse>. Acesso em: 28 out. 2025." -> ARQUIVO PÚBLICO DO ESTADO DE SÃO PAULO (Brasil). [Vista de passarela elevada com pessoa caminhando de costas, pátio com portão verde e torre de vigilância ao fundo.]. São Paulo, Brasil. Sem data sem data Sem data. Fotografia digitalizada; colorida; suporte em papel fotográfico. Disponível em: <link do dataverse>. Acesso em: 28 out. 2025. | T10: Este item pertencia à pasta intitulada "fotos escaneadas".
A11: =MID(K11, LEN(K11)-6, 3) -> 010 | B11: Pátio interno arborizado com van branca estacionada diante de construção térrea e grande pavilhão ao fundo. | C11: Item | D11: Sem data | E11: Gerado pelo Dataverse | F11: Fotografia digitalizada; colorida; suporte em papel fotográfico | G11: São Paulo, Brasil | H11: Grupo de Pesquisa em Direito e Violência de Estado | I11: Arcoenge - Demolição - Casa de Detenção do Carandiru (Fotografias) | J11: Pasta: 0001 | K11: =TEXTJOIN("", TRUE, Geral!B11:U11) -> BR-SPGPDVE_ARCOENGE-DEMOLICAO-CSDTCARANDIRU_ICO-FOT-DGZ-MB0_0001-010.JPG | L11: ='0001'!$L$2 -> A Casa de Detenção de São Paulo, conhecida como Carandiru, foi demolida em etapas. Em 2002, ocorreu a implosão dos pavilhões 6, 8 e 9. Já em 2005, dos pavilhões 2 e 5 pela empresa Arcoenge (contratada pelo governo do estado de São Paulo). A coleção Arcoenge contém subgrupos de fotos, vídeos e texto, totalizando 164 peças documentais. | M11: Pátio interno. À esquerda, copas de árvores. Ao centro, uma van branca estacionada em frente a uma construção térrea clara (que exibe um mural ou pintura na parede direita). Atrás dessa construção térrea, ergue-se um grande pavilhão de concreto. No limite inferior da foto, nota-se a borda de um telhado de fibrocimento. | N11: ='0001'!$N$2 -> O acesso aos documentos deste acervo está condicionado ao compromisso de não repassá-los a terceiros, à obrigatoriedade de mencionar que os originais pertencem ao GPDVE (?), e à necessidade de novo Termo de Responsabilidade em caso de reutilização ou uso diverso do inicialmente acordado. O uso está sujeito às restrições previstas na Lei de Arquivos (Lei nº 8.159/1991), na Lei de Direitos Autorais (Lei nº 9.610/1998), nos artigos 138 e 145 do Código Penal, e no artigo 5º, inciso X, da Constituição Federal, especialmente quanto à proteção da honra e imagem de terceiros. A pessoa física ou jurídica responsável assume integral responsabilidade civil e penal por eventuais danos decorrentes do uso das reproduções e informações, eximindo o GPDVE de qualquer responsabilidade. | O11: Sistema prisional; Arquitetura prisional; Casa de Detenção de São Paulo; Carandiru | P11: Fotografia (Iconográfico) | Q11: Digitalização de fotografia colorida (analógica original) | R11: ="Figura n – ["&B11&"]"&CHAR(10)&"Fonte: Arquivo do Estado de São Paulo, "&TEXT(D11,"yyyy")&"." -> Figura n – [Pátio interno arborizado com van branca estacionada diante de construção térrea e grande pavilhão ao fundo.] Fonte: Arquivo do Estado de São Paulo, Sem data. | S11: ="ARQUIVO PÚBLICO DO ESTADO DE SÃO PAULO (Brasil). ["&B11&"]. "&G11&". "&TEXT(D11,"dd")&" "&LOWER(TEXT(D11,"mmm"))&" "&TEXT(D11,"yyyy")&". "&F11&". Disponível em: <link do dataverse>. Acesso em: 28 out. 2025." -> ARQUIVO PÚBLICO DO ESTADO DE SÃO PAULO (Brasil). [Pátio interno arborizado com van branca estacionada diante de construção térrea e grande pavilhão ao fundo.]. São Paulo, Brasil. Sem data sem data Sem data. Fotografia digitalizada; colorida; suporte em papel fotográfico. Disponível em: <link do dataverse>. Acesso em: 28 out. 2025. | T11: Este item pertencia à pasta intitulada "fotos escaneadas".
A12: =MID(K12, LEN(K12)-6, 3) -> 011 | B12: Pátio externo subdividido por alambrado, com quadra de terra, aglomeração de pessoas e dois pavilhões ao fundo. | C12: Item | D12: Sem data | E12: Gerado pelo Dataverse | F12: Fotografia digitalizada; colorida; suporte em papel fotográfico | G12: São Paulo, Brasil | H12: Grupo de Pesquisa em Direito e Violência de Estado | I12: Arcoenge - Demolição - Casa de Detenção do Carandiru (Fotografias) | J12: Pasta: 0001 | K12: =TEXTJOIN("", TRUE, Geral!B12:U12) -> BR-SPGPDVE_ARCOENGE-DEMOLICAO-CSDTCARANDIRU_ICO-FOT-DGZ-MB0_0001-011.JPG | L12: ='0001'!$L$2 -> A Casa de Detenção de São Paulo, conhecida como Carandiru, foi demolida em etapas. Em 2002, ocorreu a implosão dos pavilhões 6, 8 e 9. Já em 2005, dos pavilhões 2 e 5 pela empresa Arcoenge (contratada pelo governo do estado de São Paulo). A coleção Arcoenge contém subgrupos de fotos, vídeos e texto, totalizando 164 peças documentais. | M12: Amplo pátio externo subdividido. Em primeiro plano, à esquerda, uma quadra de terra demarcada por linhas brancas e cercada por alambrado. Atrás do alambrado, uma extensa área de terra abriga dezenas de pessoas espalhadas em meio a pequenas estruturas improvisadas e varais com roupas. Ao fundo, um longo muro escuro divide o terreno, atrás do qual se erguem dois grandes edifícios de concreto (pavilhões) com diversas janelas retangulares. Um alto poste de iluminação ergue-se à direita, com uma torre de vigilância visível ao extremo fundo direito. | N12: ='0001'!$N$2 -> O acesso aos documentos deste acervo está condicionado ao compromisso de não repassá-los a terceiros, à obrigatoriedade de mencionar que os originais pertencem ao GPDVE (?), e à necessidade de novo Termo de Responsabilidade em caso de reutilização ou uso diverso do inicialmente acordado. O uso está sujeito às restrições previstas na Lei de Arquivos (Lei nº 8.159/1991), na Lei de Direitos Autorais (Lei nº 9.610/1998), nos artigos 138 e 145 do Código Penal, e no artigo 5º, inciso X, da Constituição Federal, especialmente quanto à proteção da honra e imagem de terceiros. A pessoa física ou jurídica responsável assume integral responsabilidade civil e penal por eventuais danos decorrentes do uso das reproduções e informações, eximindo o GPDVE de qualquer responsabilidade. | O12: Sistema prisional; Arquitetura prisional; Casa de Detenção de São Paulo; Carandiru | P12: Fotografia (Iconográfico) | Q12: Digitalização de fotografia colorida (analógica original) | R12: ="Figura n – ["&B12&"]"&CHAR(10)&"Fonte: Arquivo do Estado de São Paulo, "&TEXT(D12,"yyyy")&"." -> Figura n – [Pátio externo subdividido por alambrado, com quadra de terra, aglomeração de pessoas e dois pavilhões ao fundo.] Fonte: Arquivo do Estado de São Paulo, Sem data. | S12: ="ARQUIVO PÚBLICO DO ESTADO DE SÃO PAULO (Brasil). ["&B12&"]. "&G12&". "&TEXT(D12,"dd")&" "&LOWER(TEXT(D12,"mmm"))&" "&TEXT(D12,"yyyy")&". "&F12&". Disponível em: <link do dataverse>. Acesso em: 28 out. 2025." -> ARQUIVO PÚBLICO DO ESTADO DE SÃO PAULO (Brasil). [Pátio externo subdividido por alambrado, com quadra de terra, aglomeração de pessoas e dois pavilhões ao fundo.]. São Paulo, Brasil. Sem data sem data Sem data. Fotografia digitalizada; colorida; suporte em papel fotográfico. Disponível em: <link do dataverse>. Acesso em: 28 out. 2025. | T12: Este item pertencia à pasta intitulada "fotos escaneadas".
A13: =MID(K13, LEN(K13)-6, 3) -> 012 | B13: . Amplo campo de terra com pessoas distribuídas pelo espaço, ladeado por muro alto e pavilhão ao fundo. | C13: Item | D13: Sem data | E13: Gerado pelo Dataverse | F13: Fotografia digitalizada; colorida; suporte em papel fotográfico | G13: São Paulo, Brasil | H13: Grupo de Pesquisa em Direito e Violência de Estado | I13: Arcoenge - Demolição - Casa de Detenção do Carandiru (Fotografias) | J13: Pasta: 0001 | K13: =TEXTJOIN("", TRUE, Geral!B13:U13) -> BR-SPGPDVE_ARCOENGE-DEMOLICAO-CSDTCARANDIRU_ICO-FOT-DGZ-MB0_0001-012.JPG | L13: ='0001'!$L$2 -> A Casa de Detenção de São Paulo, conhecida como Carandiru, foi demolida em etapas. Em 2002, ocorreu a implosão dos pavilhões 6, 8 e 9. Já em 2005, dos pavilhões 2 e 5 pela empresa Arcoenge (contratada pelo governo do estado de São Paulo). A coleção Arcoenge contém subgrupos de fotos, vídeos e texto, totalizando 164 peças documentais. | M13: Amplo campo de terra liso ocupando quase toda a imagem, com diversas pessoas distribuídas pelo espaço, jogando futebol. No canto inferior esquerdo, vê-se parte da estrutura tubular de uma trave esportiva. O campo é delimitado à esquerda e à direita por altos muros escuros contínuos. Ao centro, no fundo do terreno, ergue-se um grande pavilhão retangular de concreto com cinco andares visíveis de janelas, muitas delas exibindo roupas penduradas. | N13: ='0001'!$N$2 -> O acesso aos documentos deste acervo está condicionado ao compromisso de não repassá-los a terceiros, à obrigatoriedade de mencionar que os originais pertencem ao GPDVE (?), e à necessidade de novo Termo de Responsabilidade em caso de reutilização ou uso diverso do inicialmente acordado. O uso está sujeito às restrições previstas na Lei de Arquivos (Lei nº 8.159/1991), na Lei de Direitos Autorais (Lei nº 9.610/1998), nos artigos 138 e 145 do Código Penal, e no artigo 5º, inciso X, da Constituição Federal, especialmente quanto à proteção da honra e imagem de terceiros. A pessoa física ou jurídica responsável assume integral responsabilidade civil e penal por eventuais danos decorrentes do uso das reproduções e informações, eximindo o GPDVE de qualquer responsabilidade. | O13: Sistema prisional; Arquitetura prisional; Casa de Detenção de São Paulo; Carandiru | P13: Fotografia (Iconográfico) | Q13: Digitalização de fotografia colorida (analógica original) | R13: ="Figura n – ["&B13&"]"&CHAR(10)&"Fonte: Arquivo do Estado de São Paulo, "&TEXT(D13,"yyyy")&"." -> Figura n – [. Amplo campo de terra com pessoas distribuídas pelo espaço, ladeado por muro alto e pavilhão ao fundo.] Fonte: Arquivo do Estado de São Paulo, Sem data. | S13: ="ARQUIVO PÚBLICO DO ESTADO DE SÃO PAULO (Brasil). ["&B13&"]. "&G13&". "&TEXT(D13,"dd")&" "&LOWER(TEXT(D13,"mmm"))&" "&TEXT(D13,"yyyy")&". "&F13&". Disponível em: <link do dataverse>. Acesso em: 28 out. 2025." -> ARQUIVO PÚBLICO DO ESTADO DE SÃO PAULO (Brasil). [. Amplo campo de terra com pessoas distribuídas pelo espaço, ladeado por muro alto e pavilhão ao fundo.]. São Paulo, Brasil. Sem data sem data Sem data. Fotografia digitalizada; colorida; suporte em papel fotográfico. Disponível em: <link do dataverse>. Acesso em: 28 out. 2025. | T13: Este item pertencia à pasta intitulada "fotos escaneadas".
A14: =MID(K14, LEN(K14)-6, 3) -> 013 | B14: Fachada de pavilhão e topo de muro com grade em primeiro plano. | C14: Item | D14: Sem data | E14: Gerado pelo Dataverse | F14: Fotografia digitalizada; colorida; suporte em papel fotográfico | G14: São Paulo, Brasil | H14: Grupo de Pesquisa em Direito e Violência de Estado | I14: Arcoenge - Demolição - Casa de Detenção do Carandiru (Fotografias) | J14: Pasta: 0001 | K14: =TEXTJOIN("", TRUE, Geral!B14:U14) -> BR-SPGPDVE_ARCOENGE-DEMOLICAO-CSDTCARANDIRU_ICO-FOT-DGZ-MB0_0001-013.JPG | L14: ='0001'!$L$2 -> A Casa de Detenção de São Paulo, conhecida como Carandiru, foi demolida em etapas. Em 2002, ocorreu a implosão dos pavilhões 6, 8 e 9. Já em 2005, dos pavilhões 2 e 5 pela empresa Arcoenge (contratada pelo governo do estado de São Paulo). A coleção Arcoenge contém subgrupos de fotos, vídeos e texto, totalizando 164 peças documentais. | M14: Plano fechado focado exclusivamente na fachada de um pavilhão de concreto. Na margem inferior da imagem, cruzando horizontalmente o primeiro plano, nota-se o topo de um muro escuro encimado por uma grade de metal. | N14: ='0001'!$N$2 -> O acesso aos documentos deste acervo está condicionado ao compromisso de não repassá-los a terceiros, à obrigatoriedade de mencionar que os originais pertencem ao GPDVE (?), e à necessidade de novo Termo de Responsabilidade em caso de reutilização ou uso diverso do inicialmente acordado. O uso está sujeito às restrições previstas na Lei de Arquivos (Lei nº 8.159/1991), na Lei de Direitos Autorais (Lei nº 9.610/1998), nos artigos 138 e 145 do Código Penal, e no artigo 5º, inciso X, da Constituição Federal, especialmente quanto à proteção da honra e imagem de terceiros. A pessoa física ou jurídica responsável assume integral responsabilidade civil e penal por eventuais danos decorrentes do uso das reproduções e informações, eximindo o GPDVE de qualquer responsabilidade. | O14: Sistema prisional; Arquitetura prisional; Casa de Detenção de São Paulo; Carandiru | P14: Fotografia (Iconográfico) | Q14: Digitalização de fotografia colorida (analógica original) | R14: ="Figura n – ["&B14&"]"&CHAR(10)&"Fonte: Arquivo do Estado de São Paulo, "&TEXT(D14,"yyyy")&"." -> Figura n – [Fachada de pavilhão e topo de muro com grade em primeiro plano.] Fonte: Arquivo do Estado de São Paulo, Sem data. | S14: ="ARQUIVO PÚBLICO DO ESTADO DE SÃO PAULO (Brasil). ["&B14&"]. "&G14&". "&TEXT(D14,"dd")&" "&LOWER(TEXT(D14,"mmm"))&" "&TEXT(D14,"yyyy")&". "&F14&". Disponível em: <link do dataverse>. Acesso em: 28 out. 2025." -> ARQUIVO PÚBLICO DO ESTADO DE SÃO PAULO (Brasil). [Fachada de pavilhão e topo de muro com grade em primeiro plano.]. São Paulo, Brasil. Sem data sem data Sem data. Fotografia digitalizada; colorida; suporte em papel fotográfico. Disponível em: <link do dataverse>. Acesso em: 28 out. 2025. | T14: Este item pertencia à pasta intitulada "fotos escaneadas".
... A32: =MID(K32, LEN(K32)-6, 3) -> 031 | B32: Vista elevada de campo de terra com trave de futebol e pessoas, ladeado por grande pavilhão e muro longo. | C32: Item | D32: Sem data | E32: Gerado pelo Dataverse | F32: Fotografia digitalizada; colorida; suporte em papel fotográfico | G32: São Paulo, Brasil | H32: Grupo de Pesquisa em Direito e Violência de Estado | I32: Arcoenge - Demolição - Casa de Detenção do Carandiru (Fotografias) | J32: Pasta: 0001 | K32: =TEXTJOIN("", TRUE, Geral!B32:U32) -> BR-SPGPDVE_ARCOENGE-DEMOLICAO-CSDTCARANDIRU_ICO-FOT-DGZ-MB0_0001-031.JPG | L32: ='0001'!$L$2 -> A Casa de Detenção de São Paulo, conhecida como Carandiru, foi demolida em etapas. Em 2002, ocorreu a implosão dos pavilhões 6, 8 e 9. Já em 2005, dos pavilhões 2 e 5 pela empresa Arcoenge (contratada pelo governo do estado de São Paulo). A coleção Arcoenge contém subgrupos de fotos, vídeos e texto, totalizando 164 peças documentais. | M32: Fotografia em vista elevada. No primeiro plano, à esquerda, desponta o topo texturizado de um muro de concreto espesso que cruza o canto em diagonal. O centro da imagem é tomado por um amplo pátio de terra batida onde dezenas de pessoas estão distribuídas. Algumas agrupam-se e interagem próximas a uma trave metálica de futebol instalada no meio do campo, enquanto outras caminham ou descansam nas margens. À direita, domina a cena a extensa fachada de um grande pavilhão de concreto com cinco andares de janelas retangulares recuadas, muitas exibindo roupas estendidas. Ao fundo, do lado esquerdo, um longo muro escuro separa o pátio de outras construções com telhados alongados côncavos. | N32: ='0001'!$N$2 -> O acesso aos documentos deste acervo está condicionado ao compromisso de não repassá-los a terceiros, à obrigatoriedade de mencionar que os originais pertencem ao GPDVE (?), e à necessidade de novo Termo de Responsabilidade em caso de reutilização ou uso diverso do inicialmente acordado. O uso está sujeito às restrições previstas na Lei de Arquivos (Lei nº 8.159/1991), na Lei de Direitos Autorais (Lei nº 9.610/1998), nos artigos 138 e 145 do Código Penal, e no artigo 5º, inciso X, da Constituição Federal, especialmente quanto à proteção da honra e imagem de terceiros. A pessoa física ou jurídica responsável assume integral responsabilidade civil e penal por eventuais danos decorrentes do uso das reproduções e informações, eximindo o GPDVE de qualquer responsabilidade. | O32: Sistema prisional; Arquitetura prisional; Casa de Detenção de São Paulo; Carandiru | P32: Fotografia (Iconográfico) | Q32: Digitalização de fotografia colorida (analógica original) | R32: ="Figura n – ["&B32&"]"&CHAR(10)&"Fonte: Arquivo do Estado de São Paulo, "&TEXT(D32,"yyyy")&"." -> Figura n – [Vista elevada de campo de terra com trave de futebol e pessoas, ladeado por grande pavilhão e muro longo.] Fonte: Arquivo do Estado de São Paulo, Sem data. | S32: ="ARQUIVO PÚBLICO DO ESTADO DE SÃO PAULO (Brasil). ["&B32&"]. "&G32&". "&TEXT(D32,"dd")&" "&LOWER(TEXT(D32,"mmm"))&" "&TEXT(D32,"yyyy")&". "&F32&". Disponível em: <link do dataverse>. Acesso em: 28 out. 2025." -> ARQUIVO PÚBLICO DO ESTADO DE SÃO PAULO (Brasil). [Vista elevada de campo de terra com trave de futebol e pessoas, ladeado por grande pavilhão e muro longo.]. São Paulo, Brasil. Sem data sem data Sem data. Fotografia digitalizada; colorida; suporte em papel fotográfico. Disponível em: <link do dataverse>. Acesso em: 28 out. 2025. | T32: Este item pertencia à pasta intitulada "fotos escaneadas".

Sheet 0002
A1: Cód. | B1: Título descritivo (atribuído) | C1: Nível de descrição | D1: Data de criação da fotografia | E1: Tamanho | F1: Suporte | G1: Local | H1: Autor/Responsável | I1: Denominação do catálogo temático (GPDVE ARCOENGE) | J1: Localização | K1: Código de referência | L1: História arquivística | M1: Conteúdo/Assunto | N1: Condições de acesso e reprodução | O1: Palavras-chave | P1: Gênero | Q1: Técnica de registro | R1: Legenda para publicações | S1: Citação ABNT | T1: Notas
A2: =MID(K2, LEN(K2)-6, 3) -> 001 | B2: Vista geral da torre de água e bairro residencial ao fundo. | C2: Item | D2: 37690 | E2: Gerado pelo Dataverse | F2: Fotografia digitalizada; colorida; suporte em papel fotográfico | G2: São Paulo, Brasil | H2: Grupo de Pesquisa em Direito e Violência de Estado | I2: Arcoenge - Demolição - Casa de Detenção do Carandiru (Fotografias) | J2: Pasta: 0002 | K2: =TEXTJOIN("", TRUE, Geral!B33:U33) -> BR-SPGPDVE_ARCOENGE-DEMOLICAO-CSDTCARANDIRU_ICO-FOT-DGZ-MB0_0002-001.JPG | L2: ='0001'!$L$2 -> A Casa de Detenção de São Paulo, conhecida como Carandiru, foi demolida em etapas. Em 2002, ocorreu a implosão dos pavilhões 6, 8 e 9. Já em 2005, dos pavilhões 2 e 5 pela empresa Arcoenge (contratada pelo governo do estado de São Paulo). A coleção Arcoenge contém subgrupos de fotos, vídeos e texto, totalizando 164 peças documentais. | M2: Fotografia de uma ampla área de terreno em terra batida, com marcas de escavação e entulho em primeiro plano. À esquerda, destaca-se uma alta torre de água cilíndrica de concreto com escada externa. Próximo à base da torre, observam-se equipamentos e trabalhadores da construção civil utilizando capacetes de segurança. Ao fundo, vê-se o perfil de construções de um bairro residencial sob um céu parcialmente nublado. A imagem possui um Marcador numérico "3 3 '03" no canto inferior direito. | N2: ='0001'!$N$2 -> O acesso aos documentos deste acervo está condicionado ao compromisso de não repassá-los a terceiros, à obrigatoriedade de mencionar que os originais pertencem ao GPDVE (?), e à necessidade de novo Termo de Responsabilidade em caso de reutilização ou uso diverso do inicialmente acordado. O uso está sujeito às restrições previstas na Lei de Arquivos (Lei nº 8.159/1991), na Lei de Direitos Autorais (Lei nº 9.610/1998), nos artigos 138 e 145 do Código Penal, e no artigo 5º, inciso X, da Constituição Federal, especialmente quanto à proteção da honra e imagem de terceiros. A pessoa física ou jurídica responsável assume integral responsabilidade civil e penal por eventuais danos decorrentes do uso das reproduções e informações, eximindo o GPDVE de qualquer responsabilidade. | O2: Sistema prisional; Arquitetura prisional; Casa de Detenção de São Paulo; Carandiru | P2: Fotografia (Iconográfico) | Q2: Digitalização de fotografia colorida (analógica original) | R2: ="Figura n – ["&B2&"]"&CHAR(10)&"Fonte: Arquivo do Estado de São Paulo, "&TEXT(D2,"yyyy")&"." -> Figura n – [Vista geral da torre de água e bairro residencial ao fundo.] Fonte: Arquivo do Estado de São Paulo, 2003. | S2: ="ARQUIVO PÚBLICO DO ESTADO DE SÃO PAULO (Brasil). ["&B2&"]. "&G2&". "&TEXT(D2,"dd")&" "&LOWER(TEXT(D2,"mmm"))&" "&TEXT(D2,"yyyy")&". "&F2&". Disponível em: <link do dataverse>. Acesso em: 28 out. 2025." -> ARQUIVO PÚBLICO DO ESTADO DE SÃO PAULO (Brasil). [Vista geral da torre de água e bairro residencial ao fundo.]. São Paulo, Brasil. 10 mar. 2003. Fotografia digitalizada; colorida; suporte em papel fotográfico. Disponível em: <link do dataverse>. Acesso em: 28 out. 2025. | T2: Este item pertencia à pasta intitulada "caixa-d'água 1". Com relação à data de produção da fotografia, embora a lateral das fotografias indiquem 03/03/03, optou-se por utilizar a data mais antiga contida nos metadados do arquivo digital.
A3: =MID(K3, LEN(K3)-6, 3) -> 002 | B3: Torre de água de concreto e trabalhadores. | C3: Item | D3: 37690 | E3: Gerado pelo Dataverse | F3: Fotografia digitalizada; colorida; suporte em papel fotográfico | G3: São Paulo, Brasil | H3: Grupo de Pesquisa em Direito e Violência de Estado | I3: Arcoenge - Demolição - Casa de Detenção do Carandiru (Fotografias) | J3: Pasta: 0002 | K3: =TEXTJOIN("", TRUE, Geral!B34:U34) -> BR-SPGPDVE_ARCOENGE-DEMOLICAO-CSDTCARANDIRU_ICO-FOT-DGZ-MB0_0002-002.JPG | L3: ='0001'!$L$2 -> A Casa de Detenção de São Paulo, conhecida como Carandiru, foi demolida em etapas. Em 2002, ocorreu a implosão dos pavilhões 6, 8 e 9. Já em 2005, dos pavilhões 2 e 5 pela empresa Arcoenge (contratada pelo governo do estado de São Paulo). A coleção Arcoenge contém subgrupos de fotos, vídeos e texto, totalizando 164 peças documentais. | M3: Imagem com enquadramento focado na alta torre de água de concreto, posicionada à direita, com tubulações e escada metálica visíveis. À esquerda, uma árvore de grande porte compõe o primeiro plano. No solo de terra revirada, identificam-se trabalhadores da construção civil caminhando. Ao fundo, observam-se as fachadas traseiras e telhados de edificações baixas, além de torres de transmissão elétrica no horizonte. Marcador numérico "3 3 '03" no canto inferior direito. | N3: ='0001'!$N$2 -> O acesso aos documentos deste acervo está condicionado ao compromisso de não repassá-los a terceiros, à obrigatoriedade de mencionar que os originais pertencem ao GPDVE (?), e à necessidade de novo Termo de Responsabilidade em caso de reutilização ou uso diverso do inicialmente acordado. O uso está sujeito às restrições previstas na Lei de Arquivos (Lei nº 8.159/1991), na Lei de Direitos Autorais (Lei nº 9.610/1998), nos artigos 138 e 145 do Código Penal, e no artigo 5º, inciso X, da Constituição Federal, especialmente quanto à proteção da honra e imagem de terceiros. A pessoa física ou jurídica responsável assume integral responsabilidade civil e penal por eventuais danos decorrentes do uso das reproduções e informações, eximindo o GPDVE de qualquer responsabilidade. | O3: Sistema prisional; Arquitetura prisional; Casa de Detenção de São Paulo; Carandiru | P3: Fotografia (Iconográfico) | Q3: Digitalização de fotografia colorida (analógica original) | R3: ="Figura n – ["&B3&"]"&CHAR(10)&"Fonte: Arquivo do Estado de São Paulo, "&TEXT(D3,"yyyy")&"." -> Figura n – [Torre de água de concreto e trabalhadores.] Fonte: Arquivo do Estado de São Paulo, 2003. | S3: ="ARQUIVO PÚBLICO DO ESTADO DE SÃO PAULO (Brasil). ["&B3&"]. "&G3&". "&TEXT(D3,"dd")&" "&LOWER(TEXT(D3,"mmm"))&" "&TEXT(D3,"yyyy")&". "&F3&". Disponível em: <link do dataverse>. Acesso em: 28 out. 2025." -> ARQUIVO PÚBLICO DO ESTADO DE SÃO PAULO (Brasil). [Torre de água de concreto e trabalhadores.]. São Paulo, Brasil. 10 mar. 2003. Fotografia digitalizada; colorida; suporte em papel fotográfico. Disponível em: <link do dataverse>. Acesso em: 28 out. 2025. | T3: =$T$2 -> Este item pertencia à pasta intitulada "caixa-d'água 1". Com relação à data de produção da fotografia, embora a lateral das fotografias indiquem 03/03/03, optou-se por utilizar a data mais antiga contida nos metadados do arquivo digital.
A4: =MID(K4, LEN(K4)-6, 3) -> 003 | B4: Telhados residenciais e pavilhões da Casa de Detenção do Carandiru. | C4: Item | D4: 37690 | E4: Gerado pelo Dataverse | F4: Fotografia digitalizada; colorida; suporte em papel fotográfico | G4: São Paulo, Brasil | H4: Grupo de Pesquisa em Direito e Violência de Estado | I4: Arcoenge - Demolição - Casa de Detenção do Carandiru (Fotografias) | J4: Pasta: 0002 | K4: =TEXTJOIN("", TRUE, Geral!B35:U35) -> BR-SPGPDVE_ARCOENGE-DEMOLICAO-CSDTCARANDIRU_ICO-FOT-DGZ-MB0_0002-003.JPG | L4: ='0001'!$L$2 -> A Casa de Detenção de São Paulo, conhecida como Carandiru, foi demolida em etapas. Em 2002, ocorreu a implosão dos pavilhões 6, 8 e 9. Já em 2005, dos pavilhões 2 e 5 pela empresa Arcoenge (contratada pelo governo do estado de São Paulo). A coleção Arcoenge contém subgrupos de fotos, vídeos e texto, totalizando 164 peças documentais. | M4: Fotografia em ângulo mergulhante que contrapõe o ambiente residencial à arquitetura prisional. Em primeiro e médio plano, vê-se um aglomerado de telhados de casas, intercalando telhas cerâmicas e de fibrocimento. Ao fundo, estendem-se os muros de contenção e os longos pavilhões paralelos da Casa de Detenção do Carandiru, caracterizados por pequenas janelas enfileiradas. Um campo de futebol e áreas gramadas são visíveis entre os limites do presídio e o bairro. Marcador numérico "3 3 '03" no canto inferior direito. | N4: ='0001'!$N$2 -> O acesso aos documentos deste acervo está condicionado ao compromisso de não repassá-los a terceiros, à obrigatoriedade de mencionar que os originais pertencem ao GPDVE (?), e à necessidade de novo Termo de Responsabilidade em caso de reutilização ou uso diverso do inicialmente acordado. O uso está sujeito às restrições previstas na Lei de Arquivos (Lei nº 8.159/1991), na Lei de Direitos Autorais (Lei nº 9.610/1998), nos artigos 138 e 145 do Código Penal, e no artigo 5º, inciso X, da Constituição Federal, especialmente quanto à proteção da honra e imagem de terceiros. A pessoa física ou jurídica responsável assume integral responsabilidade civil e penal por eventuais danos decorrentes do uso das reproduções e informações, eximindo o GPDVE de qualquer responsabilidade. | O4: Sistema prisional; Arquitetura prisional; Casa de Detenção de São Paulo; Carandiru | P4: Fotografia (Iconográfico) | Q4: Digitalização de fotografia colorida (analógica original) | R4: ="Figura n – ["&B4&"]"&CHAR(10)&"Fonte: Arquivo do Estado de São Paulo, "&TEXT(D4,"yyyy")&"." -> Figura n – [Telhados residenciais e pavilhões da Casa de Detenção do Carandiru.] Fonte: Arquivo do Estado de São Paulo, 2003. | S4: ="ARQUIVO PÚBLICO DO ESTADO DE SÃO PAULO (Brasil). ["&B4&"]. "&G4&". "&TEXT(D4,"dd")&" "&LOWER(TEXT(D4,"mmm"))&" "&TEXT(D4,"yyyy")&". "&F4&". Disponível em: <link do dataverse>. Acesso em: 28 out. 2025." -> ARQUIVO PÚBLICO DO ESTADO DE SÃO PAULO (Brasil). [Telhados residenciais e pavilhões da Casa de Detenção do Carandiru.]. São Paulo, Brasil. 10 mar. 2003. Fotografia digitalizada; colorida; suporte em papel fotográfico. Disponível em: <link do dataverse>. Acesso em: 28 out. 2025. | T4: =$T$2 -> Este item pertencia à pasta intitulada "caixa-d'água 1". Com relação à data de produção da fotografia, embora a lateral das fotografias indiquem 03/03/03, optou-se por utilizar a data mais antiga contida nos metadados do arquivo digital.
A5: =MID(K5, LEN(K5)-6, 3) -> 004 | B5: Vista superior de imóveis residenciais contíguos. | C5: Item | D5: 37690 | E5: Gerado pelo Dataverse | F5: Fotografia digitalizada; colorida; suporte em papel fotográfico | G5: São Paulo, Brasil | H5: Grupo de Pesquisa em Direito e Violência de Estado | I5: Arcoenge - Demolição - Casa de Detenção do Carandiru (Fotografias) | J5: Pasta: 0002 | K5: =TEXTJOIN("", TRUE, Geral!B36:U36) -> BR-SPGPDVE_ARCOENGE-DEMOLICAO-CSDTCARANDIRU_ICO-FOT-DGZ-MB0_0002-004.JPG | L5: ='0001'!$L$2 -> A Casa de Detenção de São Paulo, conhecida como Carandiru, foi demolida em etapas. Em 2002, ocorreu a implosão dos pavilhões 6, 8 e 9. Já em 2005, dos pavilhões 2 e 5 pela empresa Arcoenge (contratada pelo governo do estado de São Paulo). A coleção Arcoenge contém subgrupos de fotos, vídeos e texto, totalizando 164 peças documentais. | M5: Vista em ângulo fortemente mergulhante focada na malha de telhados do bairro vizinho ao complexo prisional. Observa-se a densa justaposição de coberturas predominantemente de telhas cerâmicas vermelhas, intercaladas com algumas extensões de fibrocimento. À esquerda, registra-se um trecho de rua asfaltada com poste de fiação elétrica, árvores e um veículo estacionado. Marcador numérico "3 3 '03" no canto inferior direito. | N5: ='0001'!$N$2 -> O acesso aos documentos deste acervo está condicionado ao compromisso de não repassá-los a terceiros, à obrigatoriedade de mencionar que os originais pertencem ao GPDVE (?), e à necessidade de novo Termo de Responsabilidade em caso de reutilização ou uso diverso do inicialmente acordado. O uso está sujeito às restrições previstas na Lei de Arquivos (Lei nº 8.159/1991), na Lei de Direitos Autorais (Lei nº 9.610/1998), nos artigos 138 e 145 do Código Penal, e no artigo 5º, inciso X, da Constituição Federal, especialmente quanto à proteção da honra e imagem de terceiros. A pessoa física ou jurídica responsável assume integral responsabilidade civil e penal por eventuais danos decorrentes do uso das reproduções e informações, eximindo o GPDVE de qualquer responsabilidade. | O5: Sistema prisional; Arquitetura prisional; Casa de Detenção de São Paulo; Carandiru | P5: Fotografia (Iconográfico) | Q5: Digitalização de fotografia colorida (analógica original) | R5: ="Figura n – ["&B5&"]"&CHAR(10)&"Fonte: Arquivo do Estado de São Paulo, "&TEXT(D5,"yyyy")&"." -> Figura n – [Vista superior de imóveis residenciais contíguos.] Fonte: Arquivo do Estado de São Paulo, 2003. | S5: ="ARQUIVO PÚBLICO DO ESTADO DE SÃO PAULO (Brasil). ["&B5&"]. "&G5&". "&TEXT(D5,"dd")&" "&LOWER(TEXT(D5,"mmm"))&" "&TEXT(D5,"yyyy")&". "&F5&". Disponível em: <link do dataverse>. Acesso em: 28 out. 2025." -> ARQUIVO PÚBLICO DO ESTADO DE SÃO PAULO (Brasil). [Vista superior de imóveis residenciais contíguos.]. São Paulo, Brasil. 10 mar. 2003. Fotografia digitalizada; colorida; suporte em papel fotográfico. Disponível em: <link do dataverse>. Acesso em: 28 out. 2025. | T5: =$T$2 -> Este item pertencia à pasta intitulada "caixa-d'água 1". Com relação à data de produção da fotografia, embora a lateral das fotografias indiquem 03/03/03, optou-se por utilizar a data mais antiga contida nos metadados do arquivo digital.
A6: =MID(K6, LEN(K6)-6, 3) -> 005 | B6: Edificação com laje e alvenaria expostas. | C6: Item | D6: 37690 | E6: Gerado pelo Dataverse | F6: Fotografia digitalizada; colorida; suporte em papel fotográfico | G6: São Paulo, Brasil | H6: Grupo de Pesquisa em Direito e Violência de Estado | I6: Arcoenge - Demolição - Casa de Detenção do Carandiru (Fotografias) | J6: Pasta: 0002 | K6: =TEXTJOIN("", TRUE, Geral!B37:U37) -> BR-SPGPDVE_ARCOENGE-DEMOLICAO-CSDTCARANDIRU_ICO-FOT-DGZ-MB0_0002-005.JPG | L6: ='0001'!$L$2 -> A Casa de Detenção de São Paulo, conhecida como Carandiru, foi demolida em etapas. Em 2002, ocorreu a implosão dos pavilhões 6, 8 e 9. Já em 2005, dos pavilhões 2 e 5 pela empresa Arcoenge (contratada pelo governo do estado de São Paulo). A coleção Arcoenge contém subgrupos de fotos, vídeos e texto, totalizando 164 peças documentais. | M6: Imagem aérea detalhando uma propriedade inserida na malha urbana que passa por intervenção estrutural. O telhado está ausente em um setor central, revelando a laje de piso, paredes de tijolos expostos sem reboco, restos de madeiramento e materiais de construção acumulados. A rua asfaltada contígua ao lote é visível na parte superior do quadro. Marcador numérico "3 3 '03" na lateral esquerda inferior. | N6: ='0001'!$N$2 -> O acesso aos documentos deste acervo está condicionado ao compromisso de não repassá-los a terceiros, à obrigatoriedade de mencionar que os originais pertencem ao GPDVE (?), e à necessidade de novo Termo de Responsabilidade em caso de reutilização ou uso diverso do inicialmente acordado. O uso está sujeito às restrições previstas na Lei de Arquivos (Lei nº 8.159/1991), na Lei de Direitos Autorais (Lei nº 9.610/1998), nos artigos 138 e 145 do Código Penal, e no artigo 5º, inciso X, da Constituição Federal, especialmente quanto à proteção da honra e imagem de terceiros. A pessoa física ou jurídica responsável assume integral responsabilidade civil e penal por eventuais danos decorrentes do uso das reproduções e informações, eximindo o GPDVE de qualquer responsabilidade. | O6: Sistema prisional; Arquitetura prisional; Casa de Detenção de São Paulo; Carandiru | P6: Fotografia (Iconográfico) | Q6: Digitalização de fotografia colorida (analógica original) | R6: ="Figura n – ["&B6&"]"&CHAR(10)&"Fonte: Arquivo do Estado de São Paulo, "&TEXT(D6,"yyyy")&"." -> Figura n – [Edificação com laje e alvenaria expostas.] Fonte: Arquivo do Estado de São Paulo, 2003. | S6: ="ARQUIVO PÚBLICO DO ESTADO DE SÃO PAULO (Brasil). ["&B6&"]. "&G6&". "&TEXT(D6,"dd")&" "&LOWER(TEXT(D6,"mmm"))&" "&TEXT(D6,"yyyy")&". "&F6&". Disponível em: <link do dataverse>. Acesso em: 28 out. 2025." -> ARQUIVO PÚBLICO DO ESTADO DE SÃO PAULO (Brasil). [Edificação com laje e alvenaria expostas.]. São Paulo, Brasil. 10 mar. 2003. Fotografia digitalizada; colorida; suporte em papel fotográfico. Disponível em: <link do dataverse>. Acesso em: 28 out. 2025. | T6: =$T$2 -> Este item pertencia à pasta intitulada "caixa-d'água 1". Com relação à data de produção da fotografia, embora a lateral das fotografias indiquem 03/03/03, optou-se por utilizar a data mais antiga contida nos metadados do arquivo digital.
A7: =MID(K7, LEN(K7)-6, 3) -> 006 | B7: Detalhe superior de imóvel parcialmente destelhado. | C7: Item | D7: 37690 | E7: Gerado pelo Dataverse | F7: Fotografia digitalizada; colorida; suporte em papel fotográfico | G7: São Paulo, Brasil | H7: Grupo de Pesquisa em Direito e Violência de Estado | I7: Arcoenge - Demolição - Casa de Detenção do Carandiru (Fotografias) | J7: Pasta: 0002 | K7: =TEXTJOIN("", TRUE, Geral!B38:U38) -> BR-SPGPDVE_ARCOENGE-DEMOLICAO-CSDTCARANDIRU_ICO-FOT-DGZ-MB0_0002-006.JPG | L7: ='0001'!$L$2 -> A Casa de Detenção de São Paulo, conhecida como Carandiru, foi demolida em etapas. Em 2002, ocorreu a implosão dos pavilhões 6, 8 e 9. Já em 2005, dos pavilhões 2 e 5 pela empresa Arcoenge (contratada pelo governo do estado de São Paulo). A coleção Arcoenge contém subgrupos de fotos, vídeos e texto, totalizando 164 peças documentais. | M7: Fotografia semelhante à anterior, com variação leve de ângulo, mantendo o foco na edificação com o telhado parcialmente ausente. Destacam-se as paredes de alvenaria interna expostas, caçilhos vazios e uma área de laje contendo tábuas de madeira empilhadas, entulho e um balde. A estrutura contrasta com os telhados intactos (cerâmicos e de fibrocimento) das construções imediatamente adjacentes. Marcador numérico "3 3 '03" no canto inferior direito. | N7: ='0001'!$N$2 -> O acesso aos documentos deste acervo está condicionado ao compromisso de não repassá-los a terceiros, à obrigatoriedade de mencionar que os originais pertencem ao GPDVE (?), e à necessidade de novo Termo de Responsabilidade em caso de reutilização ou uso diverso do inicialmente acordado. O uso está sujeito às restrições previstas na Lei de Arquivos (Lei nº 8.159/1991), na Lei de Direitos Autorais (Lei nº 9.610/1998), nos artigos 138 e 145 do Código Penal, e no artigo 5º, inciso X, da Constituição Federal, especialmente quanto à proteção da honra e imagem de terceiros. A pessoa física ou jurídica responsável assume integral responsabilidade civil e penal por eventuais danos decorrentes do uso das reproduções e informações, eximindo o GPDVE de qualquer responsabilidade. | O7: Sistema prisional; Arquitetura prisional; Casa de Detenção de São Paulo; Carandiru | P7: Fotografia (Iconográfico) | Q7: Digitalização de fotografia colorida (analógica original) | R7: ="Figura n – ["&B7&"]"&CHAR(10)&"Fonte: Arquivo do Estado de São Paulo, "&TEXT(D7,"yyyy")&"." -> Figura n – [Detalhe superior de imóvel parcialmente destelhado.] Fonte: Arquivo do Estado de São Paulo, 2003. | S7: ="ARQUIVO PÚBLICO DO ESTADO DE SÃO PAULO (Brasil). ["&B7&"]. "&G7&". "&TEXT(D7,"dd")&" "&LOWER(TEXT(D7,"mmm"))&" "&TEXT(D7,"yyyy")&". "&F7&". Disponível em: <link do dataverse>. Acesso em: 28 out. 2025." -> ARQUIVO PÚBLICO DO ESTADO DE SÃO PAULO (Brasil). [Detalhe superior de imóvel parcialmente destelhado.]. São Paulo, Brasil. 10 mar. 2003. Fotografia digitalizada; colorida; suporte em papel fotográfico. Disponível em: <link do dataverse>. Acesso em: 28 out. 2025. | T7: =$T$2 -> Este item pertencia à pasta intitulada "caixa-d'água 1". Com relação à data de produção da fotografia, embora a lateral das fotografias indiquem 03/03/03, optou-se por utilizar a data mais antiga contida nos metadados do arquivo digital.
A8: =MID(K8, LEN(K8)-6, 3) -> 007 | B8: Cobertura de fibrocimento de galpão e via pública. | C8: Item | D8: 37690 | E8: Gerado pelo Dataverse | F8: Fotografia digitalizada; colorida; suporte em papel fotográfico | G8: São Paulo, Brasil | H8: Grupo de Pesquisa em Direito e Violência de Estado | I8: Arcoenge - Demolição - Casa de Detenção do Carandiru (Fotografias) | J8: Pasta: 0002 | K8: =TEXTJOIN("", TRUE, Geral!B39:U39) -> BR-SPGPDVE_ARCOENGE-DEMOLICAO-CSDTCARANDIRU_ICO-FOT-DGZ-MB0_0002-007.JPG | L8: ='0001'!$L$2 -> A Casa de Detenção de São Paulo, conhecida como Carandiru, foi demolida em etapas. Em 2002, ocorreu a implosão dos pavilhões 6, 8 e 9. Já em 2005, dos pavilhões 2 e 5 pela empresa Arcoenge (contratada pelo governo do estado de São Paulo). A coleção Arcoenge contém subgrupos de fotos, vídeos e texto, totalizando 164 peças documentais. | M8: Vista aérea perpendicular focada em uma extensa cobertura retangular de fibrocimento, típica de galpões ou imóveis comerciais/industriais de médio porte, que preenche grande parte do enquadramento. Na extremidade superior da imagem, visualiza-se um trecho linear de calçada e rua asfaltada, além da fachada de propriedades vizinhas do outro lado da via. Marcador numérico "3 3 '03" na lateral esquerda inferior. | N8: ='0001'!$N$2 -> O acesso aos documentos deste acervo está condicionado ao compromisso de não repassá-los a terceiros, à obrigatoriedade de mencionar que os originais pertencem ao GPDVE (?), e à necessidade de novo Termo de Responsabilidade em caso de reutilização ou uso diverso do inicialmente acordado. O uso está sujeito às restrições previstas na Lei de Arquivos (Lei nº 8.159/1991), na Lei de Direitos Autorais (Lei nº 9.610/1998), nos artigos 138 e 145 do Código Penal, e no artigo 5º, inciso X, da Constituição Federal, especialmente quanto à proteção da honra e imagem de terceiros. A pessoa física ou jurídica responsável assume integral responsabilidade civil e penal por eventuais danos decorrentes do uso das reproduções e informações, eximindo o GPDVE de qualquer responsabilidade. | O8: Sistema prisional; Arquitetura prisional; Casa de Detenção de São Paulo; Carandiru | P8: Fotografia (Iconográfico) | Q8: Digitalização de fotografia colorida (analógica original) | R8: ="Figura n – ["&B8&"]"&CHAR(10)&"Fonte: Arquivo do Estado de São Paulo, "&TEXT(D8,"yyyy")&"." -> Figura n – [Cobertura de fibrocimento de galpão e via pública.] Fonte: Arquivo do Estado de São Paulo, 2003. | S8: ="ARQUIVO PÚBLICO DO ESTADO DE SÃO PAULO (Brasil). ["&B8&"]. "&G8&". "&TEXT(D8,"dd")&" "&LOWER(TEXT(D8,"mmm"))&" "&TEXT(D8,"yyyy")&". "&F8&". Disponível em: <link do dataverse>. Acesso em: 28 out. 2025." -> ARQUIVO PÚBLICO DO ESTADO DE SÃO PAULO (Brasil). [Cobertura de fibrocimento de galpão e via pública.]. São Paulo, Brasil. 10 mar. 2003. Fotografia digitalizada; colorida; suporte em papel fotográfico. Disponível em: <link do dataverse>. Acesso em: 28 out. 2025. | T8: =$T$2 -> Este item pertencia à pasta intitulada "caixa-d'água 1". Com relação à data de produção da fotografia, embora a lateral das fotografias indiquem 03/03/03, optou-se por utilizar a data mais antiga contida nos metadados do arquivo digital.
A9: =MID(K9, LEN(K9)-6, 3) -> 008 | B9: Justaposição de coberturas de fibrocimento e terreno descampado. | C9: Item | D9: 37690 | E9: Gerado pelo Dataverse | F9: Fotografia digitalizada; colorida; suporte em papel fotográfico | G9: São Paulo, Brasil | H9: Grupo de Pesquisa em Direito e Violência de Estado | I9: Arcoenge - Demolição - Casa de Detenção do Carandiru (Fotografias) | J9: Pasta: 0002 | K9: =TEXTJOIN("", TRUE, Geral!B40:U40) -> BR-SPGPDVE_ARCOENGE-DEMOLICAO-CSDTCARANDIRU_ICO-FOT-DGZ-MB0_0002-008.JPG | L9: ='0001'!$L$2 -> A Casa de Detenção de São Paulo, conhecida como Carandiru, foi demolida em etapas. Em 2002, ocorreu a implosão dos pavilhões 6, 8 e 9. Já em 2005, dos pavilhões 2 e 5 pela empresa Arcoenge (contratada pelo governo do estado de São Paulo). A coleção Arcoenge contém subgrupos de fotos, vídeos e texto, totalizando 164 peças documentais. | M9: Fotografia em vista superior registrando predominantemente telhados de fibrocimento em diferentes níveis estruturais. À direita da composição, capta-se uma faixa de terreno não pavimentado de terra avermelhada. Marcador numérico "3 3 '03" no canto inferior direito. | N9: ='0001'!$N$2 -> O acesso aos documentos deste acervo está condicionado ao compromisso de não repassá-los a terceiros, à obrigatoriedade de mencionar que os originais pertencem ao GPDVE (?), e à necessidade de novo Termo de Responsabilidade em caso de reutilização ou uso diverso do inicialmente acordado. O uso está sujeito às restrições previstas na Lei de Arquivos (Lei nº 8.159/1991), na Lei de Direitos Autorais (Lei nº 9.610/1998), nos artigos 138 e 145 do Código Penal, e no artigo 5º, inciso X, da Constituição Federal, especialmente quanto à proteção da honra e imagem de terceiros. A pessoa física ou jurídica responsável assume integral responsabilidade civil e penal por eventuais danos decorrentes do uso das reproduções e informações, eximindo o GPDVE de qualquer responsabilidade. | O9: Sistema prisional; Arquitetura prisional; Casa de Detenção de São Paulo; Carandiru | P9: Fotografia (Iconográfico) | Q9: Digitalização de fotografia colorida (analógica original) | R9: ="Figura n – ["&B9&"]"&CHAR(10)&"Fonte: Arquivo do Estado de São Paulo, "&TEXT(D9,"yyyy")&"." -> Figura n – [Justaposição de coberturas de fibrocimento e terreno descampado.] Fonte: Arquivo do Estado de São Paulo, 2003. | S9: ="ARQUIVO PÚBLICO DO ESTADO DE SÃO PAULO (Brasil). ["&B9&"]. "&G9&". "&TEXT(D9,"dd")&" "&LOWER(TEXT(D9,"mmm"))&" "&TEXT(D9,"yyyy")&". "&F9&". Disponível em: <link do dataverse>. Acesso em: 28 out. 2025." -> ARQUIVO PÚBLICO DO ESTADO DE SÃO PAULO (Brasil). [Justaposição de coberturas de fibrocimento e terreno descampado.]. São Paulo, Brasil. 10 mar. 2003. Fotografia digitalizada; colorida; suporte em papel fotográfico. Disponível em: <link do dataverse>. Acesso em: 28 out. 2025. | T9: =$T$2 -> Este item pertencia à pasta intitulada "caixa-d'água 1". Com relação à data de produção da fotografia, embora a lateral das fotografias indiquem 03/03/03, optou-se por utilizar a data mais antiga contida nos metadados do arquivo digital.
A10: =MID(K10, LEN(K10)-6, 3) -> 009 | B10: Edificação estreita e corredor de acesso lateral. | C10: Item | D10: 37690 | E10: Gerado pelo Dataverse | F10: Fotografia digitalizada; colorida; suporte em papel fotográfico | G10: São Paulo, Brasil | H10: Grupo de Pesquisa em Direito e Violência de Estado | I10: Arcoenge - Demolição - Casa de Detenção do Carandiru (Fotografias) | J10: Pasta: 0002 | K10: =TEXTJOIN("", TRUE, Geral!B41:U41) -> BR-SPGPDVE_ARCOENGE-DEMOLICAO-CSDTCARANDIRU_ICO-FOT-DGZ-MB0_0002-009.JPG | L10: ='0001'!$L$2 -> A Casa de Detenção de São Paulo, conhecida como Carandiru, foi demolida em etapas. Em 2002, ocorreu a implosão dos pavilhões 6, 8 e 9. Já em 2005, dos pavilhões 2 e 5 pela empresa Arcoenge (contratada pelo governo do estado de São Paulo). A coleção Arcoenge contém subgrupos de fotos, vídeos e texto, totalizando 164 peças documentais. | M10: Vista em ângulo mergulhante de uma edificação residencial ou de serviço de formato estreito e alongado, coberta por telhas de fibrocimento que apresentam sinais de desgaste e reparos. Lateralmente ao imóvel, observa-se um corredor/quintal parcialmente gramado que conecta os fundos do lote ao portão de acesso na via pública, visível no topo da imagem. Marcador numérico "3 3 '03" no canto inferior direito. | N10: ='0001'!$N$2 -> O acesso aos documentos deste acervo está condicionado ao compromisso de não repassá-los a terceiros, à obrigatoriedade de mencionar que os originais pertencem ao GPDVE (?), e à necessidade de novo Termo de Responsabilidade em caso de reutilização ou uso diverso do inicialmente acordado. O uso está sujeito às restrições previstas na Lei de Arquivos (Lei nº 8.159/1991), na Lei de Direitos Autorais (Lei nº 9.610/1998), nos artigos 138 e 145 do Código Penal, e no artigo 5º, inciso X, da Constituição Federal, especialmente quanto à proteção da honra e imagem de terceiros. A pessoa física ou jurídica responsável assume integral responsabilidade civil e penal por eventuais danos decorrentes do uso das reproduções e informações, eximindo o GPDVE de qualquer responsabilidade. | O10: Sistema prisional; Arquitetura prisional; Casa de Detenção de São Paulo; Carandiru | P10: Fotografia (Iconográfico) | Q10: Digitalização de fotografia colorida (analógica original) | R10: ="Figura n – ["&B10&"]"&CHAR(10)&"Fonte: Arquivo do Estado de São Paulo, "&TEXT(D10,"yyyy")&"." -> Figura n – [Edificação estreita e corredor de acesso lateral.] Fonte: Arquivo do Estado de São Paulo, 2003. | S10: ="ARQUIVO PÚBLICO DO ESTADO DE SÃO PAULO (Brasil). ["&B10&"]. "&G10&". "&TEXT(D10,"dd")&" "&LOWER(TEXT(D10,"mmm"))&" "&TEXT(D10,"yyyy")&". "&F10&". Disponível em: <link do dataverse>. Acesso em: 28 out. 2025." -> ARQUIVO PÚBLICO DO ESTADO DE SÃO PAULO (Brasil). [Edificação estreita e corredor de acesso lateral.]. São Paulo, Brasil. 10 mar. 2003. Fotografia digitalizada; colorida; suporte em papel fotográfico. Disponível em: <link do dataverse>. Acesso em: 28 out. 2025. | T10: =$T$2 -> Este item pertencia à pasta intitulada "caixa-d'água 1". Com relação à data de produção da fotografia, embora a lateral das fotografias indiquem 03/03/03, optou-se por utilizar a data mais antiga contida nos metadados do arquivo digital.
A11: =MID(K11, LEN(K11)-6, 3) -> 010 | B11: Cobertura de telhas cerâmicas com colapso parcial. | C11: Item | D11: 37690 | E11: Gerado pelo Dataverse | F11: Fotografia digitalizada; colorida; suporte em papel fotográfico | G11: São Paulo, Brasil | H11: Grupo de Pesquisa em Direito e Violência de Estado | I11: Arcoenge - Demolição - Casa de Detenção do Carandiru (Fotografias) | J11: Pasta: 0002 | K11: =TEXTJOIN("", TRUE, Geral!B42:U42) -> BR-SPGPDVE_ARCOENGE-DEMOLICAO-CSDTCARANDIRU_ICO-FOT-DGZ-MB0_0002-010.JPG | L11: ='0001'!$L$2 -> A Casa de Detenção de São Paulo, conhecida como Carandiru, foi demolida em etapas. Em 2002, ocorreu a implosão dos pavilhões 6, 8 e 9. Já em 2005, dos pavilhões 2 e 5 pela empresa Arcoenge (contratada pelo governo do estado de São Paulo). A coleção Arcoenge contém subgrupos de fotos, vídeos e texto, totalizando 164 peças documentais. | M11: Fotografia aérea detalhando um adensamento de telhados no limite da área de demolição. O elemento central é um telhado de duas águas em telha cerâmica que apresenta um dano estrutural significativo ou colapso parcial na sua lateral direita, com telhas quebradas e madeiramento escuro exposto. A estrutura é circundada por outras coberturas de fibrocimento e elementos urbanos como uma caixa d'água azul. Marcador numérico "3 3 '03" no canto inferior direito. | N11: ='0001'!$N$2 -> O acesso aos documentos deste acervo está condicionado ao compromisso de não repassá-los a terceiros, à obrigatoriedade de mencionar que os originais pertencem ao GPDVE (?), e à necessidade de novo Termo de Responsabilidade em caso de reutilização ou uso diverso do inicialmente acordado. O uso está sujeito às restrições previstas na Lei de Arquivos (Lei nº 8.159/1991), na Lei de Direitos Autorais (Lei nº 9.610/1998), nos artigos 138 e 145 do Código Penal, e no artigo 5º, inciso X, da Constituição Federal, especialmente quanto à proteção da honra e imagem de terceiros. A pessoa física ou jurídica responsável assume integral responsabilidade civil e penal por eventuais danos decorrentes do uso das reproduções e informações, eximindo o GPDVE de qualquer responsabilidade. | O11: Sistema prisional; Arquitetura prisional; Casa de Detenção de São Paulo; Carandiru | P11: Fotografia (Iconográfico) | Q11: Digitalização de fotografia colorida (analógica original) | R11: ="Figura n – ["&B11&"]"&CHAR(10)&"Fonte: Arquivo do Estado de São Paulo, "&TEXT(D11,"yyyy")&"." -> Figura n – [Cobertura de telhas cerâmicas com colapso parcial.] Fonte: Arquivo do Estado de São Paulo, 2003. | S11: ="ARQUIVO PÚBLICO DO ESTADO DE SÃO PAULO (Brasil). ["&B11&"]. "&G11&". "&TEXT(D11,"dd")&" "&LOWER(TEXT(D11,"mmm"))&" "&TEXT(D11,"yyyy")&". "&F11&". Disponível em: <link do dataverse>. Acesso em: 28 out. 2025." -> ARQUIVO PÚBLICO DO ESTADO DE SÃO PAULO (Brasil). [Cobertura de telhas cerâmicas com colapso parcial.]. São Paulo, Brasil. 10 mar. 2003. Fotografia digitalizada; colorida; suporte em papel fotográfico. Disponível em: <link do dataverse>. Acesso em: 28 out. 2025. | T11: =$T$2 -> Este item pertencia à pasta intitulada "caixa-d'água 1". Com relação à data de produção da fotografia, embora a lateral das fotografias indiquem 03/03/03, optou-se por utilizar a data mais antiga contida nos metadados do arquivo digital.
A12: =MID(K12, LEN(K12)-6, 3) -> 011 | B12: Vista superior de telhados e escavação em canteiro de obras. | C12: Item | D12: 37690 | E12: Gerado pelo Dataverse | F12: Fotografia digitalizada; colorida; suporte em papel fotográfico | G12: São Paulo, Brasil | H12: Grupo de Pesquisa em Direito e Violência de Estado | I12: Arcoenge - Demolição - Casa de Detenção do Carandiru (Fotografias) | J12: Pasta: 0002 | K12: =TEXTJOIN("", TRUE, Geral!B43:U43) -> BR-SPGPDVE_ARCOENGE-DEMOLICAO-CSDTCARANDIRU_ICO-FOT-DGZ-MB0_0002-011.JPG | L12: ='0001'!$L$2 -> A Casa de Detenção de São Paulo, conhecida como Carandiru, foi demolida em etapas. Em 2002, ocorreu a implosão dos pavilhões 6, 8 e 9. Já em 2005, dos pavilhões 2 e 5 pela empresa Arcoenge (contratada pelo governo do estado de São Paulo). A coleção Arcoenge contém subgrupos de fotos, vídeos e texto, totalizando 164 peças documentais. | M12: Fotografia em ângulo mergulhante mostrando um adensamento de telhados cerâmicos e de fibrocimento de edificações residenciais. Ao centro, destaca-se uma estrutura inacabada ou em desmanche com vigas de concreto expostas. À direita, observa-se uma via pública asfaltada com um veículo escuro estacionado e um pedestre. À extrema esquerda, nota-se uma borda de área de escavação em terra nua com a presença de um trabalhador utilizando capacete de segurança amarelo. Marcador numérico "3 3 '03" no canto inferior direito. | N12: ='0001'!$N$2 -> O acesso aos documentos deste acervo está condicionado ao compromisso de não repassá-los a terceiros, à obrigatoriedade de mencionar que os originais pertencem ao GPDVE (?), e à necessidade de novo Termo de Responsabilidade em caso de reutilização ou uso diverso do inicialmente acordado. O uso está sujeito às restrições previstas na Lei de Arquivos (Lei nº 8.159/1991), na Lei de Direitos Autorais (Lei nº 9.610/1998), nos artigos 138 e 145 do Código Penal, e no artigo 5º, inciso X, da Constituição Federal, especialmente quanto à proteção da honra e imagem de terceiros. A pessoa física ou jurídica responsável assume integral responsabilidade civil e penal por eventuais danos decorrentes do uso das reproduções e informações, eximindo o GPDVE de qualquer responsabilidade. | O12: Sistema prisional; Arquitetura prisional; Casa de Detenção de São Paulo; Carandiru | P12: Fotografia (Iconográfico) | Q12: Digitalização de fotografia colorida (analógica original) | R12: ="Figura n – ["&B12&"]"&CHAR(10)&"Fonte: Arquivo do Estado de São Paulo, "&TEXT(D12,"yyyy")&"." -> Figura n – [Vista superior de telhados e escavação em canteiro de obras.] Fonte: Arquivo do Estado de São Paulo, 2003. | S12: ="ARQUIVO PÚBLICO DO ESTADO DE SÃO PAULO (Brasil). ["&B12&"]. "&G12&". "&TEXT(D12,"dd")&" "&LOWER(TEXT(D12,"mmm"))&" "&TEXT(D12,"yyyy")&". "&F12&". Disponível em: <link do dataverse>. Acesso em: 28 out. 2025." -> ARQUIVO PÚBLICO DO ESTADO DE SÃO PAULO (Brasil). [Vista superior de telhados e escavação em canteiro de obras.]. São Paulo, Brasil. 10 mar. 2003. Fotografia digitalizada; colorida; suporte em papel fotográfico. Disponível em: <link do dataverse>. Acesso em: 28 out. 2025. | T12: =$T$2 -> Este item pertencia à pasta intitulada "caixa-d'água 1". Com relação à data de produção da fotografia, embora a lateral das fotografias indiquem 03/03/03, optou-se por utilizar a data mais antiga contida nos metadados do arquivo digital.
A13: =MID(K13, LEN(K13)-6, 3) -> 012 | B13: Telhados residenciais adjacentes a canteiro de obras e via pública. | C13: Item | D13: 37690 | E13: Gerado pelo Dataverse | F13: Fotografia digitalizada; colorida; suporte em papel fotográfico | G13: São Paulo, Brasil | H13: Grupo de Pesquisa em Direito e Violência de Estado | I13: Arcoenge - Demolição - Casa de Detenção do Carandiru (Fotografias) | J13: Pasta: 0002 | K13: =TEXTJOIN("", TRUE, Geral!B44:U44) -> BR-SPGPDVE_ARCOENGE-DEMOLICAO-CSDTCARANDIRU_ICO-FOT-DGZ-MB0_0002-012.JPG | L13: ='0001'!$L$2 -> A Casa de Detenção de São Paulo, conhecida como Carandiru, foi demolida em etapas. Em 2002, ocorreu a implosão dos pavilhões 6, 8 e 9. Já em 2005, dos pavilhões 2 e 5 pela empresa Arcoenge (contratada pelo governo do estado de São Paulo). A coleção Arcoenge contém subgrupos de fotos, vídeos e texto, totalizando 164 peças documentais. | M13: Vista aérea similar à imagem anterior, com ligeira variação de enquadramento, detalhando a justaposição de imóveis residenciais. No centro, uma edificação apresenta laje descoberta com vigamento aparente e uma pequena piscina de lona azul. À esquerda, a margem do canteiro de obras exibe solo escavado e trabalhadores. À direita, a rua asfaltada com calçadas e arborização. Marcador numérico "3 3 '03" no canto inferior direito. | N13: ='0001'!$N$2 -> O acesso aos documentos deste acervo está condicionado ao compromisso de não repassá-los a terceiros, à obrigatoriedade de mencionar que os originais pertencem ao GPDVE (?), e à necessidade de novo Termo de Responsabilidade em caso de reutilização ou uso diverso do inicialmente acordado. O uso está sujeito às restrições previstas na Lei de Arquivos (Lei nº 8.159/1991), na Lei de Direitos Autorais (Lei nº 9.610/1998), nos artigos 138 e 145 do Código Penal, e no artigo 5º, inciso X, da Constituição Federal, especialmente quanto à proteção da honra e imagem de terceiros. A pessoa física ou jurídica responsável assume integral responsabilidade civil e penal por eventuais danos decorrentes do uso das reproduções e informações, eximindo o GPDVE de qualquer responsabilidade. | O13: Sistema prisional; Arquitetura prisional; Casa de Detenção de São Paulo; Carandiru | P13: Fotografia (Iconográfico) | Q13: Digitalização de fotografia colorida (analógica original) | R13: ="Figura n – ["&B13&"]"&CHAR(10)&"Fonte: Arquivo do Estado de São Paulo, "&TEXT(D13,"yyyy")&"." -> Figura n – [Telhados residenciais adjacentes a canteiro de obras e via pública.] Fonte: Arquivo do Estado de São Paulo, 2003. | S13: ="ARQUIVO PÚBLICO DO ESTADO DE SÃO PAULO (Brasil). ["&B13&"]. "&G13&". "&TEXT(D13,"dd")&" "&LOWER(TEXT(D13,"mmm"))&" "&TEXT(D13,"yyyy")&". "&F13&". Disponível em: <link do dataverse>. Acesso em: 28 out. 2025." -> ARQUIVO PÚBLICO DO ESTADO DE SÃO PAULO (Brasil). [Telhados residenciais adjacentes a canteiro de obras e via pública.]. São Paulo, Brasil. 10 mar. 2003. Fotografia digitalizada; colorida; suporte em papel fotográfico. Disponível em: <link do dataverse>. Acesso em: 28 out. 2025. | T13: =$T$2 -> Este item pertencia à pasta intitulada "caixa-d'água 1". Com relação à data de produção da fotografia, embora a lateral das fotografias indiquem 03/03/03, optou-se por utilizar a data mais antiga contida nos metadados do arquivo digital.
A14: =MID(K14, LEN(K14)-6, 3) -> 013 | B14: Perspectiva de casas enfileiradas e área de demolição com maquinário. | C14: Item | D14: 37690 | E14: Gerado pelo Dataverse | F14: Fotografia digitalizada; colorida; suporte em papel fotográfico | G14: São Paulo, Brasil | H14: Grupo de Pesquisa em Direito e Violência de Estado | I14: Arcoenge - Demolição - Casa de Detenção do Carandiru (Fotografias) | J14: Pasta: 0002 | K14: =TEXTJOIN("", TRUE, Geral!B45:U45) -> BR-SPGPDVE_ARCOENGE-DEMOLICAO-CSDTCARANDIRU_ICO-FOT-DGZ-MB0_0002-013.JPG | L14: ='0001'!$L$2 -> A Casa de Detenção de São Paulo, conhecida como Carandiru, foi demolida em etapas. Em 2002, ocorreu a implosão dos pavilhões 6, 8 e 9. Já em 2005, dos pavilhões 2 e 5 pela empresa Arcoenge (contratada pelo governo do estado de São Paulo). A coleção Arcoenge contém subgrupos de fotos, vídeos e texto, totalizando 164 peças documentais. | M14: Fotografia em ângulo mergulhante que abrange uma extensa fileira de imóveis residenciais com telhados predominantes de cerâmica, margeados por uma via pública à direita. À esquerda, separada por um longo muro de contenção em diferentes níveis, estende-se uma ampla área de terra correspondente ao canteiro de obras. No terreno, visualiza-se uma retroescavadeira amarela e operários trabalhando junto à base do muro. Marcador numérico "3 3 '03" no canto inferior direito. | N14: ='0001'!$N$2 -> O acesso aos documentos deste acervo está condicionado ao compromisso de não repassá-los a terceiros, à obrigatoriedade de mencionar que os originais pertencem ao GPDVE (?), e à necessidade de novo Termo de Responsabilidade em caso de reutilização ou uso diverso do inicialmente acordado. O uso está sujeito às restrições previstas na Lei de Arquivos (Lei nº 8.159/1991), na Lei de Direitos Autorais (Lei nº 9.610/1998), nos artigos 138 e 145 do Código Penal, e no artigo 5º, inciso X, da Constituição Federal, especialmente quanto à proteção da honra e imagem de terceiros. A pessoa física ou jurídica responsável assume integral responsabilidade civil e penal por eventuais danos decorrentes do uso das reproduções e informações, eximindo o GPDVE de qualquer responsabilidade. | O14: Sistema prisional; Arquitetura prisional; Casa de Detenção de São Paulo; Carandiru | P14: Fotografia (Iconográfico) | Q14: Digitalização de fotografia colorida (analógica original) | R14: ="Figura n – ["&B14&"]"&CHAR(10)&"Fonte: Arquivo do Estado de São Paulo, "&TEXT(D14,"yyyy")&"." -> Figura n – [Perspectiva de casas enfileiradas e área de demolição com maquinário.] Fonte: Arquivo do Estado de São Paulo, 2003. | S14: ="ARQUIVO PÚBLICO DO ESTADO DE SÃO PAULO (Brasil). ["&B14&"]. "&G14&". "&TEXT(D14,"dd")&" "&LOWER(TEXT(D14,"mmm"))&" "&TEXT(D14,"yyyy")&". "&F14&". Disponível em: <link do dataverse>. Acesso em: 28 out. 2025." -> ARQUIVO PÚBLICO DO ESTADO DE SÃO PAULO (Brasil). [Perspectiva de casas enfileiradas e área de demolição com maquinário.]. São Paulo, Brasil. 10 mar. 2003. Fotografia digitalizada; colorida; suporte em papel fotográfico. Disponível em: <link do dataverse>. Acesso em: 28 out. 2025. | T14: =$T$2 -> Este item pertencia à pasta intitulada "caixa-d'água 1". Com relação à data de produção da fotografia, embora a lateral das fotografias indiquem 03/03/03, optou-se por utilizar a data mais antiga contida nos metadados do arquivo digital.
... A26: =MID(K26, LEN(K26)-6, 3) -> 025 | B26: Vistoria técnica apontando fissura em muro divisório (plano fechado). | C26: Item | D26: 37690 | E26: Gerado pelo Dataverse | F26: Fotografia digitalizada; colorida; suporte em papel fotográfico | G26: São Paulo, Brasil | H26: Grupo de Pesquisa em Direito e Violência de Estado | I26: Arcoenge - Demolição - Casa de Detenção do Carandiru (Fotografias) | J26: Pasta: 0002 | K26: =TEXTJOIN("", TRUE, Geral!B57:U57) -> BR-SPGPDVE_ARCOENGE-DEMOLICAO-CSDTCARANDIRU_ICO-FOT-DGZ-MB0_0002-025.JPG | L26: ='0001'!$L$2 -> A Casa de Detenção de São Paulo, conhecida como Carandiru, foi demolida em etapas. Em 2002, ocorreu a implosão dos pavilhões 6, 8 e 9. Já em 2005, dos pavilhões 2 e 5 pela empresa Arcoenge (contratada pelo governo do estado de São Paulo). A coleção Arcoenge contém subgrupos de fotos, vídeos e texto, totalizando 164 peças documentais. | M26: Imagem muito semelhante à anterior, com variação sutil de enquadramento, aproximando-se do sujeito e da área inspecionada. O mesmo profissional é registrado apontando para a rachadura vertical no muro divisório de blocos de concreto. No limite superior da imagem, são visíveis as bases dos reservatórios e equipamentos (identificados na foto 23) pertencentes ao lote vizinho. O contexto do terreno permanece com aspecto de canteiro incipiente. Marcador numérico "3 3 '03" alinhado verticalmente na lateral inferior esquerda. | N26: ='0001'!$N$2 -> O acesso aos documentos deste acervo está condicionado ao compromisso de não repassá-los a terceiros, à obrigatoriedade de mencionar que os originais pertencem ao GPDVE (?), e à necessidade de novo Termo de Responsabilidade em caso de reutilização ou uso diverso do inicialmente acordado. O uso está sujeito às restrições previstas na Lei de Arquivos (Lei nº 8.159/1991), na Lei de Direitos Autorais (Lei nº 9.610/1998), nos artigos 138 e 145 do Código Penal, e no artigo 5º, inciso X, da Constituição Federal, especialmente quanto à proteção da honra e imagem de terceiros. A pessoa física ou jurídica responsável assume integral responsabilidade civil e penal por eventuais danos decorrentes do uso das reproduções e informações, eximindo o GPDVE de qualquer responsabilidade. | O26: Sistema prisional; Arquitetura prisional; Casa de Detenção de São Paulo; Carandiru | P26: Fotografia (Iconográfico) | Q26: Digitalização de fotografia colorida (analógica original) | R26: ="Figura n – ["&B26&"]"&CHAR(10)&"Fonte: Arquivo do Estado de São Paulo, "&TEXT(D26,"yyyy")&"." -> Figura n – [Vistoria técnica apontando fissura em muro divisório (plano fechado).] Fonte: Arquivo do Estado de São Paulo, 2003. | S26: ="ARQUIVO PÚBLICO DO ESTADO DE SÃO PAULO (Brasil). ["&B26&"]. "&G26&". "&TEXT(D26,"dd")&" "&LOWER(TEXT(D26,"mmm"))&" "&TEXT(D26,"yyyy")&". "&F26&". Disponível em: <link do dataverse>. Acesso em: 28 out. 2025." -> ARQUIVO PÚBLICO DO ESTADO DE SÃO PAULO (Brasil). [Vistoria técnica apontando fissura em muro divisório (plano fechado).]. São Paulo, Brasil. 10 mar. 2003. Fotografia digitalizada; colorida; suporte em papel fotográfico. Disponível em: <link do dataverse>. Acesso em: 28 out. 2025. | T26: =$T$2 -> Este item pertencia à pasta intitulada "caixa-d'água 1". Com relação à data de produção da fotografia, embora a lateral das fotografias indiquem 03/03/03, optou-se por utilizar a data mais antiga contida nos metadados do arquivo digital.

Sheet 0003
A1: Cód. | B1: Título descritivo (atribuído) | C1: Nível de descrição | D1: Data de criação da fotografia | E1: Tamanho | F1: Suporte | G1: Local | H1: Autor/Responsável | I1: Denominação do catálogo temático (GPDVE ARCOENGE) | J1: Localização | K1: Código de referência | L1: História arquivística | M1: Conteúdo/Assunto | N1: Condições de acesso e reprodução | O1: Palavras-chave | P1: Gênero | Q1: Técnica de registro | R1: Legenda para publicações | S1: Citação ABNT | T1: Notas
A2: =MID(K2, LEN(K2)-6, 3) -> 001 | B2: Fachada cega com manchas de umidade e técnico em deslocamento. | C2: Item | D2: 37690 | E2: Gerado pelo Dataverse | F2: Fotografia digitalizada; colorida; suporte em papel fotográfico | G2: São Paulo, Brasil | H2: Grupo de Pesquisa em Direito e Violência de Estado | I2: Arcoenge - Demolição - Casa de Detenção do Carandiru (Fotografias) | J2: Pasta: 0004 | K2: =TEXTJOIN("", TRUE, Geral!B58:U58) -> BR-SPGPDVE_ARCOENGE-DEMOLICAO-CSDTCARANDIRU_ICO-FOT-DGZ-MB0_0003-001.JPG | L2: ='0001'!$L$2 -> A Casa de Detenção de São Paulo, conhecida como Carandiru, foi demolida em etapas. Em 2002, ocorreu a implosão dos pavilhões 6, 8 e 9. Já em 2005, dos pavilhões 2 e 5 pela empresa Arcoenge (contratada pelo governo do estado de São Paulo). A coleção Arcoenge contém subgrupos de fotos, vídeos e texto, totalizando 164 peças documentais. | M2: Vista ao nível do solo de uma grande parede lateral com intensas manchas escuras de umidade formando um padrão reticular horizontal. À esquerda, um técnico vestindo camisa clara e calça escura caminha de costas pelo terreno de terra batida, carregando uma prancheta. À direita, sobre um muro mais baixo, visualiza-se aparato azul com o texto/rótulo ALFATERM. Marcador numérico "3 3 '03" no canto inferior direito. | N2: ='0001'!$N$2 -> O acesso aos documentos deste acervo está condicionado ao compromisso de não repassá-los a terceiros, à obrigatoriedade de mencionar que os originais pertencem ao GPDVE (?), e à necessidade de novo Termo de Responsabilidade em caso de reutilização ou uso diverso do inicialmente acordado. O uso está sujeito às restrições previstas na Lei de Arquivos (Lei nº 8.159/1991), na Lei de Direitos Autorais (Lei nº 9.610/1998), nos artigos 138 e 145 do Código Penal, e no artigo 5º, inciso X, da Constituição Federal, especialmente quanto à proteção da honra e imagem de terceiros. A pessoa física ou jurídica responsável assume integral responsabilidade civil e penal por eventuais danos decorrentes do uso das reproduções e informações, eximindo o GPDVE de qualquer responsabilidade. | O2: Sistema prisional; Arquitetura prisional; Casa de Detenção de São Paulo; Carandiru | P2: Fotografia (Iconográfico) | Q2: Digitalização de fotografia colorida (analógica original) | R2: ="Figura n – ["&B2&"]"&CHAR(10)&"Fonte: Arquivo do Estado de São Paulo, "&TEXT(D2,"yyyy")&"." -> Figura n – [Fachada cega com manchas de umidade e técnico em deslocamento.] Fonte: Arquivo do Estado de São Paulo, 2003. | S2: ="ARQUIVO PÚBLICO DO ESTADO DE SÃO PAULO (Brasil). ["&B2&"]. "&G2&". "&TEXT(D2,"dd")&" "&LOWER(TEXT(D2,"mmm"))&" "&TEXT(D2,"yyyy")&". "&F2&". Disponível em: <link do dataverse>. Acesso em: 28 out. 2025." -> ARQUIVO PÚBLICO DO ESTADO DE SÃO PAULO (Brasil). [Fachada cega com manchas de umidade e técnico em deslocamento.]. São Paulo, Brasil. 10 mar. 2003. Fotografia digitalizada; colorida; suporte em papel fotográfico. Disponível em: <link do dataverse>. Acesso em: 28 out. 2025. | T2: Este item pertencia à pasta intitulada "caixa-d'água 2".
A3: =MID(K3, LEN(K3)-6, 3) -> 002 | B3: Muro divisório com pichações sutis e técnico apontando fissura. | C3: Item | D3: 37690 | E3: Gerado pelo Dataverse | F3: Fotografia digitalizada; colorida; suporte em papel fotográfico | G3: São Paulo, Brasil | H3: Grupo de Pesquisa em Direito e Violência de Estado | I3: Arcoenge - Demolição - Casa de Detenção do Carandiru (Fotografias) | J3: Pasta: 0004 | K3: =TEXTJOIN("", TRUE, Geral!B59:U59) -> BR-SPGPDVE_ARCOENGE-DEMOLICAO-CSDTCARANDIRU_ICO-FOT-DGZ-MB0_0003-002.JPG | L3: ='0001'!$L$2 -> A Casa de Detenção de São Paulo, conhecida como Carandiru, foi demolida em etapas. Em 2002, ocorreu a implosão dos pavilhões 6, 8 e 9. Já em 2005, dos pavilhões 2 e 5 pela empresa Arcoenge (contratada pelo governo do estado de São Paulo). A coleção Arcoenge contém subgrupos de fotos, vídeos e texto, totalizando 164 peças documentais. | M3: Fotografia panorâmica de um extenso muro divisório com pintura clara desgastada, apresentando manchas escuras de umidade no topo e na base, além de pichações esmaecidas. À direita, um técnico de camisa branca, calça jeans e óculos escuros segura uma prancheta e aponta fissura vertical no muro. À esquerda, outro homem caminha em direção oposta. O primeiro plano é de terra vermelha irregular. Marcador numérico "3 3 '03" no canto inferior direito. | N3: ='0001'!$N$2 -> O acesso aos documentos deste acervo está condicionado ao compromisso de não repassá-los a terceiros, à obrigatoriedade de mencionar que os originais pertencem ao GPDVE (?), e à necessidade de novo Termo de Responsabilidade em caso de reutilização ou uso diverso do inicialmente acordado. O uso está sujeito às restrições previstas na Lei de Arquivos (Lei nº 8.159/1991), na Lei de Direitos Autorais (Lei nº 9.610/1998), nos artigos 138 e 145 do Código Penal, e no artigo 5º, inciso X, da Constituição Federal, especialmente quanto à proteção da honra e imagem de terceiros. A pessoa física ou jurídica responsável assume integral responsabilidade civil e penal por eventuais danos decorrentes do uso das reproduções e informações, eximindo o GPDVE de qualquer responsabilidade. | O3: Sistema prisional; Arquitetura prisional; Casa de Detenção de São Paulo; Carandiru | P3: Fotografia (Iconográfico) | Q3: Digitalização de fotografia colorida (analógica original) | R3: ="Figura n – ["&B3&"]"&CHAR(10)&"Fonte: Arquivo do Estado de São Paulo, "&TEXT(D3,"yyyy")&"." -> Figura n – [Muro divisório com pichações sutis e técnico apontando fissura.] Fonte: Arquivo do Estado de São Paulo, 2003. | S3: ="ARQUIVO PÚBLICO DO ESTADO DE SÃO PAULO (Brasil). ["&B3&"]. "&G3&". "&TEXT(D3,"dd")&" "&LOWER(TEXT(D3,"mmm"))&" "&TEXT(D3,"yyyy")&". "&F3&". Disponível em: <link do dataverse>. Acesso em: 28 out. 2025." -> ARQUIVO PÚBLICO DO ESTADO DE SÃO PAULO (Brasil). [Muro divisório com pichações sutis e técnico apontando fissura.]. São Paulo, Brasil. 10 mar. 2003. Fotografia digitalizada; colorida; suporte em papel fotográfico. Disponível em: <link do dataverse>. Acesso em: 28 out. 2025. | T3: Este item pertencia à pasta intitulada "caixa-d'água 2".
A4: =MID(K4, LEN(K4)-6, 3) -> 003 | B4: Vistoria de fenda estrutural entre muros de divisa. | C4: Item | D4: 37690 | E4: Gerado pelo Dataverse | F4: Fotografia digitalizada; colorida; suporte em papel fotográfico | G4: São Paulo, Brasil | H4: Grupo de Pesquisa em Direito e Violência de Estado | I4: Arcoenge - Demolição - Casa de Detenção do Carandiru (Fotografias) | J4: Pasta: 0004 | K4: =TEXTJOIN("", TRUE, Geral!B60:U60) -> BR-SPGPDVE_ARCOENGE-DEMOLICAO-CSDTCARANDIRU_ICO-FOT-DGZ-MB0_0003-003.JPG | L4: ='0001'!$L$2 -> A Casa de Detenção de São Paulo, conhecida como Carandiru, foi demolida em etapas. Em 2002, ocorreu a implosão dos pavilhões 6, 8 e 9. Já em 2005, dos pavilhões 2 e 5 pela empresa Arcoenge (contratada pelo governo do estado de São Paulo). A coleção Arcoenge contém subgrupos de fotos, vídeos e texto, totalizando 164 peças documentais. | M4: Imagem detalhando o encontro entre duas estruturas de alvenaria: um muro de revestimento claro à esquerda e uma parede com pintura escura à direita. O técnico responsável, portando prancheta, utiliza uma caneta para apontar fenda que separa fisicamente as duas construções. O solo contém terra avermelhada e restos de vegetação. Marcador numérico "3 3 '03" alinhado verticalmente na lateral inferior esquerda. | N4: ='0001'!$N$2 -> O acesso aos documentos deste acervo está condicionado ao compromisso de não repassá-los a terceiros, à obrigatoriedade de mencionar que os originais pertencem ao GPDVE (?), e à necessidade de novo Termo de Responsabilidade em caso de reutilização ou uso diverso do inicialmente acordado. O uso está sujeito às restrições previstas na Lei de Arquivos (Lei nº 8.159/1991), na Lei de Direitos Autorais (Lei nº 9.610/1998), nos artigos 138 e 145 do Código Penal, e no artigo 5º, inciso X, da Constituição Federal, especialmente quanto à proteção da honra e imagem de terceiros. A pessoa física ou jurídica responsável assume integral responsabilidade civil e penal por eventuais danos decorrentes do uso das reproduções e informações, eximindo o GPDVE de qualquer responsabilidade. | O4: Sistema prisional; Arquitetura prisional; Casa de Detenção de São Paulo; Carandiru | P4: Fotografia (Iconográfico) | Q4: Digitalização de fotografia colorida (analógica original) | R4: ="Figura n – ["&B4&"]"&CHAR(10)&"Fonte: Arquivo do Estado de São Paulo, "&TEXT(D4,"yyyy")&"." -> Figura n – [Vistoria de fenda estrutural entre muros de divisa.] Fonte: Arquivo do Estado de São Paulo, 2003. | S4: ="ARQUIVO PÚBLICO DO ESTADO DE SÃO PAULO (Brasil). ["&B4&"]. "&G4&". "&TEXT(D4,"dd")&" "&LOWER(TEXT(D4,"mmm"))&" "&TEXT(D4,"yyyy")&". "&F4&". Disponível em: <link do dataverse>. Acesso em: 28 out. 2025." -> ARQUIVO PÚBLICO DO ESTADO DE SÃO PAULO (Brasil). [Vistoria de fenda estrutural entre muros de divisa.]. São Paulo, Brasil. 10 mar. 2003. Fotografia digitalizada; colorida; suporte em papel fotográfico. Disponível em: <link do dataverse>. Acesso em: 28 out. 2025. | T4: Este item pertencia à pasta intitulada "caixa-d'água 2".
A5: =MID(K5, LEN(K5)-6, 3) -> 004 | B5: Detalhe de avarias no reboco com exposição de alvenaria. | C5: Item | D5: 37690 | E5: Gerado pelo Dataverse | F5: Fotografia digitalizada; colorida; suporte em papel fotográfico | G5: São Paulo, Brasil | H5: Grupo de Pesquisa em Direito e Violência de Estado | I5: Arcoenge - Demolição - Casa de Detenção do Carandiru (Fotografias) | J5: Pasta: 0004 | K5: =TEXTJOIN("", TRUE, Geral!B61:U61) -> BR-SPGPDVE_ARCOENGE-DEMOLICAO-CSDTCARANDIRU_ICO-FOT-DGZ-MB0_0003-004.JPG | L5: ='0001'!$L$2 -> A Casa de Detenção de São Paulo, conhecida como Carandiru, foi demolida em etapas. Em 2002, ocorreu a implosão dos pavilhões 6, 8 e 9. Já em 2005, dos pavilhões 2 e 5 pela empresa Arcoenge (contratada pelo governo do estado de São Paulo). A coleção Arcoenge contém subgrupos de fotos, vídeos e texto, totalizando 164 peças documentais. | M5: Plano fechado de um trecho de muro com revestimento claro envelhecido. A superfície apresenta falhas do reboco, expondo a estrutura interna de tijolos avermelhados. Observam-se também respingos de tinta preta espessos na parede. A base do muro é margeada por vegetação rasteira crescendo sobre o solo. Marcador numérico "3 3 '03" alinhado verticalmente na lateral inferior esquerda. | N5: ='0001'!$N$2 -> O acesso aos documentos deste acervo está condicionado ao compromisso de não repassá-los a terceiros, à obrigatoriedade de mencionar que os originais pertencem ao GPDVE (?), e à necessidade de novo Termo de Responsabilidade em caso de reutilização ou uso diverso do inicialmente acordado. O uso está sujeito às restrições previstas na Lei de Arquivos (Lei nº 8.159/1991), na Lei de Direitos Autorais (Lei nº 9.610/1998), nos artigos 138 e 145 do Código Penal, e no artigo 5º, inciso X, da Constituição Federal, especialmente quanto à proteção da honra e imagem de terceiros. A pessoa física ou jurídica responsável assume integral responsabilidade civil e penal por eventuais danos decorrentes do uso das reproduções e informações, eximindo o GPDVE de qualquer responsabilidade. | O5: Sistema prisional; Arquitetura prisional; Casa de Detenção de São Paulo; Carandiru | P5: Fotografia (Iconográfico) | Q5: Digitalização de fotografia colorida (analógica original) | R5: ="Figura n – ["&B5&"]"&CHAR(10)&"Fonte: Arquivo do Estado de São Paulo, "&TEXT(D5,"yyyy")&"." -> Figura n – [Detalhe de avarias no reboco com exposição de alvenaria.] Fonte: Arquivo do Estado de São Paulo, 2003. | S5: ="ARQUIVO PÚBLICO DO ESTADO DE SÃO PAULO (Brasil). ["&B5&"]. "&G5&". "&TEXT(D5,"dd")&" "&LOWER(TEXT(D5,"mmm"))&" "&TEXT(D5,"yyyy")&". "&F5&". Disponível em: <link do dataverse>. Acesso em: 28 out. 2025." -> ARQUIVO PÚBLICO DO ESTADO DE SÃO PAULO (Brasil). [Detalhe de avarias no reboco com exposição de alvenaria.]. São Paulo, Brasil. 10 mar. 2003. Fotografia digitalizada; colorida; suporte em papel fotográfico. Disponível em: <link do dataverse>. Acesso em: 28 out. 2025. | T5: Este item pertencia à pasta intitulada "caixa-d'água 2".
A6: =MID(K6, LEN(K6)-6, 3) -> 005 | B6: Técnico apontando extensa fissura vertical em muro. | C6: Item | D6: 37690 | E6: Gerado pelo Dataverse | F6: Fotografia digitalizada; colorida; suporte em papel fotográfico | G6: São Paulo, Brasil | H6: Grupo de Pesquisa em Direito e Violência de Estado | I6: Arcoenge - Demolição - Casa de Detenção do Carandiru (Fotografias) | J6: Pasta: 0004 | K6: =TEXTJOIN("", TRUE, Geral!B62:U62) -> BR-SPGPDVE_ARCOENGE-DEMOLICAO-CSDTCARANDIRU_ICO-FOT-DGZ-MB0_0003-005.JPG | L6: ='0001'!$L$2 -> A Casa de Detenção de São Paulo, conhecida como Carandiru, foi demolida em etapas. Em 2002, ocorreu a implosão dos pavilhões 6, 8 e 9. Já em 2005, dos pavilhões 2 e 5 pela empresa Arcoenge (contratada pelo governo do estado de São Paulo). A coleção Arcoenge contém subgrupos de fotos, vídeos e texto, totalizando 164 peças documentais. | M6: Fotografia focada no técnico realizando vistoria estrutural. Ele aponta com uma caneta para uma longa e sinuosa trinca vertical que se estende do topo (onde há telhas e manchas de umidade escuras) até o centro de um muro claro. Na parte inferior da parede, há inscrições grossas em tinta preta. Marcador numérico "3 3 '03" alinhado verticalmente na lateral inferior esquerda. | N6: ='0001'!$N$2 -> O acesso aos documentos deste acervo está condicionado ao compromisso de não repassá-los a terceiros, à obrigatoriedade de mencionar que os originais pertencem ao GPDVE (?), e à necessidade de novo Termo de Responsabilidade em caso de reutilização ou uso diverso do inicialmente acordado. O uso está sujeito às restrições previstas na Lei de Arquivos (Lei nº 8.159/1991), na Lei de Direitos Autorais (Lei nº 9.610/1998), nos artigos 138 e 145 do Código Penal, e no artigo 5º, inciso X, da Constituição Federal, especialmente quanto à proteção da honra e imagem de terceiros. A pessoa física ou jurídica responsável assume integral responsabilidade civil e penal por eventuais danos decorrentes do uso das reproduções e informações, eximindo o GPDVE de qualquer responsabilidade. | O6: Sistema prisional; Arquitetura prisional; Casa de Detenção de São Paulo; Carandiru | P6: Fotografia (Iconográfico) | Q6: Digitalização de fotografia colorida (analógica original) | R6: ="Figura n – ["&B6&"]"&CHAR(10)&"Fonte: Arquivo do Estado de São Paulo, "&TEXT(D6,"yyyy")&"." -> Figura n – [Técnico apontando extensa fissura vertical em muro.] Fonte: Arquivo do Estado de São Paulo, 2003. | S6: ="ARQUIVO PÚBLICO DO ESTADO DE SÃO PAULO (Brasil). ["&B6&"]. "&G6&". "&TEXT(D6,"dd")&" "&LOWER(TEXT(D6,"mmm"))&" "&TEXT(D6,"yyyy")&". "&F6&". Disponível em: <link do dataverse>. Acesso em: 28 out. 2025." -> ARQUIVO PÚBLICO DO ESTADO DE SÃO PAULO (Brasil). [Técnico apontando extensa fissura vertical em muro.]. São Paulo, Brasil. 10 mar. 2003. Fotografia digitalizada; colorida; suporte em papel fotográfico. Disponível em: <link do dataverse>. Acesso em: 28 out. 2025. | T6: Este item pertencia à pasta intitulada "caixa-d'água 2".
A7: =MID(K7, LEN(K7)-6, 3) -> 006 | B7: Vistoria de trinca vertical. | C7: Item | D7: 37690 | E7: Gerado pelo Dataverse | F7: Fotografia digitalizada; colorida; suporte em papel fotográfico | G7: São Paulo, Brasil | H7: Grupo de Pesquisa em Direito e Violência de Estado | I7: Arcoenge - Demolição - Casa de Detenção do Carandiru (Fotografias) | J7: Pasta: 0004 | K7: =TEXTJOIN("", TRUE, Geral!B63:U63) -> BR-SPGPDVE_ARCOENGE-DEMOLICAO-CSDTCARANDIRU_ICO-FOT-DGZ-MB0_0003-006.JPG | L7: ='0001'!$L$2 -> A Casa de Detenção de São Paulo, conhecida como Carandiru, foi demolida em etapas. Em 2002, ocorreu a implosão dos pavilhões 6, 8 e 9. Já em 2005, dos pavilhões 2 e 5 pela empresa Arcoenge (contratada pelo governo do estado de São Paulo). A coleção Arcoenge contém subgrupos de fotos, vídeos e texto, totalizando 164 peças documentais. | M7: Imagem muito semelhante à 0004-005, com pequena alteração de ângulo, mostrando o mesmo profissional apontando para um trecho inferior da mesma fissura vertical no muro claro. Na base da imagem, sobressai uma pichação em tinta avermelhada com os dizeres parciais "AQUEIRO". Marcador numérico "3 3 '03" alinhado verticalmente na lateral inferior esquerda. | N7: ='0001'!$N$2 -> O acesso aos documentos deste acervo está condicionado ao compromisso de não repassá-los a terceiros, à obrigatoriedade de mencionar que os originais pertencem ao GPDVE (?), e à necessidade de novo Termo de Responsabilidade em caso de reutilização ou uso diverso do inicialmente acordado. O uso está sujeito às restrições previstas na Lei de Arquivos (Lei nº 8.159/1991), na Lei de Direitos Autorais (Lei nº 9.610/1998), nos artigos 138 e 145 do Código Penal, e no artigo 5º, inciso X, da Constituição Federal, especialmente quanto à proteção da honra e imagem de terceiros. A pessoa física ou jurídica responsável assume integral responsabilidade civil e penal por eventuais danos decorrentes do uso das reproduções e informações, eximindo o GPDVE de qualquer responsabilidade. | O7: Sistema prisional; Arquitetura prisional; Casa de Detenção de São Paulo; Carandiru | P7: Fotografia (Iconográfico) | Q7: Digitalização de fotografia colorida (analógica original) | R7: ="Figura n – ["&B7&"]"&CHAR(10)&"Fonte: Arquivo do Estado de São Paulo, "&TEXT(D7,"yyyy")&"." -> Figura n – [Vistoria de trinca vertical.] Fonte: Arquivo do Estado de São Paulo, 2003. | S7: ="ARQUIVO PÚBLICO DO ESTADO DE SÃO PAULO (Brasil). ["&B7&"]. "&G7&". "&TEXT(D7,"dd")&" "&LOWER(TEXT(D7,"mmm"))&" "&TEXT(D7,"yyyy")&". "&F7&". Disponível em: <link do dataverse>. Acesso em: 28 out. 2025." -> ARQUIVO PÚBLICO DO ESTADO DE SÃO PAULO (Brasil). [Vistoria de trinca vertical.]. São Paulo, Brasil. 10 mar. 2003. Fotografia digitalizada; colorida; suporte em papel fotográfico. Disponível em: <link do dataverse>. Acesso em: 28 out. 2025. | T7: Este item pertencia à pasta intitulada "caixa-d'água 2".
A8: =MID(K8, LEN(K8)-6, 3) -> 007 | B8: Técnico indicando ruptura com desprendimento de reboco. | C8: Item | D8: 37690 | E8: Gerado pelo Dataverse | F8: Fotografia digitalizada; colorida; suporte em papel fotográfico | G8: São Paulo, Brasil | H8: Grupo de Pesquisa em Direito e Violência de Estado | I8: Arcoenge - Demolição - Casa de Detenção do Carandiru (Fotografias) | J8: Pasta: 0004 | K8: =TEXTJOIN("", TRUE, Geral!B64:U64) -> BR-SPGPDVE_ARCOENGE-DEMOLICAO-CSDTCARANDIRU_ICO-FOT-DGZ-MB0_0003-007.JPG | L8: ='0001'!$L$2 -> A Casa de Detenção de São Paulo, conhecida como Carandiru, foi demolida em etapas. Em 2002, ocorreu a implosão dos pavilhões 6, 8 e 9. Já em 2005, dos pavilhões 2 e 5 pela empresa Arcoenge (contratada pelo governo do estado de São Paulo). A coleção Arcoenge contém subgrupos de fotos, vídeos e texto, totalizando 164 peças documentais. | M8: Fotografia de corpo inteiro do técnico inspecionando um dano severo no muro divisório. Ele aponta para uma falha estrutural diagonal/vertical onde grande parte do reboco cedeu, expondo os tijolos de forma irregular. No solo, junto ao muro, há terra escavada, uma estaca de madeira, uma mangueira de nível transparente e um saco plástico com materiais. Marcador numérico "3 3 '03" alinhado verticalmente na lateral inferior esquerda. | N8: ='0001'!$N$2 -> O acesso aos documentos deste acervo está condicionado ao compromisso de não repassá-los a terceiros, à obrigatoriedade de mencionar que os originais pertencem ao GPDVE (?), e à necessidade de novo Termo de Responsabilidade em caso de reutilização ou uso diverso do inicialmente acordado. O uso está sujeito às restrições previstas na Lei de Arquivos (Lei nº 8.159/1991), na Lei de Direitos Autorais (Lei nº 9.610/1998), nos artigos 138 e 145 do Código Penal, e no artigo 5º, inciso X, da Constituição Federal, especialmente quanto à proteção da honra e imagem de terceiros. A pessoa física ou jurídica responsável assume integral responsabilidade civil e penal por eventuais danos decorrentes do uso das reproduções e informações, eximindo o GPDVE de qualquer responsabilidade. | O8: Sistema prisional; Arquitetura prisional; Casa de Detenção de São Paulo; Carandiru | P8: Fotografia (Iconográfico) | Q8: Digitalização de fotografia colorida (analógica original) | R8: ="Figura n – ["&B8&"]"&CHAR(10)&"Fonte: Arquivo do Estado de São Paulo, "&TEXT(D8,"yyyy")&"." -> Figura n – [Técnico indicando ruptura com desprendimento de reboco.] Fonte: Arquivo do Estado de São Paulo, 2003. | S8: ="ARQUIVO PÚBLICO DO ESTADO DE SÃO PAULO (Brasil). ["&B8&"]. "&G8&". "&TEXT(D8,"dd")&" "&LOWER(TEXT(D8,"mmm"))&" "&TEXT(D8,"yyyy")&". "&F8&". Disponível em: <link do dataverse>. Acesso em: 28 out. 2025." -> ARQUIVO PÚBLICO DO ESTADO DE SÃO PAULO (Brasil). [Técnico indicando ruptura com desprendimento de reboco.]. São Paulo, Brasil. 10 mar. 2003. Fotografia digitalizada; colorida; suporte em papel fotográfico. Disponível em: <link do dataverse>. Acesso em: 28 out. 2025. | T8: Este item pertencia à pasta intitulada "caixa-d'água 2".
A9: =MID(K9, LEN(K9)-6, 3) -> 008 | B9: Técnico encostado em quina de muro com buracos profundos. | C9: Item | D9: 37690 | E9: Gerado pelo Dataverse | F9: Fotografia digitalizada; colorida; suporte em papel fotográfico | G9: São Paulo, Brasil | H9: Grupo de Pesquisa em Direito e Violência de Estado | I9: Arcoenge - Demolição - Casa de Detenção do Carandiru (Fotografias) | J9: Pasta: 0004 | K9: =TEXTJOIN("", TRUE, Geral!B65:U65) -> BR-SPGPDVE_ARCOENGE-DEMOLICAO-CSDTCARANDIRU_ICO-FOT-DGZ-MB0_0003-008.JPG | L9: ='0001'!$L$2 -> A Casa de Detenção de São Paulo, conhecida como Carandiru, foi demolida em etapas. Em 2002, ocorreu a implosão dos pavilhões 6, 8 e 9. Já em 2005, dos pavilhões 2 e 5 pela empresa Arcoenge (contratada pelo governo do estado de São Paulo). A coleção Arcoenge contém subgrupos de fotos, vídeos e texto, totalizando 164 peças documentais. | M9: O técnico apoia-se e aponta para a quina divisória de um muro de revestimento claro. No trecho adjacente do muro frontal, registram-se duas falhas significativas e profundas no reboco, que deixam exposta a alvenaria de tijolos e tubulações/ferragens internas. O primeiro plano é uma vala escavada com pedaços de madeira e vegetação solta. Marcador numérico "3 3 '03" alinhado verticalmente na lateral inferior esquerda. | N9: ='0001'!$N$2 -> O acesso aos documentos deste acervo está condicionado ao compromisso de não repassá-los a terceiros, à obrigatoriedade de mencionar que os originais pertencem ao GPDVE (?), e à necessidade de novo Termo de Responsabilidade em caso de reutilização ou uso diverso do inicialmente acordado. O uso está sujeito às restrições previstas na Lei de Arquivos (Lei nº 8.159/1991), na Lei de Direitos Autorais (Lei nº 9.610/1998), nos artigos 138 e 145 do Código Penal, e no artigo 5º, inciso X, da Constituição Federal, especialmente quanto à proteção da honra e imagem de terceiros. A pessoa física ou jurídica responsável assume integral responsabilidade civil e penal por eventuais danos decorrentes do uso das reproduções e informações, eximindo o GPDVE de qualquer responsabilidade. | O9: Sistema prisional; Arquitetura prisional; Casa de Detenção de São Paulo; Carandiru | P9: Fotografia (Iconográfico) | Q9: Digitalização de fotografia colorida (analógica original) | R9: ="Figura n – ["&B9&"]"&CHAR(10)&"Fonte: Arquivo do Estado de São Paulo, "&TEXT(D9,"yyyy")&"." -> Figura n – [Técnico encostado em quina de muro com buracos profundos.] Fonte: Arquivo do Estado de São Paulo, 2003. | S9: ="ARQUIVO PÚBLICO DO ESTADO DE SÃO PAULO (Brasil). ["&B9&"]. "&G9&". "&TEXT(D9,"dd")&" "&LOWER(TEXT(D9,"mmm"))&" "&TEXT(D9,"yyyy")&". "&F9&". Disponível em: <link do dataverse>. Acesso em: 28 out. 2025." -> ARQUIVO PÚBLICO DO ESTADO DE SÃO PAULO (Brasil). [Técnico encostado em quina de muro com buracos profundos.]. São Paulo, Brasil. 10 mar. 2003. Fotografia digitalizada; colorida; suporte em papel fotográfico. Disponível em: <link do dataverse>. Acesso em: 28 out. 2025. | T9: Este item pertencia à pasta intitulada "caixa-d'água 2".
A10: =MID(K10, LEN(K10)-6, 3) -> 009 | B10: Extensa fachada lateral com equipe em terreno de obras. | C10: Item | D10: 37690 | E10: Gerado pelo Dataverse | F10: Fotografia digitalizada; colorida; suporte em papel fotográfico | G10: São Paulo, Brasil | H10: Grupo de Pesquisa em Direito e Violência de Estado | I10: Arcoenge - Demolição - Casa de Detenção do Carandiru (Fotografias) | J10: Pasta: 0004 | K10: =TEXTJOIN("", TRUE, Geral!B66:U66) -> BR-SPGPDVE_ARCOENGE-DEMOLICAO-CSDTCARANDIRU_ICO-FOT-DGZ-MB0_0003-009.JPG | L10: ='0001'!$L$2 -> A Casa de Detenção de São Paulo, conhecida como Carandiru, foi demolida em etapas. Em 2002, ocorreu a implosão dos pavilhões 6, 8 e 9. Já em 2005, dos pavilhões 2 e 5 pela empresa Arcoenge (contratada pelo governo do estado de São Paulo). A coleção Arcoenge contém subgrupos de fotos, vídeos e texto, totalizando 164 peças documentais. | M10: Imagem em plano muito aberto capturando uma longa e alta fachada lateral (empena) de reboco acinzentado, arrematada por telhas no topo. A parede exibe desgaste, umidade e pichações brancas quase apagadas. À esquerda, o técnico conversa com outro indivíduo de camisa clara. À direita, um operário de capacete amarelo é registrado de costas. O canteiro incipiente apresenta terra revolvida e formas de madeira no solo. Marcador numérico "3 3 '03" no canto inferior direito. | N10: ='0001'!$N$2 -> O acesso aos documentos deste acervo está condicionado ao compromisso de não repassá-los a terceiros, à obrigatoriedade de mencionar que os originais pertencem ao GPDVE (?), e à necessidade de novo Termo de Responsabilidade em caso de reutilização ou uso diverso do inicialmente acordado. O uso está sujeito às restrições previstas na Lei de Arquivos (Lei nº 8.159/1991), na Lei de Direitos Autorais (Lei nº 9.610/1998), nos artigos 138 e 145 do Código Penal, e no artigo 5º, inciso X, da Constituição Federal, especialmente quanto à proteção da honra e imagem de terceiros. A pessoa física ou jurídica responsável assume integral responsabilidade civil e penal por eventuais danos decorrentes do uso das reproduções e informações, eximindo o GPDVE de qualquer responsabilidade. | O10: Sistema prisional; Arquitetura prisional; Casa de Detenção de São Paulo; Carandiru | P10: Fotografia (Iconográfico) | Q10: Digitalização de fotografia colorida (analógica original) | R10: ="Figura n – ["&B10&"]"&CHAR(10)&"Fonte: Arquivo do Estado de São Paulo, "&TEXT(D10,"yyyy")&"." -> Figura n – [Extensa fachada lateral com equipe em terreno de obras.] Fonte: Arquivo do Estado de São Paulo, 2003. | S10: ="ARQUIVO PÚBLICO DO ESTADO DE SÃO PAULO (Brasil). ["&B10&"]. "&G10&". "&TEXT(D10,"dd")&" "&LOWER(TEXT(D10,"mmm"))&" "&TEXT(D10,"yyyy")&". "&F10&". Disponível em: <link do dataverse>. Acesso em: 28 out. 2025." -> ARQUIVO PÚBLICO DO ESTADO DE SÃO PAULO (Brasil). [Extensa fachada lateral com equipe em terreno de obras.]. São Paulo, Brasil. 10 mar. 2003. Fotografia digitalizada; colorida; suporte em papel fotográfico. Disponível em: <link do dataverse>. Acesso em: 28 out. 2025. | T10: Este item pertencia à pasta intitulada "caixa-d'água 2".
A11: =MID(K11, LEN(K11)-6, 3) -> 010 | B11: Detalhe superior de empena cega com tijolos laterais expostos. | C11: Item | D11: 37690 | E11: Gerado pelo Dataverse | F11: Fotografia digitalizada; colorida; suporte em papel fotográfico | G11: São Paulo, Brasil | H11: Grupo de Pesquisa em Direito e Violência de Estado | I11: Arcoenge - Demolição - Casa de Detenção do Carandiru (Fotografias) | J11: Pasta: 0004 | K11: =TEXTJOIN("", TRUE, Geral!B67:U67) -> BR-SPGPDVE_ARCOENGE-DEMOLICAO-CSDTCARANDIRU_ICO-FOT-DGZ-MB0_0003-010.JPG | L11: ='0001'!$L$2 -> A Casa de Detenção de São Paulo, conhecida como Carandiru, foi demolida em etapas. Em 2002, ocorreu a implosão dos pavilhões 6, 8 e 9. Já em 2005, dos pavilhões 2 e 5 pela empresa Arcoenge (contratada pelo governo do estado de São Paulo). A coleção Arcoenge contém subgrupos de fotos, vídeos e texto, totalizando 164 peças documentais. | M11: Plano fechado no canto superior direito de uma empena de alvenaria. A superfície cinza apresenta forte acúmulo de manchas de umidade escuras na faixa rente ao telhado. Ao longo de toda a borda lateral direita, o reboco está quebrado, expondo os tijolos vermelhos estruturais de forma irregular. Fundo composto por céu azul e nuvens claras. Marcador numérico "3 3 '03" no canto inferior direito. | N11: ='0001'!$N$2 -> O acesso aos documentos deste acervo está condicionado ao compromisso de não repassá-los a terceiros, à obrigatoriedade de mencionar que os originais pertencem ao GPDVE (?), e à necessidade de novo Termo de Responsabilidade em caso de reutilização ou uso diverso do inicialmente acordado. O uso está sujeito às restrições previstas na Lei de Arquivos (Lei nº 8.159/1991), na Lei de Direitos Autorais (Lei nº 9.610/1998), nos artigos 138 e 145 do Código Penal, e no artigo 5º, inciso X, da Constituição Federal, especialmente quanto à proteção da honra e imagem de terceiros. A pessoa física ou jurídica responsável assume integral responsabilidade civil e penal por eventuais danos decorrentes do uso das reproduções e informações, eximindo o GPDVE de qualquer responsabilidade. | O11: Sistema prisional; Arquitetura prisional; Casa de Detenção de São Paulo; Carandiru | P11: Fotografia (Iconográfico) | Q11: Digitalização de fotografia colorida (analógica original) | R11: ="Figura n – ["&B11&"]"&CHAR(10)&"Fonte: Arquivo do Estado de São Paulo, "&TEXT(D11,"yyyy")&"." -> Figura n – [Detalhe superior de empena cega com tijolos laterais expostos.] Fonte: Arquivo do Estado de São Paulo, 2003. | S11: ="ARQUIVO PÚBLICO DO ESTADO DE SÃO PAULO (Brasil). ["&B11&"]. "&G11&". "&TEXT(D11,"dd")&" "&LOWER(TEXT(D11,"mmm"))&" "&TEXT(D11,"yyyy")&". "&F11&". Disponível em: <link do dataverse>. Acesso em: 28 out. 2025." -> ARQUIVO PÚBLICO DO ESTADO DE SÃO PAULO (Brasil). [Detalhe superior de empena cega com tijolos laterais expostos.]. São Paulo, Brasil. 10 mar. 2003. Fotografia digitalizada; colorida; suporte em papel fotográfico. Disponível em: <link do dataverse>. Acesso em: 28 out. 2025. | T11: Este item pertencia à pasta intitulada "caixa-d'água 2".
A12: =MID(K12, LEN(K12)-6, 3) -> 011 | B12: Detalhe de revestimento de muro divisório com manchas e escorrimentos escuros. | C12: Item | D12: 37690 | E12: Gerado pelo Dataverse | F12: Fotografia digitalizada; colorida; suporte em papel fotográfico | G12: São Paulo, Brasil | H12: Grupo de Pesquisa em Direito e Violência de Estado | I12: Arcoenge - Demolição - Casa de Detenção do Carandiru (Fotografias) | J12: Pasta: 0004 | K12: =TEXTJOIN("", TRUE, Geral!B68:U68) -> BR-SPGPDVE_ARCOENGE-DEMOLICAO-CSDTCARANDIRU_ICO-FOT-DGZ-MB0_0003-011.JPG | L12: ='0001'!$L$2 -> A Casa de Detenção de São Paulo, conhecida como Carandiru, foi demolida em etapas. Em 2002, ocorreu a implosão dos pavilhões 6, 8 e 9. Já em 2005, dos pavilhões 2 e 5 pela empresa Arcoenge (contratada pelo governo do estado de São Paulo). A coleção Arcoenge contém subgrupos de fotos, vídeos e texto, totalizando 164 peças documentais. | M12: Plano fechado detalhando a superfície de um muro divisório de alvenaria. O reboco claro apresenta forte degradação, exibindo extensas manchas de umidade, escorrimentos verticais de substância escura (possivelmente piche ou tinta), manchas avermelhadas indicativas de oxidação, fissuras estruturais e duas áreas com pintura azul sobreposta irregularmente. Marcador numérico "3 3 '03" no canto inferior direito. | N12: ='0001'!$N$2 -> O acesso aos documentos deste acervo está condicionado ao compromisso de não repassá-los a terceiros, à obrigatoriedade de mencionar que os originais pertencem ao GPDVE (?), e à necessidade de novo Termo de Responsabilidade em caso de reutilização ou uso diverso do inicialmente acordado. O uso está sujeito às restrições previstas na Lei de Arquivos (Lei nº 8.159/1991), na Lei de Direitos Autorais (Lei nº 9.610/1998), nos artigos 138 e 145 do Código Penal, e no artigo 5º, inciso X, da Constituição Federal, especialmente quanto à proteção da honra e imagem de terceiros. A pessoa física ou jurídica responsável assume integral responsabilidade civil e penal por eventuais danos decorrentes do uso das reproduções e informações, eximindo o GPDVE de qualquer responsabilidade. | O12: Sistema prisional; Arquitetura prisional; Casa de Detenção de São Paulo; Carandiru | P12: Fotografia (Iconográfico) | Q12: Digitalização de fotografia colorida (analógica original) | R12: ="Figura n – ["&B12&"]"&CHAR(10)&"Fonte: Arquivo do Estado de São Paulo, "&TEXT(D12,"yyyy")&"." -> Figura n – [Detalhe de revestimento de muro divisório com manchas e escorrimentos escuros.] Fonte: Arquivo do Estado de São Paulo, 2003. | S12: ="ARQUIVO PÚBLICO DO ESTADO DE SÃO PAULO (Brasil). ["&B12&"]. "&G12&". "&TEXT(D12,"dd")&" "&LOWER(TEXT(D12,"mmm"))&" "&TEXT(D12,"yyyy")&". "&F12&". Disponível em: <link do dataverse>. Acesso em: 28 out. 2025." -> ARQUIVO PÚBLICO DO ESTADO DE SÃO PAULO (Brasil). [Detalhe de revestimento de muro divisório com manchas e escorrimentos escuros.]. São Paulo, Brasil. 10 mar. 2003. Fotografia digitalizada; colorida; suporte em papel fotográfico. Disponível em: <link do dataverse>. Acesso em: 28 out. 2025. | T12: Este item pertencia à pasta intitulada "caixa-d'água 2".
A13: =MID(K13, LEN(K13)-6, 3) -> 012 | B13: Detalhe de avarias, umidade e oxidação em superfície de muro. | C13: Item | D13: 37690 | E13: Gerado pelo Dataverse | F13: Fotografia digitalizada; colorida; suporte em papel fotográfico | G13: São Paulo, Brasil | H13: Grupo de Pesquisa em Direito e Violência de Estado | I13: Arcoenge - Demolição - Casa de Detenção do Carandiru (Fotografias) | J13: Pasta: 0004 | K13: =TEXTJOIN("", TRUE, Geral!B69:U69) -> BR-SPGPDVE_ARCOENGE-DEMOLICAO-CSDTCARANDIRU_ICO-FOT-DGZ-MB0_0003-012.JPG | L13: ='0001'!$L$2 -> A Casa de Detenção de São Paulo, conhecida como Carandiru, foi demolida em etapas. Em 2002, ocorreu a implosão dos pavilhões 6, 8 e 9. Já em 2005, dos pavilhões 2 e 5 pela empresa Arcoenge (contratada pelo governo do estado de São Paulo). A coleção Arcoenge contém subgrupos de fotos, vídeos e texto, totalizando 164 peças documentais. | M13: Imagem em plano fechado retratando outra seção do muro divisório degradado. A superfície texturizada revela marcas e sulcos horizontais no reboco, manchas espessas de escorrimento escuro concentradas na parte inferior, manchas de oxidação avermelhada na lateral direita e uma mancha escura isolada no centro. Marcador numérico "3 3 '03" no canto inferior direito. | N13: ='0001'!$N$2 -> O acesso aos documentos deste acervo está condicionado ao compromisso de não repassá-los a terceiros, à obrigatoriedade de mencionar que os originais pertencem ao GPDVE (?), e à necessidade de novo Termo de Responsabilidade em caso de reutilização ou uso diverso do inicialmente acordado. O uso está sujeito às restrições previstas na Lei de Arquivos (Lei nº 8.159/1991), na Lei de Direitos Autorais (Lei nº 9.610/1998), nos artigos 138 e 145 do Código Penal, e no artigo 5º, inciso X, da Constituição Federal, especialmente quanto à proteção da honra e imagem de terceiros. A pessoa física ou jurídica responsável assume integral responsabilidade civil e penal por eventuais danos decorrentes do uso das reproduções e informações, eximindo o GPDVE de qualquer responsabilidade. | O13: Sistema prisional; Arquitetura prisional; Casa de Detenção de São Paulo; Carandiru | P13: Fotografia (Iconográfico) | Q13: Digitalização de fotografia colorida (analógica original) | R13: ="Figura n – ["&B13&"]"&CHAR(10)&"Fonte: Arquivo do Estado de São Paulo, "&TEXT(D13,"yyyy")&"." -> Figura n – [Detalhe de avarias, umidade e oxidação em superfície de muro.] Fonte: Arquivo do Estado de São Paulo, 2003. | S13: ="ARQUIVO PÚBLICO DO ESTADO DE SÃO PAULO (Brasil). ["&B13&"]. "&G13&". "&TEXT(D13,"dd")&" "&LOWER(TEXT(D13,"mmm"))&" "&TEXT(D13,"yyyy")&". "&F13&". Disponível em: <link do dataverse>. Acesso em: 28 out. 2025." -> ARQUIVO PÚBLICO DO ESTADO DE SÃO PAULO (Brasil). [Detalhe de avarias, umidade e oxidação em superfície de muro.]. São Paulo, Brasil. 10 mar. 2003. Fotografia digitalizada; colorida; suporte em papel fotográfico. Disponível em: <link do dataverse>. Acesso em: 28 out. 2025. | T13: Este item pertencia à pasta intitulada "caixa-d'água 2".
... A26: =MID(K26, LEN(K26)-6, 3) -> 025 | B26: Portão residencial metálico com veículo no interior. | C26: Item | D26: 37690 | E26: Gerado pelo Dataverse | F26: Fotografia digitalizada; colorida; suporte em papel fotográfico | G26: São Paulo, Brasil | H26: Grupo de Pesquisa em Direito e Violência de Estado | I26: Arcoenge - Demolição - Casa de Detenção do Carandiru (Fotografias) | J26: Pasta: 0003 | K26: =TEXTJOIN("", TRUE, Geral!B82:U82) -> BR-SPGPDVE_ARCOENGE-DEMOLICAO-CSDTCARANDIRU_ICO-FOT-DGZ-MB0_0003-025.JPG | L26: ='0001'!$L$2 -> A Casa de Detenção de São Paulo, conhecida como Carandiru, foi demolida em etapas. Em 2002, ocorreu a implosão dos pavilhões 6, 8 e 9. Já em 2005, dos pavilhões 2 e 5 pela empresa Arcoenge (contratada pelo governo do estado de São Paulo). A coleção Arcoenge contém subgrupos de fotos, vídeos e texto, totalizando 164 peças documentais. | M26: Imagem muito semelhante à 0003-024, focando no portão metálico branco de uma moradia, o qual apresenta um design com elementos vazados em linhas diagonais que formam losangos. No interior da garagem, percebe-se a presença de um automóvel branco. O lado direito do enquadramento é parcialmente preenchido pelo tronco e ramagem de uma árvore situada na calçada. Marcador numérico "3 3 '03" no canto inferior direito. | N26: ='0001'!$N$2 -> O acesso aos documentos deste acervo está condicionado ao compromisso de não repassá-los a terceiros, à obrigatoriedade de mencionar que os originais pertencem ao GPDVE (?), e à necessidade de novo Termo de Responsabilidade em caso de reutilização ou uso diverso do inicialmente acordado. O uso está sujeito às restrições previstas na Lei de Arquivos (Lei nº 8.159/1991), na Lei de Direitos Autorais (Lei nº 9.610/1998), nos artigos 138 e 145 do Código Penal, e no artigo 5º, inciso X, da Constituição Federal, especialmente quanto à proteção da honra e imagem de terceiros. A pessoa física ou jurídica responsável assume integral responsabilidade civil e penal por eventuais danos decorrentes do uso das reproduções e informações, eximindo o GPDVE de qualquer responsabilidade. | O26: Sistema prisional; Arquitetura prisional; Casa de Detenção de São Paulo; Carandiru | P26: Fotografia (Iconográfico) | Q26: Digitalização de fotografia colorida (analógica original) | R26: ="Figura n – ["&B26&"]"&CHAR(10)&"Fonte: Arquivo do Estado de São Paulo, "&TEXT(D26,"yyyy")&"." -> Figura n – [Portão residencial metálico com veículo no interior.] Fonte: Arquivo do Estado de São Paulo, 2003. | S26: ="ARQUIVO PÚBLICO DO ESTADO DE SÃO PAULO (Brasil). ["&B26&"]. "&G26&". "&TEXT(D26,"dd")&" "&LOWER(TEXT(D26,"mmm"))&" "&TEXT(D26,"yyyy")&". "&F26&". Disponível em: <link do dataverse>. Acesso em: 28 out. 2025." -> ARQUIVO PÚBLICO DO ESTADO DE SÃO PAULO (Brasil). [Portão residencial metálico com veículo no interior.]. São Paulo, Brasil. 10 mar. 2003. Fotografia digitalizada; colorida; suporte em papel fotográfico. Disponível em: <link do dataverse>. Acesso em: 28 out. 2025. | T26: Este item pertencia à pasta intitulada "caixa-d'água 2".

Sheet 0004
A1: Cód. | B1: Título descritivo (atribuído) | C1: Nível de descrição | D1: Data da fotografia | E1: Tamanho | F1: Suporte | G1: Local | H1: Autor/Responsável | I1: Denominação do catálogo temático (GPDVE ARCOENGE) | J1: Localização | K1: Código de referência | L1: História arquivística | M1: Conteúdo/Assunto | N1: Condições de acesso e reprodução | O1: Palavras-chave | P1: Gênero | Q1: Técnica de registro | R1: Legenda para publicações | S1: Citação ABNT | T1: Notas
A2: =MID('0003'!K2, LEN('0003'!K2)-6, 3) -> 001 | B2: Vista dos pavilhões prisionais preparados para demolição. | C2: Item | D2: 38550 | E2: Gerado pelo Dataverse | F2: Fotografia digitalizada; colorida; suporte em papel fotográfico | G2: São Paulo, Brasil | H2: Grupo de Pesquisa em Direito e Violência de Estado | I2: Arcoenge - Demolição - Casa de Detenção do Carandiru (Fotografias) | J2: Pasta: 0002 | K2: =TEXTJOIN("", TRUE, Geral!B83:U83) -> BR-SPGPDVE_ARCOENGE-DEMOLICAO-CSDTCARANDIRU_ICO-FOT-DGZ-MB0_0004-001.JPG | L2: ='0001'!$L$2 -> A Casa de Detenção de São Paulo, conhecida como Carandiru, foi demolida em etapas. Em 2002, ocorreu a implosão dos pavilhões 6, 8 e 9. Já em 2005, dos pavilhões 2 e 5 pela empresa Arcoenge (contratada pelo governo do estado de São Paulo). A coleção Arcoenge contém subgrupos de fotos, vídeos e texto, totalizando 164 peças documentais. | M2: Fotografia ao nível do solo revelando um amplo canteiro de obras em terra vermelha nivelada no primeiro plano. Ao fundo, erguem-se três pavilhões da Casa de Detenção do Carandiru. Os dois edifícios mais próximos têm a sua metade inferior envolvida por extensas telas brancas de proteção (pavilhões 2 e 5), evidenciando a preparação estrutural para o processo de implosão controlada. Fundo composto por céu azul sem nuvens. Existe um outdoor retangular largo vermelho na área externa, anunciando o "Parque da Juventude" e os dizeres "venha praticar a liberdade". Na lateral dele, o logo do governo do estado de São Paulo. | N2: ='0001'!$N$2 -> O acesso aos documentos deste acervo está condicionado ao compromisso de não repassá-los a terceiros, à obrigatoriedade de mencionar que os originais pertencem ao GPDVE (?), e à necessidade de novo Termo de Responsabilidade em caso de reutilização ou uso diverso do inicialmente acordado. O uso está sujeito às restrições previstas na Lei de Arquivos (Lei nº 8.159/1991), na Lei de Direitos Autorais (Lei nº 9.610/1998), nos artigos 138 e 145 do Código Penal, e no artigo 5º, inciso X, da Constituição Federal, especialmente quanto à proteção da honra e imagem de terceiros. A pessoa física ou jurídica responsável assume integral responsabilidade civil e penal por eventuais danos decorrentes do uso das reproduções e informações, eximindo o GPDVE de qualquer responsabilidade. | O2: Sistema prisional; Arquitetura prisional; Casa de Detenção de São Paulo; Carandiru | Q2: Digitalização de fotografia colorida (analógica original) | R2: ="Figura n – ["&'0003'!B2&"]"&CHAR(10)&"Fonte: Arquivo do Estado de São Paulo, "&TEXT('0003'!D2,"yyyy")&"." -> Figura n – [Fachada cega com manchas de umidade e técnico em deslocamento.] Fonte: Arquivo do Estado de São Paulo, 2003. | S2: ="ARQUIVO PÚBLICO DO ESTADO DE SÃO PAULO (Brasil). ["&'0003'!B2&"]. "&'0003'!G2&". "&TEXT('0003'!D2,"dd")&" "&LOWER(TEXT('0003'!D2,"mmm"))&" "&TEXT('0003'!D2,"yyyy")&". "&'0003'!F2&". Disponível em: <link do dataverse>. Acesso em: 28 out. 2025." -> ARQUIVO PÚBLICO DO ESTADO DE SÃO PAULO (Brasil). [Fachada cega com manchas de umidade e técnico em deslocamento.]. São Paulo, Brasil. 10 mar. 2003. Fotografia digitalizada; colorida; suporte em papel fotográfico. Disponível em: <link do dataverse>. Acesso em: 28 out. 2025. | T2: A foto "car15" não existe no diretório original. Este item pertencia ao caminho: "Carandiru -Nico (seleção 2005)" > "fotos". Nos metadados da fotografia (campo Data de criação), indica-se que sua criação se deu no 22/09/2005. A data indicada no campo "Data da fotografia" do presente dataset retrata o data exata do clique fotográfico.
A3: =MID('0003'!K3, LEN('0003'!K3)-6, 3) -> 002 | B3: Acionamento do comando de implosão pelas autoridades. | C3: Item | D3: 38550 | E3: Gerado pelo Dataverse | F3: Fotografia digitalizada; colorida; suporte em papel fotográfico | G3: São Paulo, Brasil | H3: Grupo de Pesquisa em Direito e Violência de Estado | I3: Arcoenge - Demolição - Casa de Detenção do Carandiru (Fotografias) | J3: Pasta: 0002 | K3: =TEXTJOIN("", TRUE, Geral!B84:U84) -> BR-SPGPDVE_ARCOENGE-DEMOLICAO-CSDTCARANDIRU_ICO-FOT-DGZ-MB0_0004-002.JPG | L3: ='0001'!$L$2 -> A Casa de Detenção de São Paulo, conhecida como Carandiru, foi demolida em etapas. Em 2002, ocorreu a implosão dos pavilhões 6, 8 e 9. Já em 2005, dos pavilhões 2 e 5 pela empresa Arcoenge (contratada pelo governo do estado de São Paulo). A coleção Arcoenge contém subgrupos de fotos, vídeos e texto, totalizando 164 peças documentais. | M3: Fotografia captada ao nível do solo mostrando um grupo de homens, de costas e de perfil, a observar os pavilhões prisionais. No centro, destaca-se uma figura institucional (identificável como o então governador do Estado de São Paulo, Geraldo Alkimin) a operar um dispositivo detonador de comando manual, colocado sobre um suporte metálico. Ao fundo, vislumbram-se os blocos prisionais envoltos nas telas brancas de proteção, instantes antes da demolição. Existe um outdoor retangular largo vermelho na área externa, anunciando o "Parque da Juventude" e os dizeres "venha praticar a liberdade". Na lateral dele, o logo do governo do estado de São Paulo. | N3: ='0001'!$N$2 -> O acesso aos documentos deste acervo está condicionado ao compromisso de não repassá-los a terceiros, à obrigatoriedade de mencionar que os originais pertencem ao GPDVE (?), e à necessidade de novo Termo de Responsabilidade em caso de reutilização ou uso diverso do inicialmente acordado. O uso está sujeito às restrições previstas na Lei de Arquivos (Lei nº 8.159/1991), na Lei de Direitos Autorais (Lei nº 9.610/1998), nos artigos 138 e 145 do Código Penal, e no artigo 5º, inciso X, da Constituição Federal, especialmente quanto à proteção da honra e imagem de terceiros. A pessoa física ou jurídica responsável assume integral responsabilidade civil e penal por eventuais danos decorrentes do uso das reproduções e informações, eximindo o GPDVE de qualquer responsabilidade. | O3: Sistema prisional; Arquitetura prisional; Casa de Detenção de São Paulo; Carandiru | P3: Fotografia (Iconográfico) | Q3: Digitalização de fotografia colorida (analógica original) | R3: ="Figura n – ["&'0003'!B3&"]"&CHAR(10)&"Fonte: Arquivo do Estado de São Paulo, "&TEXT('0003'!D3,"yyyy")&"." -> Figura n – [Muro divisório com pichações sutis e técnico apontando fissura.] Fonte: Arquivo do Estado de São Paulo, 2003. | S3: ="ARQUIVO PÚBLICO DO ESTADO DE SÃO PAULO (Brasil). ["&'0003'!B3&"]. "&'0003'!G3&". "&TEXT('0003'!D3,"dd")&" "&LOWER(TEXT('0003'!D3,"mmm"))&" "&TEXT('0003'!D3,"yyyy")&". "&'0003'!F3&". Disponível em: <link do dataverse>. Acesso em: 28 out. 2025." -> ARQUIVO PÚBLICO DO ESTADO DE SÃO PAULO (Brasil). [Muro divisório com pichações sutis e técnico apontando fissura.]. São Paulo, Brasil. 10 mar. 2003. Fotografia digitalizada; colorida; suporte em papel fotográfico. Disponível em: <link do dataverse>. Acesso em: 28 out. 2025. | T3: A foto "car15" não existe no diretório original. Este item pertencia ao caminho: "Carandiru -Nico (seleção 2005)" > "fotos". Nos metadados da fotografia (campo Data de criação), indica-se que sua criação se deu no 22/09/2005. A data indicada no campo "Data da fotografia" do presente dataset retrata o data exata do clique fotográfico.
A4: =MID('0003'!K4, LEN('0003'!K4)-6, 3) -> 003 | B4: Vista aérea panorâmica do complexo prisional antes da implosão. | C4: Item | D4: 38550 | E4: Gerado pelo Dataverse | F4: Fotografia digitalizada; colorida; suporte em papel fotográfico | G4: São Paulo, Brasil | H4: Grupo de Pesquisa em Direito e Violência de Estado | I4: Arcoenge - Demolição - Casa de Detenção do Carandiru (Fotografias) | J4: Pasta: 0002 | K4: =TEXTJOIN("", TRUE, Geral!B85:U85) -> BR-SPGPDVE_ARCOENGE-DEMOLICAO-CSDTCARANDIRU_ICO-FOT-DGZ-MB0_0004-003.JPG | L4: ='0001'!$L$2 -> A Casa de Detenção de São Paulo, conhecida como Carandiru, foi demolida em etapas. Em 2002, ocorreu a implosão dos pavilhões 6, 8 e 9. Já em 2005, dos pavilhões 2 e 5 pela empresa Arcoenge (contratada pelo governo do estado de São Paulo). A coleção Arcoenge contém subgrupos de fotos, vídeos e texto, totalizando 164 peças documentais. | M4: Imagem aérea em plano geral abrangendo o complexo da Casa de Detenção do Carandiru e a envolvente urbana de São Paulo. No pátio interno, delimitado por muros, encontram-se quatro grandes blocos prisionais. Os dois edifícios no primeiro plano têm as coberturas e as bases envolvidas por telas brancas contendo as inscrições "ARCOENGE" e "CDI". Em baixo, visualiza-se o muro perimetral confrontante com a via pública. Existe um outdoor retangular largo vermelho na área externa, anunciando o "Parque da Juventude" e os dizeres "venha praticar a liberdade". Na lateral dele, o logo do governo do estado de São Paulo. | N4: ='0001'!$N$2 -> O acesso aos documentos deste acervo está condicionado ao compromisso de não repassá-los a terceiros, à obrigatoriedade de mencionar que os originais pertencem ao GPDVE (?), e à necessidade de novo Termo de Responsabilidade em caso de reutilização ou uso diverso do inicialmente acordado. O uso está sujeito às restrições previstas na Lei de Arquivos (Lei nº 8.159/1991), na Lei de Direitos Autorais (Lei nº 9.610/1998), nos artigos 138 e 145 do Código Penal, e no artigo 5º, inciso X, da Constituição Federal, especialmente quanto à proteção da honra e imagem de terceiros. A pessoa física ou jurídica responsável assume integral responsabilidade civil e penal por eventuais danos decorrentes do uso das reproduções e informações, eximindo o GPDVE de qualquer responsabilidade. | O4: Sistema prisional; Arquitetura prisional; Casa de Detenção de São Paulo; Carandiru | P4: Fotografia (Iconográfico) | Q4: Digitalização de fotografia colorida (analógica original) | R4: ="Figura n – ["&'0003'!B4&"]"&CHAR(10)&"Fonte: Arquivo do Estado de São Paulo, "&TEXT('0003'!D4,"yyyy")&"." -> Figura n – [Vistoria de fenda estrutural entre muros de divisa.] Fonte: Arquivo do Estado de São Paulo, 2003. | S4: ="ARQUIVO PÚBLICO DO ESTADO DE SÃO PAULO (Brasil). ["&'0003'!B4&"]. "&'0003'!G4&". "&TEXT('0003'!D4,"dd")&" "&LOWER(TEXT('0003'!D4,"mmm"))&" "&TEXT('0003'!D4,"yyyy")&". "&'0003'!F4&". Disponível em: <link do dataverse>. Acesso em: 28 out. 2025." -> ARQUIVO PÚBLICO DO ESTADO DE SÃO PAULO (Brasil). [Vistoria de fenda estrutural entre muros de divisa.]. São Paulo, Brasil. 10 mar. 2003. Fotografia digitalizada; colorida; suporte em papel fotográfico. Disponível em: <link do dataverse>. Acesso em: 28 out. 2025. | T4: A foto "car15" não existe no diretório original. Este item pertencia ao caminho: "Carandiru -Nico (seleção 2005)" > "fotos". Nos metadados da fotografia (campo Data de criação), indica-se que sua criação se deu no 22/09/2005. A data indicada no campo "Data da fotografia" do presente dataset retrata o data exata do clique fotográfico.
A5: =MID('0003'!K5, LEN('0003'!K5)-6, 3) -> 004 | B5: Início do processo de implosão dos pavilhões prisionais. | C5: Item | D5: 38550 | E5: Gerado pelo Dataverse | F5: Fotografia digitalizada; colorida; suporte em papel fotográfico | G5: São Paulo, Brasil | H5: Grupo de Pesquisa em Direito e Violência de Estado | I5: Arcoenge - Demolição - Casa de Detenção do Carandiru (Fotografias) | J5: Pasta: 0002 | K5: =TEXTJOIN("", TRUE, Geral!B86:U86) -> BR-SPGPDVE_ARCOENGE-DEMOLICAO-CSDTCARANDIRU_ICO-FOT-DGZ-MB0_0004-004.JPG | L5: ='0001'!$L$2 -> A Casa de Detenção de São Paulo, conhecida como Carandiru, foi demolida em etapas. Em 2002, ocorreu a implosão dos pavilhões 6, 8 e 9. Já em 2005, dos pavilhões 2 e 5 pela empresa Arcoenge (contratada pelo governo do estado de São Paulo). A coleção Arcoenge contém subgrupos de fotos, vídeos e texto, totalizando 164 peças documentais. | M5: Fotografia aérea captada no exato momento da detonação dos pavilhões 2 e 5. O edifício situado à direita encontra-se na fase inicial de colapso estrutural, com a tela branca da cobertura a insuflar acentuadamente devido à pressão do ar interno. Simultaneamente, densas nuvens de poeira e detritos expandem-se rapidamente a partir das bases e das janelas de ambos os blocos do primeiro plano. O horizonte urbano ao fundo permanece inalterado. Existe um outdoor retangular largo vermelho na área externa, anunciando o "Parque da Juventude" e os dizeres "venha praticar a liberdade". Na lateral dele, o logo do governo do estado de São Paulo. | N5: ='0001'!$N$2 -> O acesso aos documentos deste acervo está condicionado ao compromisso de não repassá-los a terceiros, à obrigatoriedade de mencionar que os originais pertencem ao GPDVE (?), e à necessidade de novo Termo de Responsabilidade em caso de reutilização ou uso diverso do inicialmente acordado. O uso está sujeito às restrições previstas na Lei de Arquivos (Lei nº 8.159/1991), na Lei de Direitos Autorais (Lei nº 9.610/1998), nos artigos 138 e 145 do Código Penal, e no artigo 5º, inciso X, da Constituição Federal, especialmente quanto à proteção da honra e imagem de terceiros. A pessoa física ou jurídica responsável assume integral responsabilidade civil e penal por eventuais danos decorrentes do uso das reproduções e informações, eximindo o GPDVE de qualquer responsabilidade. | O5: Sistema prisional; Arquitetura prisional; Casa de Detenção de São Paulo; Carandiru | P5: Fotografia (Iconográfico) | Q5: Digitalização de fotografia colorida (analógica original) | R5: ="Figura n – ["&'0003'!B5&"]"&CHAR(10)&"Fonte: Arquivo do Estado de São Paulo, "&TEXT('0003'!D5,"yyyy")&"." -> Figura n – [Detalhe de avarias no reboco com exposição de alvenaria.] Fonte: Arquivo do Estado de São Paulo, 2003. | S5: ="ARQUIVO PÚBLICO DO ESTADO DE SÃO PAULO (Brasil). ["&'0003'!B5&"]. "&'0003'!G5&". "&TEXT('0003'!D5,"dd")&" "&LOWER(TEXT('0003'!D5,"mmm"))&" "&TEXT('0003'!D5,"yyyy")&". "&'0003'!F5&". Disponível em: <link do dataverse>. Acesso em: 28 out. 2025." -> ARQUIVO PÚBLICO DO ESTADO DE SÃO PAULO (Brasil). [Detalhe de avarias no reboco com exposição de alvenaria.]. São Paulo, Brasil. 10 mar. 2003. Fotografia digitalizada; colorida; suporte em papel fotográfico. Disponível em: <link do dataverse>. Acesso em: 28 out. 2025. | T5: A foto "car15" não existe no diretório original. Este item pertencia ao caminho: "Carandiru -Nico (seleção 2005)" > "fotos". Nos metadados da fotografia (campo Data de criação), indica-se que sua criação se deu no 22/09/2005. A data indicada no campo "Data da fotografia" do presente dataset retrata o data exata do clique fotográfico.
A6: =MID('0003'!K6, LEN('0003'!K6)-6, 3) -> 005 | B6: Colapso estrutural dos pavilhões prisionais durante a implosão. | C6: Item | D6: 38550 | E6: Gerado pelo Dataverse | F6: Fotografia digitalizada; colorida; suporte em papel fotográfico | G6: São Paulo, Brasil | H6: Grupo de Pesquisa em Direito e Violência de Estado | I6: Arcoenge - Demolição - Casa de Detenção do Carandiru (Fotografias) | J6: Pasta: 0002 | K6: =TEXTJOIN("", TRUE, Geral!B87:U87) -> BR-SPGPDVE_ARCOENGE-DEMOLICAO-CSDTCARANDIRU_ICO-FOT-DGZ-MB0_0004-005.JPG | L6: ='0001'!$L$2 -> A Casa de Detenção de São Paulo, conhecida como Carandiru, foi demolida em etapas. Em 2002, ocorreu a implosão dos pavilhões 6, 8 e 9. Já em 2005, dos pavilhões 2 e 5 pela empresa Arcoenge (contratada pelo governo do estado de São Paulo). A coleção Arcoenge contém subgrupos de fotos, vídeos e texto, totalizando 164 peças documentais. | M6: Imagem aérea sequencial à anterior, documentando o progresso da implosão. Os pavilhões 2 e 5 no primeiro plano encontram-se em colapso evidente, a ceder sobre as próprias fundações num movimento vertical. Grandes volumes de poeira espessa dominam a base e o perímetro das estruturas, ocultando os andares inferiores, enquanto as enormes telas brancas de proteção nas coberturas continuam fortemente insufladas e a deformar-se à medida que os edifícios colapsam. Existe um outdoor retangular largo vermelho, na área externa, anunciando o "Parque da Juventude" e os dizeres "venha praticar a liberdade". Na lateral dele, o logo do governo do estado de São Paulo. | N6: ='0001'!$N$2 -> O acesso aos documentos deste acervo está condicionado ao compromisso de não repassá-los a terceiros, à obrigatoriedade de mencionar que os originais pertencem ao GPDVE (?), e à necessidade de novo Termo de Responsabilidade em caso de reutilização ou uso diverso do inicialmente acordado. O uso está sujeito às restrições previstas na Lei de Arquivos (Lei nº 8.159/1991), na Lei de Direitos Autorais (Lei nº 9.610/1998), nos artigos 138 e 145 do Código Penal, e no artigo 5º, inciso X, da Constituição Federal, especialmente quanto à proteção da honra e imagem de terceiros. A pessoa física ou jurídica responsável assume integral responsabilidade civil e penal por eventuais danos decorrentes do uso das reproduções e informações, eximindo o GPDVE de qualquer responsabilidade. | O6: Sistema prisional; Arquitetura prisional; Casa de Detenção de São Paulo; Carandiru | P6: Fotografia (Iconográfico) | Q6: Digitalização de fotografia colorida (analógica original) | R6: ="Figura n – ["&'0003'!B6&"]"&CHAR(10)&"Fonte: Arquivo do Estado de São Paulo, "&TEXT('0003'!D6,"yyyy")&"." -> Figura n – [Técnico apontando extensa fissura vertical em muro.] Fonte: Arquivo do Estado de São Paulo, 2003. | S6: ="ARQUIVO PÚBLICO DO ESTADO DE SÃO PAULO (Brasil). ["&'0003'!B6&"]. "&'0003'!G6&". "&TEXT('0003'!D6,"dd")&" "&LOWER(TEXT('0003'!D6,"mmm"))&" "&TEXT('0003'!D6,"yyyy")&". "&'0003'!F6&". Disponível em: <link do dataverse>. Acesso em: 28 out. 2025." -> ARQUIVO PÚBLICO DO ESTADO DE SÃO PAULO (Brasil). [Técnico apontando extensa fissura vertical em muro.]. São Paulo, Brasil. 10 mar. 2003. Fotografia digitalizada; colorida; suporte em papel fotográfico. Disponível em: <link do dataverse>. Acesso em: 28 out. 2025. | T6: A foto "car15" não existe no diretório original. Este item pertencia ao caminho: "Carandiru -Nico (seleção 2005)" > "fotos". Nos metadados da fotografia (campo Data de criação), indica-se que sua criação se deu no 22/09/2005. A data indicada no campo "Data da fotografia" do presente dataset retrata o data exata do clique fotográfico.
A7: =MID('0003'!K7, LEN('0003'!K7)-6, 3) -> 006 | B7: Vista aérea panorâmica do colapso dos pavilhões durante a implosão. | C7: Item | D7: 38550 | E7: Gerado pelo Dataverse | F7: Fotografia digitalizada; colorida; suporte em papel fotográfico | G7: São Paulo, Brasil | H7: Grupo de Pesquisa em Direito e Violência de Estado | I7: Arcoenge - Demolição - Casa de Detenção do Carandiru (Fotografias) | J7: Pasta: 0002 | K7: =TEXTJOIN("", TRUE, Geral!B88:U88) -> BR-SPGPDVE_ARCOENGE-DEMOLICAO-CSDTCARANDIRU_ICO-FOT-DGZ-MB0_0004-006.JPG | L7: ='0001'!$L$2 -> A Casa de Detenção de São Paulo, conhecida como Carandiru, foi demolida em etapas. Em 2002, ocorreu a implosão dos pavilhões 6, 8 e 9. Já em 2005, dos pavilhões 2 e 5 pela empresa Arcoenge (contratada pelo governo do estado de São Paulo). A coleção Arcoenge contém subgrupos de fotos, vídeos e texto, totalizando 164 peças documentais. | M7: Imagem aérea registrando o momento avançado da implosão dos pavilhões 2 e 5 da Casa de Detenção do Carandiru. As estruturas colapsam sobre si mesmas, gerando imensas nuvens de poeira que se expandem rapidamente pelo terreno avermelhado. As telas brancas de proteção continuam visíveis, inflando sobre as lajes em queda. Ao fundo, a malha urbana da cidade, o muro de contenção e os edifícios remanescentes do complexo permanecem visíveis. Existe um outdoor retangular largo vermelho, na área externa, anunciando o "Parque da Juventude" e os dizeres "venha praticar a liberdade". Na lateral dele, o logo do governo do estado de São Paulo. | N7: ='0001'!$N$2 -> O acesso aos documentos deste acervo está condicionado ao compromisso de não repassá-los a terceiros, à obrigatoriedade de mencionar que os originais pertencem ao GPDVE (?), e à necessidade de novo Termo de Responsabilidade em caso de reutilização ou uso diverso do inicialmente acordado. O uso está sujeito às restrições previstas na Lei de Arquivos (Lei nº 8.159/1991), na Lei de Direitos Autorais (Lei nº 9.610/1998), nos artigos 138 e 145 do Código Penal, e no artigo 5º, inciso X, da Constituição Federal, especialmente quanto à proteção da honra e imagem de terceiros. A pessoa física ou jurídica responsável assume integral responsabilidade civil e penal por eventuais danos decorrentes do uso das reproduções e informações, eximindo o GPDVE de qualquer responsabilidade. | O7: Sistema prisional; Arquitetura prisional; Casa de Detenção de São Paulo; Carandiru | P7: Fotografia (Iconográfico) | Q7: Digitalização de fotografia colorida (analógica original) | R7: ="Figura n – ["&'0003'!B7&"]"&CHAR(10)&"Fonte: Arquivo do Estado de São Paulo, "&TEXT('0003'!D7,"yyyy")&"." -> Figura n – [Vistoria de trinca vertical.] Fonte: Arquivo do Estado de São Paulo, 2003. | S7: ="ARQUIVO PÚBLICO DO ESTADO DE SÃO PAULO (Brasil). ["&'0003'!B7&"]. "&'0003'!G7&". "&TEXT('0003'!D7,"dd")&" "&LOWER(TEXT('0003'!D7,"mmm"))&" "&TEXT('0003'!D7,"yyyy")&". "&'0003'!F7&". Disponível em: <link do dataverse>. Acesso em: 28 out. 2025." -> ARQUIVO PÚBLICO DO ESTADO DE SÃO PAULO (Brasil). [Vistoria de trinca vertical.]. São Paulo, Brasil. 10 mar. 2003. Fotografia digitalizada; colorida; suporte em papel fotográfico. Disponível em: <link do dataverse>. Acesso em: 28 out. 2025. | T7: A foto "car15" não existe no diretório original. Este item pertencia ao caminho: "Carandiru -Nico (seleção 2005)" > "fotos". Nos metadados da fotografia (campo Data de criação), indica-se que sua criação se deu no 22/09/2005. A data indicada no campo "Data da fotografia" do presente dataset retrata o data exata do clique fotográfico.
A8: =MID('0003'!K8, LEN('0003'!K8)-6, 3) -> 007 | B8: Autoridades observam a nuvem de poeira gerada pela implosão. | C8: Item | D8: 38550 | E8: Gerado pelo Dataverse | F8: Fotografia digitalizada; colorida; suporte em papel fotográfico | G8: São Paulo, Brasil | H8: Grupo de Pesquisa em Direito e Violência de Estado | I8: Arcoenge - Demolição - Casa de Detenção do Carandiru (Fotografias) | J8: Pasta: 0002 | K8: =TEXTJOIN("", TRUE, Geral!B89:U89) -> BR-SPGPDVE_ARCOENGE-DEMOLICAO-CSDTCARANDIRU_ICO-FOT-DGZ-MB0_0004-007.JPG | L8: ='0001'!$L$2 -> A Casa de Detenção de São Paulo, conhecida como Carandiru, foi demolida em etapas. Em 2002, ocorreu a implosão dos pavilhões 6, 8 e 9. Já em 2005, dos pavilhões 2 e 5 pela empresa Arcoenge (contratada pelo governo do estado de São Paulo). A coleção Arcoenge contém subgrupos de fotos, vídeos e texto, totalizando 164 peças documentais. | M8: Fotografia ao nível do solo capturando autoridades (incluindo o então governador de São Paulo) de costas, observando os instantes imediatamente após o acionamento dos explosivos. Uma densa nuvem de poeira marrom domina o fundo da imagem, encobrindo quase totalmente os edifícios em colapso. Um dos observadores à esquerda ergue o braço com o punho cerrado, em um gesto de celebração ou ênfase. | N8: ='0001'!$N$2 -> O acesso aos documentos deste acervo está condicionado ao compromisso de não repassá-los a terceiros, à obrigatoriedade de mencionar que os originais pertencem ao GPDVE (?), e à necessidade de novo Termo de Responsabilidade em caso de reutilização ou uso diverso do inicialmente acordado. O uso está sujeito às restrições previstas na Lei de Arquivos (Lei nº 8.159/1991), na Lei de Direitos Autorais (Lei nº 9.610/1998), nos artigos 138 e 145 do Código Penal, e no artigo 5º, inciso X, da Constituição Federal, especialmente quanto à proteção da honra e imagem de terceiros. A pessoa física ou jurídica responsável assume integral responsabilidade civil e penal por eventuais danos decorrentes do uso das reproduções e informações, eximindo o GPDVE de qualquer responsabilidade. | O8: Sistema prisional; Arquitetura prisional; Casa de Detenção de São Paulo; Carandiru | P8: Fotografia (Iconográfico) | Q8: Digitalização de fotografia colorida (analógica original) | R8: ="Figura n – ["&'0003'!B8&"]"&CHAR(10)&"Fonte: Arquivo do Estado de São Paulo, "&TEXT('0003'!D8,"yyyy")&"." -> Figura n – [Técnico indicando ruptura com desprendimento de reboco.] Fonte: Arquivo do Estado de São Paulo, 2003. | S8: ="ARQUIVO PÚBLICO DO ESTADO DE SÃO PAULO (Brasil). ["&'0003'!B8&"]. "&'0003'!G8&". "&TEXT('0003'!D8,"dd")&" "&LOWER(TEXT('0003'!D8,"mmm"))&" "&TEXT('0003'!D8,"yyyy")&". "&'0003'!F8&". Disponível em: <link do dataverse>. Acesso em: 28 out. 2025." -> ARQUIVO PÚBLICO DO ESTADO DE SÃO PAULO (Brasil). [Técnico indicando ruptura com desprendimento de reboco.]. São Paulo, Brasil. 10 mar. 2003. Fotografia digitalizada; colorida; suporte em papel fotográfico. Disponível em: <link do dataverse>. Acesso em: 28 out. 2025. | T8: A foto "car15" não existe no diretório original. Este item pertencia ao caminho: "Carandiru -Nico (seleção 2005)" > "fotos". Nos metadados da fotografia (campo Data de criação), indica-se que sua criação se deu no 22/09/2005. A data indicada no campo "Data da fotografia" do presente dataset retrata o data exata do clique fotográfico.
A9: =MID('0003'!K9, LEN('0003'!K9)-6, 3) -> 008 | B9: Pavilhões reduzidos a escombros sob nuvem de poeira dissipando. | C9: Item | D9: 38550 | E9: Gerado pelo Dataverse | F9: Fotografia digitalizada; colorida; suporte em papel fotográfico | G9: São Paulo, Brasil | H9: Grupo de Pesquisa em Direito e Violência de Estado | I9: Arcoenge - Demolição - Casa de Detenção do Carandiru (Fotografias) | J9: Pasta: 0002 | K9: =TEXTJOIN("", TRUE, Geral!B90:U90) -> BR-SPGPDVE_ARCOENGE-DEMOLICAO-CSDTCARANDIRU_ICO-FOT-DGZ-MB0_0004-008.JPG | L9: ='0001'!$L$2 -> A Casa de Detenção de São Paulo, conhecida como Carandiru, foi demolida em etapas. Em 2002, ocorreu a implosão dos pavilhões 6, 8 e 9. Já em 2005, dos pavilhões 2 e 5 pela empresa Arcoenge (contratada pelo governo do estado de São Paulo). A coleção Arcoenge contém subgrupos de fotos, vídeos e texto, totalizando 164 peças documentais. | M9: Vista aérea retratando o cenário logo após a queda total dos dois pavilhões frontais. As estruturas encontram-se reduzidas a montanhas de escombros e lajes empilhadas sobre o terreno. Uma espessa nuvem de poeira ainda encobre grande parte do cenário e se desloca para a esquerda, impulsionada pelo vento, ocultando parcialmente a cidade ao fundo. | N9: ='0001'!$N$2 -> O acesso aos documentos deste acervo está condicionado ao compromisso de não repassá-los a terceiros, à obrigatoriedade de mencionar que os originais pertencem ao GPDVE (?), e à necessidade de novo Termo de Responsabilidade em caso de reutilização ou uso diverso do inicialmente acordado. O uso está sujeito às restrições previstas na Lei de Arquivos (Lei nº 8.159/1991), na Lei de Direitos Autorais (Lei nº 9.610/1998), nos artigos 138 e 145 do Código Penal, e no artigo 5º, inciso X, da Constituição Federal, especialmente quanto à proteção da honra e imagem de terceiros. A pessoa física ou jurídica responsável assume integral responsabilidade civil e penal por eventuais danos decorrentes do uso das reproduções e informações, eximindo o GPDVE de qualquer responsabilidade. | O9: Sistema prisional; Arquitetura prisional; Casa de Detenção de São Paulo; Carandiru | P9: Fotografia (Iconográfico) | Q9: Digitalização de fotografia colorida (analógica original) | R9: ="Figura n – ["&'0003'!B9&"]"&CHAR(10)&"Fonte: Arquivo do Estado de São Paulo, "&TEXT('0003'!D9,"yyyy")&"." -> Figura n – [Técnico encostado em quina de muro com buracos profundos.] Fonte: Arquivo do Estado de São Paulo, 2003. | S9: ="ARQUIVO PÚBLICO DO ESTADO DE SÃO PAULO (Brasil). ["&'0003'!B9&"]. "&'0003'!G9&". "&TEXT('0003'!D9,"dd")&" "&LOWER(TEXT('0003'!D9,"mmm"))&" "&TEXT('0003'!D9,"yyyy")&". "&'0003'!F9&". Disponível em: <link do dataverse>. Acesso em: 28 out. 2025." -> ARQUIVO PÚBLICO DO ESTADO DE SÃO PAULO (Brasil). [Técnico encostado em quina de muro com buracos profundos.]. São Paulo, Brasil. 10 mar. 2003. Fotografia digitalizada; colorida; suporte em papel fotográfico. Disponível em: <link do dataverse>. Acesso em: 28 out. 2025. | T9: A foto "car15" não existe no diretório original. Este item pertencia ao caminho: "Carandiru -Nico (seleção 2005)" > "fotos". Nos metadados da fotografia (campo Data de criação), indica-se que sua criação se deu no 22/09/2005. A data indicada no campo "Data da fotografia" do presente dataset retrata o data exata do clique fotográfico.
A10: =MID('0003'!K10, LEN('0003'!K10)-6, 3) -> 009 | B10: Ruínas dos pavilhões após a completa dissipação da poeira. | C10: Item | D10: 38550 | E10: Gerado pelo Dataverse | F10: Fotografia digitalizada; colorida; suporte em papel fotográfico | G10: São Paulo, Brasil | H10: Grupo de Pesquisa em Direito e Violência de Estado | I10: Arcoenge - Demolição - Casa de Detenção do Carandiru (Fotografias) | J10: Pasta: 0002 | K10: =TEXTJOIN("", TRUE, Geral!B91:U91) -> BR-SPGPDVE_ARCOENGE-DEMOLICAO-CSDTCARANDIRU_ICO-FOT-DGZ-MB0_0004-009.JPG | L10: ='0001'!$L$2 -> A Casa de Detenção de São Paulo, conhecida como Carandiru, foi demolida em etapas. Em 2002, ocorreu a implosão dos pavilhões 6, 8 e 9. Já em 2005, dos pavilhões 2 e 5 pela empresa Arcoenge (contratada pelo governo do estado de São Paulo). A coleção Arcoenge contém subgrupos de fotos, vídeos e texto, totalizando 164 peças documentais. | M10: Fotografia aérea do canteiro de obras documentando o resultado final da implosão após a poeira baixar. Os dois pavilhões frontais estão completamente colapsados, restando apenas amontoados de escombros estruturais misturados às enormes telas brancas de proteção da empresa responsável. Ao fundo, isolados no pátio de terra cercado pelo muro perimetral, os outros pavilhões permanecem de pé. | N10: ='0001'!$N$2 -> O acesso aos documentos deste acervo está condicionado ao compromisso de não repassá-los a terceiros, à obrigatoriedade de mencionar que os originais pertencem ao GPDVE (?), e à necessidade de novo Termo de Responsabilidade em caso de reutilização ou uso diverso do inicialmente acordado. O uso está sujeito às restrições previstas na Lei de Arquivos (Lei nº 8.159/1991), na Lei de Direitos Autorais (Lei nº 9.610/1998), nos artigos 138 e 145 do Código Penal, e no artigo 5º, inciso X, da Constituição Federal, especialmente quanto à proteção da honra e imagem de terceiros. A pessoa física ou jurídica responsável assume integral responsabilidade civil e penal por eventuais danos decorrentes do uso das reproduções e informações, eximindo o GPDVE de qualquer responsabilidade. | O10: Sistema prisional; Arquitetura prisional; Casa de Detenção de São Paulo; Carandiru | P10: Fotografia (Iconográfico) | Q10: Digitalização de fotografia colorida (analógica original) | R10: ="Figura n – ["&'0003'!B10&"]"&CHAR(10)&"Fonte: Arquivo do Estado de São Paulo, "&TEXT('0003'!D10,"yyyy")&"." -> Figura n – [Extensa fachada lateral com equipe em terreno de obras.] Fonte: Arquivo do Estado de São Paulo, 2003. | S10: ="ARQUIVO PÚBLICO DO ESTADO DE SÃO PAULO (Brasil). ["&'0003'!B10&"]. "&'0003'!G10&". "&TEXT('0003'!D10,"dd")&" "&LOWER(TEXT('0003'!D10,"mmm"))&" "&TEXT('0003'!D10,"yyyy")&". "&'0003'!F10&". Disponível em: <link do dataverse>. Acesso em: 28 out. 2025." -> ARQUIVO PÚBLICO DO ESTADO DE SÃO PAULO (Brasil). [Extensa fachada lateral com equipe em terreno de obras.]. São Paulo, Brasil. 10 mar. 2003. Fotografia digitalizada; colorida; suporte em papel fotográfico. Disponível em: <link do dataverse>. Acesso em: 28 out. 2025. | T10: A foto "car15" não existe no diretório original. Este item pertencia ao caminho: "Carandiru -Nico (seleção 2005)" > "fotos". Nos metadados da fotografia (campo Data de criação), indica-se que sua criação se deu no 22/09/2005. A data indicada no campo "Data da fotografia" do presente dataset retrata o data exata do clique fotográfico.
A11: =MID('0003'!K11, LEN('0003'!K11)-6, 3) -> 010 | B11: Compressor de ar industrial posicionado no canteiro de obras. | C11: Item | D11: 38550 | E11: Gerado pelo Dataverse | F11: Fotografia digitalizada; colorida; suporte em papel fotográfico | G11: São Paulo, Brasil | H11: Grupo de Pesquisa em Direito e Violência de Estado | I11: Arcoenge - Demolição - Casa de Detenção do Carandiru (Fotografias) | J11: Pasta: 0002 | K11: =TEXTJOIN("", TRUE, Geral!B92:U92) -> BR-SPGPDVE_ARCOENGE-DEMOLICAO-CSDTCARANDIRU_ICO-FOT-DGZ-MB0_0004-010.JPG | L11: ='0001'!$L$2 -> A Casa de Detenção de São Paulo, conhecida como Carandiru, foi demolida em etapas. Em 2002, ocorreu a implosão dos pavilhões 6, 8 e 9. Já em 2005, dos pavilhões 2 e 5 pela empresa Arcoenge (contratada pelo governo do estado de São Paulo). A coleção Arcoenge contém subgrupos de fotos, vídeos e texto, totalizando 164 peças documentais. | M11: Fotografia ao nível do solo detalhando um grande equipamento industrial rebocável, pintado de amarelo e preto, com as inscrições "ARCOENGE" e "XA 420 900 PCM" (tratando-se de um compressor de ar). O maquinário encontra-se estacionado sobre o terreno de terra batida e pedras, em frente à fachada de um pavilhão prisional parcialmente descaracterizado. | N11: ='0001'!$N$2 -> O acesso aos documentos deste acervo está condicionado ao compromisso de não repassá-los a terceiros, à obrigatoriedade de mencionar que os originais pertencem ao GPDVE (?), e à necessidade de novo Termo de Responsabilidade em caso de reutilização ou uso diverso do inicialmente acordado. O uso está sujeito às restrições previstas na Lei de Arquivos (Lei nº 8.159/1991), na Lei de Direitos Autorais (Lei nº 9.610/1998), nos artigos 138 e 145 do Código Penal, e no artigo 5º, inciso X, da Constituição Federal, especialmente quanto à proteção da honra e imagem de terceiros. A pessoa física ou jurídica responsável assume integral responsabilidade civil e penal por eventuais danos decorrentes do uso das reproduções e informações, eximindo o GPDVE de qualquer responsabilidade. | O11: Sistema prisional; Arquitetura prisional; Casa de Detenção de São Paulo; Carandiru | P11: Fotografia (Iconográfico) | Q11: Digitalização de fotografia colorida (analógica original) | R11: ="Figura n – ["&'0003'!B11&"]"&CHAR(10)&"Fonte: Arquivo do Estado de São Paulo, "&TEXT('0003'!D11,"yyyy")&"." -> Figura n – [Detalhe superior de empena cega com tijolos laterais expostos.] Fonte: Arquivo do Estado de São Paulo, 2003. | S11: ="ARQUIVO PÚBLICO DO ESTADO DE SÃO PAULO (Brasil). ["&'0003'!B11&"]. "&'0003'!G11&". "&TEXT('0003'!D11,"dd")&" "&LOWER(TEXT('0003'!D11,"mmm"))&" "&TEXT('0003'!D11,"yyyy")&". "&'0003'!F11&". Disponível em: <link do dataverse>. Acesso em: 28 out. 2025." -> ARQUIVO PÚBLICO DO ESTADO DE SÃO PAULO (Brasil). [Detalhe superior de empena cega com tijolos laterais expostos.]. São Paulo, Brasil. 10 mar. 2003. Fotografia digitalizada; colorida; suporte em papel fotográfico. Disponível em: <link do dataverse>. Acesso em: 28 out. 2025. | T11: A foto "car15" não existe no diretório original. Este item pertencia ao caminho: "Carandiru -Nico (seleção 2005)" > "fotos". Nos metadados da fotografia (campo Data de criação), indica-se que sua criação se deu no 22/09/2005. A data indicada no campo "Data da fotografia" do presente dataset retrata o data exata do clique fotográfico.
A12: =MID('0003'!K12, LEN('0003'!K12)-6, 3) -> 011 | B12: Escavadeira com rompedor hidráulico demolindo paredes do pavilhão. | C12: Item | D12: 38550 | E12: Gerado pelo Dataverse | F12: Fotografia digitalizada; colorida; suporte em papel fotográfico | G12: São Paulo, Brasil | H12: Grupo de Pesquisa em Direito e Violência de Estado | I12: Arcoenge - Demolição - Casa de Detenção do Carandiru (Fotografias) | J12: Pasta: 0002 | K12: =TEXTJOIN("", TRUE, Geral!B93:U93) -> BR-SPGPDVE_ARCOENGE-DEMOLICAO-CSDTCARANDIRU_ICO-FOT-DGZ-MB0_0004-011.JPG | L12: ='0001'!$L$2 -> A Casa de Detenção de São Paulo, conhecida como Carandiru, foi demolida em etapas. Em 2002, ocorreu a implosão dos pavilhões 6, 8 e 9. Já em 2005, dos pavilhões 2 e 5 pela empresa Arcoenge (contratada pelo governo do estado de São Paulo). A coleção Arcoenge contém subgrupos de fotos, vídeos e texto, totalizando 164 peças documentais. | M12: Imagem registrando uma escavadeira de esteira laranja da empresa Arcoenge, equipada com um rompedor hidráulico, em atividade de demolição mecânica. O equipamento destrói a alvenaria da fachada de um pátio interno do pavilhão, gerando poeira e entulho na base. Na parede desgastada e esburacada, observam-se pinturas antigas feitas por detentos com inscrições como "Equipe Campeã do Circuito Paulista", "Luciano Caravalho-Pernambuco", "Academia", "Competição Freestyle" e "Vale Tudo". | N12: ='0001'!$N$2 -> O acesso aos documentos deste acervo está condicionado ao compromisso de não repassá-los a terceiros, à obrigatoriedade de mencionar que os originais pertencem ao GPDVE (?), e à necessidade de novo Termo de Responsabilidade em caso de reutilização ou uso diverso do inicialmente acordado. O uso está sujeito às restrições previstas na Lei de Arquivos (Lei nº 8.159/1991), na Lei de Direitos Autorais (Lei nº 9.610/1998), nos artigos 138 e 145 do Código Penal, e no artigo 5º, inciso X, da Constituição Federal, especialmente quanto à proteção da honra e imagem de terceiros. A pessoa física ou jurídica responsável assume integral responsabilidade civil e penal por eventuais danos decorrentes do uso das reproduções e informações, eximindo o GPDVE de qualquer responsabilidade. | O12: Sistema prisional; Arquitetura prisional; Casa de Detenção de São Paulo; Carandiru | P12: Fotografia (Iconográfico) | Q12: Digitalização de fotografia colorida (analógica original) | R12: ="Figura n – ["&'0003'!B12&"]"&CHAR(10)&"Fonte: Arquivo do Estado de São Paulo, "&TEXT('0003'!D12,"yyyy")&"." -> Figura n – [Detalhe de revestimento de muro divisório com manchas e escorrimentos escuros.] Fonte: Arquivo do Estado de São Paulo, 2003. | S12: ="ARQUIVO PÚBLICO DO ESTADO DE SÃO PAULO (Brasil). ["&'0003'!B12&"]. "&'0003'!G12&". "&TEXT('0003'!D12,"dd")&" "&LOWER(TEXT('0003'!D12,"mmm"))&" "&TEXT('0003'!D12,"yyyy")&". "&'0003'!F12&". Disponível em: <link do dataverse>. Acesso em: 28 out. 2025." -> ARQUIVO PÚBLICO DO ESTADO DE SÃO PAULO (Brasil). [Detalhe de revestimento de muro divisório com manchas e escorrimentos escuros.]. São Paulo, Brasil. 10 mar. 2003. Fotografia digitalizada; colorida; suporte em papel fotográfico. Disponível em: <link do dataverse>. Acesso em: 28 out. 2025. | T12: A foto "car15" não existe no diretório original. Este item pertencia ao caminho: "Carandiru -Nico (seleção 2005)" > "fotos". Nos metadados da fotografia (campo Data de criação), indica-se que sua criação se deu no 22/09/2005. A data indicada no campo "Data da fotografia" do presente dataset retrata o data exata do clique fotográfico.
A13: =MID('0003'!K13, LEN('0003'!K13)-6, 3) -> 012 | B13: Demolição mecânica da estrutura de concreto de pavilhão prisional. | C13: Item | D13: 38550 | E13: Gerado pelo Dataverse | F13: Fotografia digitalizada; colorida; suporte em papel fotográfico | G13: São Paulo, Brasil | H13: Grupo de Pesquisa em Direito e Violência de Estado | I13: Arcoenge - Demolição - Casa de Detenção do Carandiru (Fotografias) | J13: Pasta: 0002 | K13: =TEXTJOIN("", TRUE, Geral!B94:U94) -> BR-SPGPDVE_ARCOENGE-DEMOLICAO-CSDTCARANDIRU_ICO-FOT-DGZ-MB0_0004-012.JPG | L13: ='0001'!$L$2 -> A Casa de Detenção de São Paulo, conhecida como Carandiru, foi demolida em etapas. Em 2002, ocorreu a implosão dos pavilhões 6, 8 e 9. Já em 2005, dos pavilhões 2 e 5 pela empresa Arcoenge (contratada pelo governo do estado de São Paulo). A coleção Arcoenge contém subgrupos de fotos, vídeos e texto, totalizando 164 peças documentais. | M13: Fotografia semelhante à 0004-011, mostrando a escavadeira laranja operando o rompedor hidráulico nos andares superiores do pavilhão prisional. O trabalho mecânico contínuo já removeu as paredes, expondo o "esqueleto" estrutural em formato de grelha de concreto do edifício (pilares e vigas). Uma coluna de poeira cai em direção ao solo repleto de escombros cerâmicos e concreto. | N13: ='0001'!$N$2 -> O acesso aos documentos deste acervo está condicionado ao compromisso de não repassá-los a terceiros, à obrigatoriedade de mencionar que os originais pertencem ao GPDVE (?), e à necessidade de novo Termo de Responsabilidade em caso de reutilização ou uso diverso do inicialmente acordado. O uso está sujeito às restrições previstas na Lei de Arquivos (Lei nº 8.159/1991), na Lei de Direitos Autorais (Lei nº 9.610/1998), nos artigos 138 e 145 do Código Penal, e no artigo 5º, inciso X, da Constituição Federal, especialmente quanto à proteção da honra e imagem de terceiros. A pessoa física ou jurídica responsável assume integral responsabilidade civil e penal por eventuais danos decorrentes do uso das reproduções e informações, eximindo o GPDVE de qualquer responsabilidade. | O13: Sistema prisional; Arquitetura prisional; Casa de Detenção de São Paulo; Carandiru | P13: Fotografia (Iconográfico) | Q13: Digitalização de fotografia colorida (analógica original) | R13: ="Figura n – ["&'0003'!B13&"]"&CHAR(10)&"Fonte: Arquivo do Estado de São Paulo, "&TEXT('0003'!D13,"yyyy")&"." -> Figura n – [Detalhe de avarias, umidade e oxidação em superfície de muro.] Fonte: Arquivo do Estado de São Paulo, 2003. | S13: ="ARQUIVO PÚBLICO DO ESTADO DE SÃO PAULO (Brasil). ["&'0003'!B13&"]. "&'0003'!G13&". "&TEXT('0003'!D13,"dd")&" "&LOWER(TEXT('0003'!D13,"mmm"))&" "&TEXT('0003'!D13,"yyyy")&". "&'0003'!F13&". Disponível em: <link do dataverse>. Acesso em: 28 out. 2025." -> ARQUIVO PÚBLICO DO ESTADO DE SÃO PAULO (Brasil). [Detalhe de avarias, umidade e oxidação em superfície de muro.]. São Paulo, Brasil. 10 mar. 2003. Fotografia digitalizada; colorida; suporte em papel fotográfico. Disponível em: <link do dataverse>. Acesso em: 28 out. 2025. | T13: A foto "car15" não existe no diretório original. Este item pertencia ao caminho: "Carandiru -Nico (seleção 2005)" > "fotos". Nos metadados da fotografia (campo Data de criação), indica-se que sua criação se deu no 22/09/2005. A data indicada no campo "Data da fotografia" do presente dataset retrata o data exata do clique fotográfico.
A14: =MID('0003'!K14, LEN('0003'!K14)-6, 3) -> 013 | B14: Placa informativa sobre a implosão e demolição dos pavilhões. | C14: Item | D14: 38550 | E14: Gerado pelo Dataverse | F14: Fotografia digitalizada; colorida; suporte em papel fotográfico | G14: São Paulo, Brasil | H14: Grupo de Pesquisa em Direito e Violência de Estado | I14: Arcoenge - Demolição - Casa de Detenção do Carandiru (Fotografias) | J14: Pasta: 0002 | K14: =TEXTJOIN("", TRUE, Geral!B95:U95) -> BR-SPGPDVE_ARCOENGE-DEMOLICAO-CSDTCARANDIRU_ICO-FOT-DGZ-MB0_0004-013.JPG | L14: ='0001'!$L$2 -> A Casa de Detenção de São Paulo, conhecida como Carandiru, foi demolida em etapas. Em 2002, ocorreu a implosão dos pavilhões 6, 8 e 9. Já em 2005, dos pavilhões 2 e 5 pela empresa Arcoenge (contratada pelo governo do estado de São Paulo). A coleção Arcoenge contém subgrupos de fotos, vídeos e texto, totalizando 164 peças documentais. | M14: Imagem em plano fechado documentando uma placa de sinalização amarela da empresa Arcoenge. O texto institucional anuncia a "IMPLOSÃO E DEMOLIÇÃO ESPECIALIZADA DOS PAVILHÕES 2 E 5". A lona lista os nomes e os números de registro no CREA dos engenheiros responsáveis pela operação, além do telefone de contato e endereço eletrônico da empresa contratada. | N14: ='0001'!$N$2 -> O acesso aos documentos deste acervo está condicionado ao compromisso de não repassá-los a terceiros, à obrigatoriedade de mencionar que os originais pertencem ao GPDVE (?), e à necessidade de novo Termo de Responsabilidade em caso de reutilização ou uso diverso do inicialmente acordado. O uso está sujeito às restrições previstas na Lei de Arquivos (Lei nº 8.159/1991), na Lei de Direitos Autorais (Lei nº 9.610/1998), nos artigos 138 e 145 do Código Penal, e no artigo 5º, inciso X, da Constituição Federal, especialmente quanto à proteção da honra e imagem de terceiros. A pessoa física ou jurídica responsável assume integral responsabilidade civil e penal por eventuais danos decorrentes do uso das reproduções e informações, eximindo o GPDVE de qualquer responsabilidade. | O14: Sistema prisional; Arquitetura prisional; Casa de Detenção de São Paulo; Carandiru | P14: Fotografia (Iconográfico) | Q14: Digitalização de fotografia colorida (analógica original) | R14: ="Figura n – ["&'0003'!B14&"]"&CHAR(10)&"Fonte: Arquivo do Estado de São Paulo, "&TEXT('0003'!D14,"yyyy")&"." -> Figura n – [Muro divisório bipartido e vala para fundação no canteiro.] Fonte: Arquivo do Estado de São Paulo, 2003. | S14: ="ARQUIVO PÚBLICO DO ESTADO DE SÃO PAULO (Brasil). ["&'0003'!B14&"]. "&'0003'!G14&". "&TEXT('0003'!D14,"dd")&" "&LOWER(TEXT('0003'!D14,"mmm"))&" "&TEXT('0003'!D14,"yyyy")&". "&'0003'!F14&". Disponível em: <link do dataverse>. Acesso em: 28 out. 2025." -> ARQUIVO PÚBLICO DO ESTADO DE SÃO PAULO (Brasil). [Muro divisório bipartido e vala para fundação no canteiro.]. São Paulo, Brasil. 10 mar. 2003. Fotografia digitalizada; colorida; suporte em papel fotográfico. Disponível em: <link do dataverse>. Acesso em: 28 out. 2025. | T14: A foto "car15" não existe no diretório original. Este item pertencia ao caminho: "Carandiru -Nico (seleção 2005)" > "fotos". Nos metadados da fotografia (campo Data de criação), indica-se que sua criação se deu no 22/09/2005. A data indicada no campo "Data da fotografia" do presente dataset retrata o data exata do clique fotográfico.
... A21: =MID('0003'!K21, LEN('0003'!K21)-6, 3) -> 020 | B21: Escavadeiras operando sobre escombros com torre de vigilância ao fundo. | C21: Item | D21: 38550 | E21: Gerado pelo Dataverse | F21: Fotografia digitalizada; colorida; suporte em papel fotográfico | G21: São Paulo, Brasil | H21: Grupo de Pesquisa em Direito e Violência de Estado | I21: Arcoenge - Demolição - Casa de Detenção do Carandiru (Fotografias) | J21: Pasta: 0002 | K21: =TEXTJOIN("", TRUE, Geral!B102:U102) -> BR-SPGPDVE_ARCOENGE-DEMOLICAO-CSDTCARANDIRU_ICO-FOT-DGZ-MB0_0004-020.JPG | L21: ='0001'!$L$2 -> A Casa de Detenção de São Paulo, conhecida como Carandiru, foi demolida em etapas. Em 2002, ocorreu a implosão dos pavilhões 6, 8 e 9. Já em 2005, dos pavilhões 2 e 5 pela empresa Arcoenge (contratada pelo governo do estado de São Paulo). A coleção Arcoenge contém subgrupos de fotos, vídeos e texto, totalizando 164 peças documentais. | M21: Fotografia mostrando duas escavadeiras laranjas da Arcoenge em operação sobre uma vasta montanha de escombros de demolição (concreto, tijolos e ferragens retorcidas). O equipamento em primeiro plano está com o braço articulado recolhido. Ao fundo, o amplo terreno do canteiro encontra-se nivelado com terra vermelha, delimitado pelo muro de contenção perimetral, onde se destaca uma torre de vigilância prisional (guarita). O horizonte é marcado por edifícios da cidade. | N21: ='0001'!$N$2 -> O acesso aos documentos deste acervo está condicionado ao compromisso de não repassá-los a terceiros, à obrigatoriedade de mencionar que os originais pertencem ao GPDVE (?), e à necessidade de novo Termo de Responsabilidade em caso de reutilização ou uso diverso do inicialmente acordado. O uso está sujeito às restrições previstas na Lei de Arquivos (Lei nº 8.159/1991), na Lei de Direitos Autorais (Lei nº 9.610/1998), nos artigos 138 e 145 do Código Penal, e no artigo 5º, inciso X, da Constituição Federal, especialmente quanto à proteção da honra e imagem de terceiros. A pessoa física ou jurídica responsável assume integral responsabilidade civil e penal por eventuais danos decorrentes do uso das reproduções e informações, eximindo o GPDVE de qualquer responsabilidade. | O21: Sistema prisional; Arquitetura prisional; Casa de Detenção de São Paulo; Carandiru | P21: Fotografia (Iconográfico) | Q21: Digitalização de fotografia colorida (analógica original) | R21: ="Figura n – ["&'0003'!B21&"]"&CHAR(10)&"Fonte: Arquivo do Estado de São Paulo, "&TEXT('0003'!D21,"yyyy")&"." -> Figura n – [Residência em reforma com escoramento de laje e caçamba de entulho.] Fonte: Arquivo do Estado de São Paulo, 2003. | S21: ="ARQUIVO PÚBLICO DO ESTADO DE SÃO PAULO (Brasil). ["&'0003'!B21&"]. "&'0003'!G21&". "&TEXT('0003'!D21,"dd")&" "&LOWER(TEXT('0003'!D21,"mmm"))&" "&TEXT('0003'!D21,"yyyy")&". "&'0003'!F21&". Disponível em: <link do dataverse>. Acesso em: 28 out. 2025." -> ARQUIVO PÚBLICO DO ESTADO DE SÃO PAULO (Brasil). [Residência em reforma com escoramento de laje e caçamba de entulho.]. São Paulo, Brasil. 10 mar. 2003. Fotografia digitalizada; colorida; suporte em papel fotográfico. Disponível em: <link do dataverse>. Acesso em: 28 out. 2025. | T21: A foto "car15" não existe no diretório original. Este item pertencia ao caminho: "Carandiru -Nico (seleção 2005)" > "fotos". Nos metadados da fotografia (campo Data de criação), indica-se que sua criação se deu no 22/09/2005. A data indicada no campo "Data da fotografia" do presente dataset retrata o data exata do clique fotográfico.
A22: =MID('0003'!K22, LEN('0003'!K22)-6, 3) -> 021 | B22: Demolição de edificação secundária com operário próximo à máquina. | C22: Item | D22: 38550 | E22: Gerado pelo Dataverse | F22: Fotografia digitalizada; colorida; suporte em papel fotográfico | G22: São Paulo, Brasil | H22: Grupo de Pesquisa em Direito e Violência de Estado | I22: Arcoenge - Demolição - Casa de Detenção do Carandiru (Fotografias) | J22: Pasta: 0002 | K22: =TEXTJOIN("", TRUE, Geral!B103:U103) -> BR-SPGPDVE_ARCOENGE-DEMOLICAO-CSDTCARANDIRU_ICO-FOT-DGZ-MB0_0004-021.JPG | L22: ='0001'!$L$2 -> A Casa de Detenção de São Paulo, conhecida como Carandiru, foi demolida em etapas. Em 2002, ocorreu a implosão dos pavilhões 6, 8 e 9. Já em 2005, dos pavilhões 2 e 5 pela empresa Arcoenge (contratada pelo governo do estado de São Paulo). A coleção Arcoenge contém subgrupos de fotos, vídeos e texto, totalizando 164 peças documentais. | M22: Imagem de uma escavadeira laranja utilizando o rompedor hidráulico para demolir a estrutura superior (laje e cornija) de uma edificação prisional de menor porte. Um operário vestido de azul e com capacete caminha próximo às esteiras do equipamento, em meio aos escombros. Ao fundo, observam-se o muro perimetral, uma torre de vigilância e um edifício comercial de cor escura da malha urbana vizinha, sob céu nublado. | N22: ='0001'!$N$2 -> O acesso aos documentos deste acervo está condicionado ao compromisso de não repassá-los a terceiros, à obrigatoriedade de mencionar que os originais pertencem ao GPDVE (?), e à necessidade de novo Termo de Responsabilidade em caso de reutilização ou uso diverso do inicialmente acordado. O uso está sujeito às restrições previstas na Lei de Arquivos (Lei nº 8.159/1991), na Lei de Direitos Autorais (Lei nº 9.610/1998), nos artigos 138 e 145 do Código Penal, e no artigo 5º, inciso X, da Constituição Federal, especialmente quanto à proteção da honra e imagem de terceiros. A pessoa física ou jurídica responsável assume integral responsabilidade civil e penal por eventuais danos decorrentes do uso das reproduções e informações, eximindo o GPDVE de qualquer responsabilidade. | O22: Sistema prisional; Arquitetura prisional; Casa de Detenção de São Paulo; Carandiru | P22: Fotografia (Iconográfico) | Q22: Digitalização de fotografia colorida (analógica original) | R22: ="Figura n – ["&B22&"]"&CHAR(10)&"Fonte: Arquivo do Estado de São Paulo, "&TEXT(D22,"yyyy")&"." -> Figura n – [Demolição de edificação secundária com operário próximo à máquina.] Fonte: Arquivo do Estado de São Paulo, 2005. | S22: ="ARQUIVO PÚBLICO DO ESTADO DE SÃO PAULO (Brasil). ["&B22&"]. "&G22&". "&TEXT(D22,"dd")&" "&LOWER(TEXT(D22,"mmm"))&" "&TEXT(D22,"yyyy")&". "&F22&". Disponível em: <link do dataverse>. Acesso em: 28 out. 2025." -> ARQUIVO PÚBLICO DO ESTADO DE SÃO PAULO (Brasil). [Demolição de edificação secundária com operário próximo à máquina.]. São Paulo, Brasil. 17 jul. 2005. Fotografia digitalizada; colorida; suporte em papel fotográfico. Disponível em: <link do dataverse>. Acesso em: 28 out. 2025. | T22: A foto "car15" não existe no diretório original. Este item pertencia ao caminho: "Carandiru -Nico (seleção 2005)" > "fotos". Nos metadados da fotografia (campo Data de criação), indica-se que sua criação se deu no 22/09/2005. A data indicada no campo "Data da fotografia" do presente dataset retrata o data exata do clique fotográfico.
A23: =MID('0003'!K23, LEN('0003'!K23)-6, 3) -> 022 | B23: Pavilhões remanescentes refletidos em poças d'água no canteiro. | C23: Item | D23: 38550 | E23: Gerado pelo Dataverse | F23: Fotografia digitalizada; colorida; suporte em papel fotográfico | G23: São Paulo, Brasil | H23: Grupo de Pesquisa em Direito e Violência de Estado | I23: Arcoenge - Demolição - Casa de Detenção do Carandiru (Fotografias) | J23: Pasta: 0002 | K23: =TEXTJOIN("", TRUE, Geral!B104:U104) -> BR-SPGPDVE_ARCOENGE-DEMOLICAO-CSDTCARANDIRU_ICO-FOT-DGZ-MB0_0004-022.JPG | L23: ='0001'!$L$2 -> A Casa de Detenção de São Paulo, conhecida como Carandiru, foi demolida em etapas. Em 2002, ocorreu a implosão dos pavilhões 6, 8 e 9. Já em 2005, dos pavilhões 2 e 5 pela empresa Arcoenge (contratada pelo governo do estado de São Paulo). A coleção Arcoenge contém subgrupos de fotos, vídeos e texto, totalizando 164 peças documentais. | M23: Fotografia em plano aberto documentando edifícios da Casa de Detenção que permaneceram de pé após a fase inicial de demolições. A luz incide sobre as fachadas marcadas por janelas gradeadas vazias e avarias pontuais. No primeiro plano, o extenso terreno de terra vermelha apresenta poças d'água que refletem a silhueta dos edifícios sob o céu claro. Montes de escombros encontram-se acumulados nas bases das estruturas. | N23: ='0001'!$N$2 -> O acesso aos documentos deste acervo está condicionado ao compromisso de não repassá-los a terceiros, à obrigatoriedade de mencionar que os originais pertencem ao GPDVE (?), e à necessidade de novo Termo de Responsabilidade em caso de reutilização ou uso diverso do inicialmente acordado. O uso está sujeito às restrições previstas na Lei de Arquivos (Lei nº 8.159/1991), na Lei de Direitos Autorais (Lei nº 9.610/1998), nos artigos 138 e 145 do Código Penal, e no artigo 5º, inciso X, da Constituição Federal, especialmente quanto à proteção da honra e imagem de terceiros. A pessoa física ou jurídica responsável assume integral responsabilidade civil e penal por eventuais danos decorrentes do uso das reproduções e informações, eximindo o GPDVE de qualquer responsabilidade. | O23: Sistema prisional; Arquitetura prisional; Casa de Detenção de São Paulo; Carandiru | P23: Fotografia (Iconográfico) | Q23: Digitalização de fotografia colorida (analógica original) | R23: ="Figura n – ["&B23&"]"&CHAR(10)&"Fonte: Arquivo do Estado de São Paulo, "&TEXT(D23,"yyyy")&"." -> Figura n – [Pavilhões remanescentes refletidos em poças d'água no canteiro.] Fonte: Arquivo do Estado de São Paulo, 2005. | S23: ="ARQUIVO PÚBLICO DO ESTADO DE SÃO PAULO (Brasil). ["&B23&"]. "&G23&". "&TEXT(D23,"dd")&" "&LOWER(TEXT(D23,"mmm"))&" "&TEXT(D23,"yyyy")&". "&F23&". Disponível em: <link do dataverse>. Acesso em: 28 out. 2025." -> ARQUIVO PÚBLICO DO ESTADO DE SÃO PAULO (Brasil). [Pavilhões remanescentes refletidos em poças d'água no canteiro.]. São Paulo, Brasil. 17 jul. 2005. Fotografia digitalizada; colorida; suporte em papel fotográfico. Disponível em: <link do dataverse>. Acesso em: 28 out. 2025. | T23: A foto "car15" não existe no diretório original. Este item pertencia ao caminho: "Carandiru -Nico (seleção 2005)" > "fotos". Nos metadados da fotografia (campo Data de criação), indica-se que sua criação se deu no 22/09/2005. A data indicada no campo "Data da fotografia" do presente dataset retrata o data exata do clique fotográfico.
A24: =MID('0003'!K24, LEN('0003'!K24)-6, 3) -> 023 | B24: Fachada principal de pavilhão prisional com avarias e escombros na base. | C24: Item | D24: 38550 | E24: Gerado pelo Dataverse | F24: Fotografia digitalizada; colorida; suporte em papel fotográfico | G24: São Paulo, Brasil | H24: Grupo de Pesquisa em Direito e Violência de Estado | I24: Arcoenge - Demolição - Casa de Detenção do Carandiru (Fotografias) | J24: Pasta: 0002 | K24: =TEXTJOIN("", TRUE, Geral!B105:U105) -> BR-SPGPDVE_ARCOENGE-DEMOLICAO-CSDTCARANDIRU_ICO-FOT-DGZ-MB0_0004-023.JPG | L24: ='0001'!$L$2 -> A Casa de Detenção de São Paulo, conhecida como Carandiru, foi demolida em etapas. Em 2002, ocorreu a implosão dos pavilhões 6, 8 e 9. Já em 2005, dos pavilhões 2 e 5 pela empresa Arcoenge (contratada pelo governo do estado de São Paulo). A coleção Arcoenge contém subgrupos de fotos, vídeos e texto, totalizando 164 peças documentais. | M24: Vista frontal e aproximada de um dos pavilhões prisionais remanescentes. A fachada retangular exibe dezenas de pequenas aberturas (celas), diversas delas com danos significativos na alvenaria circundante, indicando o início do desmanche. A base do edifício é rebocada e pintada de branco. O primeiro plano é ocupado por montanhas de terra escura, destroços de concreto, blocos e ferragens retorcidas. | N24: ='0001'!$N$2 -> O acesso aos documentos deste acervo está condicionado ao compromisso de não repassá-los a terceiros, à obrigatoriedade de mencionar que os originais pertencem ao GPDVE (?), e à necessidade de novo Termo de Responsabilidade em caso de reutilização ou uso diverso do inicialmente acordado. O uso está sujeito às restrições previstas na Lei de Arquivos (Lei nº 8.159/1991), na Lei de Direitos Autorais (Lei nº 9.610/1998), nos artigos 138 e 145 do Código Penal, e no artigo 5º, inciso X, da Constituição Federal, especialmente quanto à proteção da honra e imagem de terceiros. A pessoa física ou jurídica responsável assume integral responsabilidade civil e penal por eventuais danos decorrentes do uso das reproduções e informações, eximindo o GPDVE de qualquer responsabilidade. | O24: Sistema prisional; Arquitetura prisional; Casa de Detenção de São Paulo; Carandiru | P24: Fotografia (Iconográfico) | Q24: Digitalização de fotografia colorida (analógica original) | R24: ="Figura n – ["&B24&"]"&CHAR(10)&"Fonte: Arquivo do Estado de São Paulo, "&TEXT(D24,"yyyy")&"." -> Figura n – [Fachada principal de pavilhão prisional com avarias e escombros na base.] Fonte: Arquivo do Estado de São Paulo, 2005. | S24: ="ARQUIVO PÚBLICO DO ESTADO DE SÃO PAULO (Brasil). ["&B24&"]. "&G24&". "&TEXT(D24,"dd")&" "&LOWER(TEXT(D24,"mmm"))&" "&TEXT(D24,"yyyy")&". "&F24&". Disponível em: <link do dataverse>. Acesso em: 28 out. 2025." -> ARQUIVO PÚBLICO DO ESTADO DE SÃO PAULO (Brasil). [Fachada principal de pavilhão prisional com avarias e escombros na base.]. São Paulo, Brasil. 17 jul. 2005. Fotografia digitalizada; colorida; suporte em papel fotográfico. Disponível em: <link do dataverse>. Acesso em: 28 out. 2025. | T24: A foto "car15" não existe no diretório original. Este item pertencia ao caminho: "Carandiru -Nico (seleção 2005)" > "fotos". Nos metadados da fotografia (campo Data de criação), indica-se que sua criação se deu no 22/09/2005. A data indicada no campo "Data da fotografia" do presente dataset retrata o data exata do clique fotográfico.
A25: =MID('0003'!K25, LEN('0003'!K25)-6, 3) -> 024 | B25: Miniescavadeira operando no interior de pavilhão em demolição. | C25: Item | D25: 38550 | E25: Gerado pelo Dataverse | F25: Fotografia digitalizada; colorida; suporte em papel fotográfico | G25: São Paulo, Brasil | H25: Grupo de Pesquisa em Direito e Violência de Estado | I25: Arcoenge - Demolição - Casa de Detenção do Carandiru (Fotografias) | J25: Pasta: 0002 | K25: =TEXTJOIN("", TRUE, Geral!B106:U106) -> BR-SPGPDVE_ARCOENGE-DEMOLICAO-CSDTCARANDIRU_ICO-FOT-DGZ-MB0_0004-024.JPG | L25: ='0001'!$L$2 -> A Casa de Detenção de São Paulo, conhecida como Carandiru, foi demolida em etapas. Em 2002, ocorreu a implosão dos pavilhões 6, 8 e 9. Já em 2005, dos pavilhões 2 e 5 pela empresa Arcoenge (contratada pelo governo do estado de São Paulo). A coleção Arcoenge contém subgrupos de fotos, vídeos e texto, totalizando 164 peças documentais. | M25: Fotografia captada a partir do interior de uma estrutura em processo de demolição mecânica. Um operador, utilizando máscara de proteção contra poeira e capacete, manobra uma miniescavadeira de esteira (branca e cinza) sobre os escombros internos, atuando na derrubada de paredes e lajes. Através das grandes aberturas escavadas na fachada do edifício, avista-se uma escavadeira laranja de grande porte da Arcoenge operando no exterior. | N25: ='0001'!$N$2 -> O acesso aos documentos deste acervo está condicionado ao compromisso de não repassá-los a terceiros, à obrigatoriedade de mencionar que os originais pertencem ao GPDVE (?), e à necessidade de novo Termo de Responsabilidade em caso de reutilização ou uso diverso do inicialmente acordado. O uso está sujeito às restrições previstas na Lei de Arquivos (Lei nº 8.159/1991), na Lei de Direitos Autorais (Lei nº 9.610/1998), nos artigos 138 e 145 do Código Penal, e no artigo 5º, inciso X, da Constituição Federal, especialmente quanto à proteção da honra e imagem de terceiros. A pessoa física ou jurídica responsável assume integral responsabilidade civil e penal por eventuais danos decorrentes do uso das reproduções e informações, eximindo o GPDVE de qualquer responsabilidade. | O25: Sistema prisional; Arquitetura prisional; Casa de Detenção de São Paulo; Carandiru | P25: Fotografia (Iconográfico) | Q25: Digitalização de fotografia colorida (analógica original) | R25: ="Figura n – ["&B25&"]"&CHAR(10)&"Fonte: Arquivo do Estado de São Paulo, "&TEXT(D25,"yyyy")&"." -> Figura n – [Miniescavadeira operando no interior de pavilhão em demolição.] Fonte: Arquivo do Estado de São Paulo, 2005. | S25: ="ARQUIVO PÚBLICO DO ESTADO DE SÃO PAULO (Brasil). ["&B25&"]. "&G25&". "&TEXT(D25,"dd")&" "&LOWER(TEXT(D25,"mmm"))&" "&TEXT(D25,"yyyy")&". "&F25&". Disponível em: <link do dataverse>. Acesso em: 28 out. 2025." -> ARQUIVO PÚBLICO DO ESTADO DE SÃO PAULO (Brasil). [Miniescavadeira operando no interior de pavilhão em demolição.]. São Paulo, Brasil. 17 jul. 2005. Fotografia digitalizada; colorida; suporte em papel fotográfico. Disponível em: <link do dataverse>. Acesso em: 28 out. 2025. | T25: A foto "car15" não existe no diretório original. Este item pertencia ao caminho: "Carandiru -Nico (seleção 2005)" > "fotos". Nos metadados da fotografia (campo Data de criação), indica-se que sua criação se deu no 22/09/2005. A data indicada no campo "Data da fotografia" do presente dataset retrata o data exata do clique fotográfico.

Sheet Classificação
B1: Local (país) | C1: Local (estado) | D1: Designação do repositório | E1: Designação do conjunto documental (FUNDO) | F1: Designação do subconjunto documental | G1: Gênero documental | H1: Espécie/Tipo documental | I1: Técnica de registro | J1: Forma documental | K1: Unidade de descrição
A2: Conteúdo | B2: Obrigatório | C2: Obrigatório | D2: Obrigatório | E2: Obrigatório | F2: Opcional | G2: Opcional | H2: Opcional | I2: Opcional | J2: Opcional | K2: Obrigatório
A3: Fotografias | B3: Brasil | C3: São Paulo | D3: Grupo de Pesquisa em Direito e Violência de Estado | E3: ARCOENGE | F3: Demolição da Casa de Detenção Carandiru | G3: Iconográfico | H3: Fotografia | I3: Digitalizado | J3: Matriz bruta (produção manual) | K3: Pasta
B4: BR | C4: SP | D4: GPDVE | E4: ARCOENGE | F4: DEMOLICAO-CSDTCARANDIRU | G4: ICO | H4: FOT | I4: DGZ | J4: MT0 | K4: 0001 0002 0003 0004
